Workbook
Name X01523bc55cc9d7891758349de91063e5054bba0: 'VENTES 2026-30 – NEUF-RÉNO'!#REF!
Name X1c1027bec0843a5e4f94050f62561fd20c91d93: 'VENTES 2026-30 – NEUF-RÉNO'!#REF!
Name X9714d30f3be8d8aef2230409d030d0767b57939: 'VENTES 2026-30 – NEUF-RÉNO'!#REF!
Name Xbab138113ded3ce224050259b53b6ee0062ae07: 'VENTES 2026-30 – NEUF-RÉNO'!#REF!
Name Xd0f99639db72f25eeee83bcc1c064b9627c8eeb: 'VENTES 2026-30 – NEUF-RÉNO'!#REF!
Name Xe58082e289258386bd204de2e5aee637eb250e8: 'VENTES 2026-30 – NEUF-RÉNO'!#REF!

Sheet Périmètre TERTIAIRE
C2: Segment Principal | D2: Sous-Segment | E2: Exemples | Q2: Tous les Sous-Segments
B3: 75 | C3: Bureaux | D3: Bureaux Tertiaire Privé (>50 salariés) (hors usines et logistique ) | E3: Immeuble tertiaire privé, siège social, centre de services,etc … | Q3: Crèches
B4: 76 | C4: Logistique / Stockage | D4: Centres de stockage / Entrepôts / Plateformes logistiques (>50 salariés) | E4: Entrepôt, plateforme logistique, centre de distribution | Q4: Haltes-garderies, jardins d’enfants (hors crèches)
B5: 77 | C5: Usines & Ateliers | D5: Usines (>50 salariés) (Hors Ateliers industriels) | E5: Usine agroalimentaire, site métallurgique, usine chimique, usine automobile | Q5: Protection Maternelle et Infantile (PMI - sites autonomes)
B6: 78 | C6: Usines & Ateliers | D6: Ateliers industriels / de maintenance (>50 personnes) | E6: Atelier de maintenance, atelier technique, atelier industriel | Q6: Écoles maternelles
B7: 95 | C7: Administrations / services publics | D7: Bureaux administratifs secondaires non ERP >50 salariés | E7: sites de gestion interne >50 salariés, directions support sans accueil, back-offices administratifs de l’État, services techniques / RH / finances de collectivités, annexes administratives d’universités ou de rectorats, back-offices CPAM, CARSAT, ARS, MSA, CROUS, bâtiments administratifs hospitaliers séparés des zones patient/public | Q7: Écoles primaires
B8: 94 | C8: Administrations / services publics | D8: Mairies / hôtels de ville | E8: Mairie, hôtel de ville | Q8: Collèges (vestiaires EPS inclus)
B9: 96 | C9: Administrations / services publics | D9: Hôtels du département Hôtels de région & Services administratifs territoriaux | E9: Conseil départemental ; hôtel de région ; siège administratif territorial central | Q9: Lycées (vestiaires EPS inclus)
Q10: Internats scolaires
C11: Segment Principal | D11: Sous-Segment | E11: Exemples | Q11: Universités
B12: 72 | C12: Commerce | D12: Centres commerciaux / Malls | E12: Centre commercial, mall, galerie marchande gérée comme entité, retail park couvert avec sanitaires communs | Q12: Grandes écoles
B13: 74 | C13: Commerce | D13: Marchés couverts | E13: Marché couvert | Q13: Résidences étudiantes et dortoirs
Q14: Centres de formation / CFA
Q15: Agences emploi / Insertion / Orientation professionnelle
Q16: Gymnases / salles multisports (hors scolaire, mais gymnase municipaux inclus)
Q17: Salles de fitness / dojos
Q18: Patinoires couvertes
Q19: Piscines couvertes
Q20: Centres de thalassothérapie / balnéothérapie / grands spas ouverts au public
Q21: Établissements thermaux
Q22: Terrains de sport (Hors scolaire, sans tribune)
Q23: Stades avec tribunes (Hors grands stades, hors terrains sport)
Q24: Grands stades avec tribunes (Type football/rugby)
Q25: Hippodromes, Centres équestres & Manèges couverts
... Q149: Crématoriums

Sheet DATA - ANALYSE - TERTIAIRE
J1: Classement ERP | Q1: Comptage | AA1: 2015-20 | AF1: 2020-25 | AK1: 2025-30 | AO1: Argu Evolution | AT1: Detail Capacité par Public | AY1: Detail Dimensionnement | BF1: =BF7/$BD$7 -> 0.0023796976 | BG1: =BG7/$BD$7 -> 0.011452295 | BH1: =BH7/$BD$7 -> 0.04796578 | BN1: Volume Pièces | CQ1: Mix Type Pièces | DG1: Durée Vie - Type Pièces | DR1: Vol Lav 25-30 | EA1: Vol Douches 25-30 | EL1: Vol Urinoirs 25-30 | EU1: Vol WC 25-30 | EX1: =EX7/5000 -> 102.9739 | EY1: =FA7/5000 -> 95.31035 | EZ1: =EY1/$EX$1 -> 0.92557779 | FD1: 33-36% | FE1: =FG7/5000 -> 1.5515564 | FF1: =FE1/$EX$1 -> 0.015067473 | FG1: =FE1/$EY$1 -> 0.016278991 | FH1: 17-19% | FI1: =FJ7/5000 -> 5.7758638 | FJ1: =FI1/$EX$1 -> 0.056090563 | FK1: =FI1/$EY$1 -> 0.060600593 | FL1: 79-81% | FM1: Vtes Réno - Neuf | FR1: Fiabilité - Hypothèses | GG1: Potentiel-Projets-Dynamisme-Menaces | HX1: Réno-Neuf | IN1: Niveau de Confort - Global | KC1: Niveau de Confort - Type Pdt | KK1: Drivers - Tendances -Niveau de Confort
J2: Exemples | Q2: Fiabilité | AO2: 2025-2030 | BA2: Nombre Pièces - Robinetterie collectivité - Etablissements Recevant du Public - IMPERATIVEMENT dotés de sanitaires | BP2: Mix 2025 | BT2: Mix 2030 | BX2: Mix 2025 | CA2: Mix 2030 | CD2: Mix 2025 | CH2: Mix 2030 | CL2: Mix 2025 | CO2: Mix 2030 | CR2: Durée Vie réelle : Nbre Années effectives de vie produit avant remplacement | DI2: Volumes 2025 | DN2: Volumes 2030 | DT2: Volumes 2025 | DX2: Mix 2030 | EC2: Volumes 2025 | EH2: Mix 2030 | EN2: Volumes 2025 | ER2: Mix 2030 | EX2: Ventes 2026-2030 | FB2: Ventes 2026-2030 | FE2: Ventes 2026-2030 | FH2: Ventes 2026-2030 | FK2: Ventes 2026-2030 | FQ2: Ventes 2026-2030 | FS2: Dynamisme Ventes 2026-2030 | GI2: Ventes 2026-2030 | GL2: Ventes 2026-2030 | GO2: Ventes 2026-2030 | GR2: Ventes 2026-2030 | GU2: Ventes 2026-2030 | GX2: Ventes 2026-2030 | HA2: Ventes 2026-2030 | HD2: Ventes 2026-2030 | HG2: Ventes 2026-2030 | HJ2: Ventes 2026-2030 | HM2: Ventes 2026-2030 | HP2: Ventes 2026-2030 | HS2: Ventes 2026-2030 | HV2: Ventes 2026-2030 | IB2: Parc 2025 | IH2: Ventes 2026-2030 | IQ2: Parc 2025 | IV2: Ventes 2026-2030 | JA2: Parc 2025 | JF2: Ventes 2026-2030 | JK2: Parc 2025 | JP2: Ventes 2026-2030 | JU2: Parc 2025 | JZ2: Ventes 2026-2030 | KE2: Niveau
AF3: Nbre Etablissements | AZ3: par Etablissement | BE3: 2025 | BF3: Total 2025 | BJ3: 2030 | BK3: Total 2030 | BP3: Lavabo | BT3: Lavabo | BX3: Douches | CA3: Douches | CC3: Urinoirs - Chasse … | CG3: Urinoirs - Chasse … | CL3: WC - Chasse … | CO3: WC - Chasse … | CS3: Lavabo | CW3: Douches | CY3: Urinoirs - Chasse … | DD3: WC - Chasse … | DI3: Lavabo | DN3: Lavabo | DT3: Douches | DX3: Douches | EC3: Urinoirs - Chasse … | EH3: Urinoirs - Chasse … | EN3: WC - Chasse … | ER3: WC - Chasse … | EX3: Tous produits | FB3: Lavabos | FE3: Douches | FH3: Urinoirs | FK3: WC | FN3: Fiabilité | FQ3: Hypothèses Rénovation | FS3: Global | FU3: Renovation | FW3: Neuf brut | GI3: Lavabos - Mitigeurs | GL3: Lavabos - Tempo. méca | GO3: Lavabos - Tempo. électro | GR3: Lavabos - Autres | GU3: Douches - Mitigeurs | GX3: Douches - Tempo. méca | HA3: Douches - Tempo. électro | HD3: Urinoirs - à Réservoir | HG3: Urinoirs - Directe méca. | HJ3: Urinoirs - Directe électro indiv. | HM3: Urinoirs - Directe électro collect. | HP3: WC - à Réservoir | HS3: WC - Directe méca. | HV3: WC - Directe électro | IB3: Volumes - Toutes Pièces | IH3: Volumes - Toutes Pièces | IK3: Fiabilité | IQ3: Lavabos | IV3: Lavabos | JA3: Douches | JF3: Douches | JK3: Urinoirs | JP3: Urinoirs | JU3: WC | JZ3: WC | KD3: Incertitude | KF3: Fiabilité
A4: ID | B4: Catégorie chapeau | C4: Segment Principal | D4: Sous-Segment | E4: Type ERP principal | F4: Type de classement | G4: ERP Hors ERP Mixte | H4: Accueil Public : oui/non variable | I4: Notes de classement | J4: Exemples | K4: Présence de sommeil (oui-non variable) | L4: Espaces sanitaires collectifs (WC et/ou douche) | M4: Unité de compte retenue | N4: Nature de la donnée | O4: Niveau de fiabilité | P4: Sous-catégorie incluse dans … | Q4: Inclure dans Total France (1/0) | R4: Surface moyenne 2026 (m²/étab.) | S4: 2000 | T4: 2005 | U4: 2010 | V4: 2015 | W4: 2016 | X4: 2017 | Y4: 2018 | Z4: 2019 | AA4: 2020 | AB4: 2021 | AC4: 2022 | AD4: 2023 | AE4: 2024 | AF4: 2025 | AG4: 2026 | AH4: 2027 | AI4: 2028 | AJ4: 2029 | AK4: 2030 | AL4: Justification Taille Parc & Evolution-Variation 2026-2030 | AM4: Calculs & Sources - Taille Parc & Evolution-Variation 2026-2030 | AN4: Sources (URL) | AP4: Capacité instantanée Moyenne 2026 TOTAL | AQ4: Capacité instantanée Moyenne 2026 Usagers Principaux | AR4: Capacité instantanée Moyenne 2026 Staff | AS4: Capacité instantanée Moyenne 2026 Autre Public | AU4: Dimensionnement sanitaire retenu par Etablissement Sanitaires collectifs >5 pers. Sanitaires individuels uniquement pour Univers Carcéral, Santé, EHPAD-USLD | AV4: Argumentaire détaillé (Dimensionnement unitaire + Hypothèse d'usage) | AW4: Pondération terrain / Hypothèse d’usage | AX4: Sources de dimensionnement (URL / références) | AZ4: Lavabos | BA4: Douches | BB4: Urinoirs | BC4: WC | BD4: TOTAL Pièces | BE4: TOTAL Lavabos | BF4: Douches | BG4: Urinoirs | BH4: WC | BI4: TOTAL Pièces | BJ4: TOTAL Lavabos | BK4: Douches | BL4: Urinoirs | BM4: WC | BO4: Mitigeurs | BP4: Tempo. Méca | BQ4: Tempo. Electro | BR4: Autres | BS4: Mitigeurs | BT4: Tempo. Méca | BU4: Tempo. Electro | BV4: Autres | BW4: Mitigeurs | BX4: Tempo. Méca | BY4: Tempo. Electro | BZ4: Mitigeurs | CA4: Tempo. Méca | CB4: Tempo. Electro | CC4: à Réservoir | CD4: Directe méca. | CE4: Directe electro indiv | CF4: Directe electro collect. | CG4: à Réservoir | CH4: Directe méca. | CI4: Directe electro indiv | CJ4: Directe electro collect. | CK4: à Réservoir | CL4: Directe mécanique | CM4: Directe electro | CN4: à Réservoir | CO4: Directe mécanique | CP4: Directe electro | CR4: Mitigeurs | CS4: Tempo. Méca | CT4: Tempo. Electro | CU4: Autres | CV4: Mitigeurs | CW4: Tempo. Méca | CX4: Tempo. Electro | CY4: à Réservoir | CZ4: Directe méca. | DA4: Directe electro indiv | DB4: Directe electro collect. | DC4: à Réservoir | DD4: Directe mécanique | DE4: Directe electro | DF4: Justification Durée de Vie réelle | DH4: Mitigeurs | DI4: Tempo. Méca | DJ4: Tempo. Electro | DK4: Autres | DL4: Justification Mix Lavabos 2025 | DM4: Mitigeurs | DN4: Tempo. Méca | DO4: Tempo. Electro | DP4: Autres | DQ4: Évolution Lavabos 2025 → 2030 | DS4: Mitigeurs | DT4: Tempo. Méca | DU4: Tempo. Electro | DV4: Justification Mix Douches 2025 | DW4: Mitigeurs | DX4: Tempo. Méca | DY4: Tempo. Electro | DZ4: Évolution Douches 2025 → 2030 | EB4: à Réservoir | EC4: Directe méca. | ED4: Directe electro indiv | EE4: Directe electro collect. | EF4: Justification Mix Urinoirs 2025 | EG4: à Réservoir | EH4: Directe méca. | EI4: Directe electro indiv | EJ4: Directe electro collect. | EK4: Évolution Urinoirs 2025 → 2030 | EM4: à Réservoir | EN4: Directe méca. | EO4: Directe electro | EP4: Justification Mix WC 2025 | EQ4: à Réservoir | ER4: Directe méca. | ES4: Directe electro | ET4: Évolution WC 2025→2030 | EV4: Split Rénovation % | EW4: Split Neuf % | EX4: Total | EY4: Rénovation | EZ4: Neuf brut | FA4: Total | FB4: Rénovation | FC4: Neuf brut | FD4: Total | FE4: Rénovation | FF4: Neuf brut | FG4: Total | FH4: Rénovation | FI4: Neuf brut | FJ4: Total | FK4: Rénovation | FL4: Neuf brut | FN4: Split % Rénovation vs. Neuf | FO4: Hypothèse % Parc 2025 rénové | FP4: Hypothèse % Réalisat° Travaux Réno | FQ4: Justification % Réalisation | FS4: Score Global (sur 5) | FT4: Classement Global sur 147 sous-segm. | FU4: Score Renovation (sur 5) | FV4: Classement sur 103 Sous-Segments | FW4: Score Neuf brut (sur 5) | FX4: Classement sur 103 Sous-Segments | FZ4: Rénovation Potentiel 2026-2030 | GA4: Neuf Potentiel 2026-2030 | GB4: Rénovation Projets Phares Programmes & Exemples 2026-2030 | GC4: Neuf Projets Phares Programmes & Exemples 2026-2030 | GD4: Rénovation Dynamique & Menaces 2026-2030 | GE4: Neuf Dynamique & Menaces 2026-2030 | GF4: Neuf & Rénovation Ventes - Dynamique & Menaces Sources & URL 2026-2030 | GH4: Total | GI4: Rénovation | GJ4: Neuf brut | GK4: Total | GL4: Rénovation | GM4: Neuf brut | GN4: Total | GO4: Rénovation | GP4: Neuf brut | GQ4: Total | GR4: Rénovation | GS4: Neuf brut | GT4: Total | GU4: Rénovation | GV4: Neuf brut | GW4: Total | GX4: Rénovation | GY4: Neuf brut | GZ4: Total | HA4: Rénovation | HB4: Neuf brut | HC4: Total | HD4: Rénovation | HE4: Neuf brut | HF4: Total | HG4: Rénovation | HH4: Neuf brut | HI4: Total | HJ4: Rénovation | HK4: Neuf brut | HL4: Total | HM4: Rénovation | HN4: Neuf brut | HO4: Total | HP4: Rénovation | HQ4: Neuf brut | HR4: Total | HS4: Rénovation | HT4: Neuf brut | HU4: Total | HV4: Rénovation | HW4: Neuf brut | HY4: Total Volumes Parc 2025 | HZ4: Entrée | IA4: Basique | IB4: Moyen | IC4: Premium | ID4: Luxe | IE4: Total Volumes Ventes 2026-2030 | IF4: Entrée | IG4: Basique | IH4: Moyen | II4: Premium | IJ4: Luxe | IK4: Score Global (sur 5) | IL4: Appréciation | IM4: Segmentation par Niveau de Confort Commentaires | IO4: Entrée | IP4: Basique | IQ4: Moyen | IR4: Premium | IS4: Luxe | IT4: Entrée | IU4: Basique | IV4: Moyen | IW4: Premium | IX4: Luxe | IY4: Entrée | IZ4: Basique | JA4: Moyen | JB4: Premium | JC4: Luxe | JD4: Entrée | JE4: Basique | JF4: Moyen | JG4: Premium | JH4: Luxe | JI4: Entrée | JJ4: Basique | JK4: Moyen | JL4: Premium | JM4: Luxe | JN4: Entrée | JO4: Basique | JP4: Moyen | JQ4: Premium | JR4: Luxe | JS4: Entrée | JT4: Basique | JU4: Moyen | JV4: Premium | JW4: Luxe | JX4: Entrée | JY4: Basique | JZ4: Moyen | KA4: Premium | KB4: Luxe | KD4: Parc | KE4: Ventes 2026-2030 | KF4: Score Global (sur 5) | KG4: Appréciation | KH4: Drivers Parc existant | KI4: Tendances Ventes 2026-2030 | KJ4: Drivers Ventes 2026-2030
A5: - | B5: - | C5: - | D5: - | E5: - | F5: - | G5: - | H5: - | I5: - | J5: - | K5: - | L5: - | M5: - | N5: - | O5: - | P5: - | Q5: - | R5: - | S5: - | T5: - | U5: - | V5: - | W5: - | X5: - | Y5: - | Z5: - | AA5: - | AB5: - | AC5: - | AD5: - | AE5: - | AF5: - | AG5: - | AH5: - | AI5: - | AJ5: - | AK5: - | AL5: - | AM5: - | AN5: - | AP5: - | AQ5: - | AR5: - | AS5: - | AU5: - | AV5: - | AW5: - | AX5: - | AZ5: - | BA5: - | BB5: - | BC5: - | BE5: - | BF5: - | BG5: - | BH5: - | BJ5: - | BK5: - | BL5: - | BM5: - | BO5: - | BP5: - | BQ5: - | BR5: - | BS5: - | BT5: - | BU5: - | BV5: - | BW5: - | BX5: - | BY5: - | BZ5: - | CA5: - | CB5: - | CC5: - | CD5: - | CE5: - | CF5: - | CG5: - | CH5: - | CI5: - | CJ5: - | CK5: - | CL5: - | CM5: - | CN5: - | CO5: - | CP5: - | CR5: - | CS5: - | CT5: - | CU5: - | CV5: - | CW5: - | CX5: - | CY5: - | CZ5: - | DA5: - | DB5: - | DC5: - | DD5: - | DE5: - | DF5: - | DH5: - | DI5: - | DJ5: - | DK5: - | DL5: - | DM5: - | DN5: - | DO5: - | DP5: - | DQ5: - | DS5: - | DT5: - | DU5: - | DV5: - | DW5: - | DX5: - | DY5: - | DZ5: - | EB5: - | EC5: - | ED5: - | EE5: - | EF5: - | EG5: - | EH5: - | EI5: - | EJ5: - | EK5: - | EM5: - | EN5: - | EO5: - | EP5: - | EQ5: - | ER5: - | ES5: - | ET5: - | EV5: - | EW5: - | EX5: - | EY5: - | EZ5: - | FA5: - | FB5: - | FC5: - | FD5: - | FE5: - | FF5: - | FG5: - | FH5: - | FI5: - | FJ5: - | FK5: - | FL5: - | FN5: - | FO5: - | FP5: - | FQ5: - | FS5: - | FT5: - | FU5: - | FV5: - | FW5: - | FX5: - | FZ5: - | GA5: - | GB5: - | GC5: - | GD5: - | GE5: - | GF5: - | GH5: - | GI5: - | GJ5: - | GK5: - | GL5: - | GM5: - | GN5: - | GO5: - | GP5: - | GQ5: - | GR5: - | GS5: - | GT5: - | GU5: - | GV5: - | GW5: - | GX5: - | GY5: - | GZ5: - | HA5: - | HB5: - | HC5: - | HD5: - | HE5: - | HF5: - | HG5: - | HH5: - | HI5: - | HJ5: - | HK5: - | HL5: - | HM5: - | HN5: - | HO5: - | HP5: - | HQ5: - | HR5: - | HS5: - | HT5: - | HU5: - | HV5: - | HW5: - | HY5: - | HZ5: - | IA5: - | IB5: - | IC5: - | ID5: - | IE5: - | IF5: - | IG5: - | IH5: - | II5: - | IJ5: - | IK5: - | IL5: - | IM5: - | IO5: - | IP5: - | IQ5: - | IR5: - | IS5: - | IT5: - | IU5: - | IV5: - | IW5: - | IX5: - | IY5: - | IZ5: - | JA5: - | JB5: - | JC5: - | JD5: - | JE5: - | JF5: - | JG5: - | JH5: - | JI5: - | JJ5: - | JK5: - | JL5: - | JM5: - | JN5: - | JO5: - | JP5: - | JQ5: - | JR5: - | JS5: - | JT5: - | JU5: - | JV5: - | JW5: - | JX5: - | JY5: - | JZ5: - | KA5: - | KB5: - | KD5: - | KE5: - | KF5: - | KG5: - | KH5: - | KI5: - | KJ5: -
C6: TOTAL (Etablissements dotés de sanitaires) | Q6: Total additionne lignes = 1 | R6: 2459.1609 | S6: 565272 | T6: 581449 | U6: 597349 | V6: 614886 | W6: 617900 | X6: 620576 | Y6: 624783 | Z6: 628795 | AA6: 620409 | AB6: 620075 | AC6: 626768 | AD6: 631586 | AE6: 636661 | AF6: 638960 | AG6: 640919 | AH6: 643045 | AI6: 644975 | AJ6: 646524 | AK6: 647940 | AP6: 153.69949 | AQ6: 135.28077 | AR6: 18.072976 | AS6: 5.503625 | AU6: Moyenne pondérée / total France | AV6: Synthèse pondérée France : sanitaires collectifs >5 pers., hors individuels sauf EHPAD/USLD. | AW6: Méthode : partir d’1 minimum sanitaire réaliste, ajusté selon taille, fréquentat° probable, puis appliquer 1 moyenne pondérée terrain (éviter qu’1 cas extrême biaise le sous-segment). Enfin, correct° selon intensité d’usage : passage court, usage quotidien, activité salissante, sport, soins, etc. | AX6: Références réglementaires, guides sectoriels et hypothèses de programmation utilisés pour le programme sanitaire unitaire. | AZ6: 9.9092186 | BA6: 2.7928842 | BB6: 1.6893713 | BC6: 8.07789 | BD6: 14135454 | BE6: 6233879.5 | BF6: 1757000.7 | BG6: 1062781.8 | BH6: 5081792.5 | BI6: 14272046 | BJ6: 6286026 | BK6: 1785842.1 | BL6: 1076541.8 | BM6: 5123636 | BO6: 0.29347467 | BP6: 0.55310218 | BQ6: 0.090947093 | BR6: 0.062476062 | BS6: 0.26362949 | BT6: 0.55885723 | BU6: 0.12087746 | BV6: 0.056635824 | BW6: 0.41385698 | BX6: 0.52808505 | BY6: 0.058057969 | BZ6: 0.37053944 | CA6: 0.55537764 | CB6: 0.074082915 | CC6: 0.087658912 | CD6: 0.55163276 | CE6: 0.11869938 | CF6: 0.24200895 | CG6: 0.072051819 | CH6: 0.5514006 | CI6: 0.1445451 | CJ6: 0.23200247 | CK6: 0.56671172 | CL6: 0.33220462 | CM6: 0.10108366 | CN6: 0.484449 | CO6: 0.36720729 | CP6: 0.14834372 | CR6: 12.426523 | CS6: 12.436186 | CT6: 9.0251239 | CU6: 10.896039 | CV6: 11.170059 | CW6: 9.6816619 | CX6: 8.0591967 | CY6: 10.149214 | CZ6: 12.075347 | DA6: 8.4200242 | DB6: 10.089803 | DC6: 12.474018 | DD6: 12.52315 | DE6: 9.1658181 | DF6: La durée de vie réelle dépend surtout de l’usage, de la maintenance, du vandalisme et du mode de rénovation, plus que de la durée théorique fabricant. Plus courte dans les sites à fort trafic ou à fortes contraintes d’hygiène, plus longue dans les environnements plus calmes. Les équipements mécaniques robustes tiennent souvent bien dans les usages intensifs, tandis que les solutions électroniques peuvent être renouvelées plus tôt pour raisons de capteurs, batteries, électrovannes ou modernisation. Part importante des remplacements se fait par lots ou lors de rénovations, pas seulement à la panne. | DH6: 1829485.7 | DI6: 3447972.3 | DJ6: 566953.22 | DK6: 389468.24 | DL6: La temporisation mécanique reste structurante dans les parcs intensifs ; la bascule 2025→2030 se fait surtout au profit de l'électronique sur les rénovations lourdes et les bâtiments tertiaires/publics. | DM6: 1657181.8 | DN6: 3512991.1 | DO6: 759838.84 | DP6: 356014.26 | DQ6: Dominant, le mitigeur recule, à chaque rénovation prévue et en neuf. Le tempo méca. résiste bien (vs. électro=> budget, installat°, entretien), mais électronique remplace en grande majorité le mitigeur (à nuancer en fonction du type d'ERP). | DS6: 727147 | DT6: 927845.79 | DU6: 102007.89 | DV6: Parc dominé par le tempo. mécanique et distance en nombre les mitigeurs. Electronique 5 à 6 fois moins représenté (que mécanique) => usage plus long, détection moins fiable que lavabo, moins de confort thermique potentiel. | DW6: 661724.92 | DX6: 991816.75 | DY6: 132300.39 | DZ6: Hausse 'électronique plus graduelle (qu'en lavabo) et variable selon ERP (exemple : plus forte sur tertiaire, commerce, que sur univers carcéral). | EB6: 93162.296 | EC6: 586265.26 | ED6: 126151.54 | EE6: 257202.71 | EF6: Parc dominé par tempo méca : robustesse, simplicité, adaptation aux usages intensifs. Electronique progresse mais reste minoritaire, freinée par contraintes maintenance/coût. | EG6: 77566.791 | EH6: 593605.77 | EI6: 155608.84 | EJ6: 249760.35 | EK6: Part temporisé électro. augmente légèrement => enjeux hygiène sans contact + maîtrise de conso. eau. Mécanique recule légèrement mais reste majoritaire => fiabilité en usage intensif. | EM6: 2879911.4 | EN6: 1688194.9 | EO6: 513686.17 | EP6: Parc WC repose surtout sur systèmes gravitaires, mécaniques, robustes, économiques, faciles à maintenir. Electronique secondaire mais présent dans lieux premium ou à forte exigence sanitaire. | EQ6: 2482140.3 | ER6: 1881436.5 | ES6: 760059.2 | ET6: Electronique gagne du terrain, surtout sur ERP récents-rénovés => exigences hygiène + automatisation => Progression faible : solutions méca conservent avantage coût/fiabilité. | EV6: 0.79594964 | EW6: 0.20405036 | EX6: 5821049.3 | EY6: 4633262.1 | EZ6: 1187787.2 | FA6: 2501271.8 | FB6: 1987652.9 | FC6: 513618.91 | FD6: 862826.07 | FE6: 697568.46 | FF6: 165257.61 | FG6: 451286.19 | FH6: 360063.11 | FI6: 91223.077 | FJ6: 2005665.2 | FK6: 1587977.6 | FL6: 417687.61 | FN6: Agrégat Pondéré | FO6: 0.060675716 | FP6: 0.82880687 | FQ6: Taux moyen pondéré France de matérialisation des travaux sur 2026-2030. | FS6: 3.19 | FT6: - | FU6: 3.97 | FV6: - | FW6: 2.24 | FX6: - | FZ6: La rénovation domine et reste plus résiliente que le neuf, dépendant moins de créations nettes d’établissements que de cycles de remplacement incompressibles, de remises à niveau d’hygiène/usage et de travaux diffus sur un parc installé très vaste et largement assujetti à des cycles de remplacement / mise à niveau. Sous-segments phares => Restaurants, EHPAD, Bureaux >50 pers., Écoles primaires, Gymnases, Salles multisports et Mairies. | GA6: Neuf plus sélectif, dépendant des cycles économiques, porté par créations d’établissements + programmes publics-privés (santé, sport, France services, industrie, carcéral, aéroports). Rythme plus volatil, concentré sur projets structurants. Sous-segments phares en neuf => Bureaux, EHPAD, Hôtels, Enseignement supérieur, Santé, Equipements sportifs. | GB6: Fonds vert / EduRénov ; Modernisation Hôpitaux (Ségur phase 2), Plan CNSA (réhab. EHPAD ; Normes accessibilité (Ad’AP)), Réno 5000 équipements sportifs (JO héritage) ; Loi de Programmation Militaire ; Transformation tertiaire ESG, France services. | GC6: Prison : plan 15 000 places, Grands projets touristiques (resorts, parcs), Nouveaux hôpitaux + CHU (reconstructions), Cliniques privées + Pôles santé, Maisons de santé pluriprofessionnelles, Campus universitaires, Learning centers, Nouveaux terminaux aéroport, Logistique, entrepôts. | GD6: Soutenue par décret Éco Énergie Tertiaire (EET) + Age avancé du parc + Logiques d’interventions par lots (sanitaires dans projets + larges : énergie, accessibilité, mise normes). Socle Investissements publics stable + Obligations réglementaires progressives => Marché résilient, diffus, peu dépendant de cycles économiques courts | GE6: Dynamique positive, concentrée sur filières motrices (santé, enseignement sup, segments tertiaires). Forte dépendance : arbitrage budget public, décision invest. privé. Sensible => cycles éco, condit° financement, délais réalisat°. Ecart fréquent intentions vs. livraisons réelles => croissance + volatile - homogène, ciblée géographiquement | GF6: https://www.ecologie.gouv.fr/eco-energie-tertiaire-eet https://www.info.gouv.fr/actualite/segur-de-la-sante-de-nouveaux-investissements-pour-l-hopital https://www.cnsa.fr/budget-et-financement/financement-des-esms/investissement-immobilier https://www.agencedusport.fr/plan-5000-equipements-generation-2024 https://www.france-services.gouv.fr/actualites/labellisation-nouvelles-maisons-france-services https://www.justice.gouv.fr/plan-15-000-places-prison https://www.defense.gouv.fr/ministere/politique-defense/loi-programmation-militaire-2024-2030 https://www.economie.gouv.fr/cedef/reindustrialisation-informations https://presse.groupeadp.fr/proposition-cre2027-2034/ https://www.garesetconnexions.sncf/fr/qui-sommes-nous/notre-modele-economique | GH6: 703546.04 | GI6: 576270.71 | GJ6: 127275.33 | GK6: 1315637.7 | GL6: 1024124.4 | GM6: 291513.26 | GN6: 310328.85 | GO6: 245464.56 | GP6: 64864.283 | GQ6: 171759.21 | GR6: 141793.16 | GS6: 29966.045 | GT6: 331189.47 | GU6: 271650.49 | GV6: 59538.982 | GW6: 472158.1 | GX6: 378940.83 | GY6: 93217.269 | GZ6: 59478.5 | HA6: 46977.145 | HB6: 12501.355 | HC6: 39711.426 | HD6: 33444.328 | HE6: 6267.0977 | HF6: 227932.93 | HG6: 177829.86 | HH6: 50103.07 | HI6: 69612.421 | HJ6: 55617.713 | HK6: 13994.708 | HL6: 114029.42 | HM6: 93171.215 | HN6: 20858.201 | HO6: 1055388.4 | HP6: 860683.44 | HQ6: 194705 | HR6: 662715.51 | HS6: 503979.11 | HT6: 158736.4 | HU6: 287561.26 | HV6: 223315.05 | HW6: 64246.205 | HY6: 14135454 | HZ6: 865403.9 | IA6: 5140157.6 | IB6: 5839913 | IC6: 2040655.4 | ID6: 249324.51 | IE6: 4633262.1 | IF6: 120886.16 | IG6: 1189421.2 | IH6: 2105519.2 | II6: 1040079.9 | IJ6: 177355.61 | IK6: 3.86 | IL6: Bonne | IO6: 0.0507 | IP6: 0.3489 | IQ6: 0.4319 | IR6: 0.1497 | IS6: 0.0188 | IT6: 0.02 | IU6: 0.2326 | IV6: 0.4683 | IW6: 0.2376 | IX6: 0.0415 | IY6: 0.072 | IZ6: 0.3519 | JA6: 0.384 | JB6: 0.1679 | JC6: 0.0242 | JD6: 0.0355 | JE6: 0.2767 | JF6: 0.4095 | JG6: 0.2317 | JH6: 0.0466 | JI6: 0.1234 | JJ6: 0.4706 | JK6: 0.3199 | JL6: 0.0759 | JM6: 0.0102 | JN6: 0.056 | JO6: 0.3741 | JP6: 0.4166 | JQ6: 0.1327 | JR6: 0.0206 | JS6: 0.0574 | JT6: 0.3634 | JU6: 0.4197 | JV6: 0.144 | JW6: 0.0155 | JX6: 0.0228 | JY6: 0.2515 | JZ6: 0.4654 | KA6: 0.2257 | KB6: 0.0346 | KD6: ±4 pts | KE6: ±5 pts | KF6: 4.15 | KG6: Bonne | KH6: Agrégation volume × mix par sous-segment ; les gros gisements (bureaux, écoles, santé, sport, hôtels, transports) pèsent davantage dans le total que les niches. | KI6: Total France pondéré par volumes 2025 et ventes 2026-2030 ; forte fréquentation tire le standard, image/privé tire premium, contrainte sanitaire renforce surtout le milieu de gamme technique. | KJ6: Agrégation volume × ventes 2026-2030 ; le neuf et les rénovations lourdes tirent le mix vers l’moyen/premium, mais la rénovation majoritaire garde un centre de gravité basique/moyen.
B7: TOTAL | C7: TERITAIRE (ci-dessous) | Q7: Total additionne lignes = 1 | R7: =IFERROR(SUMPRODUCT($Q$16:$Q$17,$AG$16:$AG$17,R$16:R$17)/SUMPRODUCT($Q$16:$Q$17,$AG$16:$AG$17),"") -> 22400.881 | S7: =SUMPRODUCT($Q$16:$Q$17,S$16:S$17) -> 1150 | T7: =SUMPRODUCT($Q$16:$Q$17,T$16:T$17) -> 1180 | U7: =SUMPRODUCT($Q$16:$Q$17,U$16:U$17) -> 1210 | V7: =SUMPRODUCT($Q$16:$Q$17,V$16:V$17) -> 1245 | W7: =SUMPRODUCT($Q$16:$Q$17,W$16:W$17) -> 1260 | X7: =SUMPRODUCT($Q$16:$Q$17,X$16:X$17) -> 1275 | Y7: =SUMPRODUCT($Q$16:$Q$17,Y$16:Y$17) -> 1290 | Z7: =SUMPRODUCT($Q$16:$Q$17,Z$16:Z$17) -> 1305 | ... AE7: =SUMPRODUCT($Q$16:$Q$17,AE$16:AE$17) -> 1344 | AF7: =SUM(AF9:AF17) -> 94469 | AG7: =SUMPRODUCT($Q$16:$Q$17,AG$16:AG$17) -> 1362 | AH7: =SUMPRODUCT($Q$16:$Q$17,AH$16:AH$17) -> 1372 | AI7: =SUMPRODUCT($Q$16:$Q$17,AI$16:AI$17) -> 1382 | AJ7: =SUMPRODUCT($Q$16:$Q$17,AJ$16:AJ$17) -> 1392 | AK7: =SUM(AK9:AK17) -> 94614 | AP7: =IFERROR(SUMPRODUCT($Q$16:$Q$17,$AG$16:$AG$17,AP$16:AP$17)/SUMPRODUCT($Q$16:$Q$17,$AG$16:$AG$17),"") -> 2298.2379 | AQ7: =IFERROR(SUMPRODUCT($Q$16:$Q$17,$AF$16:$AF$17,AQ$16:AQ$17)/SUMPRODUCT($Q$16:$Q$17,$AF$16:$AF$17),"") -> 1886.1538 | AR7: =IFERROR(SUMPRODUCT($Q$16:$Q$17,$AF$16:$AF$17,AR$16:AR$17)/SUMPRODUCT($Q$16:$Q$17,$AF$16:$AF$17),"") -> 300 | AS7: =IFERROR(SUMPRODUCT($Q$16:$Q$17,$AF$16:$AF$17,AS$16:AS$17)/SUMPRODUCT($Q$16:$Q$17,$AF$16:$AF$17),"") -> 121.53846 | AU7: Moyenne pondérée / total France | AV7: Synthèse pondérée France : sanitaires collectifs >5 pers., hors individuels sauf EHPAD/USLD. | AW7: Méthode : partir d’1 minimum sanitaire réaliste, ajusté selon taille, fréquentat° probable, puis appliquer 1 moyenne pondérée terrain (éviter qu’1 cas extrême biaise le sous-segment). Enfin, correct° selon intensité d’usage : passage court, usage quotidien, activité salissante, sport, soins, etc. | AX7: Références réglementaires, guides sectoriels et hypothèses de programmation utilisés pour le programme sanitaire unitaire. | AZ7: =IFERROR(SUMPRODUCT($Q$16:$Q$17,$AF$16:$AF$17,AZ$16:AZ$17)/SUMPRODUCT($Q$16:$Q$17,$AF$16:$AF$17),"") -> 53.076923 | BA7: =IFERROR(SUMPRODUCT($Q$16:$Q$17,$AF$16:$AF$17,BA$16:BA$17)/SUMPRODUCT($Q$16:$Q$17,$AF$16:$AF$17),"") -> 2.4615385 | BB7: =IFERROR(SUMPRODUCT($Q$16:$Q$17,$AF$16:$AF$17,BB$16:BB$17)/SUMPRODUCT($Q$16:$Q$17,$AF$16:$AF$17),"") -> 11.846154 | BC7: =IFERROR(SUMPRODUCT($Q$16:$Q$17,$AF$16:$AF$17,BC$16:BC$17)/SUMPRODUCT($Q$16:$Q$17,$AF$16:$AF$17),"") -> 49.615385 | BD7: =SUM(BE7:BH7) -> 1398497 | BE7: =SUM(BE9:BE17) -> 1312073 | BF7: =SUMPRODUCT($Q$16:$Q$17,BF$16:BF$17) -> 3328 | BG7: =SUMPRODUCT($Q$16:$Q$17,BG$16:BG$17) -> 16016 | BH7: =SUMPRODUCT($Q$16:$Q$17,BH$16:BH$17) -> 67080 | BI7: =SUM(BJ7:BM7) -> 1403350 | BJ7: =SUM(BJ9:BJ17) -> 1315225 | BK7: =SUMPRODUCT($Q$16:$Q$17,BK$16:BK$17) -> 3380 | BL7: =SUMPRODUCT($Q$16:$Q$17,BL$16:BL$17) -> 16330 | BM7: =SUMPRODUCT($Q$16:$Q$17,BM$16:BM$17) -> 68415 | BO7: =DH7/$BE7 -> 0.41255101 | BP7: =DI7/$BE7 -> 0.38172798 | BQ7: =DJ7/$BE7 -> 0.15714024 | BR7: =DK7/$BE7 -> 0.048580773 | BS7: =DM7/$BJ7 -> 0.35908327 | BT7: =DN7/$BJ7 -> 0.38969085 | BU7: =DO7/$BJ7 -> 0.21378061 | BV7: =DP7/$BJ7 -> 0.037445266 | BW7: =DS7/$BF7 -> 0.45 | BX7: =DT7/$BF7 -> 0.45 | BY7: =DU7/$BF7 -> 0.1 | BZ7: =DW7/$BK7 -> 0.4 | CA7: =DX7/$BK7 -> 0.47 | CB7: =DY7/$BK7 -> 0.13 | CC7: =EB7/$BG7 -> 0.10324675 | CD7: =EC7/$BG7 -> 0.55 | CE7: =ED7/$BG7 -> 0.1 | CF7: =EE7/$BG7 -> 0.24675325 | CG7: =EG7/$BL7 -> 0.083429271 | CH7: =EH7/$BL7 -> 0.55 | CI7: =EI7/$BL7 -> 0.12931415 | CJ7: =EJ7/$BL7 -> 0.23725658 | CK7: =EM7/$BH7 -> 0.50348837 | CL7: =EN7/$BH7 -> 0.34651163 | CM7: =EO7/$BH7 -> 0.15 | CN7: =EQ7/$BM7 -> 0.4036834 | CO7: =ER7/$BM7 -> 0.39484324 | CP7: =ES7/$BM7 -> 0.20147336 | CR7: =IFERROR(SUMPRODUCT(DH$16:DH$17,CR$16:CR$17)/SUM(DH$16:DH$17),"") -> 10.815603 | CS7: =IFERROR(SUMPRODUCT(DI$16:DI$17,CS$16:CS$17)/SUM(DI$16:DI$17),"") -> 11.933549 | CT7: =IFERROR(SUMPRODUCT(DJ$16:DJ$17,CT$16:CT$17)/SUM(DJ$16:DJ$17),"") -> 8 | CU7: =IFERROR(SUMPRODUCT(DK$16:DK$17,CU$16:CU$17)/SUM(DK$16:DK$17),"") -> 9.9275362 | CV7: =IFERROR(SUMPRODUCT(DS$16:DS$17,CV$16:CV$17)/SUM(DS$16:DS$17),"") -> 10 | CW7: =IFERROR(SUMPRODUCT(DT$16:DT$17,CW$16:CW$17)/SUM(DT$16:DT$17),"") -> 9 | CX7: =IFERROR(SUMPRODUCT(DU$16:DU$17,CX$16:CX$17)/SUM(DU$16:DU$17),"") -> 7 | CY7: =IFERROR(SUMPRODUCT(EB$16:EB$17,CY$16:CY$17)/SUM(EB$16:EB$17),"") -> 8.9056604 | CZ7: =IFERROR(SUMPRODUCT(EC$16:EC$17,CZ$16:CZ$17)/SUM(EC$16:EC$17),"") -> 11 | DA7: =IFERROR(SUMPRODUCT(ED$16:ED$17,DA$16:DA$17)/SUM(ED$16:ED$17),"") -> 7.0649351 | DB7: =IFERROR(SUMPRODUCT(EE$16:EE$17,DB$16:DB$17)/SUM(EE$16:EE$17),"") -> 9 | DC7: =IFERROR(SUMPRODUCT(EM$16:EM$17,DC$16:DC$17)/SUM(EM$16:EM$17),"") -> 11.771363 | DD7: =IFERROR(SUMPRODUCT(EN$16:EN$17,DD$16:DD$17)/SUM(EN$16:EN$17),"") -> 12 | DE7: =IFERROR(SUMPRODUCT(EO$16:EO$17,DE$16:DE$17)/SUM(EO$16:EO$17),"") -> 8.0697674 | DF7: La durée de vie réelle dépend surtout de l’usage, de la maintenance, du vandalisme et du mode de rénovation, plus que de la durée théorique fabricant. Plus courte dans les sites à fort trafic ou à fortes contraintes d’hygiène, plus longue dans les environnements plus calmes. Les équipements mécaniques robustes tiennent souvent bien dans les usages intensifs, tandis que les solutions électroniques peuvent être renouvelées plus tôt pour raisons de capteurs, batteries, électrovannes ou modernisation. Part importante des remplacements se fait par lots ou lors de rénovations, pas seulement à la panne. | DH7: =SUM(DH9:DH17) -> 541297.04 | DI7: =SUM(DI9:DI17) -> 500854.98 | DJ7: =SUM(DJ9:DJ17) -> 206179.46 | DK7: =SUM(DK9:DK17) -> 63741.52 | DM7: =SUM(DM9:DM17) -> 472275.3 | DN7: =SUM(DN9:DN17) -> 512531.15 | DO7: =SUM(DO9:DO17) -> 281169.6 | DP7: =SUM(DP9:DP17) -> 49248.95 | DS7: =SUMPRODUCT($Q$16:$Q$17,DS$16:DS$17) -> 1497.6 | DT7: =SUMPRODUCT($Q$16:$Q$17,DT$16:DT$17) -> 1497.6 | DU7: =SUMPRODUCT($Q$16:$Q$17,DU$16:DU$17) -> 332.8 | DV7: Parc dominé par le tempo. mécanique et distance en nombre les mitigeurs. Electronique 5 à 6 fois moins représenté (que mécanique) => usage plus long, détection moins fiable que lavabo, moins de confort thermique potentiel. | DW7: =SUMPRODUCT($Q$16:$Q$17,DW$16:DW$17) -> 1352 | DX7: =SUMPRODUCT($Q$16:$Q$17,DX$16:DX$17) -> 1588.6 | DY7: =SUMPRODUCT($Q$16:$Q$17,DY$16:DY$17) -> 439.4 | DZ7: Hausse 'électronique plus graduelle (qu'en lavabo) et variable selon ERP (exemple : plus forte sur tertiaire, commerce, que sur univers carcéral). | EB7: =SUMPRODUCT($Q$16:$Q$17,EB$16:EB$17) -> 1653.6 | EC7: =SUMPRODUCT($Q$16:$Q$17,EC$16:EC$17) -> 8808.8 | ED7: =SUMPRODUCT($Q$16:$Q$17,ED$16:ED$17) -> 1601.6 | EE7: =SUMPRODUCT($Q$16:$Q$17,EE$16:EE$17) -> 3952 | EF7: Parc dominé par tempo méca : robustesse, simplicité, adaptation aux usages intensifs. Electronique progresse mais reste minoritaire, freinée par contraintes maintenance/coût. | EG7: =SUMPRODUCT($Q$16:$Q$17,EG$16:EG$17) -> 1362.4 | EH7: =SUMPRODUCT($Q$16:$Q$17,EH$16:EH$17) -> 8981.5 | EI7: =SUMPRODUCT($Q$16:$Q$17,EI$16:EI$17) -> 2111.7 | EJ7: =SUMPRODUCT($Q$16:$Q$17,EJ$16:EJ$17) -> 3874.4 | EK7: Part temporisé électro. augmente légèrement => enjeux hygiène sans contact + maîtrise de conso. eau. Mécanique recule légèrement mais reste majoritaire => fiabilité en usage intensif. | EM7: =SUMPRODUCT($Q$16:$Q$17,EM$16:EM$17) -> 33774 | EN7: =SUMPRODUCT($Q$16:$Q$17,EN$16:EN$17) -> 23244 | EO7: =SUMPRODUCT($Q$16:$Q$17,EO$16:EO$17) -> 10062 | EP7: Parc WC repose surtout sur systèmes gravitaires, mécaniques, robustes, économiques, faciles à maintenir. Electronique secondaire mais présent dans lieux premium ou à forte exigence sanitaire. | EQ7: =SUMPRODUCT($Q$16:$Q$17,EQ$16:EQ$17) -> 27618 | ER7: =SUMPRODUCT($Q$16:$Q$17,ER$16:ER$17) -> 27013.2 | ES7: =SUMPRODUCT($Q$16:$Q$17,ES$16:ES$17) -> 13783.8 | ET7: Electronique gagne du terrain, surtout sur ERP récents-rénovés => exigences hygiène + automatisation => Progression faible : solutions méca conservent avantage coût/fiabilité. | EV7: =IFERROR(EY7/EX7,0) -> 0.81992162 | EW7: =IFERROR(EZ7/EX7,0) -> 0.18007838 | EX7: =EY7+EZ7 -> 514869.48 | EY7: =SUM(FB7,FE7,FH7,FK7) -> 422152.61 | EZ7: =SUM(FC7,FF7,FI7,FL7) -> 92716.861 | FA7: =SUM(FA9:FA17) -> 476551.75 | FB7: =SUM(FB9:FB17) -> 390194.47 | FC7: =SUM(FC9:FC17) -> 86357.279 | FD7: =SUM(FD9:FD17) -> 54838.454 | FE7: =SUMPRODUCT($Q$16:$Q$17,FE$16:FE$17) -> 1453.9034 | FF7: =SUMPRODUCT($Q$16:$Q$17,FF$16:FF$17) -> 226.72 | FG7: =SUMPRODUCT($Q$16:$Q$17,FG$16:FG$17) -> 7757.7818 | FH7: =SUMPRODUCT($Q$16:$Q$17,FH$16:FH$17) -> 6580.8834 | FI7: =SUMPRODUCT($Q$16:$Q$17,FI$16:FI$17) -> 1176.8984 | FJ7: =SUMPRODUCT($Q$16:$Q$17,FJ$16:FJ$17) -> 28879.319 | FK7: =SUMPRODUCT($Q$16:$Q$17,FK$16:FK$17) -> 23923.356 | FL7: =SUMPRODUCT($Q$16:$Q$17,FL$16:FL$17) -> 4955.9628 | FN7: Agrégat Pondéré | FO7: =IFERROR(SUMPRODUCT($Q$16:$Q$17,$AF$16:$AF$17,$FO$16:$FO$17)/SUMPRODUCT($Q$16:$Q$17,$AF$16:$AF$17),"") -> 0.060657692 | FP7: =IFERROR(SUMPRODUCT($Q$16:$Q$17,$AF$16:$AF$17,$FP$16:$FP$17)/SUMPRODUCT($Q$16:$Q$17,$AF$16:$AF$17),"") -> 0.82671538 | FQ7: Taux moyen pondéré France de matérialisation des travaux sur 2026-2030. | FS7: 3.19 | FT7: - | FU7: 3.97 | FV7: - | FW7: 2.24 | FX7: - | GF7: =HYPERLINK("https://www.ecologie.gouv.fr/eco-energie-tertiaire-eet","https://www.ecologie.gouv.fr/eco-energie-tertiaire-eet")&CHAR(10)&HYPERLINK("https://www.info.gouv.fr/actualite/segur-de-la-sante-de-nouveaux-investissements-pour-l-hopital","https://www.info.gouv.fr/actualite/segur-de-la-sante-de-nouveaux-investissements-pour-l-hopital")&CHAR(10)&HYPERLINK("https://www.cnsa.fr/budget-et-financement/financement-des-esms/investissement-immobilier","https://www.cnsa.fr/budget-et-financement/financement-des-esms/investissement-immobilier")&CHAR(10)&HYPERLINK("https://www.agencedusport.fr/plan-5000-equipements-generation-2024","https://www.agencedusport.fr/plan-5000-equipements-generation-2024")&CHAR(10)&HYPERLINK("https://www.france-services.gouv.fr/actualites/labellisation-nouvelles-maisons-france-services","https://www.france-services.gouv.fr/actualites/labellisation-nouvelles-maisons-france-services")&CHAR(10)&HYPERLINK("https://www.justice.gouv.fr/plan-15-000-places-prison","https://www.justice.gouv.fr/plan-15-000-places-prison")&CHAR(10)&HYPERLINK("https://www.defense.gouv.fr/ministere/politique-defense/loi-programmation-militaire-2024-2030","https://www.defense.gouv.fr/ministere/politique-defense/loi-programmation-militaire-2024-2030")&CHAR(10)&HYPERLINK("https://www.economie.gouv.fr/cedef/reindustrialisation-informations","https://www.economie.gouv.fr/cedef/reindustrialisation-informations")&CHAR(10)&HYPERLINK("https://presse.groupeadp.fr/proposition-cre2027-2034/","https://presse.groupeadp.fr/proposition-cre2027-2034/")&CHAR(10)&HYPERLINK("https://www.garesetconnexions.sncf/fr/qui-sommes-nous/notre-modele-economique","https://www.garesetconnexions.sncf/fr/qui-sommes-nous/notre-modele-economique") -> https://www.ecologie.gouv.fr/eco-energie-tertiaire-eet https://www.info.gouv.fr/actualite/segur-de-la-sante-de-nouveaux-investissements-pour-l-hopital https://www.cnsa.fr/budget-et-financement/financement-des-esms/investissement-immobilier https://www.agencedusport.fr/plan-5000-equipements-generation-2024 https://www.france-services.gouv.fr/actualites/labellisation-nouvelles-maisons-france-services https://www.justice.gouv.fr/plan-15-000-places-prison https://www.defense.gouv.fr/ministere/politique-defense/loi-programmation-militaire-2024-2030 https://www.economie.gouv.fr/cedef/reindustrialisation-informations https://presse.groupeadp.fr/proposition-cre2027-2034/ https://www.garesetconnexions.sncf/fr/qui-sommes-nous/notre-modele-economique | GH7: =SUM(GH9:GH17) -> 185836.81 | GI7: =SUM(GI9:GI17) -> 154462.69 | GJ7: =SUM(GJ9:GJ17) -> 31374.12 | GK7: =SUM(GK9:GK17) -> 168171.53 | GL7: =SUM(GL9:GL17) -> 133980.06 | GM7: =SUM(GM9:GM17) -> 34191.471 | GN7: =SUM(GN9:GN17) -> 99151.628 | GO7: =SUM(GO9:GO17) -> 81583.987 | ... GS7: =SUM(GS9:GS17) -> 3224.047 | GT7: =SUMPRODUCT($Q$16:$Q$17,GT$16:GT$17) -> 688.15111 | GU7: =SUMPRODUCT($Q$16:$Q$17,GU$16:GU$17) -> 597.46311 | GV7: =SUMPRODUCT($Q$16:$Q$17,GV$16:GV$17) -> 90.688 | GW7: =SUMPRODUCT($Q$16:$Q$17,GW$16:GW$17) -> 772.0294 | GX7: =SUMPRODUCT($Q$16:$Q$17,GX$16:GX$17) -> 665.471 | GY7: =SUMPRODUCT($Q$16:$Q$17,GY$16:GY$17) -> 106.5584 | GZ7: =SUMPRODUCT($Q$16:$Q$17,GZ$16:GZ$17) -> 220.44291 | HA7: =SUMPRODUCT($Q$16:$Q$17,HA$16:HA$17) -> 190.96931 | ... HW7: =SUMPRODUCT($Q$16:$Q$17,HW$16:HW$17) -> 1005.2918 | HY7: =SUM(HZ7:ID7) -> 1398497 | HZ7: =IFERROR(IO7*BE7,0)+IFERROR(IY7*BF7,0)+IFERROR(JI7*BG7,0)+IFERROR(JS7*BH7,0) -> 50401.462 | IA7: =IFERROR(IP7*BE7,0)+IFERROR(IZ7*BF7,0)+IFERROR(JJ7*BG7,0)+IFERROR(JT7*BH7,0) -> 555413.5 | IB7: =IFERROR(IQ7*BE7,0)+IFERROR(JA7*BF7,0)+IFERROR(JK7*BG7,0)+IFERROR(JU7*BH7,0) -> 674932.46 | IC7: =IFERROR(IR7*BE7,0)+IFERROR(JB7*BF7,0)+IFERROR(JL7*BG7,0)+IFERROR(JV7*BH7,0) -> 114374.5 | ID7: =IFERROR(IS7*BE7,0)+IFERROR(JC7*BF7,0)+IFERROR(JM7*BG7,0)+IFERROR(JW7*BH7,0) -> 3375.0808 | IE7: =SUM(IF7:IJ7) -> 422152.61 | IF7: =IFERROR(IT7*FB7,0)+IFERROR(JD7*FE7,0)+IFERROR(JN7*FH7,0)+IFERROR(JX7*FK7,0) -> 5979.7299 | IG7: =IFERROR(IU7*FB7,0)+IFERROR(JE7*FE7,0)+IFERROR(JO7*FH7,0)+IFERROR(JY7*FK7,0) -> 150099.05 | IH7: =IFERROR(IV7*FB7,0)+IFERROR(JF7*FE7,0)+IFERROR(JP7*FH7,0)+IFERROR(JZ7*FK7,0) -> 214559.12 | II7: =IFERROR(IW7*FB7,0)+IFERROR(JG7*FE7,0)+IFERROR(JQ7*FH7,0)+IFERROR(KA7*FK7,0) -> 47498.766 | IJ7: =IFERROR(IX7*FB7,0)+IFERROR(JH7*FE7,0)+IFERROR(JR7*FH7,0)+IFERROR(KB7*FK7,0) -> 4015.942 | IK7: 3.86 | IL7: Bonne | IO7: =SUMPRODUCT($BE$9:$BE$17,IO$9:IO$17)/SUM($BE$9:$BE$17) -> 0.033790102 | IP7: =SUMPRODUCT($BE$9:$BE$17,IP$9:IP$17)/SUM($BE$9:$BE$17) -> 0.39809399 | IQ7: =SUMPRODUCT($BE$9:$BE$17,IQ$9:IQ$17)/SUM($BE$9:$BE$17) -> 0.48806546 | IR7: =SUMPRODUCT($BE$9:$BE$17,IR$9:IR$17)/SUM($BE$9:$BE$17) -> 0.07845645 | IS7: =SUMPRODUCT($BE$9:$BE$17,IS$9:IS$17)/SUM($BE$9:$BE$17) -> 0.0015939967 | IT7: =SUMPRODUCT($FA$9:$FA$17,IT$9:IT$17)/SUM($FA$9:$FA$17) -> 0.012850347 | IU7: =SUMPRODUCT($FA$9:$FA$17,IU$9:IU$17)/SUM($FA$9:$FA$17) -> 0.36191729 | IV7: =SUMPRODUCT($FA$9:$FA$17,IV$9:IV$17)/SUM($FA$9:$FA$17) -> 0.51279103 | IW7: =SUMPRODUCT($FA$9:$FA$17,IW$9:IW$17)/SUM($FA$9:$FA$17) -> 0.10479162 | IX7: =SUMPRODUCT($FA$9:$FA$17,IX$9:IX$17)/SUM($FA$9:$FA$17) -> 0.0076497131 | IY7: 0.072 | IZ7: 0.3519 | JA7: 0.384 | JB7: 0.1679 | JC7: 0.0242 | JD7: 0.0355 | JE7: 0.2767 | JF7: 0.4095 | JG7: 0.2317 | JH7: 0.0466 | JI7: 0.1234 | JJ7: 0.4706 | JK7: 0.3199 | JL7: 0.0759 | JM7: 0.0102 | JN7: 0.056 | JO7: 0.3741 | JP7: 0.4166 | JQ7: 0.1327 | JR7: 0.0206 | JS7: 0.0574 | JT7: 0.3634 | JU7: 0.4197 | JV7: 0.144 | JW7: 0.0155 | JX7: 0.0228 | JY7: 0.2515 | JZ7: 0.4654 | KA7: 0.2257 | KB7: 0.0346 | KD7: ±4 pts | KE7: ±5 pts | KF7: 4.15 | KG7: Bonne | KH7: Agrégation volume × mix par sous-segment ; les gros gisements (bureaux, écoles, santé, sport, hôtels, transports) pèsent davantage dans le total que les niches. | KI7: Total France pondéré par volumes 2025 et ventes 2026-2030 ; forte fréquentation tire le standard, image/privé tire premium, contrainte sanitaire renforce surtout le milieu de gamme technique. | KJ7: Agrégation volume × ventes 2026-2030 ; le neuf et les rénovations lourdes tirent le mix vers l’moyen/premium, mais la rénovation majoritaire garde un centre de gravité basique/moyen.
J8: Evolution moyenne anuelle => | Q8: 0 = sous-catég. | S8: Variat° Annuelle en % => | T8: =(T7/S7)^(1/(T4-S4))-1 -> 0.0051637858 | U8: =(U7/T7)^(1/(U4-T4))-1 -> 0.0050338115 | V8: =(V7/U7)^(1/(V4-U4))-1 -> 0.0057193273 | W8: =W7/V7-1 -> 0.012048193 | X8: =X7/W7-1 -> 0.011904762 | Y8: =Y7/X7-1 -> 0.011764706 | Z8: =Z7/Y7-1 -> 0.011627907 | AA8: =AA7/Z7-1 -> 0.0038314176 | AB8: =AB7/AA7-1 -> 0.0045801527 | AC8: =AC7/AB7-1 -> 0.0083586626 | AD8: =AD7/AC7-1 -> 0.0067822155 | AE8: =AE7/AD7-1 -> 0.005988024 | AG8: =AG7/AF7-1 -> -0.98558257 | AH8: =AH7/AG7-1 -> 0.0073421439 | AI8: =AI7/AH7-1 -> 0.0072886297 | AJ8: =AJ7/AI7-1 -> 0.00723589 | AK8: =(AK7/AF7)^(1/(AK4-AF4))-1 -> 0.00030679071 | BH8: Variat° Annuelle en % => | BI8: =(BI7/BD7)^(1/(2030-2025))-1 -> 0.00069306945 | BJ8: =(BJ7/BE7)^(1/(2030-2025))-1 -> 0.00048000005 | BK8: =(BK7/BF7)^(1/(2030-2025))-1 -> 0.0031056499 | BL8: =(BL7/BG7)^(1/(2030-2025))-1 -> 0.003890686 | BM8: =(BM7/BH7)^(1/(2030-2025))-1 -> 0.0039490092 | DS8: =DS7/SUM(DS7:DU7) -> 0.45 | DT8: =DT7/SUM(DS7:DU7) -> 0.45 | DU8: =DU7/SUM(DS7:DU7) -> 0.1 | DV8: <= Split en % => | DW8: =DW7/SUM(DW7:DY7) -> 0.4 | DX8: =DX7/SUM(DW7:DY7) -> 0.47 | DY8: =DY7/SUM(DW7:DY7) -> 0.13 | EB8: =EB7/SUM(EB7:EE7) -> 0.10324675 | EC8: =EC7/SUM(EB7:EE7) -> 0.55 | ED8: =ED7/SUM(EB7:EE7) -> 0.1 | EE8: =EE7/SUM(EB7:EE7) -> 0.24675325 | EF8: <= Split en % => | EG8: =EG7/SUM(EG7:EJ7) -> 0.083429271 | EH8: =EH7/SUM(EG7:EJ7) -> 0.55 | EI8: =EI7/SUM(EG7:EJ7) -> 0.12931415 | EJ8: =EJ7/SUM(EG7:EJ7) -> 0.23725658 | EM8: =EM7/SUM(EL7:EO7) -> 0.50348837 | EN8: =EN7/SUM(EL7:EO7) -> 0.34651163 | EO8: =EO7/SUM(EL7:EO7) -> 0.15 | EP8: <= Split en % => | EQ8: =EQ7/SUM(EQ7:ES7) -> 0.4036834 | ER8: =ER7/SUM(EQ7:ES7) -> 0.39484324 | ES8: =ES7/SUM(EQ7:ES7) -> 0.20147336 | EX8: Split en % => | EY8: =EY7/EX7 -> 0.81992162 | EZ8: =EZ7/EX7 -> 0.18007838 | FB8: =FB7/FA7 -> 0.8187872 | FC8: =FC7/FA7 -> 0.1812128 | FE8: =FE7/FD7 -> 0.02651248 | FF8: =FF7/FD7 -> 0.0041343252 | FH8: =FH7/FG7 -> 0.84829447 | FI8: =FI7/FG7 -> 0.15170553 | FK8: =FK7/FJ7 -> 0.82839059 | FL8: =FL7/FJ7 -> 0.17160941 | GH8: Split en % => | GI8: =GI7/GH7 -> 0.83117381 | GJ8: =GJ7/GH7 -> 0.16882619 | GL8: =GL7/GK7 -> 0.79668692 | GM8: =GM7/GK7 -> 0.20331308 | GO8: =GO7/GN7 -> 0.82282045 | GP8: =GP7/GN7 -> 0.17717955 | GR8: =GR7/GQ7 -> 0.86217182 | GS8: =GS7/GQ7 -> 0.13782818 | GU8: =GU7/GT7 -> 0.86821499 | GV8: =GV7/GT7 -> 0.13178501 | GX8: =GX7/GW7 -> 0.86197624 | GY8: =GY7/GW7 -> 0.13802376 | HA8: =HA7/GZ7 -> 0.86629826 | HB8: =HB7/GZ7 -> 0.13370174 | HD8: =HD7/HC7 -> 0.87934458 | HE8: =HE7/HC7 -> 0.12065542 | HG8: =HG7/HF7 -> 0.83052373 | HH8: =HH7/HF7 -> 0.16947627 | HJ8: =HJ7/HI7 -> 0.85749882 | HK8: =HK7/HI7 -> 0.14250118 | HM8: =HM7/HL7 -> 0.86397878 | HN8: =HN7/HL7 -> 0.13602122 | HP8: =HP7/HO7 -> 0.84897404 | HQ8: =HQ7/HO7 -> 0.15102596 | HS8: =HS7/HR7 -> 0.79691071 | HT8: =HT7/HR7 -> 0.20308929 | HV8: =HV7/HU7 -> 0.83249713 | HW8: =HW7/HU7 -> 0.16750287 | HY8: Split en % => | HZ8: =HZ7/HY7 -> 0.036039736 | IA8: =IA7/HY7 -> 0.3971503 | IB8: =IB7/HY7 -> 0.48261273 | IC8: =IC7/HY7 -> 0.081783869 | ID8: =ID7/HY7 -> 0.0024133629 | IF8: =IF7/IE7 -> 0.014164853 | IG8: =IG7/IE7 -> 0.35555638 | IH8: =IH7/IE7 -> 0.50825013 | II8: =II7/IE7 -> 0.11251563 | IJ8: =IJ7/IE7 -> 0.0095130098 | IS8: Evolutions en Pts => | IT8: =(IT7-IO7)*100 -> -2.0939755 | IU8: =(IU7-IP7)*100 -> -3.6176703 | IV8: =(IV7-IQ7)*100 -> 2.4725568 | IW8: =(IW7-IR7)*100 -> 2.6335173 | IX8: =(IX7-IS7)*100 -> 0.60557164 | JC8: Evolutions en Pts => | JD8: =(JD7-IY7)*100 -> -3.65 | JE8: =(JE7-IZ7)*100 -> -7.52 | JF8: =(JF7-JA7)*100 -> 2.55 | JG8: =(JG7-JB7)*100 -> 6.38 | JH8: =(JH7-JC7)*100 -> 2.24 | JM8: Evolutions en Pts => | JN8: =(JN7-JI7)*100 -> -6.74 | JO8: =(JO7-JJ7)*100 -> -9.65 | JP8: =(JP7-JK7)*100 -> 9.67 | JQ8: =(JQ7-JL7)*100 -> 5.68 | JR8: =(JR7-JM7)*100 -> 1.04 | JW8: Evolutions en Pts => | JX8: =(JX7-JS7)*100 -> -3.46 | JY8: =(JY7-JT7)*100 -> -11.19 | JZ8: =(JZ7-JU7)*100 -> 4.57 | KA8: =(KA7-JV7)*100 -> 8.17 | KB8: =(KB7-JW7)*100 -> 1.91
A9: 1 | B9: Tertiaire & Industriel | C9: Bureaux | D9: Bureaux Tertiaire Privé (>50 salariés) (hors usines et logistique ) | E9: W ou hors ERP | F9: Hors ERP dominant / ERP ponctuel selon accueil | G9: mixte | H9: non | I9: On compte uniquement les bureaux autonomes recevant des salariés sur site, avec sanitaires dédiés ou mutualisés sur place. Ne compter que les bureaux tertiaires privés classiques et ceux intégrés à des sites logistiques (hors usines), de plus de 50 personnes. | J9: Immeuble tertiaire privé, siège social, centre de services, bureau de site logistique | K9: non | L9: oui | M9: Site Etablissement principal | N9: proxy emploi / établissements 50+ | O9: Moyenne | Q9: 1 | R9: 4200 | S9: 18000 | T9: 19500 | U9: 22000 | V9: 25500 | W9: 26200 | X9: 26900 | Y9: 27600 | Z9: 28400 | AA9: 27800 | AB9: 27900 | AC9: 28000 | AD9: 28050 | AE9: 28100 | AF9: 28100 | AG9: 28000 | AH9: 27900 | AI9: 27800 | AJ9: 27700 | AK9: 27600 | AL9: Petit rebond 2021-2024 lié à la reprise de l’emploi et à la logistique/tertiaire encore dynamiques ; puis plateau et érosion légère à partir de 2026 avec la rationalisat° immobilière, sans crash du parc. | AM9: Insee Flores 2024 établissements de 50 salariés ou plus ; proxy marché bureaux tertiaires privés. | AN9: https://www.insee.fr/fr/statistiques/8266010 https://www.insee.fr/fr/statistiques/2012766 https://www.insee.fr/fr/statistiques/2496914 | AP9: 250 | AQ9: 225 | AR9: 25 | AS9: 0 | AU9: Bureaux privés >50 salariés : sanitaires salariés par noyaux d'étage, hors public. | AV9: Capacité type ≈ 225 usagers principaux + 25 staff + 0 autre public. Occupation tertiaire stable sur journée, visiteurs faibles/non structurants. Dimensionnement unitaire retenu : cabinets et lavabos séparés selon effectif maximal simultané, pas de douche sauf usages spécifiques. Hypothèse d'usage : capacité simultanée moyenne 2026, répartition par flux réels, arrondie par blocs fonctionnels et exclusion des sanitaires strictement privatifs sauf cas explicitement collectifs. | AW9: Profil grand, capacité moyenne ≈ 250 personnes. Moyenne pondérée terrain : parc majoritairement petits/moyens sites, grands sites intégrés sans surpondération ; usage 2025 modérée, majoritairement courte. | AX9: ERP/accessibilité sanitaires publics : https://www.legifrance.gouv.fr/loda/article_lc/LEGIARTI000034485966/ ; Code du travail sanitaires salariés : https://www.legifrance.gouv.fr/codes/id/LEGISCTA000018531984 ; INRS : https://www.inrs.fr/publications/juridique/focus-juridiques/focus-sanitaires-toilettes.html | AZ9: 22 | BA9: 0.225 | BB9: 4.5 | BC9: 16 | BD9: =SUM(BE9:BH9) -> 1200572.5 | BE9: =AF9*AZ9 -> 618200 | BF9: =AF9*BA9 -> 6322.5 | BG9: =AF9*BB9 -> 126450 | BH9: =AF9*BC9 -> 449600 | BI9: =SUM(BJ9:BM9) -> 1179210 | BJ9: =AK9*AZ9 -> 607200 | BK9: =AK9*BA9 -> 6210 | BL9: =AK9*BB9 -> 124200 | BM9: =AK9*BC9 -> 441600 | BO9: 0.43 | BP9: 0.35 | BQ9: 0.17 | BR9: 0.05 | BS9: 0.36 | BT9: 0.36 | BU9: 0.24 | BV9: 0.04 | BW9: 0.5 | BX9: 0.4 | BY9: 0.1 | BZ9: 0.44 | CA9: 0.43 | CB9: 0.13 | CC9: 0.12 | CD9: 0.5 | CE9: 0.15 | CF9: 0.23 | CG9: 0.1 | CH9: 0.5 | CI9: 0.18 | CJ9: 0.22 | CK9: 0.55 | CL9: 0.3 | CM9: 0.15 | CN9: 0.47 | CO9: 0.33 | CP9: 0.2 | CR9: 13 | CS9: 14 | CT9: 10 | CU9: 12 | CV9: 12 | CW9: 11 | CX9: 9 | CY9: 11 | CZ9: 13 | DA9: 9 | DB9: 11 | DC9: 14 | DD9: 14 | DE9: 10 | DF9: Usage salarié prévisible, faible vandalisme, entretien régulier et rénovation par bail/aménagement; peu d'humidité. Durées longues, supérieures aux ERP publics ouverts. Qualité d’eau parfois défavorable, maintenance surtout corrective avec arbitrage budgétaire selon entreprise. | DH9: =$BE9*BO9 -> 265826 | DI9: =$BE9*BP9 -> 216370 | DJ9: =$BE9*BQ9 -> 105094 | DK9: =$BE9*BR9 -> 30910 | DL9: Dans les bureaux, le mitigeur reste encore très présent dans le parc existant, mais l’électronique a gagné du terrain dans les rénovations tertiaires ; le temporisé mécanique est plus minoritaire que dans l’enseignement ou le sport. Ajustement ciblé 2025 : légère baisse du mitigeur et/ou légère hausse de l’électronique pour mieux refléter la modernisation déjà visible sur les rénovations de sanitaires communs. | DM9: =$BJ9*BS9 -> 218592 | DN9: =$BJ9*BT9 -> 218592 | DO9: =$BJ9*BU9 -> 145728 | DP9: =$BJ9*BV9 -> 24288 | DQ9: 2025-2030 : progression de tempo electronique (+5,0%), surtout lors des renov. lourdes/neuf ; recul de mitigeur manuel (-5,0%) mais maintien d un socle robuste pour les remplacements partiels. | DS9: =$BF9*BW9 -> 3161.25 | DT9: =$BF9*BX9 -> 2529 | DU9: =$BF9*BY9 -> 632.25 | DV9: Bureaux Tertiaire Privé (>50 salariés) (hors usines et logistique ) : parc 2025 domine par mitigeur (50%), avec tempo mecanique en appoint. Le choix reflete usage salarie de jour, maintenance planifiee et contraintes Code du travail ; sanitaires salaries, cout global, robustesse et sobriete eau. | DW9: =$BK9*BZ9 -> 2732.4 | DX9: =$BK9*CA9 -> 2670.3 | DY9: =$BK9*CB9 -> 807.3 | DZ9: 2025-2030 : progression de tempo electronique (+3,0%), surtout lors des renov. lourdes/neuf ; recul de mitigeur (-6,0%) mais maintien d un socle robuste pour les remplacements partiels. | EB9: =$BG9*CC9 -> 15174 | EC9: =$BG9*CD9 -> 63225 | ED9: =$BG9*CE9 -> 18967.5 | EE9: =$BG9*CF9 -> 29083.5 | EF9: Bureaux Tertiaire Privé (>50 salariés) (hors usines et logistique ) : parc 2025 domine par directe mecanique (50%), avec directe electronique collective en appoint. Le choix reflete usage salarie de jour, maintenance planifiee et contraintes Code du travail ; sanitaires salaries, cout global, robustesse et sobriete eau. | EG9: =$BL9*CG9 -> 12420 | EH9: =$BL9*CH9 -> 62100 | EI9: =$BL9*CI9 -> 22356 | EJ9: =$BL9*CJ9 -> 27324 | EK9: 2025-2030 : progression de directe electronique indiv. (+3,0%), surtout lors des renov. lourdes/neuf ; recul de a reservoir (-2,0%) mais maintien d un socle robuste pour les remplacements partiels. | EM9: =$BH9*CK9 -> 247280 | EN9: =$BH9*CL9 -> 134880 | EO9: =$BH9*CM9 -> 67440 | EP9: Bureaux Tertiaire Privé (>50 salariés) (hors usines et logistique ) : parc 2025 domine par reservoir (55%), avec chasse directe mecanique en appoint. Le choix reflete usage salarie de jour, maintenance planifiee et contraintes Code du travail ; sanitaires salaries, cout global, robustesse et sobriete eau. | EQ9: =$BM9*CN9 -> 207552 | ER9: =$BM9*CO9 -> 145728 | ES9: =$BM9*CP9 -> 88320 | ET9: 2025-2030 : progression de chasse directe electronique (+5,0%), surtout lors des renov. lourdes/neuf ; recul de reservoir (-8,0%) mais maintien d un socle robuste pour les remplacements partiels. | EV9: =IFERROR(EY9/EX9,0) -> 0.85738734 | EW9: =IFERROR(EZ9/EX9,0) -> 0.14261266 | EX9: =EY9+EZ9 -> 391456.29 | EY9: =SUM(FB9,FE9,FH9,FK9) -> 335629.67 | EZ9: =SUM(FC9,FF9,FI9,FL9) -> 55826.621 | FA9: =FB9+FC9 -> 203059.87 | FB9: =SUM(GI9,GL9,GO9,GR9) -> 174313.57 | FC9: =MAX(0,$BJ9-$BE9)+$BE9*$FO9 -> 28746.3 | FD9: =FE9+FF9 -> 2423.3856 | FE9: =SUM(GU9,GX9,HA9) -> 2129.3894 | FF9: =MAX(0,$BK9-$BF9)+$BF9*$FO9 -> 293.99625 | FG9: =FH9+FI9 -> 46774.864 | FH9: =SUM(HD9,HG9,HJ9,HM9) -> 40894.939 | FI9: =MAX(0,$BL9-$BG9)+$BG9*$FO9 -> 5879.925 | FJ9: =FK9+FL9 -> 139198.17 | FK9: =SUM(HP9,HS9,HV9) -> 118291.77 | FL9: =MAX(0,$BM9-$BH9)+$BH9*$FO9 -> 20906.4 | FN9: Moyenne à Bonne | FO9: 0.0465 | FP9: 0.80365 | FQ9: 80,4% retenu : besoins transformes en travaux selon usage salarie de jour, maintenance planifiee et contraintes Code du travail. Le phasage budgetaire, les fermetures partielles et la maintenance courante limitent la conversion totale. | FS9: 3.24 | FT9: =RANK($FS9,$FS$16:$FS$17,0)+COUNTIF($FS$16:$FS17,$FS9)-1 -> #N/A | FU9: 3.87 | FV9: =RANK($FU9,$FU$16:$FU$17,0)+COUNTIF($FU$16:$FU17,$FU9)-1 -> #N/A | FW9: 2.12 | FX9: =RANK($FW9,$FW$16:$FW$17,0)+COUNTIF($FW$16:$FW17,$FW9)-1 -> #N/A | FZ9: Potentiel renovation : tire par sanitaires salaries, cout global, robustesse et sobriete eau. Les remplacements sont plutot par lots, avec arbitrage entre urgence sanitaire, budget et capacite a intervenir en site occupe. | GA9: Potentiel neuf : limite pour bureaux tertiaire privé (>50 salariés) (hors usines et logistique ), surtout via extensions, reconstructions ou projets locaux. Le neuf reste contraint par foncier, budgets et delais de mise en service. | GB9: Projets phares renovation : reprise de blocs sanitaires, accessibilite, ventilation, economie d eau, remplacement des pieces usees et adaptation aux pics de frequentation propres au sous-segment. | GC9: Projets phares neuf : creations ou reconstructions selectives, integration de sanitaires plus sobres, robustes et faciles a maintenir des la conception. | GD9: Dynamique renovation 2026-2030 : moderee, car l usure et l hygiene rendent les interventions recurrentes. Menaces : arbitrages d investissement, travaux en exploitation et cout de maintenance. | GE9: Dynamique neuf 2026-2030 : faible a moderee, dependante des projets immobiliers, de la demographie locale et des budgets de maitrise d ouvrage. | GF9: =HYPERLINK("https://anct.gouv.fr/france-services-36","https://anct.gouv.fr/france-services-36")&CHAR(10)&HYPERLINK("https://www.economie.gouv.fr/particuliers/gerer-mon-argent/beneficier-daides-et-de-reductions-dimpots/france-services-les-services-publics-pres-de-chez-vous","https://www.economie.gouv.fr/particuliers/gerer-mon-argent/beneficier-daides-et-de-reductions-dimpots/france-services-les-services-publics-pres-de-chez-vous")&CHAR(10)&HYPERLINK("https://www.ecologie.gouv.fr/eco-energie-tertiaire-eet","https://www.ecologie.gouv.fr/eco-energie-tertiaire-eet")&CHAR(10)&HYPERLINK("https://www.collectivites-locales.gouv.fr/les-collectivites-locales-en-chiffres-2025","https://www.collectivites-locales.gouv.fr/les-collectivites-locales-en-chiffres-2025")&CHAR(10)&HYPERLINK("https://www.collectivites-locales.gouv.fr/actualites/situation-mensuelle-comptable-des-collectivites-locales-au-31-decembre-2025","https://www.collectivites-locales.gouv.fr/actualites/situation-mensuelle-comptable-des-collectivites-locales-au-31-decembre-2025")&CHAR(10)&HYPERLINK("https://www.statistiques.developpement-durable.gouv.fr/construction-de-locaux-resultats-fin-janvier-2026-france-entiere","https://www.statistiques.developpement-durable.gouv.fr/construction-de-locaux-resultats-fin-janvier-2026-france-entiere")&CHAR(10)&HYPERLINK("https://www.insee.fr/fr/statistiques/8671745","https://www.insee.fr/fr/statistiques/8671745")&CHAR(10)&HYPERLINK("https://www.insee.fr/fr/statistiques/8906564","https://www.insee.fr/fr/statistiques/8906564") -> https://anct.gouv.fr/france-services-36 https://www.economie.gouv.fr/particuliers/gerer-mon-argent/beneficier-daides-et-de-reductions-dimpots/france-services-les-services-publics-pres-de-chez-vous https://www.ecologie.gouv.fr/eco-energie-tertiaire-eet https://www.collectivites-locales.gouv.fr/les-collectivites-locales-en-chiffres-2025 https://www.collectivites-locales.gouv.fr/actualites/situation-mensuelle-comptable-des-collectivites-locales-au-31-decembre-2025 https://www.statistiques.developpement-durable.gouv.fr/construction-de-locaux-resultats-fin-janvier-2026-france-entiere https://www.insee.fr/fr/statistiques/8671745 https://www.insee.fr/fr/statistiques/8906564 | GH9: =GI9+GJ9 -> 82046.365 | GI9: =IFERROR($DH9*$FP9/MAX(0.000000001,$CR9)*(INDEX($S9:$AF9,1,MATCH(MAX(2000,MIN(2025,ROUND(2026-$CR9,0))),$S$4:$AF$4,1))+INDEX($S9:$AF9,1,MATCH(MAX(2000,MIN(2025,ROUND(2027-$CR9,0))),$S$4:$AF$4,1))+INDEX($S9:$AF9,1,MATCH(MAX(2000,MIN(2025,ROUND(2028-$CR9,0))),$S$4:$AF$4,1))+INDEX($S9:$AF9,1,MATCH(MAX(2000,MIN(2025,ROUND(2029-$CR9,0))),$S$4:$AF$4,1))+INDEX($S9:$AF9,1,MATCH(MAX(2000,MIN(2025,ROUND(2030-$CR9,0))),$S$4:$AF$4,1)))/MAX(1,$AF9),0) -> 71697.697 | GJ9: =IFERROR($FC9*$BS9,0) -> 10348.668 | GK9: =GL9+GM9 -> 62372.951 | GL9: =IFERROR($DI9*$FP9/MAX(0.000000001,$CS9)*(INDEX($S9:$AF9,1,MATCH(MAX(2000,MIN(2025,ROUND(2026-$CS9,0))),$S$4:$AF$4,1))+INDEX($S9:$AF9,1,MATCH(MAX(2000,MIN(2025,ROUND(2027-$CS9,0))),$S$4:$AF$4,1))+INDEX($S9:$AF9,1,MATCH(MAX(2000,MIN(2025,ROUND(2028-$CS9,0))),$S$4:$AF$4,1))+INDEX($S9:$AF9,1,MATCH(MAX(2000,MIN(2025,ROUND(2029-$CS9,0))),$S$4:$AF$4,1))+INDEX($S9:$AF9,1,MATCH(MAX(2000,MIN(2025,ROUND(2030-$CS9,0))),$S$4:$AF$4,1)))/MAX(1,$AF9),0) -> 52024.283 | GM9: =IFERROR($FC9*$BT9,0) -> 10348.668 | GN9: =GO9+GP9 -> 48046.474 | GO9: =IFERROR($DJ9*$FP9/MAX(0.000000001,$CT9)*(INDEX($S9:$AF9,1,MATCH(MAX(2000,MIN(2025,ROUND(2026-$CT9,0))),$S$4:$AF$4,1))+INDEX($S9:$AF9,1,MATCH(MAX(2000,MIN(2025,ROUND(2027-$CT9,0))),$S$4:$AF$4,1))+INDEX($S9:$AF9,1,MATCH(MAX(2000,MIN(2025,ROUND(2028-$CT9,0))),$S$4:$AF$4,1))+INDEX($S9:$AF9,1,MATCH(MAX(2000,MIN(2025,ROUND(2029-$CT9,0))),$S$4:$AF$4,1))+INDEX($S9:$AF9,1,MATCH(MAX(2000,MIN(2025,ROUND(2030-$CT9,0))),$S$4:$AF$4,1)))/MAX(1,$AF9),0) -> 41147.362 | GP9: =IFERROR($FC9*$BU9,0) -> 6899.112 | GQ9: =GR9+GS9 -> 10594.079 | GR9: =IFERROR($DK9*$FP9/MAX(0.000000001,$CU9)*(INDEX($S9:$AF9,1,MATCH(MAX(2000,MIN(2025,ROUND(2026-$CU9,0))),$S$4:$AF$4,1))+INDEX($S9:$AF9,1,MATCH(MAX(2000,MIN(2025,ROUND(2027-$CU9,0))),$S$4:$AF$4,1))+INDEX($S9:$AF9,1,MATCH(MAX(2000,MIN(2025,ROUND(2028-$CU9,0))),$S$4:$AF$4,1))+INDEX($S9:$AF9,1,MATCH(MAX(2000,MIN(2025,ROUND(2029-$CU9,0))),$S$4:$AF$4,1))+INDEX($S9:$AF9,1,MATCH(MAX(2000,MIN(2025,ROUND(2030-$CU9,0))),$S$4:$AF$4,1)))/MAX(1,$AF9),0) -> 9444.2269 | GS9: =IFERROR($FC9*$BV9,0) -> 1149.852 | GT9: =GU9+GV9 -> 1095.2452 | GU9: =IFERROR($DS9*$FP9/MAX(0.000000001,$CV9)*(INDEX($S9:$AF9,1,MATCH(MAX(2000,MIN(2025,ROUND(2026-$CV9,0))),$S$4:$AF$4,1))+INDEX($S9:$AF9,1,MATCH(MAX(2000,MIN(2025,ROUND(2027-$CV9,0))),$S$4:$AF$4,1))+INDEX($S9:$AF9,1,MATCH(MAX(2000,MIN(2025,ROUND(2028-$CV9,0))),$S$4:$AF$4,1))+INDEX($S9:$AF9,1,MATCH(MAX(2000,MIN(2025,ROUND(2029-$CV9,0))),$S$4:$AF$4,1))+INDEX($S9:$AF9,1,MATCH(MAX(2000,MIN(2025,ROUND(2030-$CV9,0))),$S$4:$AF$4,1)))/MAX(1,$AF9),0) -> 965.88684 | GV9: =IFERROR($FF9*$BZ9,0) -> 129.35835 | GW9: =GX9+GY9 -> 1011.4562 | GX9: =IFERROR($DT9*$FP9/MAX(0.000000001,$CW9)*(INDEX($S9:$AF9,1,MATCH(MAX(2000,MIN(2025,ROUND(2026-$CW9,0))),$S$4:$AF$4,1))+INDEX($S9:$AF9,1,MATCH(MAX(2000,MIN(2025,ROUND(2027-$CW9,0))),$S$4:$AF$4,1))+INDEX($S9:$AF9,1,MATCH(MAX(2000,MIN(2025,ROUND(2028-$CW9,0))),$S$4:$AF$4,1))+INDEX($S9:$AF9,1,MATCH(MAX(2000,MIN(2025,ROUND(2029-$CW9,0))),$S$4:$AF$4,1))+INDEX($S9:$AF9,1,MATCH(MAX(2000,MIN(2025,ROUND(2030-$CW9,0))),$S$4:$AF$4,1)))/MAX(1,$AF9),0) -> 885.03783 | GY9: =IFERROR($FF9*$CA9,0) -> 126.41839 | GZ9: =HA9+HB9 -> 316.68424 | HA9: =IFERROR($DU9*$FP9/MAX(0.000000001,$CX9)*(INDEX($S9:$AF9,1,MATCH(MAX(2000,MIN(2025,ROUND(2026-$CX9,0))),$S$4:$AF$4,1))+INDEX($S9:$AF9,1,MATCH(MAX(2000,MIN(2025,ROUND(2027-$CX9,0))),$S$4:$AF$4,1))+INDEX($S9:$AF9,1,MATCH(MAX(2000,MIN(2025,ROUND(2028-$CX9,0))),$S$4:$AF$4,1))+INDEX($S9:$AF9,1,MATCH(MAX(2000,MIN(2025,ROUND(2029-$CX9,0))),$S$4:$AF$4,1))+INDEX($S9:$AF9,1,MATCH(MAX(2000,MIN(2025,ROUND(2030-$CX9,0))),$S$4:$AF$4,1)))/MAX(1,$AF9),0) -> 278.46472 | HB9: =IFERROR($FF9*$CB9,0) -> 38.219513 | HC9: =HD9+HE9 -> 5898.2195 | HD9: =IFERROR($EB9*$FP9/MAX(0.000000001,$CY9)*(INDEX($S9:$AF9,1,MATCH(MAX(2000,MIN(2025,ROUND(2026-$CY9,0))),$S$4:$AF$4,1))+INDEX($S9:$AF9,1,MATCH(MAX(2000,MIN(2025,ROUND(2027-$CY9,0))),$S$4:$AF$4,1))+INDEX($S9:$AF9,1,MATCH(MAX(2000,MIN(2025,ROUND(2028-$CY9,0))),$S$4:$AF$4,1))+INDEX($S9:$AF9,1,MATCH(MAX(2000,MIN(2025,ROUND(2029-$CY9,0))),$S$4:$AF$4,1))+INDEX($S9:$AF9,1,MATCH(MAX(2000,MIN(2025,ROUND(2030-$CY9,0))),$S$4:$AF$4,1)))/MAX(1,$AF9),0) -> 5310.227 | HE9: =IFERROR($FI9*$CG9,0) -> 587.9925 | HF9: =HG9+HH9 -> 19992.797 | HG9: =IFERROR($EC9*$FP9/MAX(0.000000001,$CZ9)*(INDEX($S9:$AF9,1,MATCH(MAX(2000,MIN(2025,ROUND(2026-$CZ9,0))),$S$4:$AF$4,1))+INDEX($S9:$AF9,1,MATCH(MAX(2000,MIN(2025,ROUND(2027-$CZ9,0))),$S$4:$AF$4,1))+INDEX($S9:$AF9,1,MATCH(MAX(2000,MIN(2025,ROUND(2028-$CZ9,0))),$S$4:$AF$4,1))+INDEX($S9:$AF9,1,MATCH(MAX(2000,MIN(2025,ROUND(2029-$CZ9,0))),$S$4:$AF$4,1))+INDEX($S9:$AF9,1,MATCH(MAX(2000,MIN(2025,ROUND(2030-$CZ9,0))),$S$4:$AF$4,1)))/MAX(1,$AF9),0) -> 17052.835 | HH9: =IFERROR($FI9*$CH9,0) -> 2939.9625 | HI9: =HJ9+HK9 -> 9412.3283 | HJ9: =IFERROR($ED9*$FP9/MAX(0.000000001,$DA9)*(INDEX($S9:$AF9,1,MATCH(MAX(2000,MIN(2025,ROUND(2026-$DA9,0))),$S$4:$AF$4,1))+INDEX($S9:$AF9,1,MATCH(MAX(2000,MIN(2025,ROUND(2027-$DA9,0))),$S$4:$AF$4,1))+INDEX($S9:$AF9,1,MATCH(MAX(2000,MIN(2025,ROUND(2028-$DA9,0))),$S$4:$AF$4,1))+INDEX($S9:$AF9,1,MATCH(MAX(2000,MIN(2025,ROUND(2029-$DA9,0))),$S$4:$AF$4,1))+INDEX($S9:$AF9,1,MATCH(MAX(2000,MIN(2025,ROUND(2030-$DA9,0))),$S$4:$AF$4,1)))/MAX(1,$AF9),0) -> 8353.9417 | HK9: =IFERROR($FI9*$CI9,0) -> 1058.3865 | HL9: =HM9+HN9 -> 11471.519 | HM9: =IFERROR($EE9*$FP9/MAX(0.000000001,$DB9)*(INDEX($S9:$AF9,1,MATCH(MAX(2000,MIN(2025,ROUND(2026-$DB9,0))),$S$4:$AF$4,1))+INDEX($S9:$AF9,1,MATCH(MAX(2000,MIN(2025,ROUND(2027-$DB9,0))),$S$4:$AF$4,1))+INDEX($S9:$AF9,1,MATCH(MAX(2000,MIN(2025,ROUND(2028-$DB9,0))),$S$4:$AF$4,1))+INDEX($S9:$AF9,1,MATCH(MAX(2000,MIN(2025,ROUND(2029-$DB9,0))),$S$4:$AF$4,1))+INDEX($S9:$AF9,1,MATCH(MAX(2000,MIN(2025,ROUND(2030-$DB9,0))),$S$4:$AF$4,1)))/MAX(1,$AF9),0) -> 10177.935 | HN9: =IFERROR($FI9*$CJ9,0) -> 1293.5835 | HO9: =HP9+HQ9 -> 69282.331 | HP9: =IFERROR($EM9*$FP9/MAX(0.000000001,$DC9)*(INDEX($S9:$AF9,1,MATCH(MAX(2000,MIN(2025,ROUND(2026-$DC9,0))),$S$4:$AF$4,1))+INDEX($S9:$AF9,1,MATCH(MAX(2000,MIN(2025,ROUND(2027-$DC9,0))),$S$4:$AF$4,1))+INDEX($S9:$AF9,1,MATCH(MAX(2000,MIN(2025,ROUND(2028-$DC9,0))),$S$4:$AF$4,1))+INDEX($S9:$AF9,1,MATCH(MAX(2000,MIN(2025,ROUND(2029-$DC9,0))),$S$4:$AF$4,1))+INDEX($S9:$AF9,1,MATCH(MAX(2000,MIN(2025,ROUND(2030-$DC9,0))),$S$4:$AF$4,1)))/MAX(1,$AF9),0) -> 59456.323 | HQ9: =IFERROR($FL9*$CN9,0) -> 9826.008 | HR9: =HS9+HT9 -> 39329.834 | HS9: =IFERROR($EN9*$FP9/MAX(0.000000001,$DD9)*(INDEX($S9:$AF9,1,MATCH(MAX(2000,MIN(2025,ROUND(2026-$DD9,0))),$S$4:$AF$4,1))+INDEX($S9:$AF9,1,MATCH(MAX(2000,MIN(2025,ROUND(2027-$DD9,0))),$S$4:$AF$4,1))+INDEX($S9:$AF9,1,MATCH(MAX(2000,MIN(2025,ROUND(2028-$DD9,0))),$S$4:$AF$4,1))+INDEX($S9:$AF9,1,MATCH(MAX(2000,MIN(2025,ROUND(2029-$DD9,0))),$S$4:$AF$4,1))+INDEX($S9:$AF9,1,MATCH(MAX(2000,MIN(2025,ROUND(2030-$DD9,0))),$S$4:$AF$4,1)))/MAX(1,$AF9),0) -> 32430.722 | HT9: =IFERROR($FL9*$CO9,0) -> 6899.112 | HU9: =HV9+HW9 -> 30586.004 | HV9: =IFERROR($EO9*$FP9/MAX(0.000000001,$DE9)*(INDEX($S9:$AF9,1,MATCH(MAX(2000,MIN(2025,ROUND(2026-$DE9,0))),$S$4:$AF$4,1))+INDEX($S9:$AF9,1,MATCH(MAX(2000,MIN(2025,ROUND(2027-$DE9,0))),$S$4:$AF$4,1))+INDEX($S9:$AF9,1,MATCH(MAX(2000,MIN(2025,ROUND(2028-$DE9,0))),$S$4:$AF$4,1))+INDEX($S9:$AF9,1,MATCH(MAX(2000,MIN(2025,ROUND(2029-$DE9,0))),$S$4:$AF$4,1))+INDEX($S9:$AF9,1,MATCH(MAX(2000,MIN(2025,ROUND(2030-$DE9,0))),$S$4:$AF$4,1)))/MAX(1,$AF9),0) -> 26404.724 | HW9: =IFERROR($FL9*$CP9,0) -> 4181.28 | HY9: =SUM(HZ9:ID9) -> 1200573.1 | HZ9: =IFERROR(IO9*BE9,0)+IFERROR(IY9*BF9,0)+IFERROR(JI9*BG9,0)+IFERROR(JS9*BH9,0) -> 40228.522 | IA9: =IFERROR(IP9*BE9,0)+IFERROR(IZ9*BF9,0)+IFERROR(JJ9*BG9,0)+IFERROR(JT9*BH9,0) -> 504645.51 | IB9: =IFERROR(IQ9*BE9,0)+IFERROR(JA9*BF9,0)+IFERROR(JK9*BG9,0)+IFERROR(JU9*BH9,0) -> 581633.05 | IC9: =IFERROR(IR9*BE9,0)+IFERROR(JB9*BF9,0)+IFERROR(JL9*BG9,0)+IFERROR(JV9*BH9,0) -> 74066.05 | ID9: =IFERROR(IS9*BE9,0)+IFERROR(JC9*BF9,0)+IFERROR(JM9*BG9,0)+IFERROR(JW9*BH9,0) -> 0 | IE9: =SUM(IF9:IJ9) -> 335629.67 | IF9: =IFERROR(IT9*FB9,0)+IFERROR(JD9*FE9,0)+IFERROR(JN9*FH9,0)+IFERROR(JX9*FK9,0) -> 3909.5038 | IG9: =IFERROR(IU9*FB9,0)+IFERROR(JE9*FE9,0)+IFERROR(JO9*FH9,0)+IFERROR(JY9*FK9,0) -> 132619.27 | IH9: =IFERROR(IV9*FB9,0)+IFERROR(JF9*FE9,0)+IFERROR(JP9*FH9,0)+IFERROR(JZ9*FK9,0) -> 169400.86 | II9: =IFERROR(IW9*FB9,0)+IFERROR(JG9*FE9,0)+IFERROR(JQ9*FH9,0)+IFERROR(KA9*FK9,0) -> 28022.096 | IJ9: =IFERROR(IX9*FB9,0)+IFERROR(JH9*FE9,0)+IFERROR(JR9*FH9,0)+IFERROR(KB9*FK9,0) -> 1677.9354 | IK9: 4.2 | IL9: Bonne | IM9: Parc existant centre sur le niveau mid, avec ventes 2026-2030 legerement plus qualitatives. Bureaux Tertiaire Privé (>50 salariés) (hors usines et logistique ) : usage salarie de jour, maintenance planifiee et contraintes Code du travail; le mix reste guide par sanitaires salaries, cout global, robustesse et sobriete eau. | IO9: 0.03 | IP9: 0.4 | IQ9: 0.5 | IR9: 0.07 | IS9: 0 | IT9: 0.0078 | IU9: 0.3728 | IV9: 0.5222 | IW9: 0.0922 | IX9: 0.005 | IY9: 0.0312 | IZ9: 0.4154 | JA9: 0.4946 | JB9: 0.0589 | JC9: 0 | JD9: 0.009 | JE9: 0.3882 | JF9: 0.5168 | JG9: 0.0811 | JH9: 0.0049 | JI9: 0.054 | JJ9: 0.5397 | JK9: 0.3748 | JL9: 0.0315 | JM9: 0 | JN9: 0.0318 | JO9: 0.5125 | JP9: 0.397 | JQ9: 0.0537 | JR9: 0.005 | JS9: 0.0326 | JT9: 0.4148 | JU9: 0.4938 | JV9: 0.0588 | JW9: 0 | JX9: 0.0104 | JY9: 0.3876 | JZ9: 0.516 | KA9: 0.081 | KB9: 0.005 | KD9: ±4 pts | KE9: ±4 pts | KF9: 4.23 | KG9: Bonne | KH9: Parc existant : sanitaires salaries, cout global, robustesse et sobriete eau; usage salarie de jour, maintenance planifiee et contraintes Code du travail. La montee en confort reste proportionnee au budget et au rythme de renovation. | KI9: image client => premiumisation ciblee | KJ9: Bureaux Tertiaire Privé (>50 salariés) (hors usines et logistique ) : ventes 2026-2030 en leger glissement vers moyen/premium lorsque le neuf ou les renov. lourdes interviennent. Le centre de gravite reste toutefois module par sanitaires salaries, cout global, robustesse et sobriete eau et par la part dominante de travaux sur parc existant.
A10: =A9+1 -> 2 | B10: Tertiaire & Industriel | C10: Logistique / Stockage | D10: Centres de stockage / Entrepôts / Plateformes logistiques (>50 salariés) | E10: W ou hors ERP | F10: Hors ERP dominant / ERP ponctuel selon accueil | G10: mixte | H10: non | I10: Sous-ensemble distingué de l'ancienne ligne 'Bureaux (>50 personnes, tertiaire privé + logistique hors usines)'. Ventilation proxy pour isoler la logistique. | J10: Entrepôt, plateforme logistique, centre de distribution | K10: non | L10: oui | M10: Site Etablissement principal | N10: proxy de ventilation d'une ligne existante (somme conservée) | O10: Moyenne | P10: Ancienne ligne : Bureaux (>50 personnes, tertiaire privé + logistique hors usines) | Q10: 1 | R10: 26000 | S10: 1500 | T10: 1750 | U10: 2050 | V10: 2400 | W10: 2480 | X10: 2570 | Y10: 2680 | Z10: 2790 | AA10: 2910 | AB10: 3020 | AC10: 3180 | AD10: 3360 | AE10: 3520 | AF10: 3650 | AG10: 3740 | AH10: 3830 | AI10: 3920 | AJ10: 4010 | AK10: 4100 | AL10: Estimation calée sur parc national d'entrepôts / plateformes logistiques de grande taille, ramenée aux sites de + 50 personnes. Hausse portée par grands EPL, e-commerce et concentration des flux. | AM10: SDES entrepôts et plateformes logistiques 2023-2024 ; Insee Flores 2024 ; proxy exploitants logistiques. | AP10: 170 | AQ10: 145 | AR10: 17 | AS10: 8 | AU10: Référence code travail - Bureaux >50 pers. : cabinets/urinoirs par sexe + lavabos. Vestiaires et sanitaires salariés, douches selon postes salissants, horaires postés et maintenance. | AV10: Capacité type ≈ 145 salariés/usagers principaux + 17 staff support + 8 visiteurs/prestataires. Application prioritaire du Code du travail : 1 lavabo/10 travailleurs, 1 WC + 1 urinoir/20 hommes, 2 WC/20 femmes, avec douches dès que les postes sont salissants ; arrondis par noyaux sanitaires/vestiaires. Calibrage selon capacité simultanée, répartition de flux et organisation réelle du site. | AW10: Profil moyen, capacité moyenne ≈ 170 personnes. Moyenne pondérée terrain : parc majoritairement petits/moyens sites, grands sites intégrés sans surpondération ; usage 2025 modérée, majoritairement courte. | AX10: Code du travail, art. R4228-1 à R4228-10 (installations sanitaires, vestiaires, lavabos, douches, WC) : https://www.legifrance.gouv.fr/codes/section_lc/LEGITEXT000006072050/LEGISCTA000018489205/ ; https://code.travail.gouv.fr/code-du-travail/r4228-10 | AZ10: 16 | BA10: 1 | BB10: 4 | BC10: 12 | BD10: =SUM(BE10:BH10) -> 120450 | BE10: =AF10*AZ10 -> 58400 | BF10: =AF10*BA10 -> 3650 | BG10: =AF10*BB10 -> 14600 | BH10: =AF10*BC10 -> 43800 | BI10: =SUM(BJ10:BM10) -> 135300 | BJ10: =AK10*AZ10 -> 65600 | BK10: =AK10*BA10 -> 4100 | BL10: =AK10*BB10 -> 16400 | BM10: =AK10*BC10 -> 49200 | BO10: 0.42 | BP10: 0.4 | BQ10: 0.13 | BR10: 0.05 | BS10: 0.37 | BT10: 0.41 | BU10: 0.18 | BV10: 0.04 | BW10: 0.5 | BX10: 0.4 | BY10: 0.1 | BZ10: 0.44 | CA10: 0.43 | CB10: 0.13 | CC10: 0.05 | CD10: 0.45 | CE10: 0.3 | CF10: 0.2 | CG10: 0.04 | CH10: 0.45 | CI10: 0.33 | CJ10: 0.18 | CK10: 0.5 | CL10: 0.25 | CM10: 0.25 | CN10: 0.42 | CO10: 0.25 | CP10: 0.33 | CR10: 13 | CS10: 13 | CT10: 10 | CU10: 12 | CV10: 12 | CW10: 11 | CX10: 9 | CY10: 11 | CZ10: 13 | DA10: 9 | DB10: 11 | DC10: 12 | DD10: 13 | DE10: 10 | DF10: Usage soutenu, parfois salissant, avec vestiaires et douches davantage sollicités. Les durées réelles restent correctes grâce à une maintenance technique présente, mais l'intensité et l'environnement raccourcissent les douches et les organes exposés. Les renouvellements se font souvent par vestiaires ou batteries sanitaires pendant des arrêts programmés. Industrie / logistique / vestiaires salariés : Usage posté, vestiaires et sanitaires salariés sollicités, qualité d’eau parfois défavorable, maintenance surtout corrective avec arbitrage budgétaire industriel. | DH10: =$BE10*BO10 -> 24528 | DI10: =$BE10*BP10 -> 23360 | DJ10: =$BE10*BQ10 -> 7592 | DK10: =$BE10*BR10 -> 2920 | DL10: Parc 2025 domine par tempo mecanique (60%+). Mitigeur manuel en appoint et éléctronique à même ordre de grandeur. Le choix reflete usage salarie, maintenance planifiee et contraintes Code du travail ; sanitaires salaries, cout global, robustesse et sobriete eau. | DM10: =$BJ10*BS10 -> 24272 | DN10: =$BJ10*BT10 -> 26896 | DO10: =$BJ10*BU10 -> 11808 | DP10: =$BJ10*BV10 -> 2624 | DQ10: Dans les bureaux, la projection 2030 privilégie la montée de l’électronique sur les rénovations tertiaires ; le temporisé mécanique reste secondaire et le mitigeur recule surtout dans les immeubles neufs ou rénovés. | DS10: =$BF10*BW10 -> 1825 | DT10: =$BF10*BX10 -> 1460 | DU10: =$BF10*BY10 -> 365 | DV10: Entrepôts/logistique : douches de vestiaires salariés, mix tertiaire-logistique avec mitigeur dominant et temporisé mécanique significatif. | DW10: =$BK10*BZ10 -> 1804 | DX10: =$BK10*CA10 -> 1763 | DY10: =$BK10*CB10 -> 533 | DZ10: Évolution modérée vers temporisé/électronique lors de rénovations, sous contrainte robustesse, maintenance et économie d’eau. | EB10: =$BG10*CC10 -> 730 | EC10: =$BG10*CD10 -> 6570 | ED10: =$BG10*CE10 -> 4380 | EE10: =$BG10*CF10 -> 2920 | EF10: Les urinoirs automatiques sont désormais courants dans l’immobilier tertiaire récent, sans avoir complètement remplacé le parc mécanique/direct existant. | EG10: =$BL10*CG10 -> 656 | EH10: =$BL10*CH10 -> 7380 | EI10: =$BL10*CI10 -> 5412 | EJ10: =$BL10*CJ10 -> 2952 | EK10: Projection prudente : recul des systèmes les plus anciens et progression graduelle de l’automatique. | EM10: =$BH10*CK10 -> 21900 | EN10: =$BH10*CL10 -> 10950 | EO10: =$BH10*CM10 -> 10950 | EP10: Le réservoir reste légèrement majoritaire dans le stock, mais la chasse directe et l’électronique sont déjà bien représentées dans les immeubles récents. | EQ10: =$BM10*CN10 -> 20664 | ER10: =$BM10*CO10 -> 12300 | ES10: =$BM10*CP10 -> 16236 | ET10: Dans les bureaux, la progression va surtout du réservoir vers l’électronique dans les opérations tertiaires lourdes ; le direct simple reste intermédiaire. | EV10: =IFERROR(EY10/EX10,0) -> 0.52505109 | EW10: =IFERROR(EZ10/EX10,0) -> 0.47494891 | EX10: =EY10+EZ10 -> 53401.272 | EY10: =SUM(FB10,FE10,FH10,FK10) -> 28038.396 | EZ10: =SUM(FC10,FF10,FI10,FL10) -> 25362.876 | FA10: =FB10+FC10 -> 24951.838 | FB10: =SUM(GI10,GL10,GO10,GR10) -> 12654.686 | FC10: =MAX(0,$BJ10-$BE10)+$BE10*$FO10 -> 12297.152 | FD10: =FE10+FF10 -> 1707.6292 | FE10: =SUM(GU10,GX10,HA10) -> 939.0572 | FF10: =MAX(0,$BK10-$BF10)+$BF10*$FO10 -> 768.572 | FG10: =FH10+FI10 -> 6918.641 | FH10: =SUM(HD10,HG10,HJ10,HM10) -> 3844.353 | FI10: =MAX(0,$BL10-$BG10)+$BG10*$FO10 -> 3074.288 | FJ10: =FK10+FL10 -> 19823.164 | FK10: =SUM(HP10,HS10,HV10) -> 10600.3 | FL10: =MAX(0,$BM10-$BH10)+$BH10*$FO10 -> 9222.864 | FN10: Moyenne à Bonne | FO10: 0.08728 | FP10: 0.82916 | FQ10: 82,9% retenu : EET, ESG et repositionnement d’actifs rendent la réno concrète, mais la vacance et les arbitrages immobiliers étalent les travaux. | FS10: 3.22 | FT10: =RANK($FS10,$FS$16:$FS$17,0)+COUNTIF($FS$16:$FS17,$FS10)-1 -> #N/A | FU10: 4.22 | FV10: =RANK($FU10,$FU$16:$FU$17,0)+COUNTIF($FU$16:$FU17,$FU10)-1 -> #N/A | FW10: 2 | FX10: =RANK($FW10,$FW$16:$FW$17,0)+COUNTIF($FW$16:$FW17,$FW10)-1 -> #N/A | FZ10: Potentiel rénovation élevé : très soutenu par le décret tertiaire, le repositionnement ESG et le besoin d’améliorer l’expérience salariés. Les lavabos et les WC portent l’essentiel des volumes, avec un poids secondaire des équipements spécialisés. En rénovation, le marché reste orienté vers des gammes fiables, disponibles et rapides à poser afin de limiter l’arrêt d’exploitation. | GA10: Potentiel neuf moyen à soutenu : le neuf existe surtout sur des immeubles prime, campus et programmes mixtes, mais le marché reste très sélectif. Le neuf est réel mais secondaire. | GB10: Projets phares réno : sanitaires salariés/visiteurs, douches vélo, parties communes, repositionnement d’immeubles anciens ou secondaires. | GC10: Projets phares neuf : immeubles prime, campus tertiaires, bureaux intégrés à des opérations mixtes ou logistiques. | GD10: Dynamique réno 2026-2030 : élevée et plus lisible que le neuf ; le remplacement sanitaire accompagne souvent la montée en qualité des immeubles. | GE10: Dynamique neuf 2026-2030 : modérée, avec polarisation sur les meilleurs actifs et un écart important entre autorisations et chantiers. Le marché est polarisé entre prime et seconde main, ce qui renforce encore le poids de la rénovation. | GF10: =HYPERLINK("https://www.ecologie.gouv.fr/eco-energie-tertiaire-eet","https://www.ecologie.gouv.fr/eco-energie-tertiaire-eet")&CHAR(10)&HYPERLINK("https://www.collectivites-locales.gouv.fr/les-collectivites-locales-en-chiffres-2025","https://www.collectivites-locales.gouv.fr/les-collectivites-locales-en-chiffres-2025")&CHAR(10)&HYPERLINK("https://www.collectivites-locales.gouv.fr/actualites/situation-mensuelle-comptable-des-collectivites-locales-au-31-decembre-2025","https://www.collectivites-locales.gouv.fr/actualites/situation-mensuelle-comptable-des-collectivites-locales-au-31-decembre-2025")&CHAR(10)&HYPERLINK("https://www.statistiques.developpement-durable.gouv.fr/construction-de-locaux-resultats-fin-janvier-2026-france-entiere","https://www.statistiques.developpement-durable.gouv.fr/construction-de-locaux-resultats-fin-janvier-2026-france-entiere")&CHAR(10)&HYPERLINK("https://www.insee.fr/fr/statistiques/8671745","https://www.insee.fr/fr/statistiques/8671745")&CHAR(10)&HYPERLINK("https://www.insee.fr/fr/statistiques/8906564","https://www.insee.fr/fr/statistiques/8906564") -> https://www.ecologie.gouv.fr/eco-energie-tertiaire-eet https://www.collectivites-locales.gouv.fr/les-collectivites-locales-en-chiffres-2025 https://www.collectivites-locales.gouv.fr/actualites/situation-mensuelle-comptable-des-collectivites-locales-au-31-decembre-2025 https://www.statistiques.developpement-durable.gouv.fr/construction-de-locaux-resultats-fin-janvier-2026-france-entiere https://www.insee.fr/fr/statistiques/8671745 https://www.insee.fr/fr/statistiques/8906564 | GH10: =GI10+GJ10 -> 9500.4141 | GI10: =IFERROR($DH10*$FP10/MAX(0.000000001,$CR10)*(INDEX($S10:$AF10,1,MATCH(MAX(2000,MIN(2025,ROUND(2026-$CR10,0))),$S$4:$AF$4,1))+INDEX($S10:$AF10,1,MATCH(MAX(2000,MIN(2025,ROUND(2027-$CR10,0))),$S$4:$AF$4,1))+INDEX($S10:$AF10,1,MATCH(MAX(2000,MIN(2025,ROUND(2028-$CR10,0))),$S$4:$AF$4,1))+INDEX($S10:$AF10,1,MATCH(MAX(2000,MIN(2025,ROUND(2029-$CR10,0))),$S$4:$AF$4,1))+INDEX($S10:$AF10,1,MATCH(MAX(2000,MIN(2025,ROUND(2030-$CR10,0))),$S$4:$AF$4,1)))/MAX(1,$AF10),0) -> 4950.4679 | GJ10: =IFERROR($FC10*$BS10,0) -> 4549.9462 | GK10: =GL10+GM10 -> 9756.5636 | GL10: =IFERROR($DI10*$FP10/MAX(0.000000001,$CS10)*(INDEX($S10:$AF10,1,MATCH(MAX(2000,MIN(2025,ROUND(2026-$CS10,0))),$S$4:$AF$4,1))+INDEX($S10:$AF10,1,MATCH(MAX(2000,MIN(2025,ROUND(2027-$CS10,0))),$S$4:$AF$4,1))+INDEX($S10:$AF10,1,MATCH(MAX(2000,MIN(2025,ROUND(2028-$CS10,0))),$S$4:$AF$4,1))+INDEX($S10:$AF10,1,MATCH(MAX(2000,MIN(2025,ROUND(2029-$CS10,0))),$S$4:$AF$4,1))+INDEX($S10:$AF10,1,MATCH(MAX(2000,MIN(2025,ROUND(2030-$CS10,0))),$S$4:$AF$4,1)))/MAX(1,$AF10),0) -> 4714.7313 | GM10: =IFERROR($FC10*$BT10,0) -> 5041.8323 | GN10: =GO10+GP10 -> 4529.6961 | GO10: =IFERROR($DJ10*$FP10/MAX(0.000000001,$CT10)*(INDEX($S10:$AF10,1,MATCH(MAX(2000,MIN(2025,ROUND(2026-$CT10,0))),$S$4:$AF$4,1))+INDEX($S10:$AF10,1,MATCH(MAX(2000,MIN(2025,ROUND(2027-$CT10,0))),$S$4:$AF$4,1))+INDEX($S10:$AF10,1,MATCH(MAX(2000,MIN(2025,ROUND(2028-$CT10,0))),$S$4:$AF$4,1))+INDEX($S10:$AF10,1,MATCH(MAX(2000,MIN(2025,ROUND(2029-$CT10,0))),$S$4:$AF$4,1))+INDEX($S10:$AF10,1,MATCH(MAX(2000,MIN(2025,ROUND(2030-$CT10,0))),$S$4:$AF$4,1)))/MAX(1,$AF10),0) -> 2316.2087 | GP10: =IFERROR($FC10*$BU10,0) -> 2213.4874 | GQ10: =GR10+GS10 -> 1165.164 | GR10: =IFERROR($DK10*$FP10/MAX(0.000000001,$CU10)*(INDEX($S10:$AF10,1,MATCH(MAX(2000,MIN(2025,ROUND(2026-$CU10,0))),$S$4:$AF$4,1))+INDEX($S10:$AF10,1,MATCH(MAX(2000,MIN(2025,ROUND(2027-$CU10,0))),$S$4:$AF$4,1))+INDEX($S10:$AF10,1,MATCH(MAX(2000,MIN(2025,ROUND(2028-$CU10,0))),$S$4:$AF$4,1))+INDEX($S10:$AF10,1,MATCH(MAX(2000,MIN(2025,ROUND(2029-$CU10,0))),$S$4:$AF$4,1))+INDEX($S10:$AF10,1,MATCH(MAX(2000,MIN(2025,ROUND(2030-$CU10,0))),$S$4:$AF$4,1)))/MAX(1,$AF10),0) -> 673.27792 | GS10: =IFERROR($FC10*$BV10,0) -> 491.88608 | GT10: =GU10+GV10 -> 758.97038 | GU10: =IFERROR($DS10*$FP10/MAX(0.000000001,$CV10)*(INDEX($S10:$AF10,1,MATCH(MAX(2000,MIN(2025,ROUND(2026-$CV10,0))),$S$4:$AF$4,1))+INDEX($S10:$AF10,1,MATCH(MAX(2000,MIN(2025,ROUND(2027-$CV10,0))),$S$4:$AF$4,1))+INDEX($S10:$AF10,1,MATCH(MAX(2000,MIN(2025,ROUND(2028-$CV10,0))),$S$4:$AF$4,1))+INDEX($S10:$AF10,1,MATCH(MAX(2000,MIN(2025,ROUND(2029-$CV10,0))),$S$4:$AF$4,1))+INDEX($S10:$AF10,1,MATCH(MAX(2000,MIN(2025,ROUND(2030-$CV10,0))),$S$4:$AF$4,1)))/MAX(1,$AF10),0) -> 420.7987 | GV10: =IFERROR($FF10*$BZ10,0) -> 338.17168 | GW10: =GX10+GY10 -> 720.0404 | GX10: =IFERROR($DT10*$FP10/MAX(0.000000001,$CW10)*(INDEX($S10:$AF10,1,MATCH(MAX(2000,MIN(2025,ROUND(2026-$CW10,0))),$S$4:$AF$4,1))+INDEX($S10:$AF10,1,MATCH(MAX(2000,MIN(2025,ROUND(2027-$CW10,0))),$S$4:$AF$4,1))+INDEX($S10:$AF10,1,MATCH(MAX(2000,MIN(2025,ROUND(2028-$CW10,0))),$S$4:$AF$4,1))+INDEX($S10:$AF10,1,MATCH(MAX(2000,MIN(2025,ROUND(2029-$CW10,0))),$S$4:$AF$4,1))+INDEX($S10:$AF10,1,MATCH(MAX(2000,MIN(2025,ROUND(2030-$CW10,0))),$S$4:$AF$4,1)))/MAX(1,$AF10),0) -> 389.55444 | GY10: =IFERROR($FF10*$CA10,0) -> 330.48596 | GZ10: =HA10+HB10 -> 228.61842 | HA10: =IFERROR($DU10*$FP10/MAX(0.000000001,$CX10)*(INDEX($S10:$AF10,1,MATCH(MAX(2000,MIN(2025,ROUND(2026-$CX10,0))),$S$4:$AF$4,1))+INDEX($S10:$AF10,1,MATCH(MAX(2000,MIN(2025,ROUND(2027-$CX10,0))),$S$4:$AF$4,1))+INDEX($S10:$AF10,1,MATCH(MAX(2000,MIN(2025,ROUND(2028-$CX10,0))),$S$4:$AF$4,1))+INDEX($S10:$AF10,1,MATCH(MAX(2000,MIN(2025,ROUND(2029-$CX10,0))),$S$4:$AF$4,1))+INDEX($S10:$AF10,1,MATCH(MAX(2000,MIN(2025,ROUND(2030-$CX10,0))),$S$4:$AF$4,1)))/MAX(1,$AF10),0) -> 128.70406 | HB10: =IFERROR($FF10*$CB10,0) -> 99.91436 | HC10: =HD10+HE10 -> 317.74874 | HD10: =IFERROR($EB10*$FP10/MAX(0.000000001,$CY10)*(INDEX($S10:$AF10,1,MATCH(MAX(2000,MIN(2025,ROUND(2026-$CY10,0))),$S$4:$AF$4,1))+INDEX($S10:$AF10,1,MATCH(MAX(2000,MIN(2025,ROUND(2027-$CY10,0))),$S$4:$AF$4,1))+INDEX($S10:$AF10,1,MATCH(MAX(2000,MIN(2025,ROUND(2028-$CY10,0))),$S$4:$AF$4,1))+INDEX($S10:$AF10,1,MATCH(MAX(2000,MIN(2025,ROUND(2029-$CY10,0))),$S$4:$AF$4,1))+INDEX($S10:$AF10,1,MATCH(MAX(2000,MIN(2025,ROUND(2030-$CY10,0))),$S$4:$AF$4,1)))/MAX(1,$AF10),0) -> 194.77722 | HE10: =IFERROR($FI10*$CG10,0) -> 122.97152 | HF10: =HG10+HH10 -> 2709.4478 | HG10: =IFERROR($EC10*$FP10/MAX(0.000000001,$CZ10)*(INDEX($S10:$AF10,1,MATCH(MAX(2000,MIN(2025,ROUND(2026-$CZ10,0))),$S$4:$AF$4,1))+INDEX($S10:$AF10,1,MATCH(MAX(2000,MIN(2025,ROUND(2027-$CZ10,0))),$S$4:$AF$4,1))+INDEX($S10:$AF10,1,MATCH(MAX(2000,MIN(2025,ROUND(2028-$CZ10,0))),$S$4:$AF$4,1))+INDEX($S10:$AF10,1,MATCH(MAX(2000,MIN(2025,ROUND(2029-$CZ10,0))),$S$4:$AF$4,1))+INDEX($S10:$AF10,1,MATCH(MAX(2000,MIN(2025,ROUND(2030-$CZ10,0))),$S$4:$AF$4,1)))/MAX(1,$AF10),0) -> 1326.0182 | HH10: =IFERROR($FI10*$CH10,0) -> 1383.4296 | HI10: =HJ10+HK10 -> 2558.9637 | HJ10: =IFERROR($ED10*$FP10/MAX(0.000000001,$DA10)*(INDEX($S10:$AF10,1,MATCH(MAX(2000,MIN(2025,ROUND(2026-$DA10,0))),$S$4:$AF$4,1))+INDEX($S10:$AF10,1,MATCH(MAX(2000,MIN(2025,ROUND(2027-$DA10,0))),$S$4:$AF$4,1))+INDEX($S10:$AF10,1,MATCH(MAX(2000,MIN(2025,ROUND(2028-$DA10,0))),$S$4:$AF$4,1))+INDEX($S10:$AF10,1,MATCH(MAX(2000,MIN(2025,ROUND(2029-$DA10,0))),$S$4:$AF$4,1))+INDEX($S10:$AF10,1,MATCH(MAX(2000,MIN(2025,ROUND(2030-$DA10,0))),$S$4:$AF$4,1)))/MAX(1,$AF10),0) -> 1544.4487 | HK10: =IFERROR($FI10*$CI10,0) -> 1014.515 | HL10: =HM10+HN10 -> 1332.4807 | HM10: =IFERROR($EE10*$FP10/MAX(0.000000001,$DB10)*(INDEX($S10:$AF10,1,MATCH(MAX(2000,MIN(2025,ROUND(2026-$DB10,0))),$S$4:$AF$4,1))+INDEX($S10:$AF10,1,MATCH(MAX(2000,MIN(2025,ROUND(2027-$DB10,0))),$S$4:$AF$4,1))+INDEX($S10:$AF10,1,MATCH(MAX(2000,MIN(2025,ROUND(2028-$DB10,0))),$S$4:$AF$4,1))+INDEX($S10:$AF10,1,MATCH(MAX(2000,MIN(2025,ROUND(2029-$DB10,0))),$S$4:$AF$4,1))+INDEX($S10:$AF10,1,MATCH(MAX(2000,MIN(2025,ROUND(2030-$DB10,0))),$S$4:$AF$4,1)))/MAX(1,$AF10),0) -> 779.10889 | HN10: =IFERROR($FI10*$CJ10,0) -> 553.37184 | HO10: =HP10+HQ10 -> 8923.1873 | HP10: =IFERROR($EM10*$FP10/MAX(0.000000001,$DC10)*(INDEX($S10:$AF10,1,MATCH(MAX(2000,MIN(2025,ROUND(2026-$DC10,0))),$S$4:$AF$4,1))+INDEX($S10:$AF10,1,MATCH(MAX(2000,MIN(2025,ROUND(2027-$DC10,0))),$S$4:$AF$4,1))+INDEX($S10:$AF10,1,MATCH(MAX(2000,MIN(2025,ROUND(2028-$DC10,0))),$S$4:$AF$4,1))+INDEX($S10:$AF10,1,MATCH(MAX(2000,MIN(2025,ROUND(2029-$DC10,0))),$S$4:$AF$4,1))+INDEX($S10:$AF10,1,MATCH(MAX(2000,MIN(2025,ROUND(2030-$DC10,0))),$S$4:$AF$4,1)))/MAX(1,$AF10),0) -> 5049.5844 | HQ10: =IFERROR($FL10*$CN10,0) -> 3873.6029 | HR10: =HS10+HT10 -> 4515.7463 | HS10: =IFERROR($EN10*$FP10/MAX(0.000000001,$DD10)*(INDEX($S10:$AF10,1,MATCH(MAX(2000,MIN(2025,ROUND(2026-$DD10,0))),$S$4:$AF$4,1))+INDEX($S10:$AF10,1,MATCH(MAX(2000,MIN(2025,ROUND(2027-$DD10,0))),$S$4:$AF$4,1))+INDEX($S10:$AF10,1,MATCH(MAX(2000,MIN(2025,ROUND(2028-$DD10,0))),$S$4:$AF$4,1))+INDEX($S10:$AF10,1,MATCH(MAX(2000,MIN(2025,ROUND(2029-$DD10,0))),$S$4:$AF$4,1))+INDEX($S10:$AF10,1,MATCH(MAX(2000,MIN(2025,ROUND(2030-$DD10,0))),$S$4:$AF$4,1)))/MAX(1,$AF10),0) -> 2210.0303 | HT10: =IFERROR($FL10*$CO10,0) -> 2305.716 | HU10: =HV10+HW10 -> 6384.2308 | HV10: =IFERROR($EO10*$FP10/MAX(0.000000001,$DE10)*(INDEX($S10:$AF10,1,MATCH(MAX(2000,MIN(2025,ROUND(2026-$DE10,0))),$S$4:$AF$4,1))+INDEX($S10:$AF10,1,MATCH(MAX(2000,MIN(2025,ROUND(2027-$DE10,0))),$S$4:$AF$4,1))+INDEX($S10:$AF10,1,MATCH(MAX(2000,MIN(2025,ROUND(2028-$DE10,0))),$S$4:$AF$4,1))+INDEX($S10:$AF10,1,MATCH(MAX(2000,MIN(2025,ROUND(2029-$DE10,0))),$S$4:$AF$4,1))+INDEX($S10:$AF10,1,MATCH(MAX(2000,MIN(2025,ROUND(2030-$DE10,0))),$S$4:$AF$4,1)))/MAX(1,$AF10),0) -> 3340.6856 | HW10: =IFERROR($FL10*$CP10,0) -> 3043.5451 | HY10: =SUM(HZ10:ID10) -> 116800 | HZ10: =IFERROR(IO10*BE10,0)+IFERROR(IY10*BF10,0)+IFERROR(JI10*BG10,0)+IFERROR(JS10*BH10,0) -> 0 | IA10: =IFERROR(IP10*BE10,0)+IFERROR(IZ10*BF10,0)+IFERROR(JJ10*BG10,0)+IFERROR(JT10*BH10,0) -> 31381.24 | IB10: =IFERROR(IQ10*BE10,0)+IFERROR(JA10*BF10,0)+IFERROR(JK10*BG10,0)+IFERROR(JU10*BH10,0) -> 61411.98 | IC10: =IFERROR(IR10*BE10,0)+IFERROR(JB10*BF10,0)+IFERROR(JL10*BG10,0)+IFERROR(JV10*BH10,0) -> 22800.82 | ID10: =IFERROR(IS10*BE10,0)+IFERROR(JC10*BF10,0)+IFERROR(JM10*BG10,0)+IFERROR(JW10*BH10,0) -> 1205.96 | IE10: =SUM(IF10:IJ10) -> 27099.339 | IF10: =IFERROR(IT10*FB10,0)+IFERROR(JD10*FE10,0)+IFERROR(JN10*FH10,0)+IFERROR(JX10*FK10,0) -> 0 | IG10: =IFERROR(IU10*FB10,0)+IFERROR(JE10*FE10,0)+IFERROR(JO10*FH10,0)+IFERROR(JY10*FK10,0) -> 3884.4301 | IH10: =IFERROR(IV10*FB10,0)+IFERROR(JF10*FE10,0)+IFERROR(JP10*FH10,0)+IFERROR(JZ10*FK10,0) -> 14156.743 | II10: =IFERROR(IW10*FB10,0)+IFERROR(JG10*FE10,0)+IFERROR(JQ10*FH10,0)+IFERROR(KA10*FK10,0) -> 8184.956 | IJ10: =IFERROR(IX10*FB10,0)+IFERROR(JH10*FE10,0)+IFERROR(JR10*FH10,0)+IFERROR(KB10*FK10,0) -> 873.21006 | IK10: 4 | IL10: Bonne | IM10: Parc existant surtout intermédiaire. Les ventes se décalent légèrement vers intermédiaire, sous l’effet combiné de l’hygiène, de l’image et des rénovations lourdes. Le neuf est un peu plus qualitatif que la rénovation, sans renverser le centre de gravité du mix. Bureaux tertiaires : le parc existant reste largement standard/intermédiaire, mais le tertiaire rénové et les sièges cherchent plus de qualité perçue, d’image et d’hygiène. | IO10: 0 | IP10: 0.2369 | IQ10: 0.5359 | IR10: 0.2142 | IS10: 0.013 | IT10: 0 | IU10: 0.1155 | IV10: 0.5112 | IW10: 0.3331 | IX10: 0.0402 | IY10: 0 | IZ10: 0 | JA10: 0 | JB10: 0 | JC10: 0 | JD10: 0 | JE10: 0 | JF10: 0 | JG10: 0 | JH10: 0 | JI10: 0 | JJ10: 0.3582 | JK10: 0.4958 | JL10: 0.1418 | JM10: 0.0042 | JN10: 0 | JO10: 0.218 | JP10: 0.5386 | JQ10: 0.228 | JR10: 0.0154 | JS10: 0 | JT10: 0.2812 | JU10: 0.5223 | JV10: 0.1877 | JW10: 0.0088 | JX10: 0 | JY10: 0.1495 | JZ10: 0.5299 | KA10: 0.2918 | KB10: 0.0288 | KD10: ±4 pts | KE10: ±5 pts | KF10: 4.4 | KG10: Bonne | KH10: Bureaux tertiaires : le parc existant reste largement standard/intermédiaire, mais le tertiaire rénové et les sièges cherchent plus de qualité perçue, d’image et d’hygiène. | KI10: image + privé ⇒ premium/luxe ↑ ; contrainte sanitaire ⇒ standard/intermédiaire technique ↑ ; poids du neuf significatif ⇒ premiumisation des ventes > parc | KJ10: Centres de stockage / entrepôts / plateformes logistiques (>50 personnes) : tertiaire privé majoritairement standard, avec premium concentré sur sièges, campus et immeubles récents. Ventes 2026-2030 : glissement vers davantage de moyen / premium, surtout sur lavabo (+14,6 pts sur premium+luxe), WC (+12,4 pts sur premium+luxe), urinoir (+9,7 pts sur premium+luxe). La rénovation reste majoritaire (70% des ventes, contre 30% en neuf) ; le neuf tire le mix vers le haut sans renverser le centre de gravité. L’écart de niveau de confort entre neuf et rénovation est net.
A11: =A10+1 -> 3 | B11: Tertiaire & Industriel | C11: Usines & Ateliers | D11: Usines (>50 salariés) (Hors Ateliers industriels) | E11: Hors ERP | F11: Hors ERP dominant / ERP ponctuel selon accueil | G11: hors ERP | H11: non | I11: Tout type d’usine de plus de 50 personnes, avec sanitaires dédiés ou mutualisés sur place. Hors bureaux autonomes et hors entrepôts / logistique sans fabrication. | J11: Usine agroalimentaire, site métallurgique, usine chimique, usine automobile | K11: non | L11: oui | M11: Site Etablissement principal | N11: proxy emploi / établissements industriels 50+ | O11: Moyenne | Q11: 1 | R11: 14000 | S11: 9900 | T11: 9600 | U11: 9100 | V11: 8600 | W11: 8500 | X11: 8420 | Y11: 8360 | Z11: 8320 | AA11: 8250 | AB11: 8300 | AC11: 8400 | AD11: 8520 | AE11: 8620 | AF11: 8700 | AG11: 8780 | AH11: 8860 | AI11: 8940 | AJ11: 9000 | AK11: 9050 | AL11: Série revue à partir du socle d'étab. industriels + 50 salariés, retranchant ateliers / maintenance (isoler les usines). Baisse jusqu'à 2020, puis stabilisation et légère reprise avec la réindustrialisation récente. | AM11: Insee Flores 2024 ; Insee Focus 2024 sur les établissements manufacturiers ; Baromètre industriel de l'État 2024. | AN11: https://www.insee.fr/fr/statistiques/8266010 https://www.insee.fr/fr/statistiques/2012766 https://www.insee.fr/fr/statistiques/8673351 | AP11: 250 | AQ11: 225 | AR11: 20 | AS11: 5 | AU11: Usine >50 salariés : sanitaires/vestiaires salariés + douches si travaux salissants. | AV11: Capacité type ≈ 225 usagers principaux + 20 staff + 5 autre public. Équipes de production et maintenance, visiteurs/prestataires minoritaires. Dimensionnement unitaire retenu : blocs par vestiaires/ateliers, douches collectives quand l'activité le justifie. Hypothèse d'usage : capacité simultanée moyenne 2026, répartition par flux réels, arrondie par blocs fonctionnels et exclusion des sanitaires strictement privatifs sauf cas explicitement collectifs. | AW11: Profil grand, capacité moyenne ≈ 250 personnes. Moyenne pondérée terrain : parc majoritairement petits/moyens sites, grands sites intégrés sans surpondération ; usage 2025 modérée, majoritairement courte. | AX11: ERP/accessibilité sanitaires publics : https://www.legifrance.gouv.fr/loda/article_lc/LEGIARTI000034485966/ ; Code du travail sanitaires salariés : https://www.legifrance.gouv.fr/codes/id/LEGISCTA000018531984 ; INRS : https://www.inrs.fr/publications/juridique/focus-juridiques/focus-sanitaires-toilettes.html | AZ11: 25 | BA11: 8 | BB11: 5.5 | BC11: 17 | BD11: =SUM(BE11:BH11) -> 482850 | BE11: =AF11*AZ11 -> 217500 | BF11: =AF11*BA11 -> 69600 | BG11: =AF11*BB11 -> 47850 | BH11: =AF11*BC11 -> 147900 | BI11: =SUM(BJ11:BM11) -> 502275 | BJ11: =AK11*AZ11 -> 226250 | BK11: =AK11*BA11 -> 72400 | BL11: =AK11*BB11 -> 49775 | BM11: =AK11*BC11 -> 153850 | BO11: 0.42 | BP11: 0.39 | BQ11: 0.14 | BR11: 0.05 | BS11: 0.39 | BT11: 0.4 | BU11: 0.18 | BV11: 0.03 | BW11: 0.5 | BX11: 0.4 | BY11: 0.1 | BZ11: 0.44 | CA11: 0.43 | CB11: 0.13 | CC11: 0.12 | CD11: 0.5 | CE11: 0.15 | CF11: 0.23 | CG11: 0.1 | CH11: 0.5 | CI11: 0.18 | CJ11: 0.22 | CK11: 0.55 | CL11: 0.3 | CM11: 0.15 | CN11: 0.47 | CO11: 0.33 | CP11: 0.2 | CR11: 13 | CS11: 14 | CT11: 10 | CU11: 12 | CV11: 12 | CW11: 11 | CX11: 9 | CY11: 11 | CZ11: 13 | DA11: 9 | DB11: 11 | DC11: 14 | DD11: 14 | DE11: 10 | DF11: Usage soutenu, salissures industrielles, avec vestiaires, douches davantage sollicités. Durées réelles restent correctes grâce à une maintenance technique présente, mais intensité et environnement raccourcissent les douches. Maintenance technique disponible mais contraintes de production. Renouvellements souvent par vestiaires ou batteries sanitaires pendant arrêts programmés. Industrie / vestiaires salariés : Usage posté, vestiaires et sanitaires salariés sollicités, qualité d’eau parfois défavorable, maintenance surtout corrective avec arbitrage budgétaire industriel. Proche logistique, avantage aux mécaniques robustes. | DH11: =$BE11*BO11 -> 91350 | DI11: =$BE11*BP11 -> 84825 | DJ11: =$BE11*BQ11 -> 30450 | DK11: =$BE11*BR11 -> 10875 | DL11: Usines (>50 salariés) (Hors Ateliers industriels) : parc 2025 domine par tempo mecanique (50%), avec mitigeur manuel en appoint. Le choix reflete usage salarie de jour, maintenance planifiee et contraintes Code du travail ; sanitaires salaries, cout global, robustesse et sobriete eau. | DM11: =$BJ11*BS11 -> 88237.5 | DN11: =$BJ11*BT11 -> 90500 | DO11: =$BJ11*BU11 -> 40725 | DP11: =$BJ11*BV11 -> 6787.5 | DQ11: 2025-2030 : progression de tempo electronique (+5,0%), surtout lors des renov. lourdes/neuf ; recul de mitigeur manuel (-5,0%) mais maintien d un socle robuste pour les remplacements partiels. | DS11: =$BF11*BW11 -> 34800 | DT11: =$BF11*BX11 -> 27840 | DU11: =$BF11*BY11 -> 6960 | DV11: Usines (>50 salariés) (Hors Ateliers industriels) : parc 2025 domine par mitigeur (50%), avec tempo mecanique en appoint. Le choix reflete usage salarie de jour, maintenance planifiee et contraintes Code du travail ; sanitaires salaries, cout global, robustesse et sobriete eau. | DW11: =$BK11*BZ11 -> 31856 | DX11: =$BK11*CA11 -> 31132 | DY11: =$BK11*CB11 -> 9412 | DZ11: 2025-2030 : progression de tempo electronique (+3,0%), surtout lors des renov. lourdes/neuf ; recul de mitigeur (-6,0%) mais maintien d un socle robuste pour les remplacements partiels. | EB11: =$BG11*CC11 -> 5742 | EC11: =$BG11*CD11 -> 23925 | ED11: =$BG11*CE11 -> 7177.5 | EE11: =$BG11*CF11 -> 11005.5 | EF11: Usines (>50 salariés) (Hors Ateliers industriels) : parc 2025 domine par directe mecanique (50%), avec directe electronique collective en appoint. Le choix reflete usage salarie de jour, maintenance planifiee et contraintes Code du travail ; sanitaires salaries, cout global, robustesse et sobriete eau. | EG11: =$BL11*CG11 -> 4977.5 | EH11: =$BL11*CH11 -> 24887.5 | EI11: =$BL11*CI11 -> 8959.5 | EJ11: =$BL11*CJ11 -> 10950.5 | EK11: 2025-2030 : progression de directe electronique indiv. (+3,0%), surtout lors des renov. lourdes/neuf ; recul de a reservoir (-2,0%) mais maintien d un socle robuste pour les remplacements partiels. | EM11: =$BH11*CK11 -> 81345 | EN11: =$BH11*CL11 -> 44370 | EO11: =$BH11*CM11 -> 22185 | EP11: Usines (>50 salariés) (Hors Ateliers industriels) : parc 2025 domine par reservoir (55%), avec chasse directe mecanique en appoint. Le choix reflete usage salarie de jour, maintenance planifiee et contraintes Code du travail ; sanitaires salaries, cout global, robustesse et sobriete eau. | EQ11: =$BM11*CN11 -> 72309.5 | ER11: =$BM11*CO11 -> 50770.5 | ES11: =$BM11*CP11 -> 30770 | ET11: 2025-2030 : progression de chasse directe electronique (+5,0%), surtout lors des renov. lourdes/neuf ; recul de reservoir (-8,0%) mais maintien d un socle robuste pour les remplacements partiels. | EV11: =IFERROR(EY11/EX11,0) -> 0.78706882 | EW11: =IFERROR(EZ11/EX11,0) -> 0.21293118 | EX11: =EY11+EZ11 -> 196671.64 | EY11: =SUM(FB11,FE11,FH11,FK11) -> 154794.12 | EZ11: =SUM(FC11,FF11,FI11,FL11) -> 41877.525 | FA11: =FB11+FC11 -> 87461.964 | FB11: =SUM(GI11,GL11,GO11,GR11) -> 68598.214 | FC11: =MAX(0,$BJ11-$BE11)+$BE11*$FO11 -> 18863.75 | FD11: =FE11+FF11 -> 30391.216 | FE11: =SUM(GU11,GX11,HA11) -> 24354.816 | FF11: =MAX(0,$BK11-$BF11)+$BF11*$FO11 -> 6036.4 | FG11: =FH11+FI11 -> 20585.775 | FH11: =SUM(HD11,HG11,HJ11,HM11) -> 16435.75 | FI11: =MAX(0,$BL11-$BG11)+$BG11*$FO11 -> 4150.025 | FJ11: =FK11+FL11 -> 58232.685 | FK11: =SUM(HP11,HS11,HV11) -> 45405.335 | FL11: =MAX(0,$BM11-$BH11)+$BH11*$FO11 -> 12827.35 | FN11: Moyenne à Bonne | FO11: 0.0465 | FP11: 0.80365 | FQ11: 80,4% retenu : besoins transformes en travaux selon usage salarie de jour, maintenance planifiee et contraintes Code du travail. Le phasage budgetaire, les fermetures partielles et la maintenance courante limitent la conversion totale. | FS11: 3.24 | FT11: =RANK($FS11,$FS$16:$FS$17,0)+COUNTIF($FS$16:$FS17,$FS11)-1 -> #N/A | FU11: 3.87 | FV11: =RANK($FU11,$FU$16:$FU$17,0)+COUNTIF($FU$16:$FU17,$FU11)-1 -> #N/A | FW11: 2.12 | FX11: =RANK($FW11,$FW$16:$FW$17,0)+COUNTIF($FW$16:$FW17,$FW11)-1 -> #N/A | FZ11: Potentiel renovation : tire par sanitaires salaries, cout global, robustesse et sobriete eau. Les remplacements sont plutot par lots, avec arbitrage entre urgence sanitaire, budget et capacite a intervenir en site occupe. | GA11: Potentiel neuf : limite pour usines (>50 salariés) (hors ateliers industriels), surtout via extensions, reconstructions ou projets locaux. Le neuf reste contraint par foncier, budgets et delais de mise en service. | GB11: Projets phares renovation : reprise de blocs sanitaires, accessibilite, ventilation, economie d eau, remplacement des pieces usees et adaptation aux pics de frequentation propres au sous-segment. | GC11: Projets phares neuf : creations ou reconstructions selectives, integration de sanitaires plus sobres, robustes et faciles a maintenir des la conception. | GD11: Dynamique renovation 2026-2030 : moderee, car l usure et l hygiene rendent les interventions recurrentes. Menaces : arbitrages d investissement, travaux en exploitation et cout de maintenance. | GE11: Dynamique neuf 2026-2030 : faible a moderee, dependante des projets immobiliers, de la demographie locale et des budgets de maitrise d ouvrage. | GF11: =HYPERLINK("https://experience.france2030.gouv.fr/fr/visit/decarbonation-de-leconomie/la-decarbonation-de-l-industrie/full/","https://experience.france2030.gouv.fr/fr/visit/decarbonation-de-leconomie/la-decarbonation-de-l-industrie/full/")&CHAR(10)&HYPERLINK("https://www.tresor.economie.gouv.fr/Articles/2025/05/19/choose-france-2025-une-edition-record-au-service-de-la-souverainete-economique-et-de-l-innovation","https://www.tresor.economie.gouv.fr/Articles/2025/05/19/choose-france-2025-une-edition-record-au-service-de-la-souverainete-economique-et-de-l-innovation")&CHAR(10)&HYPERLINK("https://www.statistiques.developpement-durable.gouv.fr/construction-de-locaux-resultats-fin-janvier-2026-france-entiere","https://www.statistiques.developpement-durable.gouv.fr/construction-de-locaux-resultats-fin-janvier-2026-france-entiere")&CHAR(10)&HYPERLINK("https://www.insee.fr/fr/statistiques/8671745","https://www.insee.fr/fr/statistiques/8671745")&CHAR(10)&HYPERLINK("https://www.insee.fr/fr/statistiques/8906564","https://www.insee.fr/fr/statistiques/8906564") -> https://experience.france2030.gouv.fr/fr/visit/decarbonation-de-leconomie/la-decarbonation-de-l-industrie/full/ https://www.tresor.economie.gouv.fr/Articles/2025/05/19/choose-france-2025-une-edition-record-au-service-de-la-souverainete-economique-et-de-l-innovation https://www.statistiques.developpement-durable.gouv.fr/construction-de-locaux-resultats-fin-janvier-2026-france-entiere https://www.insee.fr/fr/statistiques/8671745 https://www.insee.fr/fr/statistiques/8906564 | GH11: =GI11+GJ11 -> 35735.599 | GI11: =IFERROR($DH11*$FP11/MAX(0.000000001,$CR11)*(INDEX($S11:$AF11,1,MATCH(MAX(2000,MIN(2025,ROUND(2026-$CR11,0))),$S$4:$AF$4,1))+INDEX($S11:$AF11,1,MATCH(MAX(2000,MIN(2025,ROUND(2027-$CR11,0))),$S$4:$AF$4,1))+INDEX($S11:$AF11,1,MATCH(MAX(2000,MIN(2025,ROUND(2028-$CR11,0))),$S$4:$AF$4,1))+INDEX($S11:$AF11,1,MATCH(MAX(2000,MIN(2025,ROUND(2029-$CR11,0))),$S$4:$AF$4,1))+INDEX($S11:$AF11,1,MATCH(MAX(2000,MIN(2025,ROUND(2030-$CR11,0))),$S$4:$AF$4,1)))/MAX(1,$AF11),0) -> 28378.736 | GJ11: =IFERROR($FC11*$BS11,0) -> 7356.8625 | GK11: =GL11+GM11 -> 32395.506 | GL11: =IFERROR($DI11*$FP11/MAX(0.000000001,$CS11)*(INDEX($S11:$AF11,1,MATCH(MAX(2000,MIN(2025,ROUND(2026-$CS11,0))),$S$4:$AF$4,1))+INDEX($S11:$AF11,1,MATCH(MAX(2000,MIN(2025,ROUND(2027-$CS11,0))),$S$4:$AF$4,1))+INDEX($S11:$AF11,1,MATCH(MAX(2000,MIN(2025,ROUND(2028-$CS11,0))),$S$4:$AF$4,1))+INDEX($S11:$AF11,1,MATCH(MAX(2000,MIN(2025,ROUND(2029-$CS11,0))),$S$4:$AF$4,1))+INDEX($S11:$AF11,1,MATCH(MAX(2000,MIN(2025,ROUND(2030-$CS11,0))),$S$4:$AF$4,1)))/MAX(1,$AF11),0) -> 24850.006 | GM11: =IFERROR($FC11*$BT11,0) -> 7545.5 | GN11: =GO11+GP11 -> 15166.938 | GO11: =IFERROR($DJ11*$FP11/MAX(0.000000001,$CT11)*(INDEX($S11:$AF11,1,MATCH(MAX(2000,MIN(2025,ROUND(2026-$CT11,0))),$S$4:$AF$4,1))+INDEX($S11:$AF11,1,MATCH(MAX(2000,MIN(2025,ROUND(2027-$CT11,0))),$S$4:$AF$4,1))+INDEX($S11:$AF11,1,MATCH(MAX(2000,MIN(2025,ROUND(2028-$CT11,0))),$S$4:$AF$4,1))+INDEX($S11:$AF11,1,MATCH(MAX(2000,MIN(2025,ROUND(2029-$CT11,0))),$S$4:$AF$4,1))+INDEX($S11:$AF11,1,MATCH(MAX(2000,MIN(2025,ROUND(2030-$CT11,0))),$S$4:$AF$4,1)))/MAX(1,$AF11),0) -> 11771.463 | GP11: =IFERROR($FC11*$BU11,0) -> 3395.475 | GQ11: =GR11+GS11 -> 4163.9205 | GR11: =IFERROR($DK11*$FP11/MAX(0.000000001,$CU11)*(INDEX($S11:$AF11,1,MATCH(MAX(2000,MIN(2025,ROUND(2026-$CU11,0))),$S$4:$AF$4,1))+INDEX($S11:$AF11,1,MATCH(MAX(2000,MIN(2025,ROUND(2027-$CU11,0))),$S$4:$AF$4,1))+INDEX($S11:$AF11,1,MATCH(MAX(2000,MIN(2025,ROUND(2028-$CU11,0))),$S$4:$AF$4,1))+INDEX($S11:$AF11,1,MATCH(MAX(2000,MIN(2025,ROUND(2029-$CU11,0))),$S$4:$AF$4,1))+INDEX($S11:$AF11,1,MATCH(MAX(2000,MIN(2025,ROUND(2030-$CU11,0))),$S$4:$AF$4,1)))/MAX(1,$AF11),0) -> 3598.008 | GS11: =IFERROR($FC11*$BV11,0) -> 565.9125 | GT11: =GU11+GV11 -> 14169.642 | GU11: =IFERROR($DS11*$FP11/MAX(0.000000001,$CV11)*(INDEX($S11:$AF11,1,MATCH(MAX(2000,MIN(2025,ROUND(2026-$CV11,0))),$S$4:$AF$4,1))+INDEX($S11:$AF11,1,MATCH(MAX(2000,MIN(2025,ROUND(2027-$CV11,0))),$S$4:$AF$4,1))+INDEX($S11:$AF11,1,MATCH(MAX(2000,MIN(2025,ROUND(2028-$CV11,0))),$S$4:$AF$4,1))+INDEX($S11:$AF11,1,MATCH(MAX(2000,MIN(2025,ROUND(2029-$CV11,0))),$S$4:$AF$4,1))+INDEX($S11:$AF11,1,MATCH(MAX(2000,MIN(2025,ROUND(2030-$CV11,0))),$S$4:$AF$4,1)))/MAX(1,$AF11),0) -> 11513.626 | GV11: =IFERROR($FF11*$BZ11,0) -> 2656.016 | GW11: =GX11+GY11 -> 12461.552 | GX11: =IFERROR($DT11*$FP11/MAX(0.000000001,$CW11)*(INDEX($S11:$AF11,1,MATCH(MAX(2000,MIN(2025,ROUND(2026-$CW11,0))),$S$4:$AF$4,1))+INDEX($S11:$AF11,1,MATCH(MAX(2000,MIN(2025,ROUND(2027-$CW11,0))),$S$4:$AF$4,1))+INDEX($S11:$AF11,1,MATCH(MAX(2000,MIN(2025,ROUND(2028-$CW11,0))),$S$4:$AF$4,1))+INDEX($S11:$AF11,1,MATCH(MAX(2000,MIN(2025,ROUND(2029-$CW11,0))),$S$4:$AF$4,1))+INDEX($S11:$AF11,1,MATCH(MAX(2000,MIN(2025,ROUND(2030-$CW11,0))),$S$4:$AF$4,1)))/MAX(1,$AF11),0) -> 9865.8996 | GY11: =IFERROR($FF11*$CA11,0) -> 2595.652 | GZ11: =HA11+HB11 -> 3760.0229 | HA11: =IFERROR($DU11*$FP11/MAX(0.000000001,$CX11)*(INDEX($S11:$AF11,1,MATCH(MAX(2000,MIN(2025,ROUND(2026-$CX11,0))),$S$4:$AF$4,1))+INDEX($S11:$AF11,1,MATCH(MAX(2000,MIN(2025,ROUND(2027-$CX11,0))),$S$4:$AF$4,1))+INDEX($S11:$AF11,1,MATCH(MAX(2000,MIN(2025,ROUND(2028-$CX11,0))),$S$4:$AF$4,1))+INDEX($S11:$AF11,1,MATCH(MAX(2000,MIN(2025,ROUND(2029-$CX11,0))),$S$4:$AF$4,1))+INDEX($S11:$AF11,1,MATCH(MAX(2000,MIN(2025,ROUND(2030-$CX11,0))),$S$4:$AF$4,1)))/MAX(1,$AF11),0) -> 2975.2909 | HB11: =IFERROR($FF11*$CB11,0) -> 784.732 | HC11: =HD11+HE11 -> 2449.8443 | HD11: =IFERROR($EB11*$FP11/MAX(0.000000001,$CY11)*(INDEX($S11:$AF11,1,MATCH(MAX(2000,MIN(2025,ROUND(2026-$CY11,0))),$S$4:$AF$4,1))+INDEX($S11:$AF11,1,MATCH(MAX(2000,MIN(2025,ROUND(2027-$CY11,0))),$S$4:$AF$4,1))+INDEX($S11:$AF11,1,MATCH(MAX(2000,MIN(2025,ROUND(2028-$CY11,0))),$S$4:$AF$4,1))+INDEX($S11:$AF11,1,MATCH(MAX(2000,MIN(2025,ROUND(2029-$CY11,0))),$S$4:$AF$4,1))+INDEX($S11:$AF11,1,MATCH(MAX(2000,MIN(2025,ROUND(2030-$CY11,0))),$S$4:$AF$4,1)))/MAX(1,$AF11),0) -> 2034.8418 | HE11: =IFERROR($FI11*$CG11,0) -> 415.0025 | HF11: =HG11+HH11 -> 9507.5386 | HG11: =IFERROR($EC11*$FP11/MAX(0.000000001,$CZ11)*(INDEX($S11:$AF11,1,MATCH(MAX(2000,MIN(2025,ROUND(2026-$CZ11,0))),$S$4:$AF$4,1))+INDEX($S11:$AF11,1,MATCH(MAX(2000,MIN(2025,ROUND(2027-$CZ11,0))),$S$4:$AF$4,1))+INDEX($S11:$AF11,1,MATCH(MAX(2000,MIN(2025,ROUND(2028-$CZ11,0))),$S$4:$AF$4,1))+INDEX($S11:$AF11,1,MATCH(MAX(2000,MIN(2025,ROUND(2029-$CZ11,0))),$S$4:$AF$4,1))+INDEX($S11:$AF11,1,MATCH(MAX(2000,MIN(2025,ROUND(2030-$CZ11,0))),$S$4:$AF$4,1)))/MAX(1,$AF11),0) -> 7432.5261 | HH11: =IFERROR($FI11*$CH11,0) -> 2075.0125 | HI11: =HJ11+HK11 -> 3815.2732 | HJ11: =IFERROR($ED11*$FP11/MAX(0.000000001,$DA11)*(INDEX($S11:$AF11,1,MATCH(MAX(2000,MIN(2025,ROUND(2026-$DA11,0))),$S$4:$AF$4,1))+INDEX($S11:$AF11,1,MATCH(MAX(2000,MIN(2025,ROUND(2027-$DA11,0))),$S$4:$AF$4,1))+INDEX($S11:$AF11,1,MATCH(MAX(2000,MIN(2025,ROUND(2028-$DA11,0))),$S$4:$AF$4,1))+INDEX($S11:$AF11,1,MATCH(MAX(2000,MIN(2025,ROUND(2029-$DA11,0))),$S$4:$AF$4,1))+INDEX($S11:$AF11,1,MATCH(MAX(2000,MIN(2025,ROUND(2030-$DA11,0))),$S$4:$AF$4,1)))/MAX(1,$AF11),0) -> 3068.2687 | HK11: =IFERROR($FI11*$CI11,0) -> 747.0045 | HL11: =HM11+HN11 -> 4813.119 | HM11: =IFERROR($EE11*$FP11/MAX(0.000000001,$DB11)*(INDEX($S11:$AF11,1,MATCH(MAX(2000,MIN(2025,ROUND(2026-$DB11,0))),$S$4:$AF$4,1))+INDEX($S11:$AF11,1,MATCH(MAX(2000,MIN(2025,ROUND(2027-$DB11,0))),$S$4:$AF$4,1))+INDEX($S11:$AF11,1,MATCH(MAX(2000,MIN(2025,ROUND(2028-$DB11,0))),$S$4:$AF$4,1))+INDEX($S11:$AF11,1,MATCH(MAX(2000,MIN(2025,ROUND(2029-$DB11,0))),$S$4:$AF$4,1))+INDEX($S11:$AF11,1,MATCH(MAX(2000,MIN(2025,ROUND(2030-$DB11,0))),$S$4:$AF$4,1)))/MAX(1,$AF11),0) -> 3900.1135 | HN11: =IFERROR($FI11*$CJ11,0) -> 913.0055 | HO11: =HP11+HQ11 -> 29859.373 | HP11: =IFERROR($EM11*$FP11/MAX(0.000000001,$DC11)*(INDEX($S11:$AF11,1,MATCH(MAX(2000,MIN(2025,ROUND(2026-$DC11,0))),$S$4:$AF$4,1))+INDEX($S11:$AF11,1,MATCH(MAX(2000,MIN(2025,ROUND(2027-$DC11,0))),$S$4:$AF$4,1))+INDEX($S11:$AF11,1,MATCH(MAX(2000,MIN(2025,ROUND(2028-$DC11,0))),$S$4:$AF$4,1))+INDEX($S11:$AF11,1,MATCH(MAX(2000,MIN(2025,ROUND(2029-$DC11,0))),$S$4:$AF$4,1))+INDEX($S11:$AF11,1,MATCH(MAX(2000,MIN(2025,ROUND(2030-$DC11,0))),$S$4:$AF$4,1)))/MAX(1,$AF11),0) -> 23830.519 | HQ11: =IFERROR($FL11*$CN11,0) -> 6028.8545 | HR11: =HS11+HT11 -> 17231.49 | HS11: =IFERROR($EN11*$FP11/MAX(0.000000001,$DD11)*(INDEX($S11:$AF11,1,MATCH(MAX(2000,MIN(2025,ROUND(2026-$DD11,0))),$S$4:$AF$4,1))+INDEX($S11:$AF11,1,MATCH(MAX(2000,MIN(2025,ROUND(2027-$DD11,0))),$S$4:$AF$4,1))+INDEX($S11:$AF11,1,MATCH(MAX(2000,MIN(2025,ROUND(2028-$DD11,0))),$S$4:$AF$4,1))+INDEX($S11:$AF11,1,MATCH(MAX(2000,MIN(2025,ROUND(2029-$DD11,0))),$S$4:$AF$4,1))+INDEX($S11:$AF11,1,MATCH(MAX(2000,MIN(2025,ROUND(2030-$DD11,0))),$S$4:$AF$4,1)))/MAX(1,$AF11),0) -> 12998.465 | HT11: =IFERROR($FL11*$CO11,0) -> 4233.0255 | HU11: =HV11+HW11 -> 11141.822 | HV11: =IFERROR($EO11*$FP11/MAX(0.000000001,$DE11)*(INDEX($S11:$AF11,1,MATCH(MAX(2000,MIN(2025,ROUND(2026-$DE11,0))),$S$4:$AF$4,1))+INDEX($S11:$AF11,1,MATCH(MAX(2000,MIN(2025,ROUND(2027-$DE11,0))),$S$4:$AF$4,1))+INDEX($S11:$AF11,1,MATCH(MAX(2000,MIN(2025,ROUND(2028-$DE11,0))),$S$4:$AF$4,1))+INDEX($S11:$AF11,1,MATCH(MAX(2000,MIN(2025,ROUND(2029-$DE11,0))),$S$4:$AF$4,1))+INDEX($S11:$AF11,1,MATCH(MAX(2000,MIN(2025,ROUND(2030-$DE11,0))),$S$4:$AF$4,1)))/MAX(1,$AF11),0) -> 8576.3519 | HW11: =IFERROR($FL11*$CP11,0) -> 2565.47 | HY11: =SUM(HZ11:ID11) -> 482856.96 | HZ11: =IFERROR(IO11*BE11,0)+IFERROR(IY11*BF11,0)+IFERROR(JI11*BG11,0)+IFERROR(JS11*BH11,0) -> 16101.96 | IA11: =IFERROR(IP11*BE11,0)+IFERROR(IZ11*BF11,0)+IFERROR(JJ11*BG11,0)+IFERROR(JT11*BH11,0) -> 203085.4 | IB11: =IFERROR(IQ11*BE11,0)+IFERROR(JA11*BF11,0)+IFERROR(JK11*BG11,0)+IFERROR(JU11*BH11,0) -> 234141.36 | IC11: =IFERROR(IR11*BE11,0)+IFERROR(JB11*BF11,0)+IFERROR(JL11*BG11,0)+IFERROR(JV11*BH11,0) -> 29528.235 | ID11: =IFERROR(IS11*BE11,0)+IFERROR(JC11*BF11,0)+IFERROR(JM11*BG11,0)+IFERROR(JW11*BH11,0) -> 0 | IE11: =SUM(IF11:IJ11) -> 154794.12 | IF11: =IFERROR(IT11*FB11,0)+IFERROR(JD11*FE11,0)+IFERROR(JN11*FH11,0)+IFERROR(JX11*FK11,0) -> 1749.1318 | IG11: =IFERROR(IU11*FB11,0)+IFERROR(JE11*FE11,0)+IFERROR(JO11*FH11,0)+IFERROR(JY11*FK11,0) -> 61050.384 | IH11: =IFERROR(IV11*FB11,0)+IFERROR(JF11*FE11,0)+IFERROR(JP11*FH11,0)+IFERROR(JZ11*FK11,0) -> 78362.702 | II11: =IFERROR(IW11*FB11,0)+IFERROR(JG11*FE11,0)+IFERROR(JQ11*FH11,0)+IFERROR(KA11*FK11,0) -> 12860.363 | IJ11: =IFERROR(IX11*FB11,0)+IFERROR(JH11*FE11,0)+IFERROR(JR11*FH11,0)+IFERROR(KB11*FK11,0) -> 771.53509 | IK11: 4.2 | IL11: Bonne | IM11: Parc existant centre sur le niveau mid, avec ventes 2026-2030 legerement plus qualitatives. Usines (>50 salariés) (Hors Ateliers industriels) : usage salarie de jour, maintenance planifiee et contraintes Code du travail; le mix reste guide par sanitaires salaries, cout global, robustesse et sobriete eau. | IO11: 0.03 | IP11: 0.4 | IQ11: 0.5 | IR11: 0.07 | IS11: 0 | IT11: 0.0078 | IU11: 0.3728 | IV11: 0.5222 | IW11: 0.0922 | IX11: 0.005 | IY11: 0.0312 | IZ11: 0.4154 | JA11: 0.4946 | JB11: 0.0589 | JC11: 0 | JD11: 0.009 | JE11: 0.3882 | JF11: 0.5168 | JG11: 0.0811 | JH11: 0.0049 | JI11: 0.054 | JJ11: 0.5397 | JK11: 0.3748 | JL11: 0.0315 | JM11: 0 | JN11: 0.0318 | JO11: 0.5125 | JP11: 0.397 | JQ11: 0.0537 | JR11: 0.005 | JS11: 0.0326 | JT11: 0.4148 | JU11: 0.4938 | JV11: 0.0588 | JW11: 0 | JX11: 0.0104 | JY11: 0.3876 | JZ11: 0.516 | KA11: 0.081 | KB11: 0.005 | KD11: ±4 pts | KE11: ±4 pts | KF11: 4.23 | KG11: Bonne | KH11: Parc existant : sanitaires salaries, cout global, robustesse et sobriete eau; usage salarie de jour, maintenance planifiee et contraintes Code du travail. La montee en confort reste proportionnee au budget et au rythme de renovation. | KI11: image client => premiumisation ciblee | KJ11: Usines (>50 salariés) (Hors Ateliers industriels) : ventes 2026-2030 en leger glissement vers moyen/premium lorsque le neuf ou les renov. lourdes interviennent. Le centre de gravite reste toutefois module par sanitaires salaries, cout global, robustesse et sobriete eau et par la part dominante de travaux sur parc existant.
A12: =A11+1 -> 4 | B12: Tertiaire & Industriel | C12: Usines & Ateliers | D12: Ateliers industriels / de maintenance (>50 personnes) | E12: Hors ERP | F12: Hors ERP dominant / ERP ponctuel selon accueil | G12: hors ERP | H12: non | I12: Sous-ensemble distingué de l'ancienne ligne 'Usines (>50 personnes)'. Ventilation proxy pour isoler les ateliers et centres de maintenance. | J12: Atelier de maintenance, atelier technique, atelier industriel | K12: non | L12: oui | M12: Site Etablissement principal | N12: proxy de ventilation d'une ligne existante (somme conservée) | O12: Moyenne | P12: Ancienne ligne : Usines (>50 personnes) | Q12: 1 | R12: 8500 | S12: 6200 | T12: 5900 | U12: 5500 | V12: 5100 | W12: 5050 | X12: 5000 | Y12: 4960 | Z12: 4920 | AA12: 4850 | AB12: 4860 | AC12: 4900 | AD12: 4950 | AE12: 5000 | AF12: 5050 | AG12: 5090 | AH12: 5130 | AI12: 5170 | AJ12: 5200 | AK12: 5230 | AL12: Tendance baissière historique, stabilisation récente (besoins de maintenance et à quelques relocalisations industrielles). Incertitude plus forte que pour les usines ou la logistique. | AM12: Insee Flores 2024 ; Insee Focus 2024 sur l'industrie manufacturière ; proxy maintenance industrielle. | AP12: 140 | AQ12: 119 | AR12: 14 | AS12: 7 | AU12: Usine >50 pers. : base code du travail + douches collectives d'atelier/vestiaires ; pas de sanitaires individuels. | AV12: Capacité type ≈ 119 salariés/usagers principaux + 14 staff support + 7 prestataires/intérimaires. Application prioritaire du Code du travail : 1 lavabo/10 travailleurs, 1 WC + 1 urinoir/20 hommes, 2 WC/20 femmes, avec douches dès que les postes sont salissants ; arrondis par noyaux sanitaires/vestiaires. Calibrage selon capacité simultanée, répartition de flux et organisation réelle du site. | AW12: Profil moyen, capacité moyenne ≈ 140 personnes. Moyenne pondérée terrain : parc majoritairement petits/moyens sites, grands sites intégrés sans surpondération ; usage 2025 modérée, majoritairement courte. | AX12: Code du travail, art. R4228-1 à R4228-10 (installations sanitaires, vestiaires, lavabos, douches, WC) : https://www.legifrance.gouv.fr/codes/section_lc/LEGITEXT000006072050/LEGISCTA000018489205/ ; https://code.travail.gouv.fr/code-du-travail/r4228-10 | AZ12: 14 | BA12: 7 | BB12: 4.5 | BC12: 10 | BD12: =SUM(BE12:BH12) -> 179275 | BE12: =AF12*AZ12 -> 70700 | BF12: =AF12*BA12 -> 35350 | BG12: =AF12*BB12 -> 22725 | BH12: =AF12*BC12 -> 50500 | BI12: =SUM(BJ12:BM12) -> 185665 | BJ12: =AK12*AZ12 -> 73220 | BK12: =AK12*BA12 -> 36610 | BL12: =AK12*BB12 -> 23535 | BM12: =AK12*BC12 -> 52300 | BO12: 0.41 | BP12: 0.43 | BQ12: 0.12 | BR12: 0.04 | BS12: 0.38 | BT12: 0.43 | BU12: 0.15 | BV12: 0.04 | BW12: 0.25 | BX12: 0.7 | BY12: 0.05 | BZ12: 0.2 | CA12: 0.74 | CB12: 0.06 | CC12: 0.1 | CD12: 0.65 | CE12: 0.08 | CF12: 0.17 | CG12: 0.09 | CH12: 0.65 | CI12: 0.1 | CJ12: 0.16 | CK12: 0.45 | CL12: 0.5 | CM12: 0.05 | CN12: 0.37 | CO12: 0.55 | CP12: 0.08 | CR12: 12 | CS12: 13 | CT12: 9 | CU12: 11 | CV12: 11 | CW12: 11 | CX12: 8 | CY12: 10 | CZ12: 12 | DA12: 8 | DB12: 10 | DC12: 11 | DD12: 12 | DE12: 9 | DF12: Usage diffus, entretien régulier et qualité de finition plus élevée que dans les ERP de transit. Les durées de vie sont donc au-dessus de la moyenne. L'électronique reste plus courte si elle existe, surtout hors contrats de maintenance dédiés. Le remplacement se fait souvent par chambre ou par lot lors des rénovations d'étage. Hôtellerie / hébergement marchand : Usage plus résidentiel, faible vandalisme mais attente client élevée. renouvellement souvent par programme de rénovation chambre / salle de bains plus que par panne seule. | DH12: =$BE12*BO12 -> 28987 | DI12: =$BE12*BP12 -> 30401 | DJ12: =$BE12*BQ12 -> 8484 | DK12: =$BE12*BR12 -> 2828 | DL12: Dans l’industrie, le parc commun privilégie la robustesse : temporisé mécanique dominant, avec une part d’équipements spécifiques/industriels classés en 'autres'. | DM12: =$BJ12*BS12 -> 27823.6 | DN12: =$BJ12*BT12 -> 31484.6 | DO12: =$BJ12*BU12 -> 10983 | DP12: =$BJ12*BV12 -> 2928.8 | DQ12: En industrie, la bascule reste limitée : le mitigeur baisse un peu, l’électronique progresse surtout dans les sanitaires d’accueil/tertiaires, mais le socle mécanique demeure robuste sur site. | DS12: =$BF12*BW12 -> 8837.5 | DT12: =$BF12*BX12 -> 24745 | DU12: =$BF12*BY12 -> 1767.5 | DV12: Les douches de vestiaires sont très majoritairement temporisées mécaniques sur le parc existant. | DW12: =$BK12*BZ12 -> 7322 | DX12: =$BK12*CA12 -> 27091.4 | DY12: =$BK12*CB12 -> 2196.6 | DZ12: Les douches d’usine progressent modérément vers l’électronique, mais le parc reste surtout robuste et mécanique. | EB12: =$BG12*CC12 -> 2272.5 | EC12: =$BG12*CD12 -> 14771.25 | ED12: =$BG12*CE12 -> 1818 | EE12: =$BG12*CF12 -> 3863.25 | EF12: Les urinoirs restent surtout mécaniques ou collectifs anciens ; l’automatique est minoritaire. | EG12: =$BL12*CG12 -> 2118.15 | EH12: =$BL12*CH12 -> 15297.75 | EI12: =$BL12*CI12 -> 2353.5 | EJ12: =$BL12*CJ12 -> 3765.6 | EK12: Le direct mécanique reste fort ; la baisse des réservoirs profite d’abord au mécanique robuste, l’automatique progressant plus lentement. | EM12: =$BH12*CK12 -> 22725 | EN12: =$BH12*CL12 -> 25250 | EO12: =$BH12*CM12 -> 2525 | EP12: La chasse directe est déjà très présente dans les blocs industriels à fort passage, même si le réservoir reste important dans le parc ancien. | EQ12: =$BM12*CN12 -> 19351 | ER12: =$BM12*CO12 -> 28765 | ES12: =$BM12*CP12 -> 4184 | ET12: Le direct progresse pour robustesse, mais le parc existant conserve une forte inertie et le réservoir reste encore important. | EV12: =IFERROR(EY12/EX12,0) -> 0.74206673 | EW12: =IFERROR(EZ12/EX12,0) -> 0.25793327 | EX12: =EY12+EZ12 -> 91824.755 | EY12: =SUM(FB12,FE12,FH12,FK12) -> 68140.096 | EZ12: =SUM(FC12,FF12,FI12,FL12) -> 23684.659 | FA12: =FB12+FC12 -> 35390.163 | FB12: =SUM(GI12,GL12,GO12,GR12) -> 26049.734 | FC12: =MAX(0,$BJ12-$BE12)+$BE12*$FO12 -> 9340.429 | FD12: =FE12+FF12 -> 18635.599 | FE12: =SUM(GU12,GX12,HA12) -> 13965.385 | FF12: =MAX(0,$BK12-$BF12)+$BF12*$FO12 -> 4670.2145 | FG12: =FH12+FI12 -> 11927.374 | FH12: =SUM(HD12,HG12,HJ12,HM12) -> 8925.0929 | FI12: =MAX(0,$BL12-$BG12)+$BG12*$FO12 -> 3002.2807 | FJ12: =FK12+FL12 -> 25871.619 | FK12: =SUM(HP12,HS12,HV12) -> 19199.884 | FL12: =MAX(0,$BM12-$BH12)+$BH12*$FO12 -> 6671.735 | FN12: Moyenne à Bonne | FO12: 0.09647 | FP12: 0.86189 | FQ12: 86,2% retenu : les sanitaires et vestiaires sont souvent repris lors de travaux sécurité/process, mais le phasage industriel limite une matérialisation totale. | FS12: 3.45 | FT12: =RANK($FS12,$FS$16:$FS$17,0)+COUNTIF($FS$16:$FS17,$FS12)-1 -> #N/A | FU12: 4.05 | FV12: =RANK($FU12,$FU$16:$FU$17,0)+COUNTIF($FU$16:$FU17,$FU12)-1 -> #N/A | FW12: 2.72 | FX12: =RANK($FW12,$FW$16:$FW$17,0)+COUNTIF($FW$16:$FW17,$FW12)-1 -> #N/A | FZ12: Potentiel rénovation élevé : vestiaires, douches, sanitaires et bâtiments sociaux doivent suivre les exigences de sécurité, d’hygiène et de recrutement. Les volumes se concentrent surtout sur lavabos et wc. En rénovation, les maîtres d’ouvrage privilégient des références robustes, vite posées et faciles à maintenir dans des ambiances humides. | GA12: Potentiel neuf faible : soutenu par la réindustrialisation, la décarbonation et certains investissements France 2030/Choose France, mais très concentré par filière et par site. Le neuf est quasi nul dans le modèle et renvoie surtout à des reconstructions ou remplacements de sites. | GB12: Projets phares réno : vestiaires, douches, sanitaires salariés, bases vie, bâtiments sociaux et modernisation d’ateliers existants. | GC12: Projets phares neuf : nouvelles usines, extensions de capacité, ateliers, bâtiments salariés et bases vie liées à la décarbonation ou à la relocalisation. | GD12: Dynamique réno 2026-2030 : soutenue, car elle accompagne la modernisation des sites existants et l’amélioration des conditions de travail. | GE12: Dynamique neuf 2026-2030 : réelle mais très polarisée ; les grands projets tirent le marché, tandis que beaucoup d’intentions ne passent pas toutes en chantiers dans les mêmes délais. | GF12: =HYPERLINK("https://experience.france2030.gouv.fr/fr/visit/decarbonation-de-leconomie/la-decarbonation-de-l-industrie/full/","https://experience.france2030.gouv.fr/fr/visit/decarbonation-de-leconomie/la-decarbonation-de-l-industrie/full/")&CHAR(10)&HYPERLINK("https://www.tresor.economie.gouv.fr/Articles/2025/05/19/choose-france-2025-une-edition-record-au-service-de-la-souverainete-economique-et-de-l-innovation","https://www.tresor.economie.gouv.fr/Articles/2025/05/19/choose-france-2025-une-edition-record-au-service-de-la-souverainete-economique-et-de-l-innovation")&CHAR(10)&HYPERLINK("https://www.statistiques.developpement-durable.gouv.fr/construction-de-locaux-resultats-fin-janvier-2026-france-entiere","https://www.statistiques.developpement-durable.gouv.fr/construction-de-locaux-resultats-fin-janvier-2026-france-entiere")&CHAR(10)&HYPERLINK("https://www.insee.fr/fr/statistiques/8671745","https://www.insee.fr/fr/statistiques/8671745")&CHAR(10)&HYPERLINK("https://www.insee.fr/fr/statistiques/8906564","https://www.insee.fr/fr/statistiques/8906564") -> https://experience.france2030.gouv.fr/fr/visit/decarbonation-de-leconomie/la-decarbonation-de-l-industrie/full/ https://www.tresor.economie.gouv.fr/Articles/2025/05/19/choose-france-2025-une-edition-record-au-service-de-la-souverainete-economique-et-de-l-innovation https://www.statistiques.developpement-durable.gouv.fr/construction-de-locaux-resultats-fin-janvier-2026-france-entiere https://www.insee.fr/fr/statistiques/8671745 https://www.insee.fr/fr/statistiques/8906564 | GH12: =GI12+GJ12 -> 14107.616 | GI12: =IFERROR($DH12*$FP12/MAX(0.000000001,$CR12)*(INDEX($S12:$AF12,1,MATCH(MAX(2000,MIN(2025,ROUND(2026-$CR12,0))),$S$4:$AF$4,1))+INDEX($S12:$AF12,1,MATCH(MAX(2000,MIN(2025,ROUND(2027-$CR12,0))),$S$4:$AF$4,1))+INDEX($S12:$AF12,1,MATCH(MAX(2000,MIN(2025,ROUND(2028-$CR12,0))),$S$4:$AF$4,1))+INDEX($S12:$AF12,1,MATCH(MAX(2000,MIN(2025,ROUND(2029-$CR12,0))),$S$4:$AF$4,1))+INDEX($S12:$AF12,1,MATCH(MAX(2000,MIN(2025,ROUND(2030-$CR12,0))),$S$4:$AF$4,1)))/MAX(1,$AF12),0) -> 10558.253 | GJ12: =IFERROR($FC12*$BS12,0) -> 3549.363 | GK12: =GL12+GM12 -> 14453.408 | GL12: =IFERROR($DI12*$FP12/MAX(0.000000001,$CS12)*(INDEX($S12:$AF12,1,MATCH(MAX(2000,MIN(2025,ROUND(2026-$CS12,0))),$S$4:$AF$4,1))+INDEX($S12:$AF12,1,MATCH(MAX(2000,MIN(2025,ROUND(2027-$CS12,0))),$S$4:$AF$4,1))+INDEX($S12:$AF12,1,MATCH(MAX(2000,MIN(2025,ROUND(2028-$CS12,0))),$S$4:$AF$4,1))+INDEX($S12:$AF12,1,MATCH(MAX(2000,MIN(2025,ROUND(2029-$CS12,0))),$S$4:$AF$4,1))+INDEX($S12:$AF12,1,MATCH(MAX(2000,MIN(2025,ROUND(2030-$CS12,0))),$S$4:$AF$4,1)))/MAX(1,$AF12),0) -> 10437.024 | GM12: =IFERROR($FC12*$BT12,0) -> 4016.3845 | GN12: =GO12+GP12 -> 5357.2544 | GO12: =IFERROR($DJ12*$FP12/MAX(0.000000001,$CT12)*(INDEX($S12:$AF12,1,MATCH(MAX(2000,MIN(2025,ROUND(2026-$CT12,0))),$S$4:$AF$4,1))+INDEX($S12:$AF12,1,MATCH(MAX(2000,MIN(2025,ROUND(2027-$CT12,0))),$S$4:$AF$4,1))+INDEX($S12:$AF12,1,MATCH(MAX(2000,MIN(2025,ROUND(2028-$CT12,0))),$S$4:$AF$4,1))+INDEX($S12:$AF12,1,MATCH(MAX(2000,MIN(2025,ROUND(2029-$CT12,0))),$S$4:$AF$4,1))+INDEX($S12:$AF12,1,MATCH(MAX(2000,MIN(2025,ROUND(2030-$CT12,0))),$S$4:$AF$4,1)))/MAX(1,$AF12),0) -> 3956.19 | GP12: =IFERROR($FC12*$BU12,0) -> 1401.0643 | GQ12: =GR12+GS12 -> 1471.8844 | GR12: =IFERROR($DK12*$FP12/MAX(0.000000001,$CU12)*(INDEX($S12:$AF12,1,MATCH(MAX(2000,MIN(2025,ROUND(2026-$CU12,0))),$S$4:$AF$4,1))+INDEX($S12:$AF12,1,MATCH(MAX(2000,MIN(2025,ROUND(2027-$CU12,0))),$S$4:$AF$4,1))+INDEX($S12:$AF12,1,MATCH(MAX(2000,MIN(2025,ROUND(2028-$CU12,0))),$S$4:$AF$4,1))+INDEX($S12:$AF12,1,MATCH(MAX(2000,MIN(2025,ROUND(2029-$CU12,0))),$S$4:$AF$4,1))+INDEX($S12:$AF12,1,MATCH(MAX(2000,MIN(2025,ROUND(2030-$CU12,0))),$S$4:$AF$4,1)))/MAX(1,$AF12),0) -> 1098.2673 | GS12: =IFERROR($FC12*$BV12,0) -> 373.61716 | GT12: =GU12+GV12 -> 4366.1281 | GU12: =IFERROR($DS12*$FP12/MAX(0.000000001,$CV12)*(INDEX($S12:$AF12,1,MATCH(MAX(2000,MIN(2025,ROUND(2026-$CV12,0))),$S$4:$AF$4,1))+INDEX($S12:$AF12,1,MATCH(MAX(2000,MIN(2025,ROUND(2027-$CV12,0))),$S$4:$AF$4,1))+INDEX($S12:$AF12,1,MATCH(MAX(2000,MIN(2025,ROUND(2028-$CV12,0))),$S$4:$AF$4,1))+INDEX($S12:$AF12,1,MATCH(MAX(2000,MIN(2025,ROUND(2029-$CV12,0))),$S$4:$AF$4,1))+INDEX($S12:$AF12,1,MATCH(MAX(2000,MIN(2025,ROUND(2030-$CV12,0))),$S$4:$AF$4,1)))/MAX(1,$AF12),0) -> 3432.0852 | GV12: =IFERROR($FF12*$BZ12,0) -> 934.0429 | GW12: =GX12+GY12 -> 13065.797 | GX12: =IFERROR($DT12*$FP12/MAX(0.000000001,$CW12)*(INDEX($S12:$AF12,1,MATCH(MAX(2000,MIN(2025,ROUND(2026-$CW12,0))),$S$4:$AF$4,1))+INDEX($S12:$AF12,1,MATCH(MAX(2000,MIN(2025,ROUND(2027-$CW12,0))),$S$4:$AF$4,1))+INDEX($S12:$AF12,1,MATCH(MAX(2000,MIN(2025,ROUND(2028-$CW12,0))),$S$4:$AF$4,1))+INDEX($S12:$AF12,1,MATCH(MAX(2000,MIN(2025,ROUND(2029-$CW12,0))),$S$4:$AF$4,1))+INDEX($S12:$AF12,1,MATCH(MAX(2000,MIN(2025,ROUND(2030-$CW12,0))),$S$4:$AF$4,1)))/MAX(1,$AF12),0) -> 9609.8384 | GY12: =IFERROR($FF12*$CA12,0) -> 3455.9587 | GZ12: =HA12+HB12 -> 1203.6741 | HA12: =IFERROR($DU12*$FP12/MAX(0.000000001,$CX12)*(INDEX($S12:$AF12,1,MATCH(MAX(2000,MIN(2025,ROUND(2026-$CX12,0))),$S$4:$AF$4,1))+INDEX($S12:$AF12,1,MATCH(MAX(2000,MIN(2025,ROUND(2027-$CX12,0))),$S$4:$AF$4,1))+INDEX($S12:$AF12,1,MATCH(MAX(2000,MIN(2025,ROUND(2028-$CX12,0))),$S$4:$AF$4,1))+INDEX($S12:$AF12,1,MATCH(MAX(2000,MIN(2025,ROUND(2029-$CX12,0))),$S$4:$AF$4,1))+INDEX($S12:$AF12,1,MATCH(MAX(2000,MIN(2025,ROUND(2030-$CX12,0))),$S$4:$AF$4,1)))/MAX(1,$AF12),0) -> 923.46127 | HB12: =IFERROR($FF12*$CB12,0) -> 280.21287 | HC12: =HD12+HE12 -> 1231.2988 | HD12: =IFERROR($EB12*$FP12/MAX(0.000000001,$CY12)*(INDEX($S12:$AF12,1,MATCH(MAX(2000,MIN(2025,ROUND(2026-$CY12,0))),$S$4:$AF$4,1))+INDEX($S12:$AF12,1,MATCH(MAX(2000,MIN(2025,ROUND(2027-$CY12,0))),$S$4:$AF$4,1))+INDEX($S12:$AF12,1,MATCH(MAX(2000,MIN(2025,ROUND(2028-$CY12,0))),$S$4:$AF$4,1))+INDEX($S12:$AF12,1,MATCH(MAX(2000,MIN(2025,ROUND(2029-$CY12,0))),$S$4:$AF$4,1))+INDEX($S12:$AF12,1,MATCH(MAX(2000,MIN(2025,ROUND(2030-$CY12,0))),$S$4:$AF$4,1)))/MAX(1,$AF12),0) -> 961.09354 | HE12: =IFERROR($FI12*$CG12,0) -> 270.20527 | HF12: =HG12+HH12 -> 7331.7769 | HG12: =IFERROR($EC12*$FP12/MAX(0.000000001,$CZ12)*(INDEX($S12:$AF12,1,MATCH(MAX(2000,MIN(2025,ROUND(2026-$CZ12,0))),$S$4:$AF$4,1))+INDEX($S12:$AF12,1,MATCH(MAX(2000,MIN(2025,ROUND(2027-$CZ12,0))),$S$4:$AF$4,1))+INDEX($S12:$AF12,1,MATCH(MAX(2000,MIN(2025,ROUND(2028-$CZ12,0))),$S$4:$AF$4,1))+INDEX($S12:$AF12,1,MATCH(MAX(2000,MIN(2025,ROUND(2029-$CZ12,0))),$S$4:$AF$4,1))+INDEX($S12:$AF12,1,MATCH(MAX(2000,MIN(2025,ROUND(2030-$CZ12,0))),$S$4:$AF$4,1)))/MAX(1,$AF12),0) -> 5380.2945 | HH12: =IFERROR($FI12*$CH12,0) -> 1951.4825 | HI12: =HJ12+HK12 -> 1250.0739 | HJ12: =IFERROR($ED12*$FP12/MAX(0.000000001,$DA12)*(INDEX($S12:$AF12,1,MATCH(MAX(2000,MIN(2025,ROUND(2026-$DA12,0))),$S$4:$AF$4,1))+INDEX($S12:$AF12,1,MATCH(MAX(2000,MIN(2025,ROUND(2027-$DA12,0))),$S$4:$AF$4,1))+INDEX($S12:$AF12,1,MATCH(MAX(2000,MIN(2025,ROUND(2028-$DA12,0))),$S$4:$AF$4,1))+INDEX($S12:$AF12,1,MATCH(MAX(2000,MIN(2025,ROUND(2029-$DA12,0))),$S$4:$AF$4,1))+INDEX($S12:$AF12,1,MATCH(MAX(2000,MIN(2025,ROUND(2030-$DA12,0))),$S$4:$AF$4,1)))/MAX(1,$AF12),0) -> 949.84587 | HK12: =IFERROR($FI12*$CI12,0) -> 300.22807 | HL12: =HM12+HN12 -> 2114.2239 | HM12: =IFERROR($EE12*$FP12/MAX(0.000000001,$DB12)*(INDEX($S12:$AF12,1,MATCH(MAX(2000,MIN(2025,ROUND(2026-$DB12,0))),$S$4:$AF$4,1))+INDEX($S12:$AF12,1,MATCH(MAX(2000,MIN(2025,ROUND(2027-$DB12,0))),$S$4:$AF$4,1))+INDEX($S12:$AF12,1,MATCH(MAX(2000,MIN(2025,ROUND(2028-$DB12,0))),$S$4:$AF$4,1))+INDEX($S12:$AF12,1,MATCH(MAX(2000,MIN(2025,ROUND(2029-$DB12,0))),$S$4:$AF$4,1))+INDEX($S12:$AF12,1,MATCH(MAX(2000,MIN(2025,ROUND(2030-$DB12,0))),$S$4:$AF$4,1)))/MAX(1,$AF12),0) -> 1633.859 | HN12: =IFERROR($FI12*$CJ12,0) -> 480.36492 | HO12: =HP12+HQ12 -> 11293.904 | HP12: =IFERROR($EM12*$FP12/MAX(0.000000001,$DC12)*(INDEX($S12:$AF12,1,MATCH(MAX(2000,MIN(2025,ROUND(2026-$DC12,0))),$S$4:$AF$4,1))+INDEX($S12:$AF12,1,MATCH(MAX(2000,MIN(2025,ROUND(2027-$DC12,0))),$S$4:$AF$4,1))+INDEX($S12:$AF12,1,MATCH(MAX(2000,MIN(2025,ROUND(2028-$DC12,0))),$S$4:$AF$4,1))+INDEX($S12:$AF12,1,MATCH(MAX(2000,MIN(2025,ROUND(2029-$DC12,0))),$S$4:$AF$4,1))+INDEX($S12:$AF12,1,MATCH(MAX(2000,MIN(2025,ROUND(2030-$DC12,0))),$S$4:$AF$4,1)))/MAX(1,$AF12),0) -> 8825.3618 | HQ12: =IFERROR($FL12*$CN12,0) -> 2468.5419 | HR12: =HS12+HT12 -> 12866.539 | HS12: =IFERROR($EN12*$FP12/MAX(0.000000001,$DD12)*(INDEX($S12:$AF12,1,MATCH(MAX(2000,MIN(2025,ROUND(2026-$DD12,0))),$S$4:$AF$4,1))+INDEX($S12:$AF12,1,MATCH(MAX(2000,MIN(2025,ROUND(2027-$DD12,0))),$S$4:$AF$4,1))+INDEX($S12:$AF12,1,MATCH(MAX(2000,MIN(2025,ROUND(2028-$DD12,0))),$S$4:$AF$4,1))+INDEX($S12:$AF12,1,MATCH(MAX(2000,MIN(2025,ROUND(2029-$DD12,0))),$S$4:$AF$4,1))+INDEX($S12:$AF12,1,MATCH(MAX(2000,MIN(2025,ROUND(2030-$DD12,0))),$S$4:$AF$4,1)))/MAX(1,$AF12),0) -> 9197.0845 | HT12: =IFERROR($FL12*$CO12,0) -> 3669.4543 | HU12: =HV12+HW12 -> 1711.1763 | HV12: =IFERROR($EO12*$FP12/MAX(0.000000001,$DE12)*(INDEX($S12:$AF12,1,MATCH(MAX(2000,MIN(2025,ROUND(2026-$DE12,0))),$S$4:$AF$4,1))+INDEX($S12:$AF12,1,MATCH(MAX(2000,MIN(2025,ROUND(2027-$DE12,0))),$S$4:$AF$4,1))+INDEX($S12:$AF12,1,MATCH(MAX(2000,MIN(2025,ROUND(2028-$DE12,0))),$S$4:$AF$4,1))+INDEX($S12:$AF12,1,MATCH(MAX(2000,MIN(2025,ROUND(2029-$DE12,0))),$S$4:$AF$4,1))+INDEX($S12:$AF12,1,MATCH(MAX(2000,MIN(2025,ROUND(2030-$DE12,0))),$S$4:$AF$4,1)))/MAX(1,$AF12),0) -> 1177.4375 | HW12: =IFERROR($FL12*$CP12,0) -> 533.7388 | HY12: =SUM(HZ12:ID12) -> 179275 | HZ12: =IFERROR(IO12*BE12,0)+IFERROR(IY12*BF12,0)+IFERROR(JI12*BG12,0)+IFERROR(JS12*BH12,0) -> 29480.89 | IA12: =IFERROR(IP12*BE12,0)+IFERROR(IZ12*BF12,0)+IFERROR(JJ12*BG12,0)+IFERROR(JT12*BH12,0) -> 109379.97 | IB12: =IFERROR(IQ12*BE12,0)+IFERROR(JA12*BF12,0)+IFERROR(JK12*BG12,0)+IFERROR(JU12*BH12,0) -> 40414.14 | IC12: =IFERROR(IR12*BE12,0)+IFERROR(JB12*BF12,0)+IFERROR(JL12*BG12,0)+IFERROR(JV12*BH12,0) -> 0 | ID12: =IFERROR(IS12*BE12,0)+IFERROR(JC12*BF12,0)+IFERROR(JM12*BG12,0)+IFERROR(JW12*BH12,0) -> 0 | IE12: =SUM(IF12:IJ12) -> 68140.096 | IF12: =IFERROR(IT12*FB12,0)+IFERROR(JD12*FE12,0)+IFERROR(JN12*FH12,0)+IFERROR(JX12*FK12,0) -> 6069.2255 | IG12: =IFERROR(IU12*FB12,0)+IFERROR(JE12*FE12,0)+IFERROR(JO12*FH12,0)+IFERROR(JY12*FK12,0) -> 36635.288 | IH12: =IFERROR(IV12*FB12,0)+IFERROR(JF12*FE12,0)+IFERROR(JP12*FH12,0)+IFERROR(JZ12*FK12,0) -> 25435.583 | II12: =IFERROR(IW12*FB12,0)+IFERROR(JG12*FE12,0)+IFERROR(JQ12*FH12,0)+IFERROR(KA12*FK12,0) -> 0 | IJ12: =IFERROR(IX12*FB12,0)+IFERROR(JH12*FE12,0)+IFERROR(JR12*FH12,0)+IFERROR(KB12*FK12,0) -> 0 | IK12: 4.18 | IL12: Bonne | IM12: Parc existant surtout standard. Les ventes restent proches du parc, centré sur standard, car le trafic et la robustesse maintiennent un cahier des charges très fonctionnel. La rénovation restant majoritaire, le mix de ventes reste proche du parc et monte surtout d’un cran sur les opérations lourdes. Sites industriels : le sanitaire suit d’abord la logique d’exploitation, d’entretien et de robustesse ; l’image pèse peu hors bâtiments administratifs. | IO12: 0.1319 | IP12: 0.5998 | IQ12: 0.2683 | IR12: 0 | IS12: 0 | IT12: 0.076 | IU12: 0.5012 | IV12: 0.4228 | IW12: 0 | IX12: 0 | IY12: 0.1749 | IZ12: 0.6189 | JA12: 0.2062 | JB12: 0 | JC12: 0 | JD12: 0.0902 | JE12: 0.5548 | JF12: 0.355 | JG12: 0 | JH12: 0 | JI12: 0.2522 | JJ12: 0.6162 | JK12: 0.1316 | JL12: 0 | JM12: 0 | JN12: 0.137 | JO12: 0.6033 | JP12: 0.2597 | JQ12: 0 | JR12: 0 | JS12: 0.1632 | JT12: 0.6157 | JU12: 0.2211 | JV12: 0 | JW12: 0 | JX12: 0.0837 | JY12: 0.5441 | JZ12: 0.3722 | KA12: 0 | KB12: 0 | KD12: ±4 pts | KE12: ±4 pts | KF12: 4.35 | KG12: Bonne | KH12: Sites industriels : le sanitaire suit d’abord la logique d’exploitation, d’entretien et de robustesse ; l’image pèse peu hors bâtiments administratifs. | KI12: forte fréquentation ⇒ standard ↑, premium/luxe ↓ ; rénovation dominante ⇒ progression graduelle | KJ12: Usines (>50 personnes) : sanitaires d’usine exposés aux usages intensifs et à une logique strictement fonctionnelle. Ventes 2026-2030 : glissement vers davantage de moyen / premium. La rénovation reste majoritaire (81% des ventes, contre 19% en neuf) ; le neuf tire le mix vers le haut sans renverser le centre de gravité. L’écart de niveau de confort entre neuf et rénovation reste perceptible.
A13: =A12+1 -> 5 | B13: Culte, Vie civique & Services publics | C13: Administrations / services publics | D13: Mairies / hôtels de ville | E13: W | F13: ERP | G13: ERP | H13: oui | I13: Administrations recevant du public. | J13: Mairie, hôtel de ville | K13: oui | L13: oui | M13: Site Etablissement principal | N13: série publique directe | O13: Elevé | Q13: 1 | R13: 250 | S13: 37573 | T13: 37554 | U13: 37437 | V13: 37446 | W13: 37385 | X13: 37476 | Y13: 37592 | Z13: 37560 | AA13: 37563 | AB13: 37565 | AC13: 37560 | AD13: 37555 | AE13: 37566 | AF13: 37496 | AG13: 37496 | AH13: 37490 | AI13: 37480 | AJ13: 37470 | AK13: 37460 | AL13: Recompte par sites administratifs municipaux. Base = nbre communes (DGCL/Insee) ; supplément = subdivisions communales officiellement dotées d’annexe de mairie (communes associées, communes déléguées, arrondissements municipaux). | AM13: nombre de communes = proxy du nombre de mairies principales. Dynamique projetée 2027-2030: baisse très lente. Fiabilité: bonne. | AN13: https://www.vie-publique.fr/en-bref/298350-collectivites-34-875-communes-au-1er-janvier-2025 | AP13: 40 | AQ13: 25 | AR13: 12 | AS13: 3 | AU13: Mairie/hôtel de ville : bloc public/état civil + sanitaires agents. | AV13: Capacité type ≈ 25 usagers principaux + 12 staff + 3 autre public. Accueil administratif de proximité, salles de réunion et élus/agents. Dimensionnement unitaire retenu : 1 bloc public accessible + sanitaires personnel, ajustés par taille de commune. Hypothèse d'usage : capacité simultanée moyenne 2026, répartition par flux réels, arrondie par blocs fonctionnels et exclusion des sanitaires strictement privatifs sauf cas explicitement collectifs. | AW13: Profil petit, capacité moyenne ≈ 40 personnes. Moyenne pondérée terrain : parc majoritairement petits/moyens sites, grands sites intégrés sans surpondération ; usage 2025 forte à très forte. | AX13: ERP/accessibilité sanitaires publics : https://www.legifrance.gouv.fr/loda/article_lc/LEGIARTI000034485966/ ; Code du travail sanitaires salariés : https://www.legifrance.gouv.fr/codes/id/LEGISCTA000018531984 ; INRS : https://www.inrs.fr/publications/juridique/focus-juridiques/focus-sanitaires-toilettes.html | AZ13: 3 | BA13: 0 | BB13: 0.3 | BC13: 3 | BD13: =SUM(BE13:BH13) -> 236224.8 | BE13: =AF13*AZ13 -> 112488 | BF13: =AF13*BA13 -> 0 | BG13: =AF13*BB13 -> 11248.8 | BH13: =AF13*BC13 -> 112488 | BI13: =SUM(BJ13:BM13) -> 235998 | BJ13: =AK13*AZ13 -> 112380 | BK13: =AK13*BA13 -> 0 | BL13: =AK13*BB13 -> 11238 | BM13: =AK13*BC13 -> 112380 | BO13: 0.33 | BP13: 0.46 | BQ13: 0.17 | BR13: 0.04 | BS13: 0.29 | BT13: 0.46 | BU13: 0.22 | BV13: 0.03 | CC13: 0.12 | CD13: 0.5 | CE13: 0.15 | CF13: 0.23 | CG13: 0.1 | CH13: 0.5 | CI13: 0.18 | CJ13: 0.22 | CK13: 0.55 | CL13: 0.3 | CM13: 0.15 | CN13: 0.47 | CO13: 0.33 | CP13: 0.2 | CR13: 13 | CS13: 14 | CT13: 10 | CU13: 12 | CY13: 11 | CZ13: 13 | DA13: 9 | DB13: 11 | DC13: 14 | DD13: 14 | DE13: 10 | DF13: Accueil public régulier mais flux modéré, cérémonies ponctuelles et faible humidité; maintenance patrimoniale municipale. Long, proche préfecture mais trafic moindre. Usage public régulier globalement respectueux, avec maintenance patrimoniale classique. Temporisés mécaniques gardent un léger avantage de durée réelle. Electronique reste plus courte si la maintenance n'est pas contractualisée. Remplacements se font plutôt par bâtiment ou par noyau sanitaire lors de travaux programmés. Usage tertiaire moyen, faible vandalisme, rénovations par lots tirées par l’accessibilité et la trajectoire Éco Énergie Tertiaire. | DH13: =$BE13*BO13 -> 37121.04 | DI13: =$BE13*BP13 -> 51744.48 | DJ13: =$BE13*BQ13 -> 19122.96 | DK13: =$BE13*BR13 -> 4499.52 | DL13: Dans les mairies, préfectures et grands bâtiments administratifs, le parc existant reste équilibré entre mitigeur et solutions plus ERP ; l’électronique est déjà bien présente sur les rénovations. Le choix reflete accueil public de jour, flux moderes et renov. liees aux rogrammes patrimoniaux ; accessibilite, image institutionnelle et maintenance sobre. | DM13: =$BJ13*BS13 -> 32590.2 | DN13: =$BJ13*BT13 -> 51694.8 | DO13: =$BJ13*BU13 -> 24723.6 | DP13: =$BJ13*BV13 -> 3371.4 | DQ13: 2025-2030 : progression de tempo electronique (+5,0%), surtout lors des renov. lourdes/neuf ; recul de mitigeur manuel (-5,0%) mais maintien d un socle robuste pour les remplacements partiels. | DS13: =$BF13*BW13 -> 0 | DT13: =$BF13*BX13 -> 0 | DU13: =$BF13*BY13 -> 0 | DV13: Sans objet. | DW13: =$BK13*BZ13 -> 0 | DX13: =$BK13*CA13 -> 0 | DY13: =$BK13*CB13 -> 0 | DZ13: Sans objet. | EB13: =$BG13*CC13 -> 1349.856 | EC13: =$BG13*CD13 -> 5624.4 | ED13: =$BG13*CE13 -> 1687.32 | EE13: =$BG13*CF13 -> 2587.224 | EF13: Mairies / hôtels de ville : parc 2025 domine par directe mecanique (50%), avec directe electronique collective en appoint. Le choix reflete accueil public de jour, flux moderes et renov. liees aux programmes patrimoniaux ; accessibilite, image institutionnelle et maintenance sobre. | EG13: =$BL13*CG13 -> 1123.8 | EH13: =$BL13*CH13 -> 5619 | EI13: =$BL13*CI13 -> 2022.84 | EJ13: =$BL13*CJ13 -> 2472.36 | EK13: 2025-2030 : progression de directe electronique indiv. (+3,0%), surtout lors des renov. lourdes/neuf ; recul de a reservoir (-2,0%) mais maintien d un socle robuste pour les remplacements partiels. | EM13: =$BH13*CK13 -> 61868.4 | EN13: =$BH13*CL13 -> 33746.4 | EO13: =$BH13*CM13 -> 16873.2 | EP13: Mairies / hôtels de ville : parc 2025 domine par reservoir (55%), avec chasse directe mecanique en appoint. Le choix reflete accueil public de jour, flux moderes et renov. liees aux programmes patrimoniaux ; accessibilite, image institutionnelle et maintenance sobre. | EQ13: =$BM13*CN13 -> 52818.6 | ER13: =$BM13*CO13 -> 37085.4 | ES13: =$BM13*CP13 -> 22476 | ET13: 2025-2030 : progression de chasse directe electronique (+5,0%), surtout lors des renov. lourdes/neuf ; recul de reservoir (-8,0%) mais maintien d un socle robuste pour les remplacements partiels. | EV13: =IFERROR(EY13/EX13,0) -> 0.87516295 | EW13: =IFERROR(EZ13/EX13,0) -> 0.12483705 | EX13: =EY13+EZ13 -> 80988.951 | EY13: =SUM(FB13,FE13,FH13,FK13) -> 70878.53 | EZ13: =SUM(FC13,FF13,FI13,FL13) -> 10110.421 | FA13: =FB13+FC13 -> 38986.353 | FB13: =SUM(GI13,GL13,GO13,GR13) -> 34171.866 | FC13: =MAX(0,$BJ13-$BE13)+$BE13*$FO13 -> 4814.4864 | FD13: =FE13+FF13 -> 0 | FE13: =SUM(GU13,GX13,HA13) -> 0 | FF13: =MAX(0,$BK13-$BF13)+$BF13*$FO13 -> 0 | FG13: =FH13+FI13 -> 4265.449 | FH13: =SUM(HD13,HG13,HJ13,HM13) -> 3784.0004 | FI13: =MAX(0,$BL13-$BG13)+$BG13*$FO13 -> 481.44864 | FJ13: =FK13+FL13 -> 37737.149 | FK13: =SUM(HP13,HS13,HV13) -> 32922.663 | FL13: =MAX(0,$BM13-$BH13)+$BH13*$FO13 -> 4814.4864 | FN13: Moyenne à Bonne | FO13: 0.0428 | FP13: 0.77415 | FQ13: 77,4% retenu : besoins transformes en travaux selon accueil public de jour, flux moderes et renov. liees aux programmes patrimoniaux. Le phasage budgetaire, les fermetures partielles et la maintenance courante limitent la conversion totale. | FS13: 3.06 | FT13: =RANK($FS13,$FS$16:$FS$17,0)+COUNTIF($FS$16:$FS17,$FS13)-1 -> 2 | FU13: 3.57 | FV13: =RANK($FU13,$FU$16:$FU$17,0)+COUNTIF($FU$16:$FU17,$FU13)-1 -> #N/A | FW13: 2.14 | FX13: =RANK($FW13,$FW$16:$FW$17,0)+COUNTIF($FW$16:$FW17,$FW13)-1 -> #N/A | FZ13: Potentiel renovation : tire par accessibilite, image institutionnelle et maintenance sobre. Les remplacements sont plutot par lots, avec arbitrage entre urgence sanitaire, budget et capacite a intervenir en site occupe. | GA13: Potentiel neuf : limite pour mairies / hôtels de ville, surtout via extensions, reconstructions ou projets locaux. Le neuf reste contraint par foncier, budgets et delais de mise en service. | GB13: Projets phares renovation : reprise de blocs sanitaires, accessibilite, ventilation, economie d eau, remplacement des pieces usees et adaptation aux pics de frequentation propres au sous-segment. | GC13: Projets phares neuf : creations ou reconstructions selectives, integration de sanitaires plus sobres, robustes et faciles a maintenir des la conception. | GD13: Dynamique renovation 2026-2030 : moderee, car l usure et l hygiene rendent les interventions recurrentes. Menaces : arbitrages d investissement, travaux en exploitation et cout de maintenance. | GE13: Dynamique neuf 2026-2030 : faible a moderee, dependante des projets immobiliers, de la demographie locale et des budgets de maitrise d ouvrage. | GF13: =HYPERLINK("https://anct.gouv.fr/france-services-36","https://anct.gouv.fr/france-services-36")&CHAR(10)&HYPERLINK("https://www.economie.gouv.fr/particuliers/gerer-mon-argent/beneficier-daides-et-de-reductions-dimpots/france-services-les-services-publics-pres-de-chez-vous","https://www.economie.gouv.fr/particuliers/gerer-mon-argent/beneficier-daides-et-de-reductions-dimpots/france-services-les-services-publics-pres-de-chez-vous")&CHAR(10)&HYPERLINK("https://www.ecologie.gouv.fr/eco-energie-tertiaire-eet","https://www.ecologie.gouv.fr/eco-energie-tertiaire-eet")&CHAR(10)&HYPERLINK("https://www.collectivites-locales.gouv.fr/les-collectivites-locales-en-chiffres-2025","https://www.collectivites-locales.gouv.fr/les-collectivites-locales-en-chiffres-2025")&CHAR(10)&HYPERLINK("https://www.collectivites-locales.gouv.fr/actualites/situation-mensuelle-comptable-des-collectivites-locales-au-31-decembre-2025","https://www.collectivites-locales.gouv.fr/actualites/situation-mensuelle-comptable-des-collectivites-locales-au-31-decembre-2025")&CHAR(10)&HYPERLINK("https://www.statistiques.developpement-durable.gouv.fr/construction-de-locaux-resultats-fin-janvier-2026-france-entiere","https://www.statistiques.developpement-durable.gouv.fr/construction-de-locaux-resultats-fin-janvier-2026-france-entiere")&CHAR(10)&HYPERLINK("https://www.insee.fr/fr/statistiques/8671745","https://www.insee.fr/fr/statistiques/8671745")&CHAR(10)&HYPERLINK("https://www.insee.fr/fr/statistiques/8906564","https://www.insee.fr/fr/statistiques/8906564") -> https://anct.gouv.fr/france-services-36 https://www.economie.gouv.fr/particuliers/gerer-mon-argent/beneficier-daides-et-de-reductions-dimpots/france-services-les-services-publics-pres-de-chez-vous https://www.ecologie.gouv.fr/eco-energie-tertiaire-eet https://www.collectivites-locales.gouv.fr/les-collectivites-locales-en-chiffres-2025 https://www.collectivites-locales.gouv.fr/actualites/situation-mensuelle-comptable-des-collectivites-locales-au-31-decembre-2025 https://www.statistiques.developpement-durable.gouv.fr/construction-de-locaux-resultats-fin-janvier-2026-france-entiere https://www.insee.fr/fr/statistiques/8671745 https://www.insee.fr/fr/statistiques/8906564 | GH13: =GI13+GJ13 -> 12431.363 | GI13: =IFERROR($DH13*$FP13/MAX(0.000000001,$CR13)*(INDEX($S13:$AF13,1,MATCH(MAX(2000,MIN(2025,ROUND(2026-$CR13,0))),$S$4:$AF$4,1))+INDEX($S13:$AF13,1,MATCH(MAX(2000,MIN(2025,ROUND(2027-$CR13,0))),$S$4:$AF$4,1))+INDEX($S13:$AF13,1,MATCH(MAX(2000,MIN(2025,ROUND(2028-$CR13,0))),$S$4:$AF$4,1))+INDEX($S13:$AF13,1,MATCH(MAX(2000,MIN(2025,ROUND(2029-$CR13,0))),$S$4:$AF$4,1))+INDEX($S13:$AF13,1,MATCH(MAX(2000,MIN(2025,ROUND(2030-$CR13,0))),$S$4:$AF$4,1)))/MAX(1,$AF13),0) -> 11035.162 | GJ13: =IFERROR($FC13*$BS13,0) -> 1396.2011 | GK13: =GL13+GM13 -> 16495.296 | GL13: =IFERROR($DI13*$FP13/MAX(0.000000001,$CS13)*(INDEX($S13:$AF13,1,MATCH(MAX(2000,MIN(2025,ROUND(2026-$CS13,0))),$S$4:$AF$4,1))+INDEX($S13:$AF13,1,MATCH(MAX(2000,MIN(2025,ROUND(2027-$CS13,0))),$S$4:$AF$4,1))+INDEX($S13:$AF13,1,MATCH(MAX(2000,MIN(2025,ROUND(2028-$CS13,0))),$S$4:$AF$4,1))+INDEX($S13:$AF13,1,MATCH(MAX(2000,MIN(2025,ROUND(2029-$CS13,0))),$S$4:$AF$4,1))+INDEX($S13:$AF13,1,MATCH(MAX(2000,MIN(2025,ROUND(2030-$CS13,0))),$S$4:$AF$4,1)))/MAX(1,$AF13),0) -> 14280.632 | GM13: =IFERROR($FC13*$BT13,0) -> 2214.6637 | GN13: =GO13+GP13 -> 8464.997 | GO13: =IFERROR($DJ13*$FP13/MAX(0.000000001,$CT13)*(INDEX($S13:$AF13,1,MATCH(MAX(2000,MIN(2025,ROUND(2026-$CT13,0))),$S$4:$AF$4,1))+INDEX($S13:$AF13,1,MATCH(MAX(2000,MIN(2025,ROUND(2027-$CT13,0))),$S$4:$AF$4,1))+INDEX($S13:$AF13,1,MATCH(MAX(2000,MIN(2025,ROUND(2028-$CT13,0))),$S$4:$AF$4,1))+INDEX($S13:$AF13,1,MATCH(MAX(2000,MIN(2025,ROUND(2029-$CT13,0))),$S$4:$AF$4,1))+INDEX($S13:$AF13,1,MATCH(MAX(2000,MIN(2025,ROUND(2030-$CT13,0))),$S$4:$AF$4,1)))/MAX(1,$AF13),0) -> 7405.81 | GP13: =IFERROR($FC13*$BU13,0) -> 1059.187 | GQ13: =GR13+GS13 -> 1594.6962 | GR13: =IFERROR($DK13*$FP13/MAX(0.000000001,$CU13)*(INDEX($S13:$AF13,1,MATCH(MAX(2000,MIN(2025,ROUND(2026-$CU13,0))),$S$4:$AF$4,1))+INDEX($S13:$AF13,1,MATCH(MAX(2000,MIN(2025,ROUND(2027-$CU13,0))),$S$4:$AF$4,1))+INDEX($S13:$AF13,1,MATCH(MAX(2000,MIN(2025,ROUND(2028-$CU13,0))),$S$4:$AF$4,1))+INDEX($S13:$AF13,1,MATCH(MAX(2000,MIN(2025,ROUND(2029-$CU13,0))),$S$4:$AF$4,1))+INDEX($S13:$AF13,1,MATCH(MAX(2000,MIN(2025,ROUND(2030-$CU13,0))),$S$4:$AF$4,1)))/MAX(1,$AF13),0) -> 1450.2616 | GS13: =IFERROR($FC13*$BV13,0) -> 144.43459 | GT13: =GU13+GV13 -> 0 | GU13: =IFERROR($DS13*$FP13/MAX(0.000000001,$CV13)*(INDEX($S13:$AF13,1,MATCH(MAX(2000,MIN(2025,ROUND(2026-$CV13,0))),$S$4:$AF$4,1))+INDEX($S13:$AF13,1,MATCH(MAX(2000,MIN(2025,ROUND(2027-$CV13,0))),$S$4:$AF$4,1))+INDEX($S13:$AF13,1,MATCH(MAX(2000,MIN(2025,ROUND(2028-$CV13,0))),$S$4:$AF$4,1))+INDEX($S13:$AF13,1,MATCH(MAX(2000,MIN(2025,ROUND(2029-$CV13,0))),$S$4:$AF$4,1))+INDEX($S13:$AF13,1,MATCH(MAX(2000,MIN(2025,ROUND(2030-$CV13,0))),$S$4:$AF$4,1)))/MAX(1,$AF13),0) -> 0 | GV13: =IFERROR($FF13*$BZ13,0) -> 0 | GW13: =GX13+GY13 -> 0 | GX13: =IFERROR($DT13*$FP13/MAX(0.000000001,$CW13)*(INDEX($S13:$AF13,1,MATCH(MAX(2000,MIN(2025,ROUND(2026-$CW13,0))),$S$4:$AF$4,1))+INDEX($S13:$AF13,1,MATCH(MAX(2000,MIN(2025,ROUND(2027-$CW13,0))),$S$4:$AF$4,1))+INDEX($S13:$AF13,1,MATCH(MAX(2000,MIN(2025,ROUND(2028-$CW13,0))),$S$4:$AF$4,1))+INDEX($S13:$AF13,1,MATCH(MAX(2000,MIN(2025,ROUND(2029-$CW13,0))),$S$4:$AF$4,1))+INDEX($S13:$AF13,1,MATCH(MAX(2000,MIN(2025,ROUND(2030-$CW13,0))),$S$4:$AF$4,1)))/MAX(1,$AF13),0) -> 0 | GY13: =IFERROR($FF13*$CA13,0) -> 0 | GZ13: =HA13+HB13 -> 0 | HA13: =IFERROR($DU13*$FP13/MAX(0.000000001,$CX13)*(INDEX($S13:$AF13,1,MATCH(MAX(2000,MIN(2025,ROUND(2026-$CX13,0))),$S$4:$AF$4,1))+INDEX($S13:$AF13,1,MATCH(MAX(2000,MIN(2025,ROUND(2027-$CX13,0))),$S$4:$AF$4,1))+INDEX($S13:$AF13,1,MATCH(MAX(2000,MIN(2025,ROUND(2028-$CX13,0))),$S$4:$AF$4,1))+INDEX($S13:$AF13,1,MATCH(MAX(2000,MIN(2025,ROUND(2029-$CX13,0))),$S$4:$AF$4,1))+INDEX($S13:$AF13,1,MATCH(MAX(2000,MIN(2025,ROUND(2030-$CX13,0))),$S$4:$AF$4,1)))/MAX(1,$AF13),0) -> 0 | HB13: =IFERROR($FF13*$CB13,0) -> 0 | HC13: =HD13+HE13 -> 523.08758 | HD13: =IFERROR($EB13*$FP13/MAX(0.000000001,$CY13)*(INDEX($S13:$AF13,1,MATCH(MAX(2000,MIN(2025,ROUND(2026-$CY13,0))),$S$4:$AF$4,1))+INDEX($S13:$AF13,1,MATCH(MAX(2000,MIN(2025,ROUND(2027-$CY13,0))),$S$4:$AF$4,1))+INDEX($S13:$AF13,1,MATCH(MAX(2000,MIN(2025,ROUND(2028-$CY13,0))),$S$4:$AF$4,1))+INDEX($S13:$AF13,1,MATCH(MAX(2000,MIN(2025,ROUND(2029-$CY13,0))),$S$4:$AF$4,1))+INDEX($S13:$AF13,1,MATCH(MAX(2000,MIN(2025,ROUND(2030-$CY13,0))),$S$4:$AF$4,1)))/MAX(1,$AF13),0) -> 474.94271 | HE13: =IFERROR($FI13*$CG13,0) -> 48.144864 | HF13: =HG13+HH13 -> 1912.7186 | HG13: =IFERROR($EC13*$FP13/MAX(0.000000001,$CZ13)*(INDEX($S13:$AF13,1,MATCH(MAX(2000,MIN(2025,ROUND(2026-$CZ13,0))),$S$4:$AF$4,1))+INDEX($S13:$AF13,1,MATCH(MAX(2000,MIN(2025,ROUND(2027-$CZ13,0))),$S$4:$AF$4,1))+INDEX($S13:$AF13,1,MATCH(MAX(2000,MIN(2025,ROUND(2028-$CZ13,0))),$S$4:$AF$4,1))+INDEX($S13:$AF13,1,MATCH(MAX(2000,MIN(2025,ROUND(2029-$CZ13,0))),$S$4:$AF$4,1))+INDEX($S13:$AF13,1,MATCH(MAX(2000,MIN(2025,ROUND(2030-$CZ13,0))),$S$4:$AF$4,1)))/MAX(1,$AF13),0) -> 1671.9943 | HH13: =IFERROR($FI13*$CH13,0) -> 240.72432 | HI13: =HJ13+HK13 -> 813.41729 | HJ13: =IFERROR($ED13*$FP13/MAX(0.000000001,$DA13)*(INDEX($S13:$AF13,1,MATCH(MAX(2000,MIN(2025,ROUND(2026-$DA13,0))),$S$4:$AF$4,1))+INDEX($S13:$AF13,1,MATCH(MAX(2000,MIN(2025,ROUND(2027-$DA13,0))),$S$4:$AF$4,1))+INDEX($S13:$AF13,1,MATCH(MAX(2000,MIN(2025,ROUND(2028-$DA13,0))),$S$4:$AF$4,1))+INDEX($S13:$AF13,1,MATCH(MAX(2000,MIN(2025,ROUND(2029-$DA13,0))),$S$4:$AF$4,1))+INDEX($S13:$AF13,1,MATCH(MAX(2000,MIN(2025,ROUND(2030-$DA13,0))),$S$4:$AF$4,1)))/MAX(1,$AF13),0) -> 726.75654 | HK13: =IFERROR($FI13*$CI13,0) -> 86.660755 | HL13: =HM13+HN13 -> 1016.2256 | HM13: =IFERROR($EE13*$FP13/MAX(0.000000001,$DB13)*(INDEX($S13:$AF13,1,MATCH(MAX(2000,MIN(2025,ROUND(2026-$DB13,0))),$S$4:$AF$4,1))+INDEX($S13:$AF13,1,MATCH(MAX(2000,MIN(2025,ROUND(2027-$DB13,0))),$S$4:$AF$4,1))+INDEX($S13:$AF13,1,MATCH(MAX(2000,MIN(2025,ROUND(2028-$DB13,0))),$S$4:$AF$4,1))+INDEX($S13:$AF13,1,MATCH(MAX(2000,MIN(2025,ROUND(2029-$DB13,0))),$S$4:$AF$4,1))+INDEX($S13:$AF13,1,MATCH(MAX(2000,MIN(2025,ROUND(2030-$DB13,0))),$S$4:$AF$4,1)))/MAX(1,$AF13),0) -> 910.30687 | HN13: =IFERROR($FI13*$CJ13,0) -> 105.9187 | HO13: =HP13+HQ13 -> 19337.478 | HP13: =IFERROR($EM13*$FP13/MAX(0.000000001,$DC13)*(INDEX($S13:$AF13,1,MATCH(MAX(2000,MIN(2025,ROUND(2026-$DC13,0))),$S$4:$AF$4,1))+INDEX($S13:$AF13,1,MATCH(MAX(2000,MIN(2025,ROUND(2027-$DC13,0))),$S$4:$AF$4,1))+INDEX($S13:$AF13,1,MATCH(MAX(2000,MIN(2025,ROUND(2028-$DC13,0))),$S$4:$AF$4,1))+INDEX($S13:$AF13,1,MATCH(MAX(2000,MIN(2025,ROUND(2029-$DC13,0))),$S$4:$AF$4,1))+INDEX($S13:$AF13,1,MATCH(MAX(2000,MIN(2025,ROUND(2030-$DC13,0))),$S$4:$AF$4,1)))/MAX(1,$AF13),0) -> 17074.669 | HQ13: =IFERROR($FL13*$CN13,0) -> 2262.8086 | HR13: =HS13+HT13 -> 10902.236 | HS13: =IFERROR($EN13*$FP13/MAX(0.000000001,$DD13)*(INDEX($S13:$AF13,1,MATCH(MAX(2000,MIN(2025,ROUND(2026-$DD13,0))),$S$4:$AF$4,1))+INDEX($S13:$AF13,1,MATCH(MAX(2000,MIN(2025,ROUND(2027-$DD13,0))),$S$4:$AF$4,1))+INDEX($S13:$AF13,1,MATCH(MAX(2000,MIN(2025,ROUND(2028-$DD13,0))),$S$4:$AF$4,1))+INDEX($S13:$AF13,1,MATCH(MAX(2000,MIN(2025,ROUND(2029-$DD13,0))),$S$4:$AF$4,1))+INDEX($S13:$AF13,1,MATCH(MAX(2000,MIN(2025,ROUND(2030-$DD13,0))),$S$4:$AF$4,1)))/MAX(1,$AF13),0) -> 9313.4558 | HT13: =IFERROR($FL13*$CO13,0) -> 1588.7805 | HU13: =HV13+HW13 -> 7497.4355 | HV13: =IFERROR($EO13*$FP13/MAX(0.000000001,$DE13)*(INDEX($S13:$AF13,1,MATCH(MAX(2000,MIN(2025,ROUND(2026-$DE13,0))),$S$4:$AF$4,1))+INDEX($S13:$AF13,1,MATCH(MAX(2000,MIN(2025,ROUND(2027-$DE13,0))),$S$4:$AF$4,1))+INDEX($S13:$AF13,1,MATCH(MAX(2000,MIN(2025,ROUND(2028-$DE13,0))),$S$4:$AF$4,1))+INDEX($S13:$AF13,1,MATCH(MAX(2000,MIN(2025,ROUND(2029-$DE13,0))),$S$4:$AF$4,1))+INDEX($S13:$AF13,1,MATCH(MAX(2000,MIN(2025,ROUND(2030-$DE13,0))),$S$4:$AF$4,1)))/MAX(1,$AF13),0) -> 6534.5382 | HW13: =IFERROR($FL13*$CP13,0) -> 962.89728 | HY13: =SUM(HZ13:ID13) -> 236224.8 | HZ13: =IFERROR(IO13*BE13,0)+IFERROR(IY13*BF13,0)+IFERROR(JI13*BG13,0)+IFERROR(JS13*BH13,0) -> 7649.184 | IA13: =IFERROR(IP13*BE13,0)+IFERROR(IZ13*BF13,0)+IFERROR(JJ13*BG13,0)+IFERROR(JT13*BH13,0) -> 97726.2 | IB13: =IFERROR(IQ13*BE13,0)+IFERROR(JA13*BF13,0)+IFERROR(JK13*BG13,0)+IFERROR(JU13*BH13,0) -> 116006.62 | IC13: =IFERROR(IR13*BE13,0)+IFERROR(JB13*BF13,0)+IFERROR(JL13*BG13,0)+IFERROR(JV13*BH13,0) -> 14842.792 | ID13: =IFERROR(IS13*BE13,0)+IFERROR(JC13*BF13,0)+IFERROR(JM13*BG13,0)+IFERROR(JW13*BH13,0) -> 0 | IE13: =SUM(IF13:IJ13) -> 70878.53 | IF13: =IFERROR(IT13*FB13,0)+IFERROR(JD13*FE13,0)+IFERROR(JN13*FH13,0)+IFERROR(JX13*FK13,0) -> 864.31507 | IG13: =IFERROR(IU13*FB13,0)+IFERROR(JE13*FE13,0)+IFERROR(JO13*FH13,0)+IFERROR(JY13*FK13,0) -> 27616.592 | IH13: =IFERROR(IV13*FB13,0)+IFERROR(JF13*FE13,0)+IFERROR(JP13*FH13,0)+IFERROR(JZ13*FK13,0) -> 36196.804 | II13: =IFERROR(IW13*FB13,0)+IFERROR(JG13*FE13,0)+IFERROR(JQ13*FH13,0)+IFERROR(KA13*FK13,0) -> 5882.6211 | IJ13: =IFERROR(IX13*FB13,0)+IFERROR(JH13*FE13,0)+IFERROR(JR13*FH13,0)+IFERROR(KB13*FK13,0) -> 318.19658 | IK13: 4.13 | IL13: Bonne | IM13: Parc existant centre sur le niveau mid, avec ventes 2026-2030 legerement plus qualitatives. Mairies / hôtels de ville : accueil public de jour, flux moderes et renov. liees aux programmes patrimoniaux; le mix reste guide par accessibilite, image institutionnelle et maintenance sobre. | IO13: 0.03 | IP13: 0.4 | IQ13: 0.5 | IR13: 0.07 | IS13: 0 | IT13: 0.0097 | IU13: 0.3753 | IV13: 0.5202 | IW13: 0.0903 | IX13: 0.0045 | IY13: 0 | IZ13: 0 | JA13: 0 | JB13: 0 | JC13: 0 | JD13: 0 | JE13: 0 | JF13: 0 | JG13: 0 | JH13: 0 | JI13: 0.054 | JJ13: 0.5397 | JK13: 0.3748 | JL13: 0.0315 | JM13: 0 | JN13: 0.0338 | JO13: 0.515 | JP13: 0.3951 | JQ13: 0.0518 | JR13: 0.0043 | JS13: 0.0326 | JT13: 0.4148 | JU13: 0.4938 | JV13: 0.0588 | JW13: 0 | JX13: 0.0123 | JY13: 0.3901 | JZ13: 0.5141 | KA13: 0.079 | KB13: 0.0045 | KD13: ±4 pts | KE13: ±4 pts | KF13: 4.16 | KG13: Bonne | KH13: Parc existant : accessibilite, image institutionnelle et maintenance sobre; accueil public de jour, flux moderes et renov. liees aux programmes patrimoniaux. La montee en confort reste proportionnee au budget et au rythme de renovation. | KI13: image client => premiumisation ciblee | KJ13: Mairies / hôtels de ville : ventes 2026-2030 en leger glissement vers moyen/premium lorsque le neuf ou les renov. lourdes interviennent. Le centre de gravite reste toutefois module par accessibilite, image institutionnelle et maintenance sobre et par la part dominante de travaux sur parc existant.
A14: =A13+1 -> 6 | B14: Culte, Vie civique & Services publics | C14: Administrations / services publics | D14: Bureaux administratifs secondaires non ERP >50 salariés | E14: Hors ERP | F14: Hors ERP dominant / personnel uniquement | G14: mixte | H14: non | I14: Sites de gestion interne >50 salariés, directions support sans accueil, back-offices administratifs de l’État, services techniques / RH / finances de collectivités, annexes administratives d’universités ou de rectorats, back-offices CPAM, CARSAT, ARS, MSA, CROUS, bâtiments administratifs hospitaliers séparés des zones patient/public | J14: sites de gestion interne >50 salariés, directions support sans accueil, back-offices administratifs de l’État, services techniques / RH / finances de collectivités, annexes administratives d’universités ou de rectorats, back-offices CPAM, CARSAT, ARS, MSA, CROUS, bâtiments administratifs hospitaliers séparés des zones patient/public | R14: 2800 | S14: 7200 | T14: 8000 | U14: 8900 | V14: 9400 | W14: 9450 | X14: 9500 | Y14: 9550 | Z14: 9600 | AA14: 9650 | AB14: 9700 | AC14: 9800 | AD14: 9900 | AE14: 10000 | AF14: 10000 | AG14: 9950 | AH14: 9900 | AI14: 9825 | AJ14: 9750 | AK14: 9650 | AL14: Stock résiduel hors sous-segments déjà comptés dans le modèle : mairies, hôtels département/région … Érosion légère post-2025 liée à la rationalisation immobilière publique, au télétravail et aux regroupements de sites. | AM14: Besoin back-office reste structurel compte tenu du volume d’agents publics et d’établissements employeurs publics. Nombre sites secondaires décroît légèrement => réduction ciblée de surfaces bureaux de l’État, mutualisation et fermeture/regroupement sites internes. | AN14: https://www.insee.fr/fr/metadonnees/source/serie/s1042 ; https://www.insee.fr/fr/statistiques/8956736?geo=FRANCE-1 ; https://www.fonction-publique.gouv.fr/toutes-les-publications/rapport-annuel-sur-letat-de-la-fonction-publique-edition-2024 ; https://presse.economie.gouv.fr/bilan-2023-et-perspectives-2024-de-limmobilier-de-letat-un-parc-mieux-valorise-plus-sobre-et-plus-durable/ | AP14: 170 | AQ14: 150 | AR14: 17 | AS14: 3 | AU14: Bureaux administratifs non ERP : sanitaires salariés par noyaux, visiteurs négligeables. | AV14: Capacité type ≈ 150 usagers principaux + 17 staff + 3 autre public. Occupation de bureaux sans accueil public structurant. Dimensionnement unitaire retenu : cabinets/lavabos séparés selon effectif simultané et Code du travail. Hypothèse d'usage : capacité simultanée moyenne 2026, répartition par flux réels, arrondie par blocs fonctionnels et exclusion des sanitaires strictement privatifs sauf cas explicitement collectifs. | AW14: Profil moyen, capacité moyenne ≈ 170 personnes. Moyenne pondérée terrain : parc majoritairement petits/moyens sites, grands sites intégrés sans surpondération ; usage 2025 modérée, majoritairement courte. | AX14: ERP/accessibilité sanitaires publics : https://www.legifrance.gouv.fr/loda/article_lc/LEGIARTI000034485966/ ; Code du travail sanitaires salariés : https://www.legifrance.gouv.fr/codes/id/LEGISCTA000018531984 ; INRS : https://www.inrs.fr/publications/juridique/focus-juridiques/focus-sanitaires-toilettes.html | AZ14: 16 | BA14: 0 | BB14: 3.5 | BC14: 12 | BD14: =SUM(BE14:BH14) -> 315000 | BE14: =AF14*AZ14 -> 160000 | BF14: =AF14*BA14 -> 0 | BG14: =AF14*BB14 -> 35000 | BH14: =AF14*BC14 -> 120000 | BI14: =SUM(BJ14:BM14) -> 303975 | BJ14: =AK14*AZ14 -> 154400 | BK14: =AK14*BA14 -> 0 | BL14: =AK14*BB14 -> 33775 | BM14: =AK14*BC14 -> 115800 | BO14: 0.44 | BP14: 0.38 | BQ14: 0.13 | BR14: 0.05 | BS14: 0.39 | BT14: 0.39 | BU14: 0.18 | BV14: 0.04 | CC14: 0.08 | CD14: 0.45 | CE14: 0.25 | CF14: 0.22 | CG14: 0.06 | CH14: 0.45 | CI14: 0.28 | CJ14: 0.21 | CK14: 0.35 | CL14: 0.5 | CM14: 0.15 | CN14: 0.25 | CO14: 0.5 | CP14: 0.25 | CR14: 13 | CS14: 13 | CT14: 10 | CU14: 12 | CY14: 11 | CZ14: 13 | DA14: 9 | DB14: 11 | DC14: 14 | DD14: 14 | DE14: 10 | DF14: Usage principalement salariés, peu de public et faible vandalisme; nettoyage régulier. Proche tertiaire privé, légèrement contraint par cycles budgétaires publics. Repères durées: lavabos 13/13/10 ans (mit./méca/élec.), douches 12/11/9, urinoirs 11/13/9/11, WC 14/14/10. | DH14: =$BE14*BO14 -> 70400 | DI14: =$BE14*BP14 -> 60800 | DJ14: =$BE14*BQ14 -> 20800 | DK14: =$BE14*BR14 -> 8000 | DL14: Bureaux administratifs secondaires non ERP >50 salariés : parc 2025 domine par tempo mecanique (55%), avec mitigeur manuel en appoint. Le choix reflete accueil public de jour, flux moderes et renov. liees aux programmes patrimoniaux ; accessibilite, image institutionnelle et maintenance sobre. | DM14: =$BJ14*BS14 -> 60216 | DN14: =$BJ14*BT14 -> 60216 | DO14: =$BJ14*BU14 -> 27792 | DP14: =$BJ14*BV14 -> 6176 | DQ14: 2025-2030 : progression de tempo electronique (+3,0%), surtout lors des renov. lourdes/neuf ; recul de mitigeur manuel (-2,0%) mais maintien d un socle robuste pour les remplacements partiels. | DS14: =$BF14*BW14 -> 0 | DT14: =$BF14*BX14 -> 0 | DU14: =$BF14*BY14 -> 0 | DV14: Sans objet. | DW14: =$BK14*BZ14 -> 0 | DX14: =$BK14*CA14 -> 0 | DY14: =$BK14*CB14 -> 0 | DZ14: Sans objet. | EB14: =$BG14*CC14 -> 2800 | EC14: =$BG14*CD14 -> 15750 | ED14: =$BG14*CE14 -> 8750 | EE14: =$BG14*CF14 -> 7700 | EF14: Bureaux administratifs secondaires non ERP >50 salariés : parc 2025 domine par directe mecanique (45%), avec directe electronique indiv. en appoint. Le choix reflete accueil public de jour, flux moderes et renov. liees aux programmes patrimoniaux ; accessibilite, image institutionnelle et maintenance sobre. | EG14: =$BL14*CG14 -> 2026.5 | EH14: =$BL14*CH14 -> 15198.75 | EI14: =$BL14*CI14 -> 9457 | EJ14: =$BL14*CJ14 -> 7092.75 | EK14: 2025-2030 : progression de directe electronique indiv. (+3,0%), surtout lors des renov. lourdes/neuf ; recul de a reservoir (-2,0%) mais maintien d un socle robuste pour les remplacements partiels. | EM14: =$BH14*CK14 -> 42000 | EN14: =$BH14*CL14 -> 60000 | EO14: =$BH14*CM14 -> 18000 | EP14: Bureaux administratifs secondaires non ERP >50 salariés : parc 2025 domine par chasse directe mecanique (50%), avec reservoir en appoint. Le choix reflete accueil public de jour, flux moderes et renov. liees aux programmes patrimoniaux ; accessibilite, image institutionnelle et maintenance sobre. | EQ14: =$BM14*CN14 -> 28950 | ER14: =$BM14*CO14 -> 57900 | ES14: =$BM14*CP14 -> 28950 | ET14: 2025-2030 : progression de chasse directe electronique (+10,0%), surtout lors des renov. lourdes/neuf ; recul de reservoir (-10,0%) mais maintien d un socle robuste pour les remplacements partiels. | EV14: =IFERROR(EY14/EX14,0) -> 0.86989659 | EW14: =IFERROR(EZ14/EX14,0) -> 0.13010341 | EX14: =EY14+EZ14 -> 103625.26 | EY14: =SUM(FB14,FE14,FH14,FK14) -> 90143.264 | EZ14: =SUM(FC14,FF14,FI14,FL14) -> 13482 | FA14: =FB14+FC14 -> 53104.421 | FB14: =SUM(GI14,GL14,GO14,GR14) -> 46256.421 | FC14: =MAX(0,$BJ14-$BE14)+$BE14*$FO14 -> 6848 | FD14: =FE14+FF14 -> 0 | FE14: =SUM(GU14,GX14,HA14) -> 0 | FF14: =MAX(0,$BK14-$BF14)+$BF14*$FO14 -> 0 | FG14: =FH14+FI14 -> 12972.9 | FH14: =SUM(HD14,HG14,HJ14,HM14) -> 11474.9 | FI14: =MAX(0,$BL14-$BG14)+$BG14*$FO14 -> 1498 | FJ14: =FK14+FL14 -> 37547.943 | FK14: =SUM(HP14,HS14,HV14) -> 32411.943 | FL14: =MAX(0,$BM14-$BH14)+$BH14*$FO14 -> 5136 | FN14: Moyenne à Bonne | FO14: 0.0428 | FP14: 0.77575 | FQ14: 77,6% retenu : besoins transformes en travaux selon accueil public de jour, flux moderes et renov. liees aux programmes patrimoniaux. Le phasage budgetaire, les fermetures partielles et la maintenance courante limitent la conversion totale. | FS14: 3 | FT14: =RANK($FS14,$FS$16:$FS$17,0)+COUNTIF($FS$16:$FS17,$FS14)-1 -> #N/A | FU14: 3.57 | FV14: =RANK($FU14,$FU$16:$FU$17,0)+COUNTIF($FU$16:$FU17,$FU14)-1 -> #N/A | FW14: 1.98 | FX14: =RANK($FW14,$FW$16:$FW$17,0)+COUNTIF($FW$16:$FW17,$FW14)-1 -> #N/A | FZ14: Potentiel renovation : tire par accessibilite, image institutionnelle et maintenance sobre. Les remplacements sont plutot par lots, avec arbitrage entre urgence sanitaire, budget et capacite a intervenir en site occupe. | GA14: Potentiel neuf : limite pour bureaux administratifs secondaires non erp >50 salariés, surtout via extensions, reconstructions ou projets locaux. Le neuf reste contraint par foncier, budgets et delais de mise en service. | GB14: Projets phares renovation : reprise de blocs sanitaires, accessibilite, ventilation, economie d eau, remplacement des pieces usees et adaptation aux pics de frequentation propres au sous-segment. | GC14: Projets phares neuf : creations ou reconstructions selectives, integration de sanitaires plus sobres, robustes et faciles a maintenir des la conception. | GD14: Dynamique renovation 2026-2030 : moderee, car l usure et l hygiene rendent les interventions recurrentes. Menaces : arbitrages d investissement, travaux en exploitation et cout de maintenance. | GE14: Dynamique neuf 2026-2030 : faible a moderee, dependante des projets immobiliers, de la demographie locale et des budgets de maitrise d ouvrage. | GF14: =HYPERLINK("https://anct.gouv.fr/france-services-36","https://anct.gouv.fr/france-services-36")&CHAR(10)&HYPERLINK("https://www.economie.gouv.fr/particuliers/gerer-mon-argent/beneficier-daides-et-de-reductions-dimpots/france-services-les-services-publics-pres-de-chez-vous","https://www.economie.gouv.fr/particuliers/gerer-mon-argent/beneficier-daides-et-de-reductions-dimpots/france-services-les-services-publics-pres-de-chez-vous")&CHAR(10)&HYPERLINK("https://www.ecologie.gouv.fr/eco-energie-tertiaire-eet","https://www.ecologie.gouv.fr/eco-energie-tertiaire-eet")&CHAR(10)&HYPERLINK("https://www.collectivites-locales.gouv.fr/les-collectivites-locales-en-chiffres-2025","https://www.collectivites-locales.gouv.fr/les-collectivites-locales-en-chiffres-2025")&CHAR(10)&HYPERLINK("https://www.collectivites-locales.gouv.fr/actualites/situation-mensuelle-comptable-des-collectivites-locales-au-31-decembre-2025","https://www.collectivites-locales.gouv.fr/actualites/situation-mensuelle-comptable-des-collectivites-locales-au-31-decembre-2025")&CHAR(10)&HYPERLINK("https://www.statistiques.developpement-durable.gouv.fr/construction-de-locaux-resultats-fin-janvier-2026-france-entiere","https://www.statistiques.developpement-durable.gouv.fr/construction-de-locaux-resultats-fin-janvier-2026-france-entiere")&CHAR(10)&HYPERLINK("https://www.insee.fr/fr/statistiques/8671745","https://www.insee.fr/fr/statistiques/8671745")&CHAR(10)&HYPERLINK("https://www.insee.fr/fr/statistiques/8906564","https://www.insee.fr/fr/statistiques/8906564") -> https://anct.gouv.fr/france-services-36 https://www.economie.gouv.fr/particuliers/gerer-mon-argent/beneficier-daides-et-de-reductions-dimpots/france-services-les-services-publics-pres-de-chez-vous https://www.ecologie.gouv.fr/eco-energie-tertiaire-eet https://www.collectivites-locales.gouv.fr/les-collectivites-locales-en-chiffres-2025 https://www.collectivites-locales.gouv.fr/actualites/situation-mensuelle-comptable-des-collectivites-locales-au-31-decembre-2025 https://www.statistiques.developpement-durable.gouv.fr/construction-de-locaux-resultats-fin-janvier-2026-france-entiere https://www.insee.fr/fr/statistiques/8671745 https://www.insee.fr/fr/statistiques/8906564 | GH14: =GI14+GJ14 -> 22058.264 | GI14: =IFERROR($DH14*$FP14/MAX(0.000000001,$CR14)*(INDEX($S14:$AF14,1,MATCH(MAX(2000,MIN(2025,ROUND(2026-$CR14,0))),$S$4:$AF$4,1))+INDEX($S14:$AF14,1,MATCH(MAX(2000,MIN(2025,ROUND(2027-$CR14,0))),$S$4:$AF$4,1))+INDEX($S14:$AF14,1,MATCH(MAX(2000,MIN(2025,ROUND(2028-$CR14,0))),$S$4:$AF$4,1))+INDEX($S14:$AF14,1,MATCH(MAX(2000,MIN(2025,ROUND(2029-$CR14,0))),$S$4:$AF$4,1))+INDEX($S14:$AF14,1,MATCH(MAX(2000,MIN(2025,ROUND(2030-$CR14,0))),$S$4:$AF$4,1)))/MAX(1,$AF14),0) -> 19387.544 | GJ14: =IFERROR($FC14*$BS14,0) -> 2670.72 | GK14: =GL14+GM14 -> 19414.508 | GL14: =IFERROR($DI14*$FP14/MAX(0.000000001,$CS14)*(INDEX($S14:$AF14,1,MATCH(MAX(2000,MIN(2025,ROUND(2026-$CS14,0))),$S$4:$AF$4,1))+INDEX($S14:$AF14,1,MATCH(MAX(2000,MIN(2025,ROUND(2027-$CS14,0))),$S$4:$AF$4,1))+INDEX($S14:$AF14,1,MATCH(MAX(2000,MIN(2025,ROUND(2028-$CS14,0))),$S$4:$AF$4,1))+INDEX($S14:$AF14,1,MATCH(MAX(2000,MIN(2025,ROUND(2029-$CS14,0))),$S$4:$AF$4,1))+INDEX($S14:$AF14,1,MATCH(MAX(2000,MIN(2025,ROUND(2030-$CS14,0))),$S$4:$AF$4,1)))/MAX(1,$AF14),0) -> 16743.788 | GM14: =IFERROR($FC14*$BT14,0) -> 2670.72 | GN14: =GO14+GP14 -> 8937.389 | GO14: =IFERROR($DJ14*$FP14/MAX(0.000000001,$CT14)*(INDEX($S14:$AF14,1,MATCH(MAX(2000,MIN(2025,ROUND(2026-$CT14,0))),$S$4:$AF$4,1))+INDEX($S14:$AF14,1,MATCH(MAX(2000,MIN(2025,ROUND(2027-$CT14,0))),$S$4:$AF$4,1))+INDEX($S14:$AF14,1,MATCH(MAX(2000,MIN(2025,ROUND(2028-$CT14,0))),$S$4:$AF$4,1))+INDEX($S14:$AF14,1,MATCH(MAX(2000,MIN(2025,ROUND(2029-$CT14,0))),$S$4:$AF$4,1))+INDEX($S14:$AF14,1,MATCH(MAX(2000,MIN(2025,ROUND(2030-$CT14,0))),$S$4:$AF$4,1)))/MAX(1,$AF14),0) -> 7704.749 | GP14: =IFERROR($FC14*$BU14,0) -> 1232.64 | GQ14: =GR14+GS14 -> 2694.26 | GR14: =IFERROR($DK14*$FP14/MAX(0.000000001,$CU14)*(INDEX($S14:$AF14,1,MATCH(MAX(2000,MIN(2025,ROUND(2026-$CU14,0))),$S$4:$AF$4,1))+INDEX($S14:$AF14,1,MATCH(MAX(2000,MIN(2025,ROUND(2027-$CU14,0))),$S$4:$AF$4,1))+INDEX($S14:$AF14,1,MATCH(MAX(2000,MIN(2025,ROUND(2028-$CU14,0))),$S$4:$AF$4,1))+INDEX($S14:$AF14,1,MATCH(MAX(2000,MIN(2025,ROUND(2029-$CU14,0))),$S$4:$AF$4,1))+INDEX($S14:$AF14,1,MATCH(MAX(2000,MIN(2025,ROUND(2030-$CU14,0))),$S$4:$AF$4,1)))/MAX(1,$AF14),0) -> 2420.34 | GS14: =IFERROR($FC14*$BV14,0) -> 273.92 | GT14: =GU14+GV14 -> 0 | GU14: =IFERROR($DS14*$FP14/MAX(0.000000001,$CV14)*(INDEX($S14:$AF14,1,MATCH(MAX(2000,MIN(2025,ROUND(2026-$CV14,0))),$S$4:$AF$4,1))+INDEX($S14:$AF14,1,MATCH(MAX(2000,MIN(2025,ROUND(2027-$CV14,0))),$S$4:$AF$4,1))+INDEX($S14:$AF14,1,MATCH(MAX(2000,MIN(2025,ROUND(2028-$CV14,0))),$S$4:$AF$4,1))+INDEX($S14:$AF14,1,MATCH(MAX(2000,MIN(2025,ROUND(2029-$CV14,0))),$S$4:$AF$4,1))+INDEX($S14:$AF14,1,MATCH(MAX(2000,MIN(2025,ROUND(2030-$CV14,0))),$S$4:$AF$4,1)))/MAX(1,$AF14),0) -> 0 | GV14: =IFERROR($FF14*$BZ14,0) -> 0 | GW14: =GX14+GY14 -> 0 | GX14: =IFERROR($DT14*$FP14/MAX(0.000000001,$CW14)*(INDEX($S14:$AF14,1,MATCH(MAX(2000,MIN(2025,ROUND(2026-$CW14,0))),$S$4:$AF$4,1))+INDEX($S14:$AF14,1,MATCH(MAX(2000,MIN(2025,ROUND(2027-$CW14,0))),$S$4:$AF$4,1))+INDEX($S14:$AF14,1,MATCH(MAX(2000,MIN(2025,ROUND(2028-$CW14,0))),$S$4:$AF$4,1))+INDEX($S14:$AF14,1,MATCH(MAX(2000,MIN(2025,ROUND(2029-$CW14,0))),$S$4:$AF$4,1))+INDEX($S14:$AF14,1,MATCH(MAX(2000,MIN(2025,ROUND(2030-$CW14,0))),$S$4:$AF$4,1)))/MAX(1,$AF14),0) -> 0 | GY14: =IFERROR($FF14*$CA14,0) -> 0 | GZ14: =HA14+HB14 -> 0 | HA14: =IFERROR($DU14*$FP14/MAX(0.000000001,$CX14)*(INDEX($S14:$AF14,1,MATCH(MAX(2000,MIN(2025,ROUND(2026-$CX14,0))),$S$4:$AF$4,1))+INDEX($S14:$AF14,1,MATCH(MAX(2000,MIN(2025,ROUND(2027-$CX14,0))),$S$4:$AF$4,1))+INDEX($S14:$AF14,1,MATCH(MAX(2000,MIN(2025,ROUND(2028-$CX14,0))),$S$4:$AF$4,1))+INDEX($S14:$AF14,1,MATCH(MAX(2000,MIN(2025,ROUND(2029-$CX14,0))),$S$4:$AF$4,1))+INDEX($S14:$AF14,1,MATCH(MAX(2000,MIN(2025,ROUND(2030-$CX14,0))),$S$4:$AF$4,1)))/MAX(1,$AF14),0) -> 0 | HB14: =IFERROR($FF14*$CB14,0) -> 0 | HC14: =HD14+HE14 -> 1027.8323 | HD14: =IFERROR($EB14*$FP14/MAX(0.000000001,$CY14)*(INDEX($S14:$AF14,1,MATCH(MAX(2000,MIN(2025,ROUND(2026-$CY14,0))),$S$4:$AF$4,1))+INDEX($S14:$AF14,1,MATCH(MAX(2000,MIN(2025,ROUND(2027-$CY14,0))),$S$4:$AF$4,1))+INDEX($S14:$AF14,1,MATCH(MAX(2000,MIN(2025,ROUND(2028-$CY14,0))),$S$4:$AF$4,1))+INDEX($S14:$AF14,1,MATCH(MAX(2000,MIN(2025,ROUND(2029-$CY14,0))),$S$4:$AF$4,1))+INDEX($S14:$AF14,1,MATCH(MAX(2000,MIN(2025,ROUND(2030-$CY14,0))),$S$4:$AF$4,1)))/MAX(1,$AF14),0) -> 937.95227 | HE14: =IFERROR($FI14*$CG14,0) -> 89.88 | HF14: =HG14+HH14 -> 5011.5122 | HG14: =IFERROR($EC14*$FP14/MAX(0.000000001,$CZ14)*(INDEX($S14:$AF14,1,MATCH(MAX(2000,MIN(2025,ROUND(2026-$CZ14,0))),$S$4:$AF$4,1))+INDEX($S14:$AF14,1,MATCH(MAX(2000,MIN(2025,ROUND(2027-$CZ14,0))),$S$4:$AF$4,1))+INDEX($S14:$AF14,1,MATCH(MAX(2000,MIN(2025,ROUND(2028-$CZ14,0))),$S$4:$AF$4,1))+INDEX($S14:$AF14,1,MATCH(MAX(2000,MIN(2025,ROUND(2029-$CZ14,0))),$S$4:$AF$4,1))+INDEX($S14:$AF14,1,MATCH(MAX(2000,MIN(2025,ROUND(2030-$CZ14,0))),$S$4:$AF$4,1)))/MAX(1,$AF14),0) -> 4337.4122 | HH14: =IFERROR($FI14*$CH14,0) -> 674.1 | HI14: =HJ14+HK14 -> 4039.6067 | HJ14: =IFERROR($ED14*$FP14/MAX(0.000000001,$DA14)*(INDEX($S14:$AF14,1,MATCH(MAX(2000,MIN(2025,ROUND(2026-$DA14,0))),$S$4:$AF$4,1))+INDEX($S14:$AF14,1,MATCH(MAX(2000,MIN(2025,ROUND(2027-$DA14,0))),$S$4:$AF$4,1))+INDEX($S14:$AF14,1,MATCH(MAX(2000,MIN(2025,ROUND(2028-$DA14,0))),$S$4:$AF$4,1))+INDEX($S14:$AF14,1,MATCH(MAX(2000,MIN(2025,ROUND(2029-$DA14,0))),$S$4:$AF$4,1))+INDEX($S14:$AF14,1,MATCH(MAX(2000,MIN(2025,ROUND(2030-$DA14,0))),$S$4:$AF$4,1)))/MAX(1,$AF14),0) -> 3620.1667 | HK14: =IFERROR($FI14*$CI14,0) -> 419.44 | HL14: =HM14+HN14 -> 2893.9488 | HM14: =IFERROR($EE14*$FP14/MAX(0.000000001,$DB14)*(INDEX($S14:$AF14,1,MATCH(MAX(2000,MIN(2025,ROUND(2026-$DB14,0))),$S$4:$AF$4,1))+INDEX($S14:$AF14,1,MATCH(MAX(2000,MIN(2025,ROUND(2027-$DB14,0))),$S$4:$AF$4,1))+INDEX($S14:$AF14,1,MATCH(MAX(2000,MIN(2025,ROUND(2028-$DB14,0))),$S$4:$AF$4,1))+INDEX($S14:$AF14,1,MATCH(MAX(2000,MIN(2025,ROUND(2029-$DB14,0))),$S$4:$AF$4,1))+INDEX($S14:$AF14,1,MATCH(MAX(2000,MIN(2025,ROUND(2030-$DB14,0))),$S$4:$AF$4,1)))/MAX(1,$AF14),0) -> 2579.3688 | HN14: =IFERROR($FI14*$CJ14,0) -> 314.58 | HO14: =HP14+HQ14 -> 11884.624 | HP14: =IFERROR($EM14*$FP14/MAX(0.000000001,$DC14)*(INDEX($S14:$AF14,1,MATCH(MAX(2000,MIN(2025,ROUND(2026-$DC14,0))),$S$4:$AF$4,1))+INDEX($S14:$AF14,1,MATCH(MAX(2000,MIN(2025,ROUND(2027-$DC14,0))),$S$4:$AF$4,1))+INDEX($S14:$AF14,1,MATCH(MAX(2000,MIN(2025,ROUND(2028-$DC14,0))),$S$4:$AF$4,1))+INDEX($S14:$AF14,1,MATCH(MAX(2000,MIN(2025,ROUND(2029-$DC14,0))),$S$4:$AF$4,1))+INDEX($S14:$AF14,1,MATCH(MAX(2000,MIN(2025,ROUND(2030-$DC14,0))),$S$4:$AF$4,1)))/MAX(1,$AF14),0) -> 10600.624 | HQ14: =IFERROR($FL14*$CN14,0) -> 1284 | HR14: =HS14+HT14 -> 17711.748 | HS14: =IFERROR($EN14*$FP14/MAX(0.000000001,$DD14)*(INDEX($S14:$AF14,1,MATCH(MAX(2000,MIN(2025,ROUND(2026-$DD14,0))),$S$4:$AF$4,1))+INDEX($S14:$AF14,1,MATCH(MAX(2000,MIN(2025,ROUND(2027-$DD14,0))),$S$4:$AF$4,1))+INDEX($S14:$AF14,1,MATCH(MAX(2000,MIN(2025,ROUND(2028-$DD14,0))),$S$4:$AF$4,1))+INDEX($S14:$AF14,1,MATCH(MAX(2000,MIN(2025,ROUND(2029-$DD14,0))),$S$4:$AF$4,1))+INDEX($S14:$AF14,1,MATCH(MAX(2000,MIN(2025,ROUND(2030-$DD14,0))),$S$4:$AF$4,1)))/MAX(1,$AF14),0) -> 15143.748 | HT14: =IFERROR($FL14*$CO14,0) -> 2568 | HU14: =HV14+HW14 -> 7951.5713 | HV14: =IFERROR($EO14*$FP14/MAX(0.000000001,$DE14)*(INDEX($S14:$AF14,1,MATCH(MAX(2000,MIN(2025,ROUND(2026-$DE14,0))),$S$4:$AF$4,1))+INDEX($S14:$AF14,1,MATCH(MAX(2000,MIN(2025,ROUND(2027-$DE14,0))),$S$4:$AF$4,1))+INDEX($S14:$AF14,1,MATCH(MAX(2000,MIN(2025,ROUND(2028-$DE14,0))),$S$4:$AF$4,1))+INDEX($S14:$AF14,1,MATCH(MAX(2000,MIN(2025,ROUND(2029-$DE14,0))),$S$4:$AF$4,1))+INDEX($S14:$AF14,1,MATCH(MAX(2000,MIN(2025,ROUND(2030-$DE14,0))),$S$4:$AF$4,1)))/MAX(1,$AF14),0) -> 6667.5713 | HW14: =IFERROR($FL14*$CP14,0) -> 1284 | HY14: =SUM(HZ14:ID14) -> 315000 | HZ14: =IFERROR(IO14*BE14,0)+IFERROR(IY14*BF14,0)+IFERROR(JI14*BG14,0)+IFERROR(JS14*BH14,0) -> 10602 | IA14: =IFERROR(IP14*BE14,0)+IFERROR(IZ14*BF14,0)+IFERROR(JJ14*BG14,0)+IFERROR(JT14*BH14,0) -> 132665.5 | IB14: =IFERROR(IQ14*BE14,0)+IFERROR(JA14*BF14,0)+IFERROR(JK14*BG14,0)+IFERROR(JU14*BH14,0) -> 152374 | IC14: =IFERROR(IR14*BE14,0)+IFERROR(JB14*BF14,0)+IFERROR(JL14*BG14,0)+IFERROR(JV14*BH14,0) -> 19358.5 | ID14: =IFERROR(IS14*BE14,0)+IFERROR(JC14*BF14,0)+IFERROR(JM14*BG14,0)+IFERROR(JW14*BH14,0) -> 0 | IE14: =SUM(IF14:IJ14) -> 90143.264 | IF14: =IFERROR(IT14*FB14,0)+IFERROR(JD14*FE14,0)+IFERROR(JN14*FH14,0)+IFERROR(JX14*FK14,0) -> 1154.0769 | IG14: =IFERROR(IU14*FB14,0)+IFERROR(JE14*FE14,0)+IFERROR(JO14*FH14,0)+IFERROR(JY14*FK14,0) -> 35814.35 | IH14: =IFERROR(IV14*FB14,0)+IFERROR(JF14*FE14,0)+IFERROR(JP14*FH14,0)+IFERROR(JZ14*FK14,0) -> 45345.058 | II14: =IFERROR(IW14*FB14,0)+IFERROR(JG14*FE14,0)+IFERROR(JQ14*FH14,0)+IFERROR(KA14*FK14,0) -> 7413.0271 | IJ14: =IFERROR(IX14*FB14,0)+IFERROR(JH14*FE14,0)+IFERROR(JR14*FH14,0)+IFERROR(KB14*FK14,0) -> 416.75272 | IK14: 4.13 | IL14: Bonne | IM14: Parc existant centre sur le niveau mid, avec ventes 2026-2030 legerement plus qualitatives. Bureaux administratifs secondaires non ERP >50 salariés : accueil public de jour, flux moderes et renov. liees aux programmes patrimoniaux; le mix reste guide par accessibilite, image institutionnelle et maintenance sobre. | IO14: 0.03 | IP14: 0.4 | IQ14: 0.5 | IR14: 0.07 | IS14: 0 | IT14: 0.0088 | IU14: 0.3742 | IV14: 0.5212 | IW14: 0.0912 | IX14: 0.0046 | IY14: 0 | IZ14: 0 | JA14: 0 | JB14: 0 | JC14: 0 | JD14: 0 | JE14: 0 | JF14: 0 | JG14: 0 | JH14: 0 | JI14: 0.054 | JJ14: 0.5397 | JK14: 0.3748 | JL14: 0.0315 | JM14: 0 | JN14: 0.0329 | JO14: 0.5139 | JP14: 0.396 | JQ14: 0.0527 | JR14: 0.0045 | JS14: 0.0326 | JT14: 0.4148 | JU14: 0.4938 | JV14: 0.0588 | JW14: 0 | JX14: 0.0114 | JY14: 0.389 | JZ14: 0.515 | KA14: 0.0799 | KB14: 0.0047 | KD14: ±4 pts | KE14: ±4 pts | KF14: 4.16 | KG14: Bonne | KH14: Parc existant : accessibilite, image institutionnelle et maintenance sobre; accueil public de jour, flux moderes et renov. liees aux programmes patrimoniaux. La montee en confort reste proportionnee au budget et au rythme de renovation. | KI14: image client => premiumisation ciblee | KJ14: Bureaux administratifs secondaires non ERP >50 salariés : ventes 2026-2030 en leger glissement vers moyen/premium lorsque le neuf ou les renov. lourdes interviennent. Le centre de gravite reste toutefois module par accessibilite, image institutionnelle et maintenance sobre et par la part dominante de travaux sur parc existant.
A15: =A14+1 -> 7 | B15: Culte, Vie civique & Services publics | C15: Administrations / services publics | D15: Hôtels du département Hôtels de région & Services administratifs territoriaux | E15: W | F15: ERP / variable | G15: ERP | H15: oui | I15: Administrations recevant du public. | J15: Conseil départemental ; hôtel de région ; siège administratif territorial central | K15: non | L15: oui | M15: Site / établissement principal | N15: ajout qualitatif – à quantifier avant intégration | O15: Élevé | Q15: 1 | R15: 3800 | S15: 128 | T15: 131 | U15: 134 | V15: 136 | W15: 131 | X15: 129 | Y15: 127 | Z15: 126 | AA15: 125 | AB15: 124 | AC15: 123 | AD15: 122 | AE15: 122 | AF15: 121 | AG15: 121 | AH15: 120 | AI15: 120 | AJ15: 119 | AK15: 119 | AL15: Ancrage sur 101 départements et 26 puis 18 régions ; supplément multi-sites fondé sur organisations territoriales officiellement affichées par Régions. Anciens doublons sites régionaux désormais traités plus restrictivement. | AM15: Pour salariés, présence sanitaires universelle (code du travail) ; pour public, non-systématique. 2026-30 => Quelques sites centraux multiples subsistent , mais moins qu’avant la fusion régions. | AN15: https://www.collectivites-locales.gouv.fr/bis-ndeg195-les-structures-territoriales-au-1er-janvier-2025 https://www.insee.fr/fr/statistiques/5039877?sommaire=5040030 https://www.insee.fr/fr/metadonnees/definition/c2297 https://www.collectivites-locales.gouv.fr/connaitre-les-acteurs-et-les-institutions/structures-territoriales/les-communes/le-territoire-communal/la-creation-dune-commune-nouvelle https://codegeo.fr/ https://www.legifrance.gouv.fr/codes/section_lc/LEGITEXT000006072050/LEGISCTA000018489205/ | AP15: 350 | AQ15: 240 | AR15: 85 | AS15: 25 | AU15: Hôtel département/région : bloc public/assemblée + sanitaires agents par étages. | AV15: Capacité type ≈ 240 usagers principaux + 85 staff + 25 autre public. Accueil institutionnel, réunions, élus, agents et visiteurs. Dimensionnement unitaire retenu : batteries public/assemblée + noyaux salariés, PMR par niveaux ouverts. Hypothèse d'usage : capacité simultanée moyenne 2026, répartition par flux réels, arrondie par blocs fonctionnels et exclusion des sanitaires strictement privatifs sauf cas explicitement collectifs. | AW15: Profil grand, capacité moyenne ≈ 350 personnes. Moyenne pondérée terrain : parc majoritairement petits/moyens sites, grands sites intégrés sans surpondération ; usage 2025 forte à très forte. | AX15: ERP/accessibilité sanitaires publics : https://www.legifrance.gouv.fr/loda/article_lc/LEGIARTI000034485966/ ; Code du travail sanitaires salariés : https://www.legifrance.gouv.fr/codes/id/LEGISCTA000018531984 ; INRS : https://www.inrs.fr/publications/juridique/focus-juridiques/focus-sanitaires-toilettes.html | AZ15: 25 | BA15: 0 | BB15: 6 | BC15: 20 | BD15: =SUM(BE15:BH15) -> 6171 | BE15: =AF15*AZ15 -> 3025 | BF15: =AF15*BA15 -> 0 | BG15: =AF15*BB15 -> 726 | BH15: =AF15*BC15 -> 2420 | BI15: =SUM(BJ15:BM15) -> 6069 | BJ15: =AK15*AZ15 -> 2975 | BK15: =AK15*BA15 -> 0 | BL15: =AK15*BB15 -> 714 | BM15: =AK15*BC15 -> 2380 | BO15: 0.36 | BP15: 0.42 | BQ15: 0.18 | BR15: 0.04 | BS15: 0.32 | BT15: 0.41 | BU15: 0.24 | BV15: 0.03 | CC15: 0.12 | CD15: 0.5 | CE15: 0.15 | CF15: 0.23 | CG15: 0.1 | CH15: 0.5 | CI15: 0.18 | CJ15: 0.22 | CK15: 0.55 | CL15: 0.3 | CM15: 0.15 | CN15: 0.47 | CO15: 0.33 | CP15: 0.2 | CR15: 13 | CS15: 14 | CT15: 10 | CU15: 12 | CY15: 11 | CZ15: 13 | DA15: 9 | DB15: 11 | DC15: 14 | DD15: 14 | DE15: 10 | DF15: Guichets territoriaux, flux sociaux/modérés, maintenance publique externalisée; faible humidité. Proche France Services, plus long si site récent et fréquentation faible. Repères durées: lavabos 13/14/10 ans (mit./méca/élec.), douches 12/11/9, urinoirs 11/13/9/11, WC 14/14/10. | DH15: =$BE15*BO15 -> 1089 | DI15: =$BE15*BP15 -> 1270.5 | DJ15: =$BE15*BQ15 -> 544.5 | DK15: =$BE15*BR15 -> 121 | DL15: Hôtels du département Hôtels de région & Services administratifs territoriaux : parc 2025 domine par tempo mecanique (50%), avec mitigeur manuel en appoint. Le choix reflete accueil public de jour, flux moderes et renov. liees aux programmes patrimoniaux ; accessibilite, image institutionnelle et maintenance sobre. | DM15: =$BJ15*BS15 -> 952 | DN15: =$BJ15*BT15 -> 1219.75 | DO15: =$BJ15*BU15 -> 714 | DP15: =$BJ15*BV15 -> 89.25 | DQ15: 2025-2030 : progression de tempo electronique (+5,0%), surtout lors des renov. lourdes/neuf ; recul de mitigeur manuel (-5,0%) mais maintien d un socle robuste pour les remplacements partiels. | DS15: =$BF15*BW15 -> 0 | DT15: =$BF15*BX15 -> 0 | DU15: =$BF15*BY15 -> 0 | DV15: Sans objet. | DW15: =$BK15*BZ15 -> 0 | DX15: =$BK15*CA15 -> 0 | DY15: =$BK15*CB15 -> 0 | DZ15: Sans objet. | EB15: =$BG15*CC15 -> 87.12 | EC15: =$BG15*CD15 -> 363 | ED15: =$BG15*CE15 -> 108.9 | EE15: =$BG15*CF15 -> 166.98 | EF15: Hôtels du département Hôtels de région & Services administratifs territoriaux : parc 2025 domine par directe mecanique (50%), avec directe electronique collective en appoint. Le choix reflete accueil public de jour, flux moderes et renov. liees aux programmes patrimoniaux ; accessibilite, image institutionnelle et maintenance sobre. | EG15: =$BL15*CG15 -> 71.4 | EH15: =$BL15*CH15 -> 357 | EI15: =$BL15*CI15 -> 128.52 | EJ15: =$BL15*CJ15 -> 157.08 | EK15: 2025-2030 : progression de directe electronique indiv. (+3,0%), surtout lors des renov. lourdes/neuf ; recul de a reservoir (-2,0%) mais maintien d un socle robuste pour les remplacements partiels. | EM15: =$BH15*CK15 -> 1331 | EN15: =$BH15*CL15 -> 726 | EO15: =$BH15*CM15 -> 363 | EP15: Hôtels du département Hôtels de région & Services administratifs territoriaux : parc 2025 domine par reservoir (55%), avec chasse directe mecanique en appoint. Le choix reflete accueil public de jour, flux moderes et renov. liees aux programmes patrimoniaux ; accessibilite, image institutionnelle et maintenance sobre. | EQ15: =$BM15*CN15 -> 1118.6 | ER15: =$BM15*CO15 -> 785.4 | ES15: =$BM15*CP15 -> 476 | ET15: 2025-2030 : progression de chasse directe electronique (+5,0%), surtout lors des renov. lourdes/neuf ; recul de reservoir (-8,0%) mais maintien d un socle robuste pour les remplacements partiels. | EV15: =IFERROR(EY15/EX15,0) -> 0.88583637 | EW15: =IFERROR(EZ15/EX15,0) -> 0.11416363 | EX15: =EY15+EZ15 -> 2313.5108 | EY15: =SUM(FB15,FE15,FH15,FK15) -> 2049.392 | EZ15: =SUM(FC15,FF15,FI15,FL15) -> 264.1188 | FA15: =FB15+FC15 -> 1138.4137 | FB15: =SUM(GI15,GL15,GO15,GR15) -> 1008.9437 | FC15: =MAX(0,$BJ15-$BE15)+$BE15*$FO15 -> 129.47 | FD15: =FE15+FF15 -> 0 | FE15: =SUM(GU15,GX15,HA15) -> 0 | FF15: =MAX(0,$BK15-$BF15)+$BF15*$FO15 -> 0 | FG15: =FH15+FI15 -> 294.46245 | FH15: =SUM(HD15,HG15,HJ15,HM15) -> 263.38965 | FI15: =MAX(0,$BL15-$BG15)+$BG15*$FO15 -> 31.0728 | FJ15: =FK15+FL15 -> 880.63459 | FK15: =SUM(HP15,HS15,HV15) -> 777.05859 | FL15: =MAX(0,$BM15-$BH15)+$BH15*$FO15 -> 103.576 | FN15: Moyenne à Bonne | FO15: 0.0428 | FP15: 0.77415 | FQ15: 77,4% retenu : besoins transformes en travaux selon accueil public de jour, flux moderes et renov. liees aux programmes patrimoniaux. Le phasage budgetaire, les fermetures partielles et la maintenance courante limitent la conversion totale. | FS15: 3.06 | FT15: =RANK($FS15,$FS$16:$FS$17,0)+COUNTIF($FS$16:$FS17,$FS15)-1 -> 2 | FU15: 3.57 | FV15: =RANK($FU15,$FU$16:$FU$17,0)+COUNTIF($FU$16:$FU17,$FU15)-1 -> #N/A | FW15: 2.14 | FX15: =RANK($FW15,$FW$16:$FW$17,0)+COUNTIF($FW$16:$FW17,$FW15)-1 -> #N/A | FZ15: Potentiel renovation : tire par accessibilite, image institutionnelle et maintenance sobre. Les remplacements sont plutot par lots, avec arbitrage entre urgence sanitaire, budget et capacite a intervenir en site occupe. | GA15: Potentiel neuf : limite pour hôtels du département hôtels de région & services administratifs territoriaux, surtout via extensions, reconstructions ou projets locaux. Le neuf reste contraint par foncier, budgets et delais de mise en service. | GB15: Projets phares renovation : reprise de blocs sanitaires, accessibilite, ventilation, economie d eau, remplacement des pieces usees et adaptation aux pics de frequentation propres au sous-segment. | GC15: Projets phares neuf : creations ou reconstructions selectives, integration de sanitaires plus sobres, robustes et faciles a maintenir des la conception. | GD15: Dynamique renovation 2026-2030 : moderee, car l usure et l hygiene rendent les interventions recurrentes. Menaces : arbitrages d investissement, travaux en exploitation et cout de maintenance. | GE15: Dynamique neuf 2026-2030 : faible a moderee, dependante des projets immobiliers, de la demographie locale et des budgets de maitrise d ouvrage. | GF15: =HYPERLINK("https://anct.gouv.fr/france-services-36","https://anct.gouv.fr/france-services-36")&CHAR(10)&HYPERLINK("https://www.economie.gouv.fr/particuliers/gerer-mon-argent/beneficier-daides-et-de-reductions-dimpots/france-services-les-services-publics-pres-de-chez-vous","https://www.economie.gouv.fr/particuliers/gerer-mon-argent/beneficier-daides-et-de-reductions-dimpots/france-services-les-services-publics-pres-de-chez-vous")&CHAR(10)&HYPERLINK("https://www.ecologie.gouv.fr/eco-energie-tertiaire-eet","https://www.ecologie.gouv.fr/eco-energie-tertiaire-eet")&CHAR(10)&HYPERLINK("https://www.collectivites-locales.gouv.fr/les-collectivites-locales-en-chiffres-2025","https://www.collectivites-locales.gouv.fr/les-collectivites-locales-en-chiffres-2025")&CHAR(10)&HYPERLINK("https://www.collectivites-locales.gouv.fr/actualites/situation-mensuelle-comptable-des-collectivites-locales-au-31-decembre-2025","https://www.collectivites-locales.gouv.fr/actualites/situation-mensuelle-comptable-des-collectivites-locales-au-31-decembre-2025")&CHAR(10)&HYPERLINK("https://www.statistiques.developpement-durable.gouv.fr/construction-de-locaux-resultats-fin-janvier-2026-france-entiere","https://www.statistiques.developpement-durable.gouv.fr/construction-de-locaux-resultats-fin-janvier-2026-france-entiere")&CHAR(10)&HYPERLINK("https://www.insee.fr/fr/statistiques/8671745","https://www.insee.fr/fr/statistiques/8671745")&CHAR(10)&HYPERLINK("https://www.insee.fr/fr/statistiques/8906564","https://www.insee.fr/fr/statistiques/8906564") -> https://anct.gouv.fr/france-services-36 https://www.economie.gouv.fr/particuliers/gerer-mon-argent/beneficier-daides-et-de-reductions-dimpots/france-services-les-services-publics-pres-de-chez-vous https://www.ecologie.gouv.fr/eco-energie-tertiaire-eet https://www.collectivites-locales.gouv.fr/les-collectivites-locales-en-chiffres-2025 https://www.collectivites-locales.gouv.fr/actualites/situation-mensuelle-comptable-des-collectivites-locales-au-31-decembre-2025 https://www.statistiques.developpement-durable.gouv.fr/construction-de-locaux-resultats-fin-janvier-2026-france-entiere https://www.insee.fr/fr/statistiques/8671745 https://www.insee.fr/fr/statistiques/8906564 | GH15: =GI15+GJ15 -> 397.3012 | GI15: =IFERROR($DH15*$FP15/MAX(0.000000001,$CR15)*(INDEX($S15:$AF15,1,MATCH(MAX(2000,MIN(2025,ROUND(2026-$CR15,0))),$S$4:$AF$4,1))+INDEX($S15:$AF15,1,MATCH(MAX(2000,MIN(2025,ROUND(2027-$CR15,0))),$S$4:$AF$4,1))+INDEX($S15:$AF15,1,MATCH(MAX(2000,MIN(2025,ROUND(2028-$CR15,0))),$S$4:$AF$4,1))+INDEX($S15:$AF15,1,MATCH(MAX(2000,MIN(2025,ROUND(2029-$CR15,0))),$S$4:$AF$4,1))+INDEX($S15:$AF15,1,MATCH(MAX(2000,MIN(2025,ROUND(2030-$CR15,0))),$S$4:$AF$4,1)))/MAX(1,$AF15),0) -> 355.8708 | GJ15: =IFERROR($FC15*$BS15,0) -> 41.4304 | GK15: =GL15+GM15 -> 441.51246 | GL15: =IFERROR($DI15*$FP15/MAX(0.000000001,$CS15)*(INDEX($S15:$AF15,1,MATCH(MAX(2000,MIN(2025,ROUND(2026-$CS15,0))),$S$4:$AF$4,1))+INDEX($S15:$AF15,1,MATCH(MAX(2000,MIN(2025,ROUND(2027-$CS15,0))),$S$4:$AF$4,1))+INDEX($S15:$AF15,1,MATCH(MAX(2000,MIN(2025,ROUND(2028-$CS15,0))),$S$4:$AF$4,1))+INDEX($S15:$AF15,1,MATCH(MAX(2000,MIN(2025,ROUND(2029-$CS15,0))),$S$4:$AF$4,1))+INDEX($S15:$AF15,1,MATCH(MAX(2000,MIN(2025,ROUND(2030-$CS15,0))),$S$4:$AF$4,1)))/MAX(1,$AF15),0) -> 388.42976 | GM15: =IFERROR($FC15*$BT15,0) -> 53.0827 | GN15: =GO15+GP15 -> 253.33127 | GO15: =IFERROR($DJ15*$FP15/MAX(0.000000001,$CT15)*(INDEX($S15:$AF15,1,MATCH(MAX(2000,MIN(2025,ROUND(2026-$CT15,0))),$S$4:$AF$4,1))+INDEX($S15:$AF15,1,MATCH(MAX(2000,MIN(2025,ROUND(2027-$CT15,0))),$S$4:$AF$4,1))+INDEX($S15:$AF15,1,MATCH(MAX(2000,MIN(2025,ROUND(2028-$CT15,0))),$S$4:$AF$4,1))+INDEX($S15:$AF15,1,MATCH(MAX(2000,MIN(2025,ROUND(2029-$CT15,0))),$S$4:$AF$4,1))+INDEX($S15:$AF15,1,MATCH(MAX(2000,MIN(2025,ROUND(2030-$CT15,0))),$S$4:$AF$4,1)))/MAX(1,$AF15),0) -> 222.25847 | GP15: =IFERROR($FC15*$BU15,0) -> 31.0728 | GQ15: =GR15+GS15 -> 46.268812 | GR15: =IFERROR($DK15*$FP15/MAX(0.000000001,$CU15)*(INDEX($S15:$AF15,1,MATCH(MAX(2000,MIN(2025,ROUND(2026-$CU15,0))),$S$4:$AF$4,1))+INDEX($S15:$AF15,1,MATCH(MAX(2000,MIN(2025,ROUND(2027-$CU15,0))),$S$4:$AF$4,1))+INDEX($S15:$AF15,1,MATCH(MAX(2000,MIN(2025,ROUND(2028-$CU15,0))),$S$4:$AF$4,1))+INDEX($S15:$AF15,1,MATCH(MAX(2000,MIN(2025,ROUND(2029-$CU15,0))),$S$4:$AF$4,1))+INDEX($S15:$AF15,1,MATCH(MAX(2000,MIN(2025,ROUND(2030-$CU15,0))),$S$4:$AF$4,1)))/MAX(1,$AF15),0) -> 42.384712 | GS15: =IFERROR($FC15*$BV15,0) -> 3.8841 | GT15: =GU15+GV15 -> 0 | GU15: =IFERROR($DS15*$FP15/MAX(0.000000001,$CV15)*(INDEX($S15:$AF15,1,MATCH(MAX(2000,MIN(2025,ROUND(2026-$CV15,0))),$S$4:$AF$4,1))+INDEX($S15:$AF15,1,MATCH(MAX(2000,MIN(2025,ROUND(2027-$CV15,0))),$S$4:$AF$4,1))+INDEX($S15:$AF15,1,MATCH(MAX(2000,MIN(2025,ROUND(2028-$CV15,0))),$S$4:$AF$4,1))+INDEX($S15:$AF15,1,MATCH(MAX(2000,MIN(2025,ROUND(2029-$CV15,0))),$S$4:$AF$4,1))+INDEX($S15:$AF15,1,MATCH(MAX(2000,MIN(2025,ROUND(2030-$CV15,0))),$S$4:$AF$4,1)))/MAX(1,$AF15),0) -> 0 | GV15: =IFERROR($FF15*$BZ15,0) -> 0 | GW15: =GX15+GY15 -> 0 | GX15: =IFERROR($DT15*$FP15/MAX(0.000000001,$CW15)*(INDEX($S15:$AF15,1,MATCH(MAX(2000,MIN(2025,ROUND(2026-$CW15,0))),$S$4:$AF$4,1))+INDEX($S15:$AF15,1,MATCH(MAX(2000,MIN(2025,ROUND(2027-$CW15,0))),$S$4:$AF$4,1))+INDEX($S15:$AF15,1,MATCH(MAX(2000,MIN(2025,ROUND(2028-$CW15,0))),$S$4:$AF$4,1))+INDEX($S15:$AF15,1,MATCH(MAX(2000,MIN(2025,ROUND(2029-$CW15,0))),$S$4:$AF$4,1))+INDEX($S15:$AF15,1,MATCH(MAX(2000,MIN(2025,ROUND(2030-$CW15,0))),$S$4:$AF$4,1)))/MAX(1,$AF15),0) -> 0 | GY15: =IFERROR($FF15*$CA15,0) -> 0 | GZ15: =HA15+HB15 -> 0 | HA15: =IFERROR($DU15*$FP15/MAX(0.000000001,$CX15)*(INDEX($S15:$AF15,1,MATCH(MAX(2000,MIN(2025,ROUND(2026-$CX15,0))),$S$4:$AF$4,1))+INDEX($S15:$AF15,1,MATCH(MAX(2000,MIN(2025,ROUND(2027-$CX15,0))),$S$4:$AF$4,1))+INDEX($S15:$AF15,1,MATCH(MAX(2000,MIN(2025,ROUND(2028-$CX15,0))),$S$4:$AF$4,1))+INDEX($S15:$AF15,1,MATCH(MAX(2000,MIN(2025,ROUND(2029-$CX15,0))),$S$4:$AF$4,1))+INDEX($S15:$AF15,1,MATCH(MAX(2000,MIN(2025,ROUND(2030-$CX15,0))),$S$4:$AF$4,1)))/MAX(1,$AF15),0) -> 0 | HB15: =IFERROR($FF15*$CB15,0) -> 0 | HC15: =HD15+HE15 -> 35.993172 | HD15: =IFERROR($EB15*$FP15/MAX(0.000000001,$CY15)*(INDEX($S15:$AF15,1,MATCH(MAX(2000,MIN(2025,ROUND(2026-$CY15,0))),$S$4:$AF$4,1))+INDEX($S15:$AF15,1,MATCH(MAX(2000,MIN(2025,ROUND(2027-$CY15,0))),$S$4:$AF$4,1))+INDEX($S15:$AF15,1,MATCH(MAX(2000,MIN(2025,ROUND(2028-$CY15,0))),$S$4:$AF$4,1))+INDEX($S15:$AF15,1,MATCH(MAX(2000,MIN(2025,ROUND(2029-$CY15,0))),$S$4:$AF$4,1))+INDEX($S15:$AF15,1,MATCH(MAX(2000,MIN(2025,ROUND(2030-$CY15,0))),$S$4:$AF$4,1)))/MAX(1,$AF15),0) -> 32.885892 | HE15: =IFERROR($FI15*$CG15,0) -> 3.10728 | HF15: =HG15+HH15 -> 134.16 | HG15: =IFERROR($EC15*$FP15/MAX(0.000000001,$CZ15)*(INDEX($S15:$AF15,1,MATCH(MAX(2000,MIN(2025,ROUND(2026-$CZ15,0))),$S$4:$AF$4,1))+INDEX($S15:$AF15,1,MATCH(MAX(2000,MIN(2025,ROUND(2027-$CZ15,0))),$S$4:$AF$4,1))+INDEX($S15:$AF15,1,MATCH(MAX(2000,MIN(2025,ROUND(2028-$CZ15,0))),$S$4:$AF$4,1))+INDEX($S15:$AF15,1,MATCH(MAX(2000,MIN(2025,ROUND(2029-$CZ15,0))),$S$4:$AF$4,1))+INDEX($S15:$AF15,1,MATCH(MAX(2000,MIN(2025,ROUND(2030-$CZ15,0))),$S$4:$AF$4,1)))/MAX(1,$AF15),0) -> 118.6236 | HH15: =IFERROR($FI15*$CH15,0) -> 15.5364 | HI15: =HJ15+HK15 -> 54.441969 | HJ15: =IFERROR($ED15*$FP15/MAX(0.000000001,$DA15)*(INDEX($S15:$AF15,1,MATCH(MAX(2000,MIN(2025,ROUND(2026-$DA15,0))),$S$4:$AF$4,1))+INDEX($S15:$AF15,1,MATCH(MAX(2000,MIN(2025,ROUND(2027-$DA15,0))),$S$4:$AF$4,1))+INDEX($S15:$AF15,1,MATCH(MAX(2000,MIN(2025,ROUND(2028-$DA15,0))),$S$4:$AF$4,1))+INDEX($S15:$AF15,1,MATCH(MAX(2000,MIN(2025,ROUND(2029-$DA15,0))),$S$4:$AF$4,1))+INDEX($S15:$AF15,1,MATCH(MAX(2000,MIN(2025,ROUND(2030-$DA15,0))),$S$4:$AF$4,1)))/MAX(1,$AF15),0) -> 48.848865 | HK15: =IFERROR($FI15*$CI15,0) -> 5.593104 | HL15: =HM15+HN15 -> 69.867309 | HM15: =IFERROR($EE15*$FP15/MAX(0.000000001,$DB15)*(INDEX($S15:$AF15,1,MATCH(MAX(2000,MIN(2025,ROUND(2026-$DB15,0))),$S$4:$AF$4,1))+INDEX($S15:$AF15,1,MATCH(MAX(2000,MIN(2025,ROUND(2027-$DB15,0))),$S$4:$AF$4,1))+INDEX($S15:$AF15,1,MATCH(MAX(2000,MIN(2025,ROUND(2028-$DB15,0))),$S$4:$AF$4,1))+INDEX($S15:$AF15,1,MATCH(MAX(2000,MIN(2025,ROUND(2029-$DB15,0))),$S$4:$AF$4,1))+INDEX($S15:$AF15,1,MATCH(MAX(2000,MIN(2025,ROUND(2030-$DB15,0))),$S$4:$AF$4,1)))/MAX(1,$AF15),0) -> 63.031293 | HN15: =IFERROR($FI15*$CJ15,0) -> 6.836016 | HO15: =HP15+HQ15 -> 455.60714 | HP15: =IFERROR($EM15*$FP15/MAX(0.000000001,$DC15)*(INDEX($S15:$AF15,1,MATCH(MAX(2000,MIN(2025,ROUND(2026-$DC15,0))),$S$4:$AF$4,1))+INDEX($S15:$AF15,1,MATCH(MAX(2000,MIN(2025,ROUND(2027-$DC15,0))),$S$4:$AF$4,1))+INDEX($S15:$AF15,1,MATCH(MAX(2000,MIN(2025,ROUND(2028-$DC15,0))),$S$4:$AF$4,1))+INDEX($S15:$AF15,1,MATCH(MAX(2000,MIN(2025,ROUND(2029-$DC15,0))),$S$4:$AF$4,1))+INDEX($S15:$AF15,1,MATCH(MAX(2000,MIN(2025,ROUND(2030-$DC15,0))),$S$4:$AF$4,1)))/MAX(1,$AF15),0) -> 406.92642 | HQ15: =IFERROR($FL15*$CN15,0) -> 48.68072 | HR15: =HS15+HT15 -> 256.13994 | HS15: =IFERROR($EN15*$FP15/MAX(0.000000001,$DD15)*(INDEX($S15:$AF15,1,MATCH(MAX(2000,MIN(2025,ROUND(2026-$DD15,0))),$S$4:$AF$4,1))+INDEX($S15:$AF15,1,MATCH(MAX(2000,MIN(2025,ROUND(2027-$DD15,0))),$S$4:$AF$4,1))+INDEX($S15:$AF15,1,MATCH(MAX(2000,MIN(2025,ROUND(2028-$DD15,0))),$S$4:$AF$4,1))+INDEX($S15:$AF15,1,MATCH(MAX(2000,MIN(2025,ROUND(2029-$DD15,0))),$S$4:$AF$4,1))+INDEX($S15:$AF15,1,MATCH(MAX(2000,MIN(2025,ROUND(2030-$DD15,0))),$S$4:$AF$4,1)))/MAX(1,$AF15),0) -> 221.95986 | HT15: =IFERROR($FL15*$CO15,0) -> 34.18008 | HU15: =HV15+HW15 -> 168.88751 | HV15: =IFERROR($EO15*$FP15/MAX(0.000000001,$DE15)*(INDEX($S15:$AF15,1,MATCH(MAX(2000,MIN(2025,ROUND(2026-$DE15,0))),$S$4:$AF$4,1))+INDEX($S15:$AF15,1,MATCH(MAX(2000,MIN(2025,ROUND(2027-$DE15,0))),$S$4:$AF$4,1))+INDEX($S15:$AF15,1,MATCH(MAX(2000,MIN(2025,ROUND(2028-$DE15,0))),$S$4:$AF$4,1))+INDEX($S15:$AF15,1,MATCH(MAX(2000,MIN(2025,ROUND(2029-$DE15,0))),$S$4:$AF$4,1))+INDEX($S15:$AF15,1,MATCH(MAX(2000,MIN(2025,ROUND(2030-$DE15,0))),$S$4:$AF$4,1)))/MAX(1,$AF15),0) -> 148.17231 | HW15: =IFERROR($FL15*$CP15,0) -> 20.7152 | HY15: =SUM(HZ15:ID15) -> 6171 | HZ15: =IFERROR(IO15*BE15,0)+IFERROR(IY15*BF15,0)+IFERROR(JI15*BG15,0)+IFERROR(JS15*BH15,0) -> 208.846 | IA15: =IFERROR(IP15*BE15,0)+IFERROR(IZ15*BF15,0)+IFERROR(JJ15*BG15,0)+IFERROR(JT15*BH15,0) -> 2605.6382 | IB15: =IFERROR(IQ15*BE15,0)+IFERROR(JA15*BF15,0)+IFERROR(JK15*BG15,0)+IFERROR(JU15*BH15,0) -> 2979.6008 | IC15: =IFERROR(IR15*BE15,0)+IFERROR(JB15*BF15,0)+IFERROR(JL15*BG15,0)+IFERROR(JV15*BH15,0) -> 376.915 | ID15: =IFERROR(IS15*BE15,0)+IFERROR(JC15*BF15,0)+IFERROR(JM15*BG15,0)+IFERROR(JW15*BH15,0) -> 0 | IE15: =SUM(IF15:IJ15) -> 2049.392 | IF15: =IFERROR(IT15*FB15,0)+IFERROR(JD15*FE15,0)+IFERROR(JN15*FH15,0)+IFERROR(JX15*FK15,0) -> 28.247145 | IG15: =IFERROR(IU15*FB15,0)+IFERROR(JE15*FE15,0)+IFERROR(JO15*FH15,0)+IFERROR(JY15*FK15,0) -> 817.43281 | IH15: =IFERROR(IV15*FB15,0)+IFERROR(JF15*FE15,0)+IFERROR(JP15*FH15,0)+IFERROR(JZ15*FK15,0) -> 1028.4036 | II15: =IFERROR(IW15*FB15,0)+IFERROR(JG15*FE15,0)+IFERROR(JQ15*FH15,0)+IFERROR(KA15*FK15,0) -> 166.13883 | IJ15: =IFERROR(IX15*FB15,0)+IFERROR(JH15*FE15,0)+IFERROR(JR15*FH15,0)+IFERROR(KB15*FK15,0) -> 9.169586 | IK15: 4.13 | IL15: Bonne | IM15: Parc existant centre sur le niveau mid, avec ventes 2026-2030 legerement plus qualitatives. Hôtels du département Hôtels de région & Services administratifs territoriaux : accueil public de jour, flux moderes et renov. liees aux programmes patrimoniaux; le mix reste guide par accessibilite, image institutionnelle et maintenance sobre. | IO15: 0.03 | IP15: 0.4 | IQ15: 0.5 | IR15: 0.07 | IS15: 0 | IT15: 0.0097 | IU15: 0.3753 | IV15: 0.5202 | IW15: 0.0903 | IX15: 0.0045 | IY15: 0 | IZ15: 0 | JA15: 0 | JB15: 0 | JC15: 0 | JD15: 0 | JE15: 0 | JF15: 0 | JG15: 0 | JH15: 0 | JI15: 0.054 | JJ15: 0.5397 | JK15: 0.3748 | JL15: 0.0315 | JM15: 0 | JN15: 0.0338 | JO15: 0.515 | JP15: 0.3951 | JQ15: 0.0518 | JR15: 0.0043 | JS15: 0.0326 | JT15: 0.4148 | JU15: 0.4938 | JV15: 0.0588 | JW15: 0 | JX15: 0.0123 | JY15: 0.3901 | JZ15: 0.5141 | KA15: 0.079 | KB15: 0.0045 | KD15: ±4 pts | KE15: ±4 pts | KF15: 4.16 | KG15: Bonne | KH15: Parc existant : accessibilite, image institutionnelle et maintenance sobre; accueil public de jour, flux moderes et renov. liees aux programmes patrimoniaux. La montee en confort reste proportionnee au budget et au rythme de renovation. | KI15: image client => premiumisation ciblee | KJ15: Hôtels du département Hôtels de région & Services administratifs territoriaux : ventes 2026-2030 en leger glissement vers moyen/premium lorsque le neuf ou les renov. lourdes interviennent. Le centre de gravite reste toutefois module par accessibilite, image institutionnelle et maintenance sobre et par la part dominante de travaux sur parc existant.
