Workbook

Sheet Hypothèses - DuréeVie - ERP&Pdt
A1: Méthodologie de durée de vie réelle (parc installé 2025)
A2: Horizon de calcul des pièces à rénover | C2: 5 ans (2025-2030). Formule principale sur l’onglet principal : stock 2025 × min(1 ; 5 / durée de vie réelle).
A4: Code profil | B4: Libellé profil | C4: Usage / logique | D4: Lav M | E4: Lav TM | F4: Lav TE | G4: Lav Aut | H4: Dou M | I4: Dou TM | J4: Dou TE | K4: Uri Res | L4: Uri DM | M4: Uri DEI | N4: Uri DEC | O4: WC Res | P4: WC DM | Q4: WC DE | R4: Sources / éléments tangibles (URLs)
A5: P1 | B5: Petite enfance supervisée | C5: Faible vandalisme, forte supervision adulte et maintenance régulière, mais lavage des mains intensif. Renouvellement plutôt par campagne bâtiment qu’en urgence. | D5: 14 | E5: 13 | F5: 10 | G5: 12 | H5: 14 | I5: 13 | J5: 10 | K5: 13 | L5: 14 | M5: 10 | N5: 12 | O5: 15 | P5: 15 | Q5: 11 | R5: https://www.delabie.fr/nos-services/notre-expertise/nos-solutions/robinetterie-pour-lieux-publics | https://www.delabie.fr/nos-produits/robinetterie-pour-lieux-publics/robinet-de-lavabo-temporise/740500-robinet-de-lavabo-temporise-temposoft-2
A6: P2 | B6: Enseignement intensif sous contrainte budgétaire | C6: Pics interclasses, usage quotidien élevé, vandalisme modéré et budgets publics souvent lissés. Le temporisé et la chasse directe tiennent mieux que le manuel/réservoir en usage intensif. | D6: 12 | E6: 13 | F6: 9 | G6: 11 | H6: 12 | I6: 11 | J6: 8 | K6: 10 | L6: 13 | M6: 9 | N6: 11 | O6: 11 | P6: 13 | Q6: 10 | R6: https://www.delabie.fr/nos-services/notre-expertise/nos-solutions/robinetterie-pour-lieux-publics | https://www.renovation-bati-scolaire.fr/ressources/fonds-vert-2025
A7: P3 | B7: Campus tertiaire / enseignement supérieur | C7: Usage adulte, fréquentation soutenue mais moins agressive, rénovations périodiques de campus et obligations de mise à niveau tertiaire. | D7: 13 | E7: 14 | F7: 10 | G7: 12 | H7: 13 | I7: 12 | J7: 9 | K7: 11 | L7: 14 | M7: 10 | N7: 12 | O7: 12 | P7: 14 | Q7: 11 | R7: https://www.ecologie.gouv.fr/eco-energie-tertiaire-eet | https://www.delabie.fr/nos-services/notre-expertise/nos-solutions/robinetterie-pour-lieux-publics
A8: P4 | B8: Résidentiel éducatif / jeunesse | C8: Usage résidentiel ou semi-résidentiel, douches plus sollicitées, pics saisonniers mais moindre vandalisme que le scolaire de jour. | D8: 14 | E8: 13 | F8: 10 | G8: 12 | H8: 13 | I8: 12 | J8: 9 | K8: 12 | L8: 13 | M8: 9 | N8: 11 | O8: 14 | P8: 13 | Q8: 10 | R8: https://www.ecologie.gouv.fr/politiques-publiques/sante-construction-plomb-legionelle | https://www.delabie.fr/nos-services/notre-expertise/nos-solutions/robinetterie-pour-lieux-publics
A9: P5 | B9: Loisirs jeunesse / usage saisonnier | C9: Fréquentation par pics, usage parfois extérieur/saisonnier, surveillance variable et maintenance souvent concentrée hors saison. | D9: 13 | E9: 13 | F9: 9 | G9: 11 | H9: 12 | I9: 11 | J9: 8 | K9: 10 | L9: 12 | M9: 8 | N9: 10 | O9: 11 | P9: 12 | Q9: 9 | R9: https://www.ecologie.gouv.fr/politiques-publiques/sante-construction-plomb-legionelle | https://www.delabie.fr/nos-services/notre-expertise/nos-solutions/robinetterie-pour-lieux-publics
A10: P6 | B10: Santé hospitalière aiguë | C10: Forte exigence d’hygiène, prévention légionelles, nettoyage fréquent et remplacements préventifs liés aux travaux Ségur ou à la conformité sanitaire. | D10: 12 | E10: 11 | F10: 8 | G10: 10 | H10: 11 | I10: 10 | J10: 8 | K10: 10 | L10: 12 | M10: 8 | N10: 10 | O10: 12 | P10: 12 | Q10: 9 | R10: https://fides.sante.gouv.fr/soins-et-maladies/maladies/maladies-et-infections-respiratoires/article/prevention-de-la-legionellose-les-obligations-par-type-d-installation-et-d | https://igas.gouv.fr/pour-un-pilotage-renforce-des-investissements-immobiliers-des-etablissements-de-sante-consolider-lexpertise-et-la-maitrise-douvrage-hospitaliere-0 | https://www.delabie.fr/nos-services/notre-expertise/dossiers-thematiques/chasse-directe-la-reponse-adaptee-aux-problematiques-des-lieux-publics
A11: P7 | B11: Santé spécialisée / ambulatoire / médico-éducatif | C11: Contrainte hygiène maintenue mais fréquentation moins continue que l’hospitalier aigu ; maintenance régulière, renouvellement par lots lors de travaux ciblés. | D11: 12 | E11: 12 | F11: 9 | G11: 10 | H11: 12 | I11: 11 | J11: 8 | K11: 11 | L11: 12 | M11: 8 | N11: 10 | O11: 12 | P11: 12 | Q11: 9 | R11: https://fides.sante.gouv.fr/soins-et-maladies/maladies/maladies-et-infections-respiratoires/article/prevention-de-la-legionellose-les-obligations-par-type-d-installation-et-d | https://www.delabie.fr/nos-services/notre-expertise/nos-solutions/robinetterie-pour-lieux-publics
A12: P8 | B12: Médico-social résidentiel / seniors / handicap | C12: Forte part d’usage résidentiel ou en chambre, moindre vandalisme, mais entretien régulier pour limiter stagnation/tartre ; remplacement souvent en lots de chambres ou d’unités. | D12: 14 | E12: 13 | F12: 10 | G12: 12 | H12: 13 | I12: 12 | J12: 9 | K12: 13 | L12: 13 | M12: 9 | N12: 11 | O12: 15 | P12: 13 | Q12: 10 | R12: https://cpias-occitanie.fr/outils-cpias-occitanie/guide-legionelles-en-ehpad/ | https://fides.sante.gouv.fr/soins-et-maladies/maladies/maladies-et-infections-respiratoires/article/prevention-de-la-legionellose-les-obligations-par-type-d-installation-et-d | https://www.delabie.com/our-services/our-expertise/dossiers/direct-flush-designed-to-solve-the-problems-faced-by-public-places
A13: P9 | B13: Culture / conférence / exposition | C13: Usage public modéré à fort mais irrégulier, pics événementiels, budgets municipaux/intercommunaux et rénovation par campagnes plutôt que remplacement à la panne. | D13: 13 | E13: 13 | F13: 10 | G13: 12 | H13: 13 | I13: 12 | J13: 9 | K13: 11 | L13: 13 | M13: 9 | N13: 11 | O13: 12 | P13: 13 | Q13: 10 | R13: https://www.ecologie.gouv.fr/eco-energie-tertiaire-eet | https://www.delabie.fr/nos-services/notre-expertise/dossiers-thematiques/chasse-directe-la-reponse-adaptee-aux-problematiques-des-lieux-publics
A14: P10 | B14: Restauration / bars / nightlife / loisirs indoor | C14: Longues amplitudes, forte humidité, nettoyage agressif, image commerciale importante et vandalisme plus élevé en soirée/nuit. | D14: 10 | E14: 11 | F14: 8 | G14: 9 | H14: 11 | I14: 10 | J14: 8 | K14: 9 | L14: 11 | M14: 8 | N14: 9 | O14: 10 | P14: 11 | Q14: 9 | R14: https://www.delabie.fr/nos-services/notre-expertise/dossiers-thematiques/chasse-directe-la-reponse-adaptee-aux-problematiques-des-lieux-publics | https://www.cws.com/fr-LU/hygiene/centre-de-connaissances/sanitaires-anti-vandalisme
A15: P11 | B15: Commerce / transport / parkings / sanitaires publics très intensifs | C15: Très forte fréquentation, disponibilité immédiate requise, vandalisme et coûts d’exploitation élevés ; la temporisation mécanique et la chasse directe sont favorisées. | D15: 9 | E15: 11 | F15: 8 | G15: 9 | H15: 10 | I15: 10 | J15: 8 | K15: 8 | L15: 11 | M15: 8 | N15: 9 | O15: 9 | P15: 12 | Q15: 9 | R15: https://www.delabie.fr/nos-services/notre-expertise/dossiers-thematiques/chasse-directe-la-reponse-adaptee-aux-problematiques-des-lieux-publics | https://www.cws.com/fr-LU/hygiene/centre-de-connaissances/sanitaires-anti-vandalisme | https://www.delabie.fr/nos-produits/robinetterie-pour-lieux-publics/robinet-d-urinoir-automatique-et-temporise/479410-robinet-d-urinoir-automatique-tempomatic-4
A16: P12 | B16: Bureaux / administration / justice | C16: Usage tertiaire moyen, faible vandalisme, rénovations par lots tirées par l’immobilier tertiaire, l’accessibilité et la trajectoire Éco Énergie Tertiaire. | D16: 13 | E16: 13 | F16: 10 | G16: 12 | H16: 13 | I16: 12 | J16: 9 | K16: 11 | L16: 13 | M16: 9 | N16: 11 | O16: 12 | P16: 13 | Q16: 10 | R16: https://www.ecologie.gouv.fr/eco-energie-tertiaire-eet | https://www.delabie.fr/nos-services/notre-expertise/dossiers-thematiques/systeme-de-chasse-directe-wc-la-revolution-du-public
... A23: P19 | B23: Culte / associatif faible intensité | C23: Fréquentation faible à modérée, faible vandalisme, remplacement souvent différé pour raisons budgétaires ; équipements conservés plus longtemps. | D23: 15 | E23: 14 | F23: 10 | G23: 13 | H23: 14 | I23: 13 | J23: 9 | K23: 13 | L23: 14 | M23: 9 | N23: 12 | O23: 15 | P23: 14 | Q23: 10 | R23: https://www.ecologie.gouv.fr/eco-energie-tertiaire-eet | https://www.delabie.fr/nos-services/notre-expertise/nos-solutions/robinetterie-pour-lieux-publics
A26: Repères techniques utilisés
A27: R1 | B27: Robinetterie temporisée collective : durée de vie des piles 3 à 6 ans et mécanismes/électrovannes ≥ 500 000 manoeuvres. | C27: https://www.delabie.fr/nos-services/notre-expertise/nos-solutions/robinetterie-pour-lieux-publics
A28: R2 | B28: Lavabo temporisé : 3 l/min, temporisation ~7 s, garantie 30 ans. | C28: https://www.delabie.fr/nos-produits/robinetterie-pour-lieux-publics/robinet-de-lavabo-temporise/740500-robinet-de-lavabo-temporise-temposoft-2
A29: R3 | B29: Douche temporisée : ~15 s, mécanisme testé à plus de 500 000 manoeuvres. | C29: https://www.sider.biz/produit/robinet-temporise-delabie-m1-2.153713015
A30: R4 | B30: Urinoir temporisé : ~3 s, résistance > 500 000 manoeuvres. | C30: https://www.materiauxnet.com/robinet-d-urinoir-delabie-tempostop-alimentation-en-ligne.html
A31: R5 | B31: Urinoir électronique : rinçage périodique hygiénique 24h, mode affluence. | C31: https://www.delabie.fr/nos-produits/robinetterie-pour-lieux-publics/robinet-d-urinoir-automatique-et-temporise/479410-robinet-d-urinoir-automatique-tempomatic-4
A32: R6 | B32: WC chasse directe : conçue pour forte fréquentation, résistante au vandalisme, >500 000 manoeuvres, plus hygiénique que réservoir. | C32: https://www.delabie.fr/nos-services/notre-expertise/dossiers-thematiques/chasse-directe-la-reponse-adaptee-aux-problematiques-des-lieux-publics
A33: R7 | B33: Prévention légionelles : éviter stagnation, tartre et corrosion ; sujet critique dans santé/EHPAD. | C33: https://fides.sante.gouv.fr/soins-et-maladies/maladies/maladies-et-infections-respiratoires/article/prevention-de-la-legionellose-les-obligations-par-type-d-installation-et-d
A34: R8 | B34: Éco Énergie Tertiaire : -40 % d’énergie finale en 2030 pour le tertiaire > 1 000 m² ; favorise les rénovations par lots. | C34: https://www.ecologie.gouv.fr/eco-energie-tertiaire-eet
A35: R9 | B35: Sport : 182 700 équipements sportifs, gymnases et salles en zones urbaines ; occupation parfois très élevée. | C35: https://www.insee.fr/fr/statistiques/8376522
A36: R10 | B36: Hôpital : plan Ségur 7,5 Md€ pour moderniser le patrimoine hospitalier, mise en oeuvre cependant décalée. | C36: https://igas.gouv.fr/pour-un-pilotage-renforce-des-investissements-immobiliers-des-etablissements-de-sante-consolider-lexpertise-et-la-maitrise-douvrage-hospitaliere-0
A37: R11 | B37: Prisons : plan 15 000 places, parc ancien et fortement sollicité ; renouvellement partiel par nouveaux établissements d’ici 2027. | C37: https://www.justice.gouv.fr/plan-15-000-places-prison
A38: R12 | B38: Hôtels : rénovations typiquement par campagnes, souvent 7 à 10 ans pour maintenir le standard ; exemples de refresh à 20 ans quand l’asset reste fonctionnel. | C38: https://conceptrenodeco.fr/guides/renovation-hotel-moderniser-chambres-espaces/ | https://baudet-sa.com/detail-realisation/ibis-munster

Sheet Split Neuf-Réno selon CHAT
B2: Q1 | C2: Tout en occultant toutes les recherches précédentes réalisées sur le sujet ... peux-tu me dire, via d'autres sources, en France, sur la robinetterie sanitaire collective (lavabos + urinoirs + douche + WC), pour les ERP uniquement, quel serait en volume de pièces, le % consacré à la vente neuve et quel % serait consacré à la rénovation, sur la période 2025-2030, en tenant compte aussi de tous les facteurs endogènes et exogènes identifiés (notamment dynamique économique, dynamique de la construction, dynamique du marché de la robinetterie, impact de la situation internationale, finances puliques, politiques publiques, investissements privés, programme de relance nationaux, écart entre intention et réalisation, ou tout autre élément impactant l'activité) . Merci de me livrer un niveau de fiabilité de ta réponse, ta méthodologie et tes sources.
C4: Je repars de zéro et je vais construire une estimation indépendante, en m’appuyant cette fois sur des sources publiques/sectorielles externes et une modélisation explicite du marché ERP.
C6: Je tiens la structure du modèle. Le cœur de la réponse va reposer sur un point simple : en ERP, le volume neuf est mécaniquement limité par les mises en chantier annuelles, alors que la rénovation est tirée par un parc existant immense, par les obligations de rénovation tertiaire et par les programmes écoles/hôpitaux/bâtiments publics.
C8: Thought for 8m 36s
C10: Oui. En repartant indépendamment des échanges précédents et en m’appuyant sur des sources externes publiques/sectorielles, mon estimation centrale pour la robinetterie sanitaire collective en ERP en France — périmètre lavabos + urinoirs + douches + WC, en volume de pièces, hors logement — est la suivante :
C12: Année | D12: Volume total estimé (pièces) | E12: Neuf | F12: Rénovation
C13: 2025 | D13: 565000 | E13: 110 000 (20 %) | F13: 455 000 (80 %)
C14: 2026 | D14: 570000 | E14: 115 000 (20 %) | F14: 455 000 (80 %)
C15: 2027 | D15: 585000 | E15: 120 000 (21 %) | F15: 465 000 (79 %)
C16: 2028 | D16: 600000 | E16: 128 000 (21 %) | F16: 472 000 (79 %)
C17: 2029 | D17: 615000 | E17: 135 000 (22 %) | F17: 480 000 (78 %)
C18: 2030 | D18: 630000 | E18: 142 000 (23 %) | F18: 488 000 (77 %)
C20: Ma lecture synthétique est donc : sur 2025-2030, le marché ERP restera très majoritairement un marché de rénovation, autour de 77 % à 80 % des volumes, tandis que le neuf représenterait 20 % à 23 % selon les années. Cette domination de la rénovation est cohérente avec la taille du parc tertiaire existant, les obligations réglementaires de réduction de consommation dans l’existant, et le fait que la construction neuve non résidentielle reste nettement plus petite que le stock en exploitation.
C22: Ce qui me fait pencher vers 80/20 plutôt que 50/50
C24: Le point décisif est le poids du parc existant. L’ADEME estime la surface tertiaire chauffée à 976 millions de m² en 2023, et le Cerema estime qu’environ 740 millions de m² de locaux tertiaires de métropole sont déjà dans le champ du dispositif Éco Énergie Tertiaire pour les surfaces de plus de 1 000 m². En parallèle, le cahier 2026 du Fonds vert rappelle un parc tertiaire d’environ 1 milliard de m², dont plus du tiers pour les bâtiments publics de l’État et des collectivités, et indique que les collectivités détiennent à elles seules plus de 225 000 bâtiments pour 280 millions de m². Ce stock immense crée mécaniquement un volant de remplacement et de rénovation très supérieur à ce que peut générer le seul flux annuel de bâtiments neufs.
C26: À l’inverse, le neuf part d’un flux plus étroit. Sur les douze mois allant de février 2025 à janvier 2026, les mises en chantier de locaux non résidentiels atteignent 21,0 millions de m², en hausse de 2,8 %, mais les autorisations baissent encore légèrement à 37,2 millions de m² (-1,9 %). La FFB souligne en outre que le non-résidentiel neuf a encore reculé de 6,6 % en volume en 2025 après -4,1 % en 2024, même si les surfaces commencées ont montré une inflexion positive en 2025. Autrement dit : le neuf cesse de se dégrader autant qu’en 2024, mais il ne redevient pas le moteur principal du marché.
C28: Les facteurs qui soutiennent la rénovation ERP jusqu’en 2030
C30: Le principal moteur structurel est réglementaire : le dispositif Éco Énergie Tertiaire impose pour les bâtiments concernés une baisse de consommation d’énergie de -40 % en 2030, -50 % en 2040 et -60 % en 2050. Le cahier 2026 du Fonds vert rappelle aussi que la directive européenne sur l’efficacité énergétique impose une rénovation à haut niveau de performance d’au moins 3 % des surfaces des bâtiments publics de plus de 250 m² chauffés ou refroidis, ainsi qu’une baisse annuelle de 1,9 % de la consommation d’énergie des organismes publics. Même si la robinetterie n’est pas le premier poste d’investissement d’une rénovation énergétique, elle entre souvent dans les lots “sanitaires / eau / confort d’été / mise en conformité / modernisation”. Le Fonds vert rend d’ailleurs explicitement éligibles les équipements permettant de réduire la consommation d’eau.
C32: Le deuxième moteur est la massification de programmes ciblés sur les ERP publics. Côté scolaire, la Banque des Territoires indique environ 53 000 établissements scolaires publics, 130 millions de m² de surface et un programme EduRénov visant 10 000 projets d’ici 2027, avec 2 Md€ de prêts et 50 M€ d’ingénierie. En juillet 2025, Localtis indiquait déjà 5 000 chantiers engagés, et la ministre évoquait 2 Md€ supplémentaires. Côté santé, le Ségur représente 19 Md€ d’investissement jusqu’en 2030, dont une part majeure pour les établissements de santé. Côté justice, le ministère a aussi lancé des opérations de rénovation énergétique sur des tribunaux, centres de détention et autres sites. Tout cela alimente un flux de rénovation sanitaire dans des ERP très équipés en lavabos, WC, urinoirs et douches.
C34: Les facteurs qui freinent le marché
C36: Je ne vois pas un scénario de forte accélération linéaire, parce que plusieurs freins sont réels. La FFB signale une activité d’entretien-amélioration en recul, avec un non-résidentiel à -0,6 % entre T3 2024 et T3 2025, et même une légère érosion de la rénovation énergétique non résidentielle. La Banque des Territoires note un contexte budgétaire tendu pour les collectivités, une baisse de certaines aides et surtout un écart important entre étude et réalisation : selon Actee/Banque des Territoires, près de 50 % des projets s’arrêtent entre l’étude technique et la réalisation. Côté santé, le ministère évoque en 2025 un déficit estimé à 2,9 Md€ fin 2024 pour les établissements publics de santé, ce qui peut ralentir ou phaser certains investissements hors opérations déjà financées.
C38: Le contexte macro ne pousse pas non plus à un emballement. En mars 2026, la Banque de France prévoit une croissance du PIB français de 0,9 % en 2026, puis 0,8 % en 2027 avant 1,2 % en 2028, en soulignant que la hausse des prix de l’énergie et la détérioration du contexte géopolitique pèseraient sur l’activité et l’investissement des entreprises. La Banque mondiale anticipe de son côté des prix des métaux de base en hausse de 3 % en 2025, globalement stables en 2026, puis autour de +2 % en 2027. Enfin, l’indice Insee des prix de production de la robinetterie d’équipement du bâtiment est passé de 100 en 2021 à 120,7 en février 2026, ce qui signifie que la pression prix a déjà été forte depuis 2021, même si le rythme semble désormais plus calme. Cela tend à soutenir la valeur, mais à limiter le volume si les budgets chantier sont serrés.
C40: Ma méthodologie
C42: Je n’ai pas trouvé de série publique prête à l’emploi donnant directement le nombre de pièces de robinetterie sanitaire collective ERP vendues en France, ni leur ventilation neuf/rénovation. Les chiffres ci-dessus sont donc modélisés. Les statistiques publiques consultées décrivent surtout le parc tertiaire, la construction neuve non résidentielle, les programmes de rénovation et les prix de la robinetterie, pas ce sous-segment précis. La robinetterie sanitaire représente par ailleurs près de la moitié de la production commercialisée en valeur de la robinetterie de bâtiment, ce qui confirme l’importance du segment, mais pas son split ERP/neuf/réno.
... C68: Je peux aussi vous livrer une version plus “cabinet de conseil”, avec scénario bas / central / haut, ou un découpage par type de pièce : lavabos, urinoirs, douches, WC.

Sheet Chat avec Chat
B2: Q1 | C2: En France, en robinetterie collective quelle proportion du parc existant entre mitigeur, robinetterie électronique et robinetterie mécanique temporisée ? ... aussi pour les années 2026-2030, chaque année, quelle proportion entre chaque type de robinet - et pourquoi ? ... beaucoup de différence entre parc existant et ventes 2026-2030 ?
C4: Je vais chercher des sources de marché et des repères techniques français/européens, puis distinguer clairement parc installé et ventes neuves. Sur ce sujet, il est probable qu’on doive raisonner par estimation documentée plutôt que par statistique officielle unique.
C6: J’ai les principaux moteurs de fond : hygiène/sans contact, économie d’eau, maîtrise du risque sanitaire et maintenance/coût total. Je vais maintenant transformer ça en une estimation chiffrée cohérente, en séparant bien le parc installé des ventes annuelles.
C8: Réflexion durant 2m 29s
C10: Oui, mais il faut poser un cadre clair : il n’existe pas, à ma connaissance, de statistique publique française donnant la répartition nationale exacte du parc de robinetterie collective entre mitigeur, électronique et mécanique temporisée. Donc ce qui suit est une estimation de travail pour la robinetterie de lavabo / lave-mains en lieux collectifs (ERP, tertiaire, enseignement, santé, sport, transport), construite à partir des offres réellement dominantes du marché pro, des contraintes d’hygiène et de gestion de l’eau, et du rythme de renouvellement du parc.
C12: Ma lecture du parc existant 2026 en France est la suivante :
C14: robinetterie mécanique temporisée : ~54 %
C15: mitigeur “classique” manuel : ~32 %
C16: robinetterie électronique : ~14 %
C18: C’est cohérent avec un parc historiquement tiré par la temporisation mécanique dans les sanitaires à fort passage, parce qu’elle reste robuste, simple, économique et pensée pour l’usage intensif ; par exemple, les modèles temporisés pro affichent typiquement 3 l/min, ~15 s d’écoulement et jusqu’à 500 000 manœuvres. Le mitigeur manuel reste encore très présent dans les zones moins intensives, les bureaux, les locaux du personnel et une partie du parc ancien. L’électronique progresse, mais part d’un parc plus récent.
C20: Pour les ventes 2026, j’estimerais plutôt :
C22: mécanique temporisée : ~47 %
C23: électronique : ~33 %
... C28: Ma projection des ventes annuelles pour 2026-2030 serait :
C30: Année | D30: Mitigeur manuel | E30: Électronique | F30: Mécanique temporisée
C31: 2026 | D31: 0.2 | E31: 0.33 | F31: 0.47
C32: 2027 | D32: 0.19 | E32: 0.35 | F32: 0.46
C33: 2028 | D33: 0.18 | E33: 0.37 | F33: 0.45
C34: 2029 | D34: 0.17 | E34: 0.39 | F34: 0.44
C35: 2030 | D35: 0.16 | E35: 0.41 | F35: 0.43
C37: L’idée derrière cette courbe est simple : la temporisée mécanique reste très forte car elle garde un avantage de coût d’achat, de simplicité de maintenance et de résistance au vandalisme / usage intensif ; l’électronique gagne du terrain tous les ans grâce à l’hygiène sans contact, à la baisse des consommations d’eau et aux exigences de maîtrise sanitaire ; le mitigeur manuel recule dans les sanitaires collectifs à fort passage, mais ne disparaît pas car il garde des positions dans les bureaux, locaux de service et petites rénovations sous contrainte budgétaire.
C39: La projection du parc installé évolue forcément plus lentement. J’estimerais :
C41: Année | D41: Mitigeur manuel | E41: Électronique | F41: Mécanique temporisée
C42: 2026 | D42: 0.32 | E42: 0.14 | F42: 0.54
C43: 2027 | D43: 0.31 | E43: 0.15 | F43: 0.54
C44: 2028 | D44: 0.3 | E44: 0.17 | F44: 0.53
C45: 2029 | D45: 0.29 | E45: 0.18 | F45: 0.53
C46: 2030 | D46: 0.28 | E46: 0.2 | F46: 0.52
C48: Donc en 2030, même avec des ventes déjà très favorables à l’électronique, le parc resterait encore majoritairement temporisé mécanique, parce que la robinetterie collective se renouvelle lentement, souvent au fil des opérations de maintenance lourde, de réhabilitation sanitaire ou de remise en conformité, et non en remplacement massif annuel. La dynamique du non-résidentiel en France s’améliore un peu, mais on n’est pas dans un scénario de vague de reconstruction capable de retourner très vite le parc ; le Trésor signalait récemment une reprise portée par le non-résidentiel, tout en indiquant que l’investissement public ralentirait, et les données de construction de locaux montraient en 2025 une hausse modérée des autorisations, pas un boom.
C50: Sur votre question “beaucoup de différence entre parc existant et ventes ?”, ma réponse est oui, assez nettement. En 2026, dans cette estimation, l’électronique représente ~14 % du parc mais ~33 % des ventes. À l’inverse, le mitigeur manuel ferait encore ~32 % du parc mais seulement ~20 % des ventes. La temporisée mécanique, elle, reste forte des deux côtés : ~54 % du parc et ~47 % des ventes. C’est typiquement le profil d’un marché de remplacement où la nouvelle demande bascule plus vite que le stock installé.
C53: Pourquoi cette bascule se fait-elle ainsi ?
C55: D’abord, l’hygiène. Les fabricants et distributeurs pro poussent clairement le sans-contact pour les ERP et les établissements de soins ; Delabie met en avant la suppression du contact manuel, et les modèles électroniques récents intègrent souvent des fonctions de rinçage périodique utiles contre la stagnation. En parallèle, les obligations de gestion de la qualité de l’eau se renforcent, avec les plans de gestion de la sécurité sanitaire de l’eau et la vigilance sur les légionelles dans les ERP et établissements de santé.
C57: Ensuite, l’eau et l’énergie. Dans un sanitaire collectif, passer d’un robinet manuel “laissé ouvert” à une solution temporisée ou électronique à faible débit abaisse fortement les consommations. Les acteurs du marché mettent en avant des débits préréglés bas et, pour le sans-contact, des économies très élevées sur le lavage des mains. Cela pousse les cahiers des charges vers le temporisé et l’électronique, surtout en rénovation tertiaire.
C59: Enfin, le coût total. La temporisée mécanique garde un très bon rapport coût / robustesse / maintenance, donc elle reste souvent le choix rationnel dans les écoles, gymnases, équipements sportifs ou sanitaires publics très sollicités. L’électronique progresse surtout là où l’hygiène, l’image, le confort d’usage ou la gestion technique du bâtiment justifient le surcoût : santé, tertiaire premium, transport, aéroports, grands ERP récents.
C61: Mon point de vigilance : si vous élargissez la définition en intégrant beaucoup de bureaux internes, cuisines, locaux techniques ou hébergement, la part du mitigeur manuel remonte un peu. À l’inverse, si vous ciblez surtout sanitaires publics à fort trafic ou santé, la part de l’électronique dans les ventes peut être 5 à 10 points plus haute que mon scénario central.
C63: Pour un usage de modélisation, je vous conseillerais donc de retenir ce scénario central France 2026 :
C65: parc existant : manuel 32 % / électronique 14 % / temporisé mécanique 54 %
C66: ventes 2026 : manuel 20 % / électronique 33 % / temporisé mécanique 47 %
C67: ventes 2030 : manuel 16 % / électronique 41 % / temporisé mécanique 43 %
C69: Et la conclusion de fond est : oui, il y a une vraie différence entre parc et ventes ; l’électronique surperforme fortement en ventes, mais le parc reste dominé par la temporisation mécanique jusqu’en 2030.
B73: Q2 | C73: D'après ton raisonnement, peux-tu renseigner un mix par type de produit selon la technologie employée (mix lavabos, mix douches, mix urinoirs et mix WC), d'après les libellés de colonnes T à AF. Pour chaque type de produit, merci de justifier ton mix par des éléments tangibles par rapport au parc existant, pour chaque ligne. merci de ne considérer que les sanitaires communs dimensionnés pour accueillir plus de 5 personnes - donc, ne pas considérer les sanitaires individuels ... sauf pour EHPAD - USLD et les les catégories Santé hospitalière, Santé spécialisée et Univers carcéral (si toutefois il y a de l'individuel).
C76: La logique de fond appliquée est celle-ci : le temporisé mécanique reste dominant dans les parcs collectifs intensifs et robustes comme l’enseignement, le sport, l’industrie ou une partie des ERP publics, car c’est la techno historiquement la plus répandue en collectivité, robuste et économe en eau ; l’électronique monte surtout dans les segments rénovés à enjeu d’hygiène et d’image comme aéroports, gares, malls, bureaux récents ou certains sites de santé ; les mitigeurs restent dominants là où le parc ressemble davantage à de l’hébergement ou du soin, en particulier en santé et en EHPAD. Les WC à chasse directe prennent le dessus dans les ERP publics à fort trafic, tandis que les réservoirs restent très présents dans les parcs plus résidentiels ou de chambre.
C78: Si vous voulez, je peux maintenant vous faire une version 2026-2030 du même fichier, avec projection annuelle des mix par technologie.
C80: J’ai confirmé l’écart : le total lavabos 2025 du fichier ressort autour de 41,5 % mitigeurs, 34,1 % temporisés mécaniques, 17,4 % électroniques et 7,1 % autres. Je vais maintenant cibler les lignes les plus contributrices qui surpondèrent le manuel ou les “autres”, sans refaire tout le tableau arbitrairement.
C82: J’ai confirmé que le 32/54/14 décrit surtout les sanitaires collectifs intensifs, pas forcément le total élargi du tableau. Je sécurise maintenant l’écriture du fichier et le rendu final du bloc 2030 avec les justifications sur l’onglet principal.
C84: J’ai :
C86: remis les justifications sur l’onglet ERP - Sanitaires collectifs 7 ;
C87: ajouté le mix 2030 sur les mêmes familles de colonnes, en AH:AU ;
C88: ajouté les justifications 2025 et les justifications d’évolution 2025→2030 sur le même onglet, en AV:BE ;
C89: conservé l’onglet Références techno et enrichi les sources ;
C90: supprimé l’ancien onglet séparé Justifications mix techno 2025 pour éviter les doublons.
C92: Sur le re-challenge 2025, je n’ai pas forcé tout le tableau à coller au benchmark global 32 / 54 / 14. Je l’ai seulement corrigé là où il y avait un vrai sujet de sous-pondération du temporisé ou de l’électronique dans des sanitaires communs rénovés. Le total pondéré du tableau reste plus “mitigeur” que ce benchmark, et c’est cohérent avec le périmètre réel du fichier : il inclut aussi de la santé, de l’EHPAD, de l’hébergement, de la restauration, du culte et des petits ERP de proximité, où le mitigeur manuel ou médical reste structurellement plus présent. À l’inverse, les blocs collectifs intensifs restent bien dominés par le temporisé mécanique, avec une montée graduelle de l’électronique. Cela colle au marché pro : le temporisé collectif reste une base robuste et économe en eau, tandis que l’électronique progresse grâce au sans-contact et au rinçage périodique ; en santé, les gammes médicales restent disponibles en mécanique comme en électronique.
C94: Pour 2030, j’ai gardé une logique de projection de parc installé, pas de ventes annuelles. J’ai donc fait monter l’électronique de façon graduelle, surtout dans le tertiaire, les transports, le commerce, la culture et les sanitaires publics, en cohérence avec la poursuite des rénovations du parc tertiaire à horizon 2030 et avec le renforcement des logiques de maîtrise sanitaire de l’eau.
C96: Pour les WC et urinoirs, la trajectoire 2030 favorise surtout la chasse directe et l’automatique dans les ERP intensifs, sans faire disparaître trop vite les réservoirs et les systèmes mécaniques dans les parcs plus lents à rénover. C’est cohérent avec le fait que la chasse directe est documentée comme plus adaptée aux lieux publics intensifs, alors que les WC à réservoir restent plus proches d’une logique d’habitat et demeurent présents dans le stock existant.
B100: Q3 | C100: A partir du document attaché, pour chacune des colonnes G à T, peux-tu me donner en colonnes suivantes, une durée de vie de produit pour chacune des colonnes ? ... En durée de vie, je n'entends pas une durée de vie théorique du produit ... je souhaite que pour chaque sous-catégorie, tu m'indiques une durée de vie réelle par type de produit, en te basant sur des critères comme l'usage, la fréquentation des lieux, l'intensité d'utilisation, le vandalisme, le budget envisagé sur la période 2025-2030, éventuellement les politiques publiques, le fait de rénover individuellement (panne) ou par lots (batch de rénovation), ou tout autre élément estimé et utile susceptible de raccourcir ou prolonger la durée de vie du produit. A l'issue, j'aimerais estimer le nombre de pièces par type de produit pour chaque sous-catégorie qui devront être rénovées à partir du parc existant précédemment calculé. Merci de justifier pour chaque sous-catégorie, type de produit et techno, cette durée de vie réelle du produit et de me livrer un niveau de fiabilité à chaque fois. Merci d'approfondir toutes tes recherches.
C102: J’ai ajouté :
C104: les durées de vie réelles par techno pour chaque sous-catégorie,
C105: le nombre de pièces du parc 2025 à rénover sur 2025-2030,
C106: un niveau de fiabilité par techno,
C107: un argumentaire détaillé par sous-catégorie,
C108: une colonne sources.
C110: À noter : j’ai traité la durée de vie comme une durée réelle d’exploitation (usage, intensité, vandalisme, humidité, maintenance, arbitrages budgétaires, rénovation par lots), pas comme une durée théorique fabricant.
B113: Q4 | C113: Un peu surpris de certaines de tes durées de vie réelles ... notamment une durée de vie réelle des mitigeurs plus longue que les temporisés - l'écart de durée de vie des tempo mécaniques avec les électroniques ... Aussi l'écart important de durée de vie du même produit entre sous-segments différents ... Peux-tu justifier ces écarts (au global - et pour chaque sous-catégorie - autrement dit, qu'est-ce que de manière tangible, dans l'usage, intensité, vandalisme, humidité, maintenance, arbitrages budgétaires, rénovation par lots, on aboutit à cette durée de vie) et éventuellement modifier ton document en faisant une recherche un peu plus approfondie pour chaque techno et chaque sous-segment ... Si tu fais des modifs, merci de me livrer une synthèse des modifications réalisées ... Donc, merci de me livre un doc. Excel mis à jour.
C115: J’ai revu la logique pour :
C117: remonter / resserrer les durées des temporisés mécaniques vs mitigeurs dans les usages partagés,
C118: réduire les écarts trop forts entre tempo mécaniques et électroniques,
C119: resserrer les écarts entre sous-segments sauf cas vraiment extrêmes (piscines, transport très intensif, toilettes publiques, carcéral),
C120: ajouter une feuille “Synthèse écarts DV” qui explique la logique globale,
C121: ajouter des colonnes fiabilité par techno,
C122: réécrire les argumentaires par sous-catégorie.
C124: Principaux ancrages utilisés :
C126: la maintenance et l’entretien conditionnent directement la durée réelle des équipements sanitaires ; l’absence d’entretien, l’humidité, la corrosion et les fuites accélèrent les remplacements
C127: en collectivités, les mécanismes temporisés / électrovannes sont annoncés à au moins 500 000 manœuvres, alors que la durée moyenne des piles des systèmes électroniques est donnée à 350 000 cycles (3 à 6 ans), ce qui explique pourquoi le temporisé mécanique reste souvent au moins aussi durable que le mitigeur en usage partagé intensif
C128: les temporisés sont explicitement recommandés dans les sanitaires à risque de vandalisme (ex. scolaires, aires d’autoroute), tandis que l’électronique gagne surtout sur l’hygiène et le rinçage périodique des réseaux
C129: l’électronique reste pertinente en santé / usages intensifs grâce au sans-contact, au rinçage automatique et à la maintenance facilitée
... C131: comme borne générale, un robinet électronique est souvent donné autour de 5 à 10 ans selon usage et entretien, ce qui m’a servi de garde-fou pour ne pas surévaluer cette techno
B134: Q5 | C134: Peux-tu maintenant me donner en quelques phrases une synthèse de ces justifications de durée de vie regroupant l'ensemble de ce que tu constates sur les sous-segments ?
C136: Globalement, la durée de vie réelle des équipements sanitaires collectifs dépend bien davantage du niveau d’usage, de la pression d’exploitation et du mode de gestion du parc que de la durée théorique fabricant. Les durées les plus courtes se concentrent dans les sous-segments à fort trafic, exposés au vandalisme, à l’encrassement, aux réglages fréquents et à une maintenance plus réactive, comme les transports, certains ERP publics, le sport, l’enseignement dense ou l’univers carcéral.
C138: À l’inverse, les durées sont plus longues dans les environnements mieux maîtrisés, à fréquentation plus régulière ou plus résidentielle, où les usages sont moins intensifs et les remplacements plus espacés, comme une partie des bureaux, de l’hébergement ou de certains établissements médico-sociaux. Les segments de santé ont un profil particulier : même quand l’usage n’est pas toujours extrême, les contraintes d’hygiène, de sécurité sanitaire de l’eau, de maintenance préventive et de conformité tendent à raccourcir la durée effective de certains équipements.
C140: On observe aussi une différence nette selon les technologies : les dispositifs mécaniques robustes tiennent souvent bien dans les contextes intensifs, tandis que les équipements électroniques peuvent être remplacés plus tôt non seulement pour usure, mais aussi pour raisons de batteries, capteurs, électrovannes, obsolescence ou politique de rénovation. Enfin, beaucoup de renouvellements ne se font pas uniquement “à la panne” : dans plusieurs sous-segments, ils dépendent aussi de campagnes de rénovation par lots, de contraintes budgétaires 2025-2030, de programmes publics et de la logique de modernisation du parc, ce qui accélère certains remplacements et en retarde d’autres.
B143: Q6 | C143: A ton avis, au global dans les ERP, sur le parc existant, quel mix produit en % tu me proposerait pour les urinoirs ? voir image attachée
C145: Oui — sans reprendre le travail d’avant, je proposerais pour les urinoirs sur parc existant ERP le split suivant :
C147: Mix 2025 proposé
C149: À réservoir : 8 %
C150: Chasse directe méca. : 42 %
C151: Chasse directe électro indiv. : 30 %
C152: Chasse directe électro collect. : 20 %
C154: Mix 2030 proposé
C156: À réservoir : 5 %
C157: Chasse directe méca. : 35 %
C158: Chasse directe électro indiv. : 42 %
C159: Chasse directe électro collect. : 18 %
C161: Le point le plus solide, à mon avis, est que l’urinoir en ERP est d’abord un marché de chasse directe, pas de réservoir. Des sources distributeur et fabricant décrivent l’urinoir comme étant “souvent raccordé au système d’évacuation en flux direct, c’est-à-dire sans réservoir”, tandis que DELABIE et SCHELL structurent très visiblement leurs offres urinoirs autour de robinets temporisés et de robinets de chasse directe apparents ou encastrés.
... C180: Je dirais incertitude moyenne à assez élevée : je n’ai pas trouvé de statistique publique France donnant le parc installé d’urinoirs ERP par technologie de chasse. C’est donc un split de marché argumenté, construit à partir de la logique d’usage, du positionnement des gammes collectivités et du fait que les offres actuelles visibles sont très majoritairement orientées chasse directe, avec une montée forte du sans contact.
B183: Q7 | C183: même chose pour les WCs merci de ne pas te référer au travail d'avant et de prendre d'autres sources pour proposer un split ...
C185: Oui — sans reprendre le travail d’avant, et en me basant plutôt sur des sources techniques externes sur les usages en collectivités / semi-public, je proposerais pour le parc existant ERP ce split WC :
C187: Mix 2025 proposé
C189: Chasse à réservoir : 55 %
C190: Chasse directe méca / temporisée : 35 %
C191: Chasse électronique : 10 %
...

Sheet Re-Challenge Data
B2: ERP | C2: 1 | D2: En France, Peux-tu me dire le nombre d'ERP comptabilisé. Combien d'étabilssements dans le Parc existant 2025.
E4: Oui — si tu parles bien des ERP = établissements recevant du public, le chiffre officiel récent utilisé par l’État pour la France est d’environ 2 millions d’ERP. La page gouvernementale mise à jour en février 2025 indique explicitement que « quelque 2 millions d’ERP sont aujourd’hui recensés en France ».
E6: Donc, pour le parc existant 2025, la bonne réponse est :
E8: ≈ 2 000 000 d’établissements (ERP) en France.
E10: Point utile : dans le dossier de presse gouvernemental de février 2025, l’État rappelle aussi qu’il reste 900 000 ERP non engagés dans une démarche d’accessibilité, ce qui confirme qu’on parle bien d’un parc national très proche de 2 millions d’établissements.
E12: Je n’ai pas trouvé, dans les sources officielles consultées, un total 2025 plus précis à l’unité que cet ordre de grandeur officiel. Si tu veux, je peux te donner ensuite une formulation prête à coller dans une note ou un slide.
C15: 2 | D15: Et parmi ces ERP, combien doivent compter des sanitaires (endroits où on trouve lavabo, douche, urinoirs, WC) ?
E17: Pas avec un chiffre national fiable à ce stade.
E19: La raison est que la règle n’est pas “tous les ERP doivent avoir des sanitaires ouverts au public”. Pour l’accessibilité, le texte dit : “chaque niveau accessible, lorsque des sanitaires y sont prévus pour le public” doit comporter au moins un WC adapté avec lavabo accessible. Autrement dit, l’obligation d’accessibilité porte sur les sanitaires s’ils existent pour le public ; elle ne dit pas que tous les ERP doivent forcément en proposer au public. Le guide ministériel ajoute que la mise à disposition de sanitaires est une obligation pour les cafés-restaurants et pour d’autres établissements, mais pas de façon générale pour l’ensemble des ERP.
E21: En revanche, pour le personnel, le Code du travail est beaucoup plus large : l’employeur doit mettre à disposition des travailleurs des lavabos, des cabinets d’aisance et, le cas échéant, des douches. Il fixe aussi des seuils minimaux, notamment 1 lavabo pour 10 travailleurs, et au moins 1 WC + 1 urinoir pour 20 hommes et 2 WC pour 20 femmes.
E23: Donc, la réponse la plus juste est la suivante : sur les ≈ 2 millions d’ERP recensés en France, il n’existe pas, dans les sources publiques officielles que j’ai trouvées, de nombre national publié disant combien “doivent compter des sanitaires”. Pour les sanitaires ouverts au public, ce sous-ensemble dépend du type d’activité et de la configuration de l’établissement. Pour les sanitaires dans l’établissement au sens large, il faut en plus savoir si l’ERP emploie des travailleurs. Les données ouvertes d’Acceslibre décrivent des champs d’accessibilité, y compris sur les toilettes, mais elles sont alimentées pour les collectivités renseignées et via des contributions volontaires ; ce n’est pas présenté comme un décompte national exhaustif de tous les ERP tenus d’avoir des sanitaires.
E25: En pratique :
E27: si tu parles des sanitaires ouverts au public : je ne peux pas te donner un nombre France 2025 sérieux à partir d’une source officielle unique ;
E28: si tu parles des sanitaires présents dans l’établissement, y compris pour le personnel : cela concerne probablement une très grande partie des ERP avec salariés, mais là encore je n’ai pas trouvé de total national consolidé.
E30: Je peux te faire maintenant une estimation argumentée du volume d’ERP concernés, en séparant sanitaires public et sanitaires personnel.
C33: 3 | D33: Faire maintenant une estimation argumentée du volume d’ERP concernés, en séparant sanitaires public et sanitaires personnel.
E35: Oui. En prenant comme base le parc 2025 d’environ 2,0 millions d’ERP en France, mon estimation raisonnable est la suivante : sanitaires ouverts au public : 0,5 à 0,8 million d’ERP ; sanitaires pour le personnel : 1,3 à 1,6 million d’ERP. Le point central que je retiendrais est ~650 000 ERP pour le public et ~1 450 000 ERP pour le personnel.
E37: Je précise l’hypothèse : ici, je parle d’ERP ayant au moins un local sanitaire au sens large, donc typiquement WC + lavabo, pas forcément une douche ni un urinoir. C’est important, car les douches ne sont exigées que dans certains cas pour le personnel, et côté public la réglementation vise aussi des établissements particuliers comportant des douches, de l’hébergement, des espaces d’essayage, etc.
E39: Pour les sanitaires ouverts au public, la règle juridique de base n’est pas “tous les ERP doivent en avoir”. Le texte d’accessibilité dit que chaque niveau accessible, lorsque des sanitaires sont prévus pour le public, doit comporter au moins un WC adapté avec lavabo accessible. Autrement dit, l’obligation porte sur l’accessibilité des sanitaires publics s’ils existent, pas sur leur présence universelle dans les 2 millions d’ERP.
E41: Ensuite, il faut regarder la composition probable du parc. Les sources gouvernementales prennent comme exemples d’ERP des lieux très variés, allant de la boulangerie, du coiffeur, du tabac ou de la pharmacie jusqu’aux écoles, établissements de santé et lieux culturels. Or, dans les petits ERP de proximité — très souvent de 5e catégorie — les sanitaires ouverts au public ne sont pas systématiques. Le Sénat rappelle d’ailleurs que, parmi les 900 000 ERP encore hors démarche d’accessibilité, près de 90 % relèvent de la 5e catégorie, ce qui confirme le poids des petits établissements dans le parc.
E43: À l’inverse, certains groupes d’ERP ont très probablement des sanitaires publics dans la grande majorité des cas : cafés, bars, restaurants, hôtels et hébergements, établissements de santé, écoles, équipements sportifs, lieux culturels, certaines gares et de nombreuses administrations recevant du public de façon prolongée. Pour les cafés et bars, la DGCCRF précise par exemple que l’exploitant peut refuser l’accès aux toilettes aux personnes qui ne consomment pas, ce qui montre bien que les toilettes font partie du service attendu pour la clientèle.
E45: À partir de là, mon inférence est que la part des ERP avec sanitaires ouverts au public est vraisemblablement bien inférieure à la moitié, mais nettement au-dessus d’un noyau trop restrictif comme les seuls restaurants/hôtels/écoles/hôpitaux. La fourchette la plus crédible me paraît être 25 % à 40 % du parc ERP, soit 500 000 à 800 000 ERP, avec un point central autour de 650 000. C’est une estimation de structure, pas un décompte officiel publié.
E47: Pour les sanitaires du personnel, la logique est différente. Le Code du travail impose à l’employeur de mettre à disposition des travailleurs des lavabos, des cabinets d’aisance et, le cas échéant, des douches. Il fixe aussi des minima, notamment 1 lavabo pour 10 travailleurs au plus et, pour les WC, 1 cabinet + 1 urinoir pour 20 hommes et 2 cabinets pour 20 femmes. Donc, dès qu’un ERP emploie du personnel, l’existence d’un sanitaire pour les travailleurs devient la situation normale.
E49: Le meilleur point d’appui statistique que j’ai trouvé est l’Insee : fin 2024, la France compte 2 411 570 établissements avec activité salariée dans l’année, dont 1 594 079 dans la sphère présentielle, c’est-à-dire les activités tournées vers la population présente sur le territoire. Comme le parc ERP est de l’ordre de 2 millions et qu’il comprend aussi beaucoup de petits établissements sans salarié ou avec uniquement un exploitant indépendant, on n’est pas à 2 millions d’ERP ayant une obligation “personnel” au sens du Code du travail. Mais on est clairement sur une majorité importante du parc.
E51: Mon estimation pour les sanitaires personnel est donc 65 % à 80 % du parc ERP, soit 1,3 à 1,6 million d’ERP, avec un point central autour de 1,45 million. Là encore, c’est une approximation argumentée : elle colle mieux aux ordres de grandeur Insee qu’une hypothèse trop basse, mais elle évite aussi de supposer à tort que quasiment tous les ERP ont du personnel salarié permanent.
E53: En résumé, sur ~2,0 millions d’ERP en France, je retiendrais :
E54: ~650 000 ERP avec sanitaires ouverts au public
E55: ~1 450 000 ERP avec sanitaires pour le personnel
C58: 4 | D58: J'ai réalisé un comptage fin ... Mon total est loin de ton compte ... Quels ERP mentionnés sont alors sous-évalués ? Quels ERP aurais-je pu oublier dans la liste (je pense au wagon de train, WC dans les avions, Douches à trouver sur les plages, autres ???). Peux-tu me mettre à la suite de la liste ces ERP Sous-Segment ? Merci de retrouver et de compléter le Segment Principal et la Catégorie chapeau et de compléter les lignes suivantes du tableau. Comment expliques-tu la différence entre ce que je trouve et ton chiffre ?
E60: Je vais ouvrir ton fichier Excel, repérer les lignes à compléter, puis comparer ta logique de comptage avec le périmètre “ERP” officiel pour expliquer l’écart.
E62: J’ai trouvé l’écart principal : ton fichier additionne aujourd’hui environ 720 000 unités, alors que le parc ERP national de référence est autour de 2 millions. L’écart vient surtout d’un périmètre très “équipements / institutions / grands sites”, avec probablement une forte sous-couverture des petits commerces et services de proximité.
E64: J’ai identifié les familles à ajouter et je les injecte dans le fichier, avec un second onglet qui explique l’écart et isole les faux “oubliés” qui ne sont en fait pas des ERP stricts.
E66: J’y ai ajouté une vingtaine de sous-segments probables manquants, et un onglet “Analyse écart”. Le total du fichier passe de 739 966 à 1 349 749 après ces ajouts de travail. Les plus gros angles morts que j’ai ajoutés sont surtout :
E68: petits commerces de proximité : boulangeries, boucheries, épiceries/supérettes, pharmacies, coiffure, beauté, opticiens, tabac, habillement, etc. ;
E69: santé ambulatoire : cabinets médicaux, dentaires, paramédicaux, laboratoires, imagerie ;
E70: services de proximité : agences bancaires, assurances, immobilier, réseau postal.
E72: Pourquoi l’écart avec le chiffre national reste important : le chiffre officiel d’environ 2 millions d’ERP vise un parc très large de bâtiments, locaux et enceintes recevant du public, avec un poids très fort des petits ERP de 5e catégorie très diffus dans le tissu de proximité. Ton fichier, lui, ressemblait davantage à un inventaire d’équipements, institutions et grands sites, donc il sous-comptait mécaniquement le “long tail” des petits commerces et cabinets.
E74: Sur tes exemples :
E76: wagons de train, WC dans les avions, bus / cars / tram / métro / RER : je les ai ajoutés dans le tableau, mais en Hors ERP avec 0 en comptage ERP. La raison est qu’ils relèvent du matériel roulant et de l’accessibilité des transports, encadrés par le code des transports, pas du parc ERP bâti.
E77: blocs sanitaires fixes de plage / front de mer : je les ai rangés en cas limite / mixte. Ils peuvent relever du domaine public, d’un équipement balnéaire ou d’un établissement support ; donc ce n’est pas une bonne idée de les ajouter en masse sans contrôle local, au risque de faire du double compte.
E79: Les sous-segments que je considère comme les plus sous-évalués dans ta liste sont surtout :
... E87: Je peux maintenant te faire une version 2 plus agressive, en rebouclant encore plus le long tail des petits commerces pour te rapprocher davantage des ~2 millions.
C90: 5 | D90: Merci de revoir le fichier ... ERP ou pas, ce qui m'intéresse, ce sont les établissements publics ou privé qui reçoivent du public, mais qui comptent une partie sanitaire, ce qui n'est pas les cas de boulanangeries, superettes, etcc ... peux-tu me relivrer un fichier Excel et de me faire une synthèse de ce que tu as ajouté, à partir de mon fichier attaché ?
E92: Je reprends ton fichier en changeant le critère : je ne garde que les lieux qui reçoivent du public et où il y a vraiment une composante sanitaire pertinente. Je vais filtrer les ajouts précédents, compléter les manques plausibles, puis te relendre un Excel propre.
E94: J’ai bien recentré le périmètre : je repars du fichier d’origine et je n’ajoute plus des commerces “généraux”. Je ne garde que les lieux où la composante sanitaire est soit centrale, soit structurellement attendue pour l’accueil du public.
E96: Ce que j’ai fait dans ton fichier d’origine :
E98: j’ai retiré la logique “ERP large” que j’avais suivie auparavant ;
E99: je n’ai ajouté que des sites/établissements où la composante sanitaire est réelle et structurante ;
E100: j’ai aussi ajouté, à part, les cas que tu évoquais mais qui ne sont pas des établissements fixes.
E102: Ajouts intégrés au total :
E104: Bains-douches municipaux / douches publiques fixes : 180
E105: Blocs sanitaires de plage / front de mer : 1 800
E106: Établissements thermaux : 115
E107: Centres de thalassothérapie / balnéothérapie / grands spas : 320
E108: Bases nautiques / centres nautiques avec vestiaires-douches : 1 400
... E140: Si tu veux, je peux faire une V2 encore plus stricte, en ne gardant que les lieux où les sanitaires sont centraux et non simplement “présents”.
C143: 6 | D143: Parfait - toujours dans cette logique de sites/établissements où la composante sanitaire est réelle et structurante ... est-ce qu'il serait pertinent de rajouter les éléments de la liste attachée suivante ... si oui, merci de les intégrer et de mettre à jour le précédent document livré ... Je pense aussi à intgérer, une ligne dans sous-segment pour ... Est-ce que les cantines, cuisines et refectoires des Écoles maternelles des Écoles primaires, Lycées, Universités, Grandes écoles, sont bien comptabilisées dans mon tableaux - si ce n'est pas le cas, rajout d'1 ligne par type d'établissement ... Est-ce que les Ateliers (type garage, ou autre ...) sont intégrés dans mon tableau ? si elles sont incluses dans les usines, merci de les distinguer et de créer 2 lignes différentes. Est-ce que les Centres de stockages et centres logistiques sont intégrés dans mon tableau ? si ils sont inclus dans les bureaux, merci de les distinguer, et de créer des lignes différentes. Y a t'il aussi des sanitaires dans les stations de métro en France ? à priori pas pour le public, mais peut-être pour le personnel ... à vrai dire, je ne pense pas, mais si c'est le cas, merci de le rajouter ... Merci aussi de quantifier tout ce qui est "Matériel roulant / transport mobile".
E145: J’ai déjà confirmé deux points importants dans le fichier actuel :
E147: 1. les cantines / cuisines / réfectoires ne sont pas isolés en lignes dédiées ;
E148: 2. les ateliers, centres logistiques/stockage et les stations de métro ne sont pas distingués non plus.
E150: Je vais donc les traiter explicitement, avec des lignes séparées et des unités de compte claires pour éviter les doubles comptes.
E152: Je mets maintenant à jour le classeur en distinguant ce qui doit rester additif au total des sites de ce qui doit être quantifié mais non additionné parce que c’est interne à un site déjà compté ou mobile.
E154: J’ai traité les ajouts que tu as explicitement listés. Je n’ai pas vu d’autre pièce jointe exploitable que le classeur, donc je suis parti de ton fichier + de ta liste dans le message.
E156: Ce que j’ai ajouté ou modifié dans le document :
E158: ajout additif au total : Garages / ateliers de réparation automobile recevant du public ;
E159: reventilation sans effet sur le total :
E160: Bureaux tertiaires privés (>50 personnes, hors logistique) / Centres de stockage / entrepôts / plateformes logistiques (>50 personnes) ;
E161: Usines de production (>50 personnes, hors ateliers distingués) / Ateliers industriels / de maintenance (>50 personnes) ;
E162: ajouts non additifs car déjà inclus dans un site existant :
... E198: Si tu veux, je peux maintenant te faire une V3 plus stricte, en ne gardant dans le total que les sites où la fonction sanitaire est vraiment centrale et pas seulement présente.
C201: 7 | D201: OK - A t'on maintenant vraiment une liste exhaustive ... rappel de la logique : à chaque fois qu'il peut y avoir des sanitaire au moins 1 produit parmi lavabo, douche, urinoir WC, a t'on bien tous les établissements qui peuvent recevoir du public ... si tu en trouves des nouveaux, merci de faire un tableau avec seulement les nouvelles lignes que tu as trouvées ... je veux vraiment une réflexion poussée pour ne rien oublier !!!
E203: Je repars du fichier actuel et je vais le challenger comme une taxonomie quasi exhaustive, pas seulement comme un ajout incrémental. L’objectif est de sortir uniquement les nouvelles lignes manquantes plausibles, en séparant ce qui est site fixe, interne non additif, et mobile / hors site.
E205: J’ai isolé une dernière famille d’omissions très probables : funéraire, hébergement social, parcs/loisirs structurés et soins ambulatoires spécialisés. Je te prépare un onglet dédié qui liste seulement ces lignes nouvelles, sans toucher au total principal tant qu’on n’a pas arbitré les doublons.
E207: J’ai ajouté un nouvel onglet “Nouvelles lignes V3” avec 17 lignes nouvelles plausibles, sans toucher au total principal du tableau précédent. J’ai laissé la colonne 2025 vide sur cet onglet, car plusieurs de ces familles demandent encore un arbitrage anti-doublons avant d’être additionnées proprement.
E209: Mon verdict honnête : on est maintenant beaucoup plus proche d’une liste quasi exhaustive, mais je ne peux pas certifier une exhaustivité “absolue” au sens juridique strict, parce que la frontière dépend encore de l’exploitation réelle du site, et parce que des exploitations groupées peuvent être comptées ensemble ou séparément selon leur configuration. Le règlement ERP prévoit d’ailleurs que des établissements non explicitement cités peuvent relever de mesures adaptées, et que des bâtiments d’une même exploitation ou des exploitations groupées non isolées peuvent être considérés comme un seul établissement.
E211: Les grandes omissions que j’ai retenues sont surtout :
E212: casinos ; parcs d’attractions / parcs à thèmes ; zoos / parcs animaliers ; aquariums ; chambres funéraires / funérariums ; crématoriums ; centres d’hébergement d’urgence ; CHRS ; CADA / HUDA / CAES ; foyers de jeunes travailleurs / résidences sociales / foyers de travailleurs migrants ; accueils de jour avec douches ; cabinets dentaires / centres dentaires ; laboratoires de biologie médicale ; centres d’imagerie ; centres de dialyse ambulatoire ; villages de vacances ; centres équestres / manèges couverts avec accueil public. Ces ajouts sont cohérents avec les textes ou référentiels officiels sur les casinos, les établissements de plein air, les établissements zoologiques fixes ouverts au public, les chambres funéraires et crématoriums, l’hébergement social et l’asile, les logements-foyers/FJT, les villages de vacances, ainsi que les catégories de lieux de soins recensées par Santé.fr.
E214: J’ai aussi intégré dans l’onglet une colonne “Traitement conseillé” pour distinguer ce qui peut être ajouté comme site autonome de ce qui doit être ajouté seulement s’il n’est pas déjà absorbé par une autre ligne. C’est particulièrement important pour les aquariums intégrés à un musée ou un zoo, et pour les centres d’imagerie / dialyse / laboratoires quand ils sont physiquement inclus dans un hôpital ou une clinique déjà comptés. Cette prudence est cohérente avec la logique ERP de classement par exploitation réelle et par groupement.
E216: La prochaine étape utile serait de faire une V4 d’arbitrage, où je passe ces 17 lignes en trois statuts : à additionner, à laisser hors total, à fusionner avec une ligne existante.
C219: 8 | D219: A ton avis, est-ce que certains sous-segments cités viennent en doublons ? Quels sont les doublons intégral, les doublons partiels et un sous-segment qui serait contenu dans un autre ?
E221: Oui — mais surtout des doublons de maille de comptage, plus que des “vrais doublons textuels”.
E223: Mon avis global sur le classeur actuel :
E225: très peu de doublons intégraux purs ;
E226: pas mal de doublons partiels ;
E227: plusieurs sous-segments qui sont en réalité des composantes internes d’un site déjà compté ailleurs.
E229: Le point important est celui-ci : dans ton fichier, beaucoup de recouvrements viennent du fait qu’on mélange parfois :
E231: un site autonome,
E232: une fonction interne à ce site,
E233: et parfois une spécialité hébergée dans un site plus large.
E235: 1) Doublons intégraux ou quasi-intégraux
E237: Je ne vois presque aucun doublon intégral pur dans les libellés actuels, parce que beaucoup ont déjà été “protégés” par des mentions du type hors, autonome, si site autonome, hors déjà compté.
E239: Les seuls quasi-doublons forts que je retiendrais sont :
... E438: Sous-segment | Type de doublon | Avec quelle ligne, directement exploitable pour ton Excel.
C441: 9 | D441: Peux-tu revoir la Surface moyenne 2026 (m²/étab.) et le nombre d'établissements en France pour les années demandées ? Merci de me livrer un Excel pour les établissements suivants ? (ne pas mettre à jour le gros tableau, seulement me livrer les lignes concernées, hors ligne Total) ... un commentaire ? Attention le nombre d'hôtels ne doivent pas inclure les établissements suivants : Villages de vacances / Clubs vacances / Centres de vacances familiaux Résidences de tourisme Auberges de jeunesse Pensions de famille Hôtels-restaurants d’altitude Refuges de montagne Campings Aires d’accueil des gens du voyage
E443: Commentaires (important)
E445: 1. Hôtels
E447: J’ai volontairement rehaussé la base 2000–2010 pour corriger un biais fréquent : sous-comptage historique
E448: Les 18–19k hôtels en 2025–2030 sont cohérents avec :
E449: concentration du parc
E450: disparition des petits indépendants
...

Sheet Détail Recherche - Nbre ERP
B2: 1 | C2: Enfance, enseignement et jeunesse | D2: Enfance / jeunesse | E2: Centres de loisirs sans hébergement | G2: Oui — en ordre de grandeur, je vous proposerais ceci pour la France entière, en parlant des ALSH / centres aérés / centres de loisirs sans hébergement :
G4: Année | H4: Estimation d’ordre de grandeur
G5: 2000 | H5: ≈ 12 000
G6: 2010 | H6: ≈ 20 000
G7: 2020 | H7: ≈ 32 000
G8: 2025 | H8: ≈ 32 000
G9: 2030 (prévision centrale) | H9: ≈ 32 000
G11: Avec une lecture un peu plus prudente :
G13: 2000 : 10 000 à 15 000
G14: 2010 : 18 000 à 22 000
G15: 2020 : environ 32 000
G16: 2025 : environ 32 000
G17: 2030 : 30 000 à 34 000, centre de fourchette ≈ 32 000
G19: Pourquoi cette estimation tient la route :
G21: En base récente, l’INJEP donne 32 000 lieux d’accueil en 2020-2021 pour les accueils de loisirs, et encore 32 000 lieux d’accueil en 2024-2025. Cela suggère un plateau national autour de 32 000 depuis le début des années 2020.
G23: Pour remonter dans le temps, on a un très bon repère sur le périscolaire : en 2015-2016, l’INJEP indique 28 600 lieux d’accueil périscolaire. Et un article de synthèse reprenant l’étude INJEP précise qu’en 2014-2015 on était à 23 200 lieux, contre environ 18 000 en 2012-2013, ce dernier chiffre étant déductible des 900 000 places pour un nombre moyen de 50 places par structure.
G25: Du coup, pour 2010, un ordre de grandeur autour de 20 000 est cohérent : on est avant l’explosion liée à la réforme des rythmes éducatifs de 2013-2015, mais déjà dans une phase de montée en charge engagée entre 2008 et 2013.
G27: Pour 2000, je serais plus prudent : je n’ai pas trouvé de série publique homogène donnant un chiffre national directement comparable. En revanche, une étude sur le milieu rural indique que la moitié des accueils observés ont été créés après 2000 et que la croissance s’est accélérée entre 2000 et 2010, ce qui va bien dans le sens d’un parc nettement plus faible en 2000 qu’en 2010 et très inférieur au niveau actuel. D’où ma fourchette 10 000 à 15 000, avec un point central à 12 000.
G29: Pour 2030, je n’ai pas trouvé de prévision publique officielle. Mon estimation ≈ 32 000 est donc une projection tendancielle, fondée sur la stabilité observée entre 2020-2021 et 2024-2025, plutôt qu’une prévision administrative publiée.
... G35: Je peux aussi vous transformer ça en tableau “rapport/Excel-ready” avec trois colonnes : valeur, statut (officiel ou estimé), justification.
B39: 10 | C39: Enfance, enseignement et jeunesse | D39: Enseignement supérieur | E39: Universités | G39: Je vais repartir sur une base plus nette ici, car pour les universités il existe normalement des séries officielles plus stables que pour les ALSH. Je cherche d’abord le décompte institutionnel exact par année, puis je ferai une projection 2030 séparée du constat historique.
G41: J’ai la base juridique actuelle sous la main. Le point délicat maintenant, ce sont les années intermédiaires, parce que le nombre dépend des fusions, scissions et changements de statut (par exemple certains établissements sortent de la catégorie “université” pour devenir “grand établissement”).
G43: Réflexion durant 6m 47s
G45: Oui. En prenant “universités” au sens juridique du code de l’éducation (et non l’ensemble des établissements du supérieur), j’estimerais le tableau suivant pour la France :
G47: Année | H47: Nombre d’universités
G48: 2000 | H48: 82
G49: 2005 | H49: 81
G50: 2010 | H50: 79
G51: 2015 | H51: ≈ 71
G52: 2020 | H52: 59
G53: 2025 | H53: 45
G54: 2030 (prévision centrale) | H54: ≈ 42
G56: Lecture rapide :
G58: 2000 : 82. C’est le décompte direct du décret de classification du 15 mars 2000, qui énumère les universités une par une.
G59: 2005 : 81. La principale rupture entre 2000 et 2005 est le passage de Paris-IX Dauphine au statut de grand établissement par le décret du 26 février 2004 ; on retire donc 1 université au total de 2000.
G60: 2010 : 79. À la baisse liée à Dauphine s’ajoute la fusion de Strasbourg-I, II et III en une seule Université de Strasbourg en 2009, soit un effet net de –2. On passe donc de 81 à 79.
G61: 2015 : ≈ 71. Le meilleur point solide trouvé est la version en vigueur au 1er janvier 2016 de l’article D711-1, qui énumère 71 universités. Ce niveau est cohérent avec les grandes fusions antérieures : Aix-Marseille en 2012, Université de Lorraine en 2012 sous statut de grand établissement, ainsi que les réorganisations Bordeaux / Guyane / Montpellier intervenues avant 2016. Pour un “repère 2015”, je retiens donc environ 71.
G62: 2020 : 59. La version en vigueur du 1er janvier 2020 au 1er janvier 2021 de l’article D711-1 permet un décompte direct de 59 universités.
G63: 2025 : 45. La version en vigueur depuis le 1er mars 2025 du même article permet un décompte direct de 45 universités.
G65: Pour 2030, je n’ai pas trouvé de prévision publique officielle du nombre d’universités. La publication officielle de projections du ministère porte sur les effectifs étudiants, pas sur le nombre d’établissements ; elle projette un supérieur autour de 3,1 millions d’inscrits à l’horizon 2030-2033. Du coup, 42 est une projection tendancielle personnelle, fondée sur la poursuite d’une consolidation plus lente qu’entre 2015 et 2025 ; je mettrais une fourchette raisonnable à 40–45.
B68: 18 | C68: Santé et médico-social | D68: Médico-social | E68: Établissements médico-éducatifs | G68: Oui, mais avec une précaution importante : pour les “établissements médico-éducatifs”, la série publique la plus exploitable est celle de la DREES sur les établissements et services médico-sociaux pour enfants et adolescents handicapés. Les millésimes d’observation disponibles sont surtout 2001, 2006, 2010, 2014, 2018 et 2022 ; pour 2000, 2005, 2015, 2020, 2025 et 2030, il faut donc faire des estimations à partir de ces points.
G70: Je vous propose cet ordre de grandeur pour la France :
G72: Année | H72: Nombre d’établissements / structures
G73: 2000 | H73: ≈ 2 900
G74: 2005 | H74: ≈ 3 300
G75: 2010 | H75: ≈ 3 600
G76: 2015 | H76: ≈ 3 900
G77: 2020 | H77: ≈ 4 100
G78: 2025 | H78: ≈ 3 900 à 4 000
G79: 2030 (prévision centrale) | H79: ≈ 3 700 à 3 900
G81: Base documentaire utilisée :
G83: 2001 : la DREES donne 2 892 établissements et services médico-sociaux pour enfants et adolescents handicapés au 31 décembre 2001.
G84: 2014 : la DREES indique 3 760 structures pour enfants en France fin 2014.
G85: 2018 : la DREES donne 4 170 structures fin 2018.
G86: 2022 : la DREES donne 4 030 structures fin 2022.
G88: Pour 2005, j’ai interpolé entre le point officiel de 2001 (2 892) et le niveau reconstitué à partir de la DREES pour 2006, soit environ 3 370 structures déduit de la hausse de +19,6 % entre 2006 et 2022 mentionnée dans la fiche DREES 2024. Cela donne un ordre de grandeur autour de 3 300 pour 2005.
G90: Pour 2010, j’ai retenu ≈ 3 600 par interpolation entre 2006 (~3 370 reconstitué) et 2014 (3 760 observé). Pour 2015, j’ai retenu ≈ 3 900 par interpolation entre 2014 (3 760) et 2018 (4 170). Pour 2020, j’ai retenu ≈ 4 100 à mi-chemin entre 2018 (4 170) et 2022 (4 030).
G92: Pour 2025, je n’ai pas trouvé de publication officielle plus récente que 2022 donnant un nouveau total national de structures sur ce champ précis ; la projection la plus prudente est donc un niveau quasi stable ou légèrement en retrait, soit ~3 900 à 4 000. Pour 2030, il n’existe pas à ma connaissance de prévision publique officielle du nombre de structures ; en prolongeant la légère inflexion observée entre 2018 et 2022, on obtient une fourchette centrale ~3 700 à 3 900. C’est une projection tendancielle, pas une prévision administrative.
G94: En version “rapport”, je résumerais ainsi : 2000 ~2,9k ; 2005 ~3,3k ; 2010 ~3,6k ; 2015 ~3,9k ; 2020 ~4,1k ; 2025 ~3,9–4,0k ; 2030 ~3,7–3,9k.
B97: 22 | C97: Santé et médico-social | D97: Santé hospitalière | E97: Hôpitaux privés | G97: Ce que je peux affirmer solidement
G99: Les points d’ancrage officiels DREES que j’ai retrouvés sont :
G101: 2016 : 686 établissements privés à but non lucratif = 21 CLCC + 665 autres.
G102: 2018 : 682 établissements privés à but non lucratif.
G103: 2019 : 671 établissements privés à but non lucratif.
G104: 2022 : 658 établissements privés à but non lucratif.
G105: 2023 : 657 établissements privés à but non lucratif dans le Panorama 2025, avec une estimation administrative antérieure à 656 avant révision.
G106: 2024 : 655 établissements privés à but non lucratif.
G108: Comment j’ai approché les années demandées
G110: Je n’ai pas retrouvé, dans ce tour, de série officielle homogène déjà publiée donnant directement 2000, 2005, 2010, 2015 et 2020 pour exactement cette catégorie. J’ai donc utilisé la tendance DREES observable : baisse lente du nombre d’établissements privés à but non lucratif sur longue période, plus régulière depuis les années 2010, sous l’effet des restructurations, regroupements et rationalisations. La DREES souligne d’ailleurs que le nombre de structures diminue lentement sous l’effet des réorganisations, et que certaines comparaisons longues doivent être maniées avec prudence en raison des changements de champ et de nomenclature.
G112: Lecture rapide
G114: La catégorie est globalement en érosion lente, pas en chute brutale.
G115: Entre 2018 et 2024, on passe de 682 à 655, soit une baisse d’environ 4 % sur 6 ans.
... G123: la DREES rappelle aussi que certaines éditions plus anciennes ne sont pas parfaitement comparables aux plus récentes.
B128: 24 | C128: Santé et médico-social | D128: Santé hospitalière | E128: Hôpitaux universitaires / CHU | G128: Il faut distinguer deux périmètres, car les sources publiques ne comptent pas toujours la même chose :
G130: 1. périmètre large “établissements hospitaliers universitaires / CHR-CHU” : la liste réglementaire des centres hospitaliers régionaux liée au dispositif hospitalo-universitaire ;
G131: 2. périmètre strict “CHU/CHRU” : les établissements explicitement comptés comme CHU dans certains rapports et communications.
G133: Réponse la plus robuste
G135: Pour un besoin de nombre d’établissements, le périmètre le plus solide juridiquement est le périmètre large CHR-CHU. Sur cette base, on obtient :
G137: 83.355556
G138: 83.563889
G139: 83.772222
G140: 83.980556
G141: 84.188889
G142: 84.397917
G143: 2030 : pas de prévision officielle publiée ; scénario central = 33 si aucun nouvel établissement n’est créé ou fusionné.
G145: Pourquoi ce chiffrage
G147: Au 10 septembre 2009, le Code de la santé publique liste déjà 32 centres hospitaliers régionaux dans cette catégorie, dont Metz-Thionville, Orléans et La Réunion. Cette base permet d’ancrer les années 2000, 2005, 2010, 2015 et 2020 à 32 établissements en l’absence de changement réglementaire identifié avant 2025.
G149: En 2025, un décret crée le centre hospitalier régional de Guyane, puis l’ARS Guyane indique que le CHU de Guyane a été officiellement créé le 16 juin 2025. Dans la liste réglementaire actuelle, la Guyane apparaît en “10° bis”, ce qui porte le total à 33 établissements dans ce périmètre large.
G151: Si vous vouliez le périmètre strict “CHU” seulement
G153: Là, les sources sont moins homogènes :
G155: un rapport de 2003 indique 29 CHU en France ;
G156: le CHU de La Réunion se présente comme le 30e CHU de France en 2012 ;
G157: le CHU d’Orléans affirme être devenu le 33e CHU de France le 12 octobre 2023 ;
G158: pour la Guyane, les communications publiques de 2025-2026 ne sont pas parfaitement alignées sur le rang ordinal.
G160: Donc, pour une série historique propre, je vous recommande d’utiliser le périmètre large “établissements hospitaliers universitaires / CHR-CHU” : 32, 32, 32, 32, 32, 33, puis 33 en projection 2030.
B163: 25 | C163: Santé et médico-social | D163: Santé spécialisée | E163: Centres de psychiatrie | G163: Voici la lecture la plus solide que j’ai pu reconstituer pour la France en prenant comme référence les établissements de santé ayant une activité/autorisation en psychiatrie. Il y a toutefois une rupture de série entre les sources anciennes DREES/SAE et les chiffres récents ATIH/PMSI, donc il faut lire 2005–2019 et 2020–2023 avec prudence.
G165: Année | H165: Nombre d’établissements | I165: Statut
G166: 2000 | H166: pas de chiffre officiel strictement comparable trouvé | I166: en 2000, la DREES publie surtout des secteurs (830 secteurs de psychiatrie générale, 320 de psychiatrie infanto-juvénile), pas un total national directement comparable d’établissements
G167: 2005 | H167: 621 | I167: officiel DREES, total des établissements de psychiatrie (378 exclusifs + 243 non exclusifs)
G168: 2010 | H168: ≈ 510 | I168: approximation lue sur le graphique officiel DREES 2008–2019
...

Sheet ERP -Sans sanitaires collectifs
A1: ID | B1: Catégorie chapeau | C1: Catégorie principale | D1: Sous-catégorie | E1: Type ERP principal | F1: Type de classement | G1: Notes de classement | H1: Exemples | I1: ERP / hors ERP / mixte | J1: Accueil du public : oui/non/variable | K1: Présence de sommeil : oui/non/variable | L1: Espaces sanitaires collectifs (WC et/ou douche) | M1: Unité de compte retenue | N1: Nature de la donnée | O1: Niveau de fiabilité | P1: Risque de doublon ERP | Q1: Doublon potentiel avec | R1: Sous-catégorie incluse dans | S1: Justification de stagnation / faible variation | T1: Surface moyenne 2026 (m² / établissement) | U1: Capacité instantanée moyenne 2026 (places/lits/usagers) | V1: Inclure dans Total France (1/0) | W1: Justification de la projection | X1: Sources (URL) | Y1: 2000 | Z1: 2005 | AA1: 2010 | AB1: 2015 | AC1: 2016 | AD1: 2017 | AE1: 2018 | AF1: 2019 | AG1: 2020 | AH1: 2021 | AI1: 2022 | AJ1: 2023 | AK1: 2024 | AL1: 2025 | AM1: 2026 | AN1: 2027 | AO1: 2028 | AP1: 2029 | AQ1: 2030
B2: TOTAL | C2: France | D2: TOTAL FRANCE (formule pilotée par la colonne « Inclure dans Total France (1/0) ») | P2: formule | S2: Le total additionne uniquement les lignes marquées 1 ; vous pouvez modifier ces drapeaux pour inclure/exclure des sous-catégories. | T2: =IFERROR(SUMPRODUCT($V$3:$V$12,$AM$3:$AM$12,T$3:T$12)/SUMPRODUCT($V$3:$V$12,$AM$3:$AM$12),"") -> 93.364325 | U2: =IFERROR(SUMPRODUCT($V$3:$V$12,$AM$3:$AM$12,U$3:U$12)/SUMPRODUCT($V$3:$V$12,$AM$3:$AM$12),"") -> 14.724334 | V2: - | Y2: =SUMPRODUCT($V$3:$V$12,Y$3:Y$12) -> 23882 | Z2: =SUMPRODUCT($V$3:$V$12,Z$3:Z$12) -> 23051 | AA2: =SUMPRODUCT($V$3:$V$12,AA$3:AA$12) -> 22448 | AB2: =SUMPRODUCT($V$3:$V$12,AB$3:AB$12) -> 22059 | AC2: =SUMPRODUCT($V$3:$V$12,AC$3:AC$12) -> 22006 | AD2: =SUMPRODUCT($V$3:$V$12,AD$3:AD$12) -> 21961 | AE2: =SUMPRODUCT($V$3:$V$12,AE$3:AE$12) -> 21922 | AF2: =SUMPRODUCT($V$3:$V$12,AF$3:AF$12) -> 21893 | ... AQ2: =SUMPRODUCT($V$3:$V$12,AQ$3:AQ$12) -> 21774
A3: 1 | B3: Enfance, enseignement et jeunesse | C3: Formation | D3: Auto-écoles | E3: R ou W | F3: ERP | G3: Classement selon activité dominante et configuration. | H3: Auto-école avec salle de cours | I3: ERP | J3: variable | K3: non | L3: non | M3: site / établissement principal | N3: proxy public / estimation encadrée | O3: faible | P3: non | S3: Pas de stagnation structurelle : la série évolue à la baisse sur la période 2000-2026 ; la projection prolonge cette tendance avec prudence. | T3: 120 | U3: 20 | V3: 1 | W3: proxy SIRUS/BPE catégorie école de conduite. Dynamique projetée 2027-2030: baisse légère. Fiabilité: faible. | X3: https://www.insee.fr/fr/metadonnees/source/fichier/BPE_evol_1924_liste_a_plat_TYPEQU.html | Y3: 14894 | Z3: 14164 | AA3: 13470 | AB3: 12810 | AC3: 12682 | AD3: 12555 | AE3: 12429 | AF3: 12305 | AG3: 12243 | AH3: 12182 | AI3: 12121 | AJ3: 12060 | AK3: 12000 | AL3: 11940 | AM3: 11880 | AN3: 11821 | AO3: 11762 | AP3: 11703 | AQ3: 11644
A4: 2 | B4: Enfance, enseignement et jeunesse | C4: Petite enfance | D4: Haltes-garderies | E4: R | F4: ERP | G4: Accueil occasionnel de jeunes enfants. | H4: Halte-garderie, jardin d’enfants | I4: ERP | J4: oui | K4: non | L4: non | M4: site / établissement principal | N4: proxy public / estimation encadrée | O4: faible | P4: non | S4: Pas de stagnation structurelle : la série évolue à la baisse sur la période 2000-2026 ; la projection prolonge cette tendance avec prudence. | T4: 150 | U4: 20 | V4: 1 | W4: proxy DREES; recul au profit des crèches et micro-crèches. Dynamique projetée 2027-2030: baisse structurelle. Fiabilité: faible. | X4: https://drees.solidarites-sante.gouv.fr/communique-de-presse-jeux-de-donnees/jeux-de-donnees/250528_DATA_donnees-departementales-sur-l-offre-daccueil-du-jeune-enfant-2023 | Y4: 3034 | Z4: 2474 | AA4: 2017 | AB4: 1645 | AC4: 1579 | AD4: 1516 | AE4: 1455 | AF4: 1397 | AG4: 1355 | AH4: 1315 | AI4: 1275 | AJ4: 1237 | AK4: 1200 | AL4: 1164 | AM4: 1129 | AN4: 1095 | AO4: 1062 | AP4: 1030 | AQ4: 999
A5: 3 | B5: Enfance, enseignement et jeunesse | C5: Petite enfance | D5: Jardins d’enfants | E5: R | F5: ERP | G5: Relève du secteur enseignement / éveil. | H5: Jardin d’enfants privé | I5: ERP | J5: oui | K5: non | L5: non | M5: site / établissement principal | N5: proxy public / estimation encadrée | O5: faible | P5: non | S5: Pas de stagnation structurelle : la série évolue à la baisse sur la période 2000-2026 ; la projection prolonge cette tendance avec prudence. | T5: 200 | U5: 30 | V5: 1 | W5: estimation sectorielle. Dynamique projetée 2027-2030: baisse structurelle. Fiabilité: faible. | X5: https://drees.solidarites-sante.gouv.fr/communique-de-presse-jeux-de-donnees/jeux-de-donnees/250528_DATA_donnees-departementales-sur-l-offre-daccueil-du-jeune-enfant-2023 | Y5: 633 | Z5: 516 | AA5: 421 | AB5: 343 | AC5: 329 | AD5: 316 | AE5: 303 | AF5: 291 | AG5: 282 | AH5: 274 | AI5: 266 | AJ5: 258 | AK5: 250 | AL5: 242 | AM5: 235 | AN5: 228 | AO5: 221 | AP5: 214 | AQ5: 208
A6: 4 | B6: Santé et médico-social | C6: Médico-social | D6: Autres établissements spécialisés pour personnes âgées | E6: Variable | F6: Cas particulier | G6: Catégorie de regroupement pour structures spécialisées non couvertes ailleurs ; classement selon l’activité dominante, le niveau de soins, l’hébergement et l’ouverture au public. | H6: Petite unité de vie, maison d’accueil rurale, structure spécialisée seniors | I6: mixte | J6: variable | K6: variable | L6: non | M6: site / établissement principal | N6: proxy résiduel / catégorie non homogène | O6: faible | P6: oui | Q6: EHPAD ; Résidences autonomie / foyers-logements ; USLD | R6: EHPAD ; Résidences autonomie / foyers-logements ; USLD | S6: Faute de série nationale homogène publiée annuellement pour cette sous-catégorie, le proxy est lissé ; la faible variation reflète une prudence méthodologique. | T6: 1200 | U6: 25 | V6: 0 | W6: Catégorie résiduelle et hétérogène ; la projection reste plate par prudence pour éviter des doubles comptes. Fiabilité: faible. | X6: https://drees.solidarites-sante.gouv.fr/jeux-de-donnees/jeux-de-donnees/les-residents-en-etablissements-dhebergement-pour-personnes-agees | Y6: 650 | Z6: 650 | AA6: 650 | AB6: 650 | AC6: 650 | AD6: 650 | AE6: 650 | AF6: 650 | AG6: 650 | AH6: 650 | AI6: 650 | AJ6: 650 | AK6: 650 | AL6: 650 | AM6: 650 | AN6: 650 | AO6: 650 | AP6: 650 | AQ6: 650
A7: 5 | B7: Santé et médico-social | C7: Médico-social | D7: Habitat inclusif / habitats regroupés seniors | E7: Variable | F7: Cas particulier | G7: Logements privatifs avec espaces partagés et projet de vie sociale ; le classement dépend de la configuration immobilière et de l’ouverture au public. | H7: Habitat inclusif seniors, béguinage, habitat regroupé seniors | I7: mixte | J7: variable | K7: oui | L7: non | M7: site / établissement principal | N7: proxy habitat accompagné / estimation encadrée | O7: faible | P7: oui | Q7: Résidences autonomie / foyers-logements ; Résidences services seniors | S7: Pas de stagnation structurelle : la série évolue à la hausse sur la période 2000-2026 ; la projection prolonge cette tendance avec prudence. | T7: 500 | U7: 12 | V7: 1 | W7: Catégorie en développement mais encore mal couverte statistiquement ; projection modérément haussière. Fiabilité: faible. | X7: https://drees.solidarites-sante.gouv.fr/sites/default/files/2025-09/PAPH%20-%20Fiche%2009%20-%20Les%20%C3%A9tablissements%20d%E2%80%99h%C3%A9bergement%20pour%20personnes%20%C3%A2g%C3%A9es_0.pdf | Y7: 95 | Z7: 127 | AA7: 170 | AB7: 228 | AC7: 242 | AD7: 257 | AE7: 272 | AF7: 288 | AG7: 299 | AH7: 311 | AI7: 324 | AJ7: 337 | AK7: 350 | AL7: 362 | AM7: 375 | AN7: 388 | AO7: 402 | AP7: 416 | AQ7: 431
A8: 6 | B8: Santé et médico-social | C8: Médico-social | D8: Hébergements temporaires seniors | E8: Variable | F8: Cas particulier | G8: Accueil temporaire pour personnes âgées, souvent adossé à un EHPAD ou à une autre structure ; classement selon l’établissement support et l’exploitation. | H8: Hébergement temporaire, accueil de répit avec nuitées | I8: mixte | J8: oui | K8: variable | L8: non | M8: site / établissement principal | N8: sous-produit de structures seniors / proxy non additif | O8: faible | P8: oui | Q8: EHPAD ; Résidences autonomie / foyers-logements ; Résidences services seniors | R8: EHPAD ; Résidences autonomie / foyers-logements ; Résidences services seniors | S8: Pas de stagnation structurelle : la série évolue à la hausse sur la période 2000-2026 ; la projection prolonge cette tendance avec prudence. | T8: 700 | U8: 15 | V8: 0 | W8: L’hébergement temporaire est souvent adossé à d’autres structures seniors ; projection en légère hausse mais non additive. Fiabilité: faible. | X8: https://drees.solidarites-sante.gouv.fr/jeux-de-donnees/jeux-de-donnees/les-residents-en-etablissements-dhebergement-pour-personnes-agees | Y8: 1437 | Z8: 1587 | AA8: 1752 | AB8: 1934 | AC8: 1973 | AD8: 2012 | AE8: 2052 | AF8: 2093 | AG8: 2114 | AH8: 2135 | AI8: 2157 | AJ8: 2178 | AK8: 2200 | AL8: 2222 | AM8: 2244 | AN8: 2266 | AO8: 2289 | AP8: 2312 | AQ8: 2335
A9: 7 | B9: Culture, patrimoine et événementiel | C9: Documentation | D9: Centres de documentation | E9: S | F9: ERP | G9: Consultation documentaire. | H9: Centre de documentation spécialisé | I9: ERP | J9: oui | K9: non | L9: non | M9: site / établissement principal | N9: proxy public / stock documentaire spécifique | O9: faible | P9: oui | Q9: Bibliothèques / médiathèques | R9: Bibliothèques / médiathèques (lorsqu’il s’agit d’un service interne) | S9: Faute de série nationale homogène publiée annuellement pour cette sous-catégorie, le proxy est lissé ; la faible variation reflète une prudence méthodologique. | T9: 250 | U9: 20 | V9: 0 | W9: Série conservatrice ; le stock autonome de centres de documentation varie peu et se recoupe parfois avec bibliothèques/médiathèques. Fiabilité: faible. | X9: https://www.insee.fr/fr/metadonnees/source/serie/s1161 | Y9: 1675 | Z9: 1634 | AA9: 1594 | AB9: 1555 | AC9: 1547 | AD9: 1539 | AE9: 1531 | AF9: 1523 | AG9: 1518 | AH9: 1514 | AI9: 1509 | AJ9: 1505 | AK9: 1500 | AL9: 1496 | AM9: 1492 | AN9: 1488 | AO9: 1484 | AP9: 1480 | AQ9: 1476
A10: 8 | B10: Commerce, restauration et loisirs | C10: Commerce | D10: Showrooms / halls de vente | E10: M | F10: ERP | G10: Vente et démonstration. | H10: Showroom automobile, showroom ameublement | I10: ERP | J10: oui | K10: non | L10: non | M10: site / établissement principal | N10: proxy commerce spécialisé / estimation encadrée | O10: faible | P10: oui | Q10: Centres commerciaux / malls ; Industrie + logistique + stockage | S10: Faute de série nationale homogène publiée annuellement pour cette sous-catégorie, le proxy est lissé ; la faible variation reflète une prudence méthodologique. | T10: 800 | U10: 60 | V10: 0 | W10: Proxy large sur les espaces commerciaux de démonstration, conservé stable faute de série nationale homogène. Fiabilité: faible. | X10: https://www.insee.fr/fr/metadonnees/source/serie/s1161 | Y10: 9500 | Z10: 9500 | AA10: 9500 | AB10: 9500 | AC10: 9500 | AD10: 9500 | AE10: 9500 | AF10: 9500 | AG10: 9500 | AH10: 9500 | AI10: 9500 | AJ10: 9500 | AK10: 9500 | AL10: 9500 | AM10: 9500 | AN10: 9500 | AO10: 9500 | AP10: 9500 | AQ10: 9500
A11: 9 | B11: Culte, vie civique et services publics | C11: Administrations / bureaux | D11: Bureaux avec accueil du public | E11: W | F11: ERP | G11: Bureaux avec accueil du public | H11: Immeuble tertiaire, siège administratif | I11: ERP | J11: oui | K11: non | L11: non | M11: site / établissement principal | N11: proxy large / parc tertiaire recevant du public | O11: faible | P11: oui | Q11: Mairies / hôtels de ville ; Maisons France Services / guichets publics ; Préfectures / services administratifs ; Centres de santé / centres médicaux ; Auto-écoles ; Centres de formation / CFA | S11: Faute de série nationale homogène publiée annuellement pour cette sous-catégorie, le proxy est lissé ; la faible variation reflète une prudence méthodologique. | T11: 250 | U11: 20 | V11: 0 | W11: Catégorie volontairement large et non homogène ; le proxy reste stable pour éviter d’additionner plusieurs sous-catégories déjà détaillées. Fiabilité: faible. | X11: https://www.insee.fr/fr/metadonnees/source/serie/s1161 | Y11: 120000 | Z11: 120000 | AA11: 120000 | AB11: 120000 | AC11: 120000 | AD11: 120000 | AE11: 120000 | AF11: 120000 | AG11: 120000 | AH11: 120000 | AI11: 120000 | AJ11: 120000 | AK11: 120000 | AL11: 120000 | AM11: 120000 | AN11: 120000 | AO11: 120000 | AP11: 120000 | AQ11: 120000
A12: 10 | B12: Sanitaires publics | C12: Sanitaires publics | D12: Toilettes publiques (sur la voie publique) | E12: Variable | F12: Souvent équipement isolé / non type autonome | G12: Pas de type ERP autonome. | H12: Sanisette, bloc sanitaires public | I12: mixte | J12: oui | K12: non | L12: non | M12: site / établissement principal | N12: proxy public / estimation encadrée | O12: faible | P12: non | S12: Pas de stagnation structurelle : la série évolue à la hausse sur la période 2000-2026 ; la projection prolonge cette tendance avec prudence. | T12: 25 | U12: 6 | V12: 1 | W12: proxy équipements d’hygiène urbaine. Dynamique projetée 2027-2030: hausse légère. Fiabilité: faible. | X12: https://www.insee.fr/fr/metadonnees/source/serie/s1161 | Y12: 5226 | Z12: 5770 | AA12: 6370 | AB12: 7033 | AC12: 7174 | AD12: 7317 | AE12: 7463 | AF12: 7612 | AG12: 7688 | AH12: 7765 | AI12: 7842 | AJ12: 7921 | AK12: 8000 | AL12: 8080 | AM12: 8161 | AN12: 8243 | AO12: 8325 | AP12: 8408 | AQ12: 8492
A13: =#REF!+1 -> #REF! | B13: Industrie et logistique | C13: Industrie / logistique | D13: Industrie + logistique + stockage | E13: Variable | F13: Souvent hors ERP autonome | G13: Le site industriel, logistique ou de stockage n’est pas un type ERP en soi. | H13: Site industriel avec showroom | I13: mixte | J13: oui | K13: non | L13: variable | M13: site / établissement principal | N13: sous-espace / proxy non additif | O13: faible | P13: non | Q13: Showrooms / halls de vente ; Bureaux avec accueil du public ; Restaurants | S13: Sous-espace rattaché à un site parent ; la série varie peu car elle suit un stock principal administré et non un marché autonome. | T13: 12000 | U13: 120 | V13: 0 | W13: proxy sites industriels/logistiques avec accueil du public. Dynamique projetée 2027-2030: hausse légère. Fiabilité: faible. Risque de doublon: oui si addition avec la catégorie parente ou avec des sous-espaces d’un même site. | X13: https://www.insee.fr/fr/statistiques/2011101 | Y13: 9796 | Z13: 10816 | AA13: 11942 | AB13: 13185 | AC13: 13449 | AD13: 13718 | AE13: 13992 | AF13: 14272 | AG13: 14415 | AH13: 14559 | AI13: 14704 | AJ13: 14851 | AK13: 15000 | AL13: 15150 | AM13: 15302 | AN13: 15455 | AO13: 15610 | AP13: 15766 | AQ13: 15924
B18: Catégorie chapeau | C18: Segment Principal | D18: Sous-Segment | E18: Type ERP principal | F18: Type de classement | G18: Notes de classement | H18: Exemples | I18: ERP Hors ERP Mixte | J18: Accueil Public : oui/non variable | K18: Présence de sommeil (oui-non variable) | L18: Espaces sanitaires collectifs (WC et/ou douche) | M18: Unité de compte retenue | N18: Nature de la donnée | O18: Niveau de fiabilité | P18: Sous-catégorie incluse dans … | AL18: 2025
B19: - | C19: - | D19: - | E19: - | F19: - | G19: - | H19: - | I19: - | J19: - | K19: - | L19: - | M19: - | N19: - | O19: - | P19: - | AL19: -
B20: Commerce, Restauration & Loisirs | C20: Commerce alimentaire de proximité | D20: Boulangeries / pâtisseries artisanales | E20: M | F20: ERP | G20: Petit commerce alimentaire recevant du public. Très fréquent dans le tissu de proximité ; sanitaires publics non systématiques mais sanitaires personnel fréquents. | H20: Boulangerie, pâtisserie, terminal de cuisson | I20: ERP | J20: oui | K20: non | L20: variable | M20: Site / point de vente | N20: estimation de structure / ordre de grandeur | O20: Moyen | AL20: 35000
B21: Commerce, Restauration & Loisirs | C21: Commerce alimentaire de proximité | D21: Boucheries / charcuteries / poissonneries | E21: M | F21: ERP | G21: Petit commerce alimentaire recevant du public ; souvent omis dans les listes macros de grands équipements. | H21: Boucherie, charcuterie, poissonnerie | I21: ERP | J21: oui | K21: non | L21: variable | M21: Site / point de vente | N21: estimation de structure / ordre de grandeur | O21: Moyen | AL21: 12000
B22: Commerce, Restauration & Loisirs | C22: Commerce alimentaire de proximité | D22: Épiceries / supérettes / commerces alimentaires spécialisés | E22: M | F22: ERP | G22: Commerces alimentaires de proximité avec accueil public ; gros volume diffus de 5e catégorie. | H22: Supérette, épicerie fine, magasin bio, primeur | I22: ERP | J22: oui | K22: non | L22: variable | M22: Site / point de vente | N22: estimation de structure / ordre de grandeur | O22: Moyen | AL22: 20000
B23: Commerce, Restauration & Loisirs | C23: Grande distribution alimentaire | D23: Supermarchés / hypermarchés / drives avec accueil public | E23: M | F23: ERP | G23: Grands commerces alimentaires recevant du public ; à distinguer des seuls centres commerciaux. | H23: Supermarché, hypermarché, drive avec accueil clientèle | I23: ERP | J23: oui | K23: non | L23: oui | M23: Site / magasin | N23: estimation de structure / ordre de grandeur | O23: Moyen | AL23: 8000
B24: Commerce, Restauration & Loisirs | C24: Commerce santé-beauté | D24: Pharmacies d’officine | E24: M | F24: ERP | G24: Officines ouvertes au public ; sous-segment massif si seules les structures de santé sont comptées. | H24: Pharmacie de centre-ville, pharmacie de quartier | I24: ERP | J24: oui | K24: non | L24: oui | M24: Site / officine | N24: source sectorielle officielle | O24: Elevé | AL24: 20242
B25: Commerce, Restauration & Loisirs | C25: Services personnels | D25: Salons de coiffure / barbiers | E25: M | F25: ERP | G25: Très grand volume de petits ERP de proximité, souvent absents des listes d’équipements. | H25: Salon de coiffure, barber shop | I25: ERP | J25: oui | K25: non | L25: variable | M25: Site / point de vente | N25: estimation de structure / ordre de grandeur | O25: Moyen | AL25: 85000
B26: Commerce, Restauration & Loisirs | C26: Services personnels | D26: Instituts de beauté / ongleries / esthétiques | E26: M | F26: ERP | G26: Réseau très diffus de petits établissements recevant du public. | H26: Institut de beauté, onglerie, esthéticienne en local | I26: ERP | J26: oui | K26: non | L26: variable | M26: Site / point de vente | N26: estimation de structure / ordre de grandeur | O26: Moyen | AL26: 40000
B27: Commerce, Restauration & Loisirs | C27: Commerce santé-beauté | D27: Opticiens / audioprothésistes / appareillage recevant du public | E27: M | F27: ERP | G27: Commerces spécialisés avec accueil public régulier. | H27: Opticien, audioprothésiste, magasin d’appareillage | I27: ERP | J27: oui | K27: non | L27: variable | M27: Site / point de vente | N27: estimation de structure / ordre de grandeur | O27: Moyen | AL27: 15000
B28: Commerce, Restauration & Loisirs | C28: Commerce non alimentaire | D28: Magasins d’habillement / chaussures / accessoires | E28: M | F28: ERP | G28: Commerces de détail recevant du public ; fortement sous-représentés si l’on ne retient que les malls. | H28: Boutique de vêtements, magasin de chaussures | I28: ERP | J28: oui | K28: non | L28: variable | M28: Site / point de vente | N28: estimation de structure / ordre de grandeur | O28: Moyen | AL28: 35000
B29: Commerce, Restauration & Loisirs | C29: Commerce non alimentaire | D29: Librairies / papeteries / presse | E29: M | F29: ERP | G29: Commerces culturels et de proximité avec accueil public. | H29: Librairie, papeterie, maison de la presse | I29: ERP | J29: oui | K29: non | L29: variable | M29: Site / point de vente | N29: estimation de structure / ordre de grandeur | O29: Moyen | AL29: 8000
B30: Commerce, Restauration & Loisirs | C30: Commerce non alimentaire | D30: Bureaux de tabac / presse-tabac / FDJ | E30: M | F30: ERP | G30: Réseau dense de commerces de proximité recevant du public. | H30: Bureau de tabac, presse-tabac, point FDJ | I30: ERP | J30: oui | K30: non | L30: variable | M30: Site / point de vente | N30: estimation de structure / ordre de grandeur | O30: Moyen | AL30: 23000
B31: Commerce, Restauration & Loisirs | C31: Commerce non alimentaire | D31: Fleuristes / jardineries de proximité | E31: M | F31: ERP | G31: Commerces spécialisés de proximité recevant du public. | H31: Fleuriste, jardinerie de centre-ville | I31: ERP | J31: oui | K31: non | L31: variable | M31: Site / point de vente | N31: estimation de structure / ordre de grandeur | O31: Moyen | AL31: 10000
... B44: Transport, Mobilité & Stationnement | C44: Matériel roulant urbain / interurbain | D44: Bus, cars, rames de tram, métro, RER | E44: N/A | F44: Hors ERP | G44: Transports publics et matériel roulant, non ERP au sens du code de la construction. | H44: Bus urbain, tramway, métro | I44: Hors ERP | J44: oui | K44: non | L44: variable | M44: Non additionnable au parc ERP | N44: hors périmètre ERP strict | O44: Elevé | AL44: 0
B45: Sanitaires publics | C45: Sanitaires publics | D45: Blocs sanitaires fixes de plage / front de mer | E45: Variable | F45: Cas particulier | G45: Selon l’implantation, peut relever du domaine public, d’un équipement balnéaire, d’une plage aménagée ou d’un établissement lié. À traiter au cas par cas pour éviter les doubles comptes. | H45: WC/douches fixes de plage, sanitaires de front de mer | I45: mixte | J45: oui | K45: non | L45: oui | M45: Bloc sanitaire / site | N45: cas limite / à vérifier localement | O45: Moyen | P45: Toilettes publiques (sur la voie publique) | AL45: 0

Sheet Risque de doublons ERP
A1: Catégorie chapeau | B1: Catégorie principale | C1: Sous-catégorie | D1: Doublon potentiel avec | E1: Sous-catégorie incluse dans | F1: Pourquoi risque de doublon ? | G1: Type de risque | H1: Recommandation de déduplication | I1: Inclure dans Total France par défaut (1/0) | J1: Source principale
A2: Commerce, restauration et loisirs | B2: Commerce | C2: Showrooms / halls de vente | D2: Centres commerciaux / malls ; Industrie + logistique + stockage | F2: Des implantations ou emprises peuvent être comptées à la fois dans cette ligne et dans une autre ligne voisine, selon l’unité de compte retenue. | G2: co-localisation / recouvrement partiel | H2: Laisser la ligne à 0 dans la colonne « Inclure dans Total France » sauf si vous retirez les lignes plus fines/plus larges qui se recoupent. | I2: 0 | J2: https://www.insee.fr/fr/metadonnees/source/serie/s1161
A3: Culte, vie civique et services publics | B3: Administrations / bureaux | C3: Bureaux avec accueil du public | D3: Mairies / hôtels de ville ; Maisons France Services / guichets publics ; Préfectures / services administratifs ; Centres de santé / centres médicaux ; Auto-écoles ; Centres de formation / CFA | F3: Catégorie transverse ou site mixte : le même lieu peut déjà être couvert par plusieurs sous-catégories plus fines. | G3: site mixte / recouvrement fonctionnel | H3: Laisser la ligne à 0 dans la colonne « Inclure dans Total France » sauf si vous retirez les lignes plus fines/plus larges qui se recoupent. | I3: 0 | J3: https://www.insee.fr/fr/metadonnees/source/serie/s1161
A4: Culture, patrimoine et événementiel | B4: Documentation | C4: Centres de documentation | D4: Bibliothèques / médiathèques | E4: Bibliothèques / médiathèques (lorsqu’il s’agit d’un service interne) | F4: La sous-catégorie est généralement un sous-ensemble fonctionnel d’un site plus large déjà compté ailleurs. | G4: incluse dans une catégorie plus large | H4: Par défaut, ne pas sommer cette ligne avec Bibliothèques / médiathèques (lorsqu’il s’agit d’un service interne). Conserver une seule maille de compte dans le total France. | I4: 0 | J4: https://www.insee.fr/fr/metadonnees/source/serie/s1161
A5: Industrie et logistique | B5: Industrie / logistique | C5: Industrie + logistique + stockage | D5: Showrooms / halls de vente ; Bureaux avec accueil du public ; Restaurants | F5: La ligne décrit un sous-espace ou un usage interne d’un site principal et n’est donc pas additive avec le site parent. | G5: sous-espace / site parent | H5: Laisser la ligne à 0 dans la colonne « Inclure dans Total France » sauf si vous retirez les lignes plus fines/plus larges qui se recoupent. | I5: 0 | J5: https://www.insee.fr/fr/statistiques/2011101
A6: Santé et médico-social | B6: Médico-social | C6: Autres établissements spécialisés pour personnes âgées | D6: EHPAD ; Résidences autonomie / foyers-logements ; USLD | E6: EHPAD ; Résidences autonomie / foyers-logements ; USLD | F6: La sous-catégorie est généralement un sous-ensemble fonctionnel d’un site plus large déjà compté ailleurs. | G6: incluse dans une catégorie plus large | H6: Par défaut, ne pas sommer cette ligne avec EHPAD ; Résidences autonomie / foyers-logements ; USLD. Conserver une seule maille de compte dans le total France. | I6: 0 | J6: https://drees.solidarites-sante.gouv.fr/jeux-de-donnees/jeux-de-donnees/les-residents-en-etablissements-dhebergement-pour-personnes-agees
A7: Santé et médico-social | B7: Médico-social | C7: Habitat inclusif / habitats regroupés seniors | D7: Résidences autonomie / foyers-logements ; Résidences services seniors | F7: Des implantations ou emprises peuvent être comptées à la fois dans cette ligne et dans une autre ligne voisine, selon l’unité de compte retenue. | G7: co-localisation / recouvrement partiel | H7: Vérifier l’unité de compte et éviter de sommer cette ligne avec Résidences autonomie / foyers-logements ; Résidences services seniors lorsqu’un même site est susceptible d’être compté deux fois. | I7: 1 | J7: https://drees.solidarites-sante.gouv.fr/sites/default/files/2025-09/PAPH%20-%20Fiche%2009%20-%20Les%20%C3%A9tablissements%20d%E2%80%99h%C3%A9bergement%20pour%20personnes%20%C3%A2g%C3%A9es_0.pdf
A8: Santé et médico-social | B8: Médico-social | C8: Hébergements temporaires seniors | D8: EHPAD ; Résidences autonomie / foyers-logements ; Résidences services seniors | E8: EHPAD ; Résidences autonomie / foyers-logements ; Résidences services seniors | F8: La sous-catégorie est généralement un sous-ensemble fonctionnel d’un site plus large déjà compté ailleurs. | G8: incluse dans une catégorie plus large | H8: Par défaut, ne pas sommer cette ligne avec EHPAD ; Résidences autonomie / foyers-logements ; Résidences services seniors. Conserver une seule maille de compte dans le total France. | I8: 0 | J8: https://drees.solidarites-sante.gouv.fr/jeux-de-donnees/jeux-de-donnees/les-residents-en-etablissements-dhebergement-pour-personnes-agees
A9: Santé et médico-social | B9: Médico-social | C9: Résidences services seniors | D9: Résidences autonomie / foyers-logements ; Habitat inclusif / habitats regroupés seniors | F9: Des implantations ou emprises peuvent être comptées à la fois dans cette ligne et dans une autre ligne voisine, selon l’unité de compte retenue. | G9: co-localisation / recouvrement partiel | H9: Vérifier l’unité de compte et éviter de sommer cette ligne avec Résidences autonomie / foyers-logements ; Habitat inclusif / habitats regroupés seniors lorsqu’un même site est susceptible d’être compté deux fois. | I9: 1 | J9: https://drees.solidarites-sante.gouv.fr/sites/default/files/2025-09/PAPH%20-%20Fiche%2009%20-%20Les%20%C3%A9tablissements%20d%E2%80%99h%C3%A9bergement%20pour%20personnes%20%C3%A2g%C3%A9es_0.pdf
A10: Santé et médico-social | B10: Santé ambulatoire | C10: Maisons de santé | D10: Centres de santé / centres médicaux ; Bureaux avec accueil du public | F10: Des implantations ou emprises peuvent être comptées à la fois dans cette ligne et dans une autre ligne voisine, selon l’unité de compte retenue. | G10: co-localisation / recouvrement partiel | H10: Vérifier l’unité de compte et éviter de sommer cette ligne avec Centres de santé / centres médicaux ; Bureaux avec accueil du public lorsqu’un même site est susceptible d’être compté deux fois. | I10: 1 | J10: https://sante.gouv.fr/systeme-de-sante/structures-de-soins/article/les-maisons-de-sante-300889
A11: Santé et médico-social | B11: Santé hospitalière | C11: Cliniques | D11: Centres de rééducation ; Centres de psychiatrie ; Maternités | F11: Des implantations ou emprises peuvent être comptées à la fois dans cette ligne et dans une autre ligne voisine, selon l’unité de compte retenue. | G11: co-localisation / recouvrement partiel | H11: Vérifier l’unité de compte et éviter de sommer cette ligne avec Centres de rééducation ; Centres de psychiatrie ; Maternités lorsqu’un même site est susceptible d’être compté deux fois. | I11: 1 | J11: https://drees.solidarites-sante.gouv.fr/publications-communique-de-presse/etudes-et-resultats/251113_ER_etablissements-de-sante
A12: Santé et médico-social | B12: Santé hospitalière | C12: Hôpitaux privés | D12: Centres de rééducation ; Centres de psychiatrie ; Maternités ; Hôpitaux d’instruction des armées et centres médicaux recevant du public | F12: Des implantations ou emprises peuvent être comptées à la fois dans cette ligne et dans une autre ligne voisine, selon l’unité de compte retenue. | G12: co-localisation / recouvrement partiel | H12: Vérifier l’unité de compte et éviter de sommer cette ligne avec Centres de rééducation ; Centres de psychiatrie ; Maternités ; Hôpitaux d’instruction des armées et centres médicaux recevant du public lorsqu’un même site est susceptible d’être compté deux fois. | I12: 1 | J12: https://drees.solidarites-sante.gouv.fr/publications-communique-de-presse/etudes-et-resultats/251113_ER_etablissements-de-sante
A13: Santé et médico-social | B13: Santé hospitalière | C13: Hôpitaux publics | D13: Hôpitaux universitaires / CHU ; Centres de psychiatrie ; Centres de rééducation ; Maternités ; Hôpitaux d’instruction des armées et centres médicaux recevant du public | F13: Des implantations ou emprises peuvent être comptées à la fois dans cette ligne et dans une autre ligne voisine, selon l’unité de compte retenue. | G13: co-localisation / recouvrement partiel | H13: Vérifier l’unité de compte et éviter de sommer cette ligne avec Hôpitaux universitaires / CHU ; Centres de psychiatrie ; Centres de rééducation ; Maternités ; Hôpitaux d’instruction des armées et centres médicaux recevant du public lorsqu’un même site est susceptible d’être compté deux fois. | I13: 1 | J13: https://drees.solidarites-sante.gouv.fr/publications-communique-de-presse/etudes-et-resultats/251113_ER_etablissements-de-sante
A14: Santé et médico-social | B14: Santé hospitalière | C14: Hôpitaux universitaires / CHU | D14: Hôpitaux publics | E14: Hôpitaux publics | F14: La sous-catégorie est généralement un sous-ensemble fonctionnel d’un site plus large déjà compté ailleurs. | G14: incluse dans une catégorie plus large | H14: Par défaut, ne pas sommer cette ligne avec Hôpitaux publics. Conserver une seule maille de compte dans le total France. | I14: 0 | J14: https://drees.solidarites-sante.gouv.fr/publications-communique-de-presse/etudes-et-resultats/251113_ER_etablissements-de-sante
A15: Santé et médico-social | B15: Santé spécialisée | C15: Centres de psychiatrie | D15: Hôpitaux publics ; Hôpitaux privés ; Cliniques | E15: Hôpitaux publics ; Hôpitaux privés ; Cliniques | F15: La sous-catégorie est généralement un sous-ensemble fonctionnel d’un site plus large déjà compté ailleurs. | G15: incluse dans une catégorie plus large | H15: Par défaut, ne pas sommer cette ligne avec Hôpitaux publics ; Hôpitaux privés ; Cliniques. Conserver une seule maille de compte dans le total France. | I15: 0 | J15: https://drees.solidarites-sante.gouv.fr/publications-communique-de-presse-documents-de-reference/panoramas-de-la-drees/250522_Panorama_etablissements-de-sante2025
A16: Santé et médico-social | B16: Santé spécialisée | C16: Centres de rééducation | D16: Hôpitaux publics ; Hôpitaux privés ; Cliniques | E16: Hôpitaux publics ; Hôpitaux privés ; Cliniques | F16: La sous-catégorie est généralement un sous-ensemble fonctionnel d’un site plus large déjà compté ailleurs. | G16: incluse dans une catégorie plus large | H16: Par défaut, ne pas sommer cette ligne avec Hôpitaux publics ; Hôpitaux privés ; Cliniques. Conserver une seule maille de compte dans le total France. | I16: 0 | J16: https://drees.solidarites-sante.gouv.fr/publications-communique-de-presse-documents-de-reference/panoramas-de-la-drees/250522_Panorama_etablissements-de-sante2025
A17: Santé et médico-social | B17: Santé spécialisée | C17: Maternités | D17: Hôpitaux publics ; Hôpitaux privés ; Cliniques | E17: Hôpitaux publics ; Hôpitaux privés ; Cliniques (quand la maternité n’est pas autonome) | F17: La sous-catégorie est généralement un sous-ensemble fonctionnel d’un site plus large déjà compté ailleurs. | G17: incluse dans une catégorie plus large | H17: Par défaut, ne pas sommer cette ligne avec Hôpitaux publics ; Hôpitaux privés ; Cliniques (quand la maternité n’est pas autonome). Conserver une seule maille de compte dans le total France. | I17: 0 | J17: https://drees.solidarites-sante.gouv.fr/sites/default/files/2025-05/DREES%20-%20Pano%20-%20ES%202025%20-%20Fiche%2018_La%20naissance%20_les%20maternit%C3%A9s.pdf
A18: Sécurité et justice | B18: Sécurité et justice | C18: Commissariats / postes de police - halls d’accueil, guichets et zones de dépôt de plainte | D18: Commissariats / postes de police - postes de proximité et antennes avec accueil public | F18: Des implantations ou emprises peuvent être comptées à la fois dans cette ligne et dans une autre ligne voisine, selon l’unité de compte retenue. | G18: co-localisation / recouvrement partiel | H18: Vérifier l’unité de compte et éviter de sommer cette ligne avec Commissariats / postes de police - postes de proximité et antennes avec accueil public lorsqu’un même site est susceptible d’être compté deux fois. | I18: 1 | J18: https://www.interieur.gouv.fr/actualites/communiques-de-presse/95-de-population-vit-a-moins-de-14-minutes-dun-lieu-daccueil-de
A19: Sécurité et justice | B19: Sécurité et justice | C19: Commissariats / postes de police - locaux de sûreté, garde à vue et zones opérationnelles | D19: Commissariats / postes de police - halls d’accueil, guichets et zones de dépôt de plainte | E19: Commissariats / postes de police - halls d’accueil, guichets et zones de dépôt de plainte | F19: La sous-catégorie est généralement un sous-ensemble fonctionnel d’un site plus large déjà compté ailleurs. | G19: incluse dans une catégorie plus large | H19: Par défaut, ne pas sommer cette ligne avec Commissariats / postes de police - halls d’accueil, guichets et zones de dépôt de plainte. Conserver une seule maille de compte dans le total France. | I19: 0 | J19: https://www.interieur.gouv.fr/actualites/communiques-de-presse/95-de-population-vit-a-moins-de-14-minutes-dun-lieu-daccueil-de
A20: Sécurité et justice | B20: Sécurité et justice | C20: Commissariats / postes de police - postes de proximité et antennes avec accueil public | D20: Commissariats / postes de police - halls d’accueil, guichets et zones de dépôt de plainte | F20: Des implantations ou emprises peuvent être comptées à la fois dans cette ligne et dans une autre ligne voisine, selon l’unité de compte retenue. | G20: co-localisation / recouvrement partiel | H20: Laisser la ligne à 0 dans la colonne « Inclure dans Total France » sauf si vous retirez les lignes plus fines/plus larges qui se recoupent. | I20: 0 | J20: https://www.interieur.gouv.fr/actualites/communiques-de-presse/95-de-population-vit-a-moins-de-14-minutes-dun-lieu-daccueil-de
A21: Sécurité et justice | B21: Sécurité et justice | C21: Commissariats / postes de police - salles de réunion, de prévention ou de conférence ouvertes au public | D21: Commissariats / postes de police - halls d’accueil, guichets et zones de dépôt de plainte ; Commissariats / postes de police - postes de proximité et antennes avec accueil public | E21: Commissariats / postes de police - halls d’accueil, guichets et zones de dépôt de plainte ; Commissariats / postes de police - postes de proximité et antennes avec accueil public | F21: La sous-catégorie est généralement un sous-ensemble fonctionnel d’un site plus large déjà compté ailleurs. | G21: incluse dans une catégorie plus large | H21: Par défaut, ne pas sommer cette ligne avec Commissariats / postes de police - halls d’accueil, guichets et zones de dépôt de plainte ; Commissariats / postes de police - postes de proximité et antennes avec accueil public. Conserver une seule maille de compte dans le total France. | I21: 0 | J21: https://www.interieur.gouv.fr/actualites/communiques-de-presse/95-de-population-vit-a-moins-de-14-minutes-dun-lieu-daccueil-de
A22: Sécurité et justice | B22: Sécurité et justice | C22: Forces armées - Unités d'hébergement des militaires / réservistes | D22: Forces armées - centres de recrutement et bureaux d’information ; Forces armées - hôpitaux d’instruction des armées et centres médicaux recevant du public ; Forces armées - salles de conférence, auditoriums et espaces événementiels ouverts au public | F22: Ligne d’hébergement collectif interne à une emprise militaire ; elle n’est pas additive avec d’autres usages recevant ponctuellement du public sur le même site. | G22: sous-espace / hébergement interne | H22: Laisser la ligne à 0 dans la colonne « Inclure dans Total France » sauf si vous adoptez une convention spécifique de comptage des bâtiments d’hébergement collectif militaires. | I22: 0 | J22: https://www.defense.gouv.fr/sites/default/files/ssm/EcoDef%20140.pdf ; https://www.ccomptes.fr/fr/publications/les-conditions-dhebergement-dans-les-bases-de-defense-exercices-2011-2021
A23: Sécurité et justice | B23: Sécurité et justice | C23: Forces armées - centres de recrutement et bureaux d’information | D23: Bureaux avec accueil du public | F23: La ligne décrit un sous-espace ou un usage interne d’un site principal et n’est donc pas additive avec le site parent. | G23: sous-espace / site parent | H23: Vérifier l’unité de compte et éviter de sommer cette ligne avec Bureaux avec accueil du public lorsqu’un même site est susceptible d’être compté deux fois. | I23: 1 | J23: https://www.defense.gouv.fr/sga/nous-rejoindre/cirfa
A24: Sécurité et justice | B24: Sécurité et justice | C24: Forces armées - restaurants ou équipements sportifs ouverts au public sur emprise militaire | D24: Restaurants ; Cafés / bars / brasseries ; Gymnases / salles multisports ; Salles de fitness / dojos | F24: La ligne décrit un sous-espace ou un usage interne d’un site principal et n’est donc pas additive avec le site parent. | G24: sous-espace / site parent | H24: Laisser la ligne à 0 dans la colonne « Inclure dans Total France » sauf si vous retirez les lignes civiles plus larges qui se recoupent. | I24: 0 | J24: https://www.defense.gouv.fr/
A25: Sécurité et justice | B25: Sécurité et justice | C25: Forces armées - hôpitaux d’instruction des armées et centres médicaux recevant du public | D25: Hôpitaux publics ; Hôpitaux privés ; Cliniques | F25: La ligne décrit un sous-espace ou un usage interne d’un site principal et n’est donc pas additive avec le site parent. | G25: sous-espace / site parent | H25: Vérifier l’unité de compte et éviter de sommer cette ligne avec Hôpitaux publics ; Hôpitaux privés ; Cliniques lorsqu’un même site est susceptible d’être compté deux fois. | I25: 1 | J25: https://www.defense.gouv.fr/sante
A26: Sécurité et justice | B26: Sécurité et justice | C26: Forces armées - salles de conférence, auditoriums et espaces événementiels ouverts au public | D26: Salles de conférence / réunion ; Salles de spectacle / auditoriums | F26: La ligne décrit un sous-espace ou un usage interne d’un site principal et n’est donc pas additive avec le site parent. | G26: sous-espace / site parent | H26: Laisser la ligne à 0 dans la colonne « Inclure dans Total France » sauf si vous retirez les lignes plus fines/plus larges qui se recoupent. | I26: 0 | J26: https://www.defense.gouv.fr/
A27: Sécurité et justice | B27: Univers carcéral | C27: Maisons d’arrêt | D27: Centres pénitentiaires | E27: Centres pénitentiaires (lorsqu’un quartier maison d’arrêt est intégré à un site composite) | F27: Risque de recouvrement si l’unité de compte mélange établissement autonome et quartier fonctionnel au sein d’un centre pénitentiaire. | G27: site composite / recouvrement partiel
A28: Sécurité et justice | B28: Univers carcéral | C28: Centres de détention | D28: Centres pénitentiaires | E28: Centres pénitentiaires (lorsqu’un quartier centre de détention est intégré à un site composite) | F28: Risque de recouvrement si l’unité de compte mélange établissement autonome et quartier fonctionnel au sein d’un centre pénitentiaire. | G28: site composite / recouvrement partiel
A29: Sécurité et justice | B29: Univers carcéral | C29: Maisons centrales | D29: Centres pénitentiaires (cas rares de restructuration de site) | F29: Risque limité mais possible en cas de lecture trop large des sites pénitentiaires spécialisés ou restructurés. | G29: recouvrement ponctuel
A30: Sécurité et justice | B30: Univers carcéral | C30: Centres pénitentiaires | D30: Maisons d’arrêt ; Centres de détention | F30: Le centre pénitentiaire est un site composite pouvant regrouper plusieurs quartiers fonctionnels déjà décrits par d’autres sous-catégories. | G30: établissement composite / site parent
A31: Sécurité et justice | B31: Univers carcéral | C31: Centres de semi-liberté | D31: Centres pour peines aménagées | F31: Ces deux catégories sont proches dans leur finalité d’exécution aménagée et peuvent être confondues selon le périmètre retenu. | G31: recouvrement fonctionnel
A32: Sécurité et justice | B32: Univers carcéral | C32: Centres pour peines aménagées | D32: Centres de semi-liberté | F32: Ces deux catégories sont proches dans leur finalité d’exécution aménagée et peuvent être confondues selon le périmètre retenu. | G32: recouvrement fonctionnel
A33: Sécurité et justice | B33: Univers carcéral | C33: Centres éducatifs fermés | D33: Établissements médico-éducatifs | F33: Le recouvrement tient surtout à la proximité fonctionnelle et à des périmètres d’inventaire différents ; ce n’est pas un doublon pénitentiaire strict. | G33: proximité fonctionnelle
A34: Sécurité et justice | B34: Univers carcéral | C34: Unités hospitalières sécurisées | D34: Hôpitaux publics ; Hôpitaux privés ; Cliniques | E34: Hôpitaux publics ; Hôpitaux privés ; Cliniques | F34: Les unités hospitalières sécurisées sont des composantes du champ sanitaire ; elles ne doivent pas être additionnées au parc hospitalier global. | G34: incluse dans une catégorie plus large
A35: Sécurité et justice | B35: Tribunaux | C35: Tribunaux judiciaires | D35: Palais de justice et bâtiments judiciaires multi-usages ; Autres bâtiments judiciaires autonomes recevant du public | E35: Palais de justice et bâtiments judiciaires multi-usages (lorsque l’unité de compte retenue est le bâtiment) | F35: Risque de recouvrement si l’on mélange comptage par juridiction et comptage par bâtiment. | G35: juridiction vs bâtiment
A36: Sécurité et justice | B36: Tribunaux | C36: Palais de justice et bâtiments judiciaires multi-usages | D36: Tribunaux judiciaires ; Tribunaux de commerce autonomes ; Conseils de prud’hommes autonomes | F36: Un même palais peut accueillir plusieurs juridictions ; le site ne doit pas être additionné aux juridictions qui y siègent si l’unité de compte est le bâtiment. | G36: site multi-juridictions
A37: Sécurité et justice | B37: Tribunaux | C37: Maisons de justice et du droit | D37: Autres bâtiments judiciaires autonomes recevant du public | F37: Le risque est limité mais certaines implantations de proximité peuvent être agrégées dans une catégorie résiduelle de bâtiments judiciaires autonomes. | G37: recouvrement partiel
A38: Sécurité et justice | B38: Tribunaux | C38: Tribunaux de commerce autonomes | D38: Palais de justice et bâtiments judiciaires multi-usages | F38: Risque de recouvrement si un tribunal de commerce est hébergé dans un palais de justice compté par site. | G38: co-localisation / recouvrement partiel
A39: Sécurité et justice | B39: Tribunaux | C39: Conseils de prud’hommes autonomes | D39: Palais de justice et bâtiments judiciaires multi-usages | F39: Risque de recouvrement si le conseil de prud’hommes est hébergé dans un palais de justice compté par site. | G39: co-localisation / recouvrement partiel
A40: Sécurité et justice | B40: Tribunaux | C40: Autres bâtiments judiciaires autonomes recevant du public | D40: Tribunaux judiciaires ; Palais de justice et bâtiments judiciaires multi-usages ; Maisons de justice et du droit | F40: Catégorie résiduelle pouvant recouvrir des sites déjà comptés ailleurs si le périmètre n’est pas strictement défini. | G40: catégorie résiduelle / recouvrement partiel
A41: Transport, mobilité et stationnement | B41: Transport / mobilité | C41: Aires d’autoroute | D41: Stations-service ; Restaurants ; Fast-food / cafétérias / food courts ; Hôtels ; Parcs de stationnement couverts | F41: La ligne décrit un sous-espace ou un usage interne d’un site principal et n’est donc pas additive avec le site parent. | G41: sous-espace / site parent | H41: Laisser la ligne à 0 dans la colonne « Inclure dans Total France » sauf si vous retirez les lignes plus fines/plus larges qui se recoupent. | I41: 0 | J41: https://www.autoroutes.fr/fr/aires-de-services/
A42: Transport, mobilité et stationnement | B42: Transport / mobilité | C42: Stations-service | D42: Aires d’autoroute | F42: Des implantations ou emprises peuvent être comptées à la fois dans cette ligne et dans une autre ligne voisine, selon l’unité de compte retenue. | G42: site mixte / recouvrement fonctionnel | H42: Vérifier l’unité de compte et éviter de sommer cette ligne avec Aires d’autoroute lorsqu’un même site est susceptible d’être compté deux fois. | I42: 1 | J42: https://www.insee.fr/fr/statistiques/8610258?geo=FE-1

Sheet Méthode et limites
A1: Champ des séries | B1: Les années 2000-2026 sont remplies à partir de séries publiques directes quand elles existent ; sinon à partir de proxies publics / estimations encadrées. Certaines lignes sont recalées sur des ancrages 2024-2025 récents (BPE Insee, DEPP, Justice, Intérieur).
A2: Fiabilité | B2: bonne = série publique directe ou ancrage robuste ; moyenne = proxy proche, ancré par une source officielle récente ; faible = estimation sectorielle, catégorie résiduelle, ou sous-catégorie ne faisant pas l’objet d’une série publique homogène.
A3: Sous-catégories stables | B3: Quand une sous-catégorie varie peu ou pas, une justification explicite est désormais donnée dans la colonne « Justification de stagnation / faible variation ». Cette stabilité peut refléter soit un stock institutionnel mature, soit un lissage méthodologique prudent en l’absence de série homogène.
A4: Risque de doublon | B4: La colonne « Doublon potentiel avec » indique les autres sous-catégories susceptibles de recouper la ligne. La colonne « Sous-catégorie incluse dans » précise quand la ligne est généralement comprise dans une catégorie plus large.
A5: Total France (V2 comptable) | B5: Le total en ligne 2 de chaque onglet est une formule Excel pilotée par la colonne « Inclure dans Total France (1/0) ». Mettre 1 pour inclure la ligne dans le total, 0 pour l’exclure. Cela permet de tester différentes conventions de déduplication sans casser les séries.
A6: Interprétation du total | B6: Le total France n’a de sens qu’avec une unité de compte stable (site / établissement principal / entité d’exploitation). Les sous-espaces, emprises mixtes et catégories transverses sont exclus par défaut lorsqu’ils créent un risque fort de double comptage.
A7: Surface moyenne 2026 | B7: La colonne « Surface moyenne 2026 » donne un ordre de grandeur moyen par établissement. Ce n’est pas une série officielle exhaustive : ce sont des benchmarks 2026, établis à partir d’ordres de grandeur publics, de ratios sectoriels quand disponibles et de proxys d’ingénierie d’exploitation.
A8: Capacité instantanée moyenne 2026 | B8: La colonne « Capacité instantanée moyenne 2026 » correspond à des places / lits / usagers selon le type d’établissement. Elle sert à comparer l’ordre de grandeur opérationnel moyen d’un site ; elle ne constitue pas une norme réglementaire.
A9: Projections 2027-2030 | B9: Les projections 2027-2030 prolongent les tendances récentes avec prudence. Elles sont peu dynamiques pour les stocks institutionnels stables ; plus dynamiques pour les segments clairement en croissance (par ex. CFA, certaines formes d’habitat seniors).
A10: Limite majeure | B10: Certaines lignes détaillent des sous-usages d’un même site (tribunaux, commissariats, prisons, emprises militaires, aires d’autoroute, etc.). Elles sont documentées pour l’analyse, mais ne doivent pas être additionnées au site parent sans règle de déduplication explicite.

Sheet ANALYSE - ERP => SOUS-SEGMENT
J1: Classement ERP | Q1: Comptage | AA1: 2015-20 | AF1: 2020-25 | AK1: 2025-30 | AO1: Argu Evolution | AT1: Detail Capacité par Public | AY1: Detail Dimensionnement | BE1: =BE6/$BD$6 -> 0.44101019 | BF1: =BF6/$BD$6 -> 0.12429743 | BG1: =BG6/$BD$6 -> 0.075185542 | BH1: =BH6/$BD$6 -> 0.35950683 | BN1: Volume Pièces | CQ1: Mix Type Pièces | DG1: Durée Vie - Type Pièces | DR1: Vol Lav 25-30 | EA1: Vol Douches 25-30 | EL1: Vol Urinoirs 25-30 | EU1: Vol WC 25-30 | EX1: =EX6/5000 -> 1167.31 | EY1: =FA6/5000 -> 502.7226 | EZ1: =EY1/$EX$1 -> 0.43066761 | FA1: =FD6/5000 -> 172.85965 | FB1: =FA1/$EX$1 -> 0.14808376 | FC1: =FA1/$EY$1 -> 0.34384699 | FD1: 33-36% | FE1: =FG6/5000 -> 90.494883 | FF1: =FE1/$EX$1 -> 0.077524295 | FG1: =FE1/$EY$1 -> 0.18000958 | FH1: 17-19% | FI1: =FJ6/5000 -> 401.23285 | FJ1: =FI1/$EX$1 -> 0.34372433 | FK1: =FI1/$EY$1 -> 0.79811977 | FL1: 79-81% | FM1: Vtes Réno - Neuf | FR1: Fiabilité - Hypothèses | GG1: Potentiel-Projets-Dynamisme-Menaces | HX1: Réno-Neuf | IN1: Niveau de Confort - Global | KC1: Niveau de Confort - Type Pdt | KK1: Drivers - Tendances -Niveau de Confort
J2: Exemples | Q2: Fiabilité | AO2: 2025-2030 | BA2: Nombre Pièces - Robinetterie collectivité - Etablissements Recevant du Public - IMPERATIVEMENT dotés de sanitaires | BP2: Mix 2025 | BT2: Mix 2030 | BX2: Mix 2025 | CA2: Mix 2030 | CD2: Mix 2025 | CH2: Mix 2030 | CL2: Mix 2025 | CO2: Mix 2030 | CR2: Durée Vie réelle : Nbre Années effectives de vie produit avant remplacement | DI2: Volumes 2025 | DN2: Volumes 2030 | DT2: Volumes 2025 | DX2: Mix 2030 | EC2: Volumes 2025 | EH2: Mix 2030 | EN2: Volumes 2025 | ER2: Mix 2030 | EX2: Ventes 2026-2030 | FB2: Ventes 2026-2030 | FE2: Ventes 2026-2030 | FH2: Ventes 2026-2030 | FK2: Ventes 2026-2030 | FQ2: Ventes 2026-2030 | FS2: Dynamisme Ventes 2026-2030 | GI2: Ventes 2026-2030 | GL2: Ventes 2026-2030 | GO2: Ventes 2026-2030 | GR2: Ventes 2026-2030 | GU2: Ventes 2026-2030 | GX2: Ventes 2026-2030 | HA2: Ventes 2026-2030 | HD2: Ventes 2026-2030 | HG2: Ventes 2026-2030 | HJ2: Ventes 2026-2030 | HM2: Ventes 2026-2030 | HP2: Ventes 2026-2030 | HS2: Ventes 2026-2030 | HV2: Ventes 2026-2030 | IB2: Parc 2025 | IH2: Ventes 2026-2030 | IQ2: Parc 2025 | IV2: Ventes 2026-2030 | JA2: Parc 2025 | JF2: Ventes 2026-2030 | JK2: Parc 2025 | JP2: Ventes 2026-2030 | JU2: Parc 2025 | JZ2: Ventes 2026-2030 | KE2: Niveau
R3: Nombre Etablissements Recevant du Public - IMPERATIVEMENT dotés de sanitaires | AZ3: par Etablissement | BF3: Total 2025 | BK3: Total 2030 | BP3: Lavabo | BT3: Lavabo | BX3: Douches | CA3: Douches | CC3: Urinoirs - Chasse … | CG3: Urinoirs - Chasse … | CL3: WC - Chasse … | CO3: WC - Chasse … | CS3: Lavabo | CW3: Douches | CY3: Urinoirs - Chasse … | DD3: WC - Chasse … | DI3: Lavabo | DN3: Lavabo | DT3: Douches | DX3: Douches | EC3: Urinoirs - Chasse … | EH3: Urinoirs - Chasse … | EN3: WC - Chasse … | ER3: WC - Chasse … | EX3: Tous produits | FB3: Lavabos | FE3: Douches | FH3: Urinoirs | FK3: WC | FN3: Fiabilité | FQ3: Hypothèses Rénovation | FS3: Global | FU3: Renovation | FW3: Neuf brut | GI3: Lavabos - Mitigeurs | GL3: Lavabos - Tempo. méca | GO3: Lavabos - Tempo. électro | GR3: Lavabos - Autres | GU3: Douches - Mitigeurs | GX3: Douches - Tempo. méca | HA3: Douches - Tempo. électro | HD3: Urinoirs - à Réservoir | HG3: Urinoirs - Directe méca. | HJ3: Urinoirs - Directe électro indiv. | HM3: Urinoirs - Directe électro collect. | HP3: WC - à Réservoir | HS3: WC - Directe méca. | HV3: WC - Directe électro | IB3: Volumes - Toutes Pièces | IH3: Volumes - Toutes Pièces | IK3: Fiabilité | IQ3: Lavabos | IV3: Lavabos | JA3: Douches | JF3: Douches | JK3: Urinoirs | JP3: Urinoirs | JU3: WC | JZ3: WC | KD3: Incertitude | KF3: Fiabilité
A4: ID | B4: Catégorie chapeau | C4: Segment Principal | D4: Sous-Segment | E4: Type ERP principal | F4: Type de classement | G4: ERP Hors ERP Mixte | H4: Accueil Public : oui/non variable | I4: Notes de classement | J4: Exemples | K4: Présence de sommeil (oui-non variable) | L4: Espaces sanitaires collectifs (WC et/ou douche) | M4: Unité de compte retenue | N4: Nature de la donnée | O4: Niveau de fiabilité | P4: Sous-catégorie incluse dans … | Q4: Inclure dans Total France (1/0) | R4: Surface moyenne 2026 (m²/étab.) | S4: 2000 | T4: 2005 | U4: 2010 | V4: 2015 | W4: 2016 | X4: 2017 | Y4: 2018 | Z4: 2019 | AA4: 2020 | AB4: 2021 | AC4: 2022 | AD4: 2023 | AE4: 2024 | AF4: 2025 | AG4: 2026 | AH4: 2027 | AI4: 2028 | AJ4: 2029 | AK4: 2030 | AL4: Justification Taille Parc & Evolution-Variation 2026-2030 | AM4: Calculs & Sources - Taille Parc & Evolution-Variation 2026-2030 | AN4: Sources (URL) | AP4: Capacité instantanée Moyenne 2026 TOTAL | AQ4: Capacité instantanée Moyenne 2026 Usagers Principaux | AR4: Capacité instantanée Moyenne 2026 Staff | AS4: Capacité instantanée Moyenne 2026 Autre Public | AU4: Dimensionnement sanitaire retenu par Etablissement Sanitaires collectifs >5 pers. Sanitaires individuels uniquement pour Univers Carcéral, Santé, EHPAD-USLD | AV4: Argumentaire détaillé (Dimensionnement unitaire + Hypothèse d'usage) | AW4: Pondération terrain / Hypothèse d’usage | AX4: Sources de dimensionnement (URL / références) | AZ4: Lavabos | BA4: Douches | BB4: Urinoirs | BC4: WC | BD4: TOTAL Pièces | BE4: Lavabos | BF4: Douches | BG4: Urinoirs | BH4: WC | BI4: TOTAL Pièces | BJ4: Lavabos | BK4: Douches | BL4: Urinoirs | BM4: WC | BO4: Mitigeurs | BP4: Tempo. Méca | BQ4: Tempo. Electro | BR4: Autres | BS4: Mitigeurs | BT4: Tempo. Méca | BU4: Tempo. Electro | BV4: Autres | BW4: Mitigeurs | BX4: Tempo. Méca | BY4: Tempo. Electro | BZ4: Mitigeurs | CA4: Tempo. Méca | CB4: Tempo. Electro | CC4: à Réservoir | CD4: Directe méca. | CE4: Directe electro indiv | CF4: Directe electro collect. | CG4: à Réservoir | CH4: Directe méca. | CI4: Directe electro indiv | CJ4: Directe electro collect. | CK4: à Réservoir | CL4: Directe mécanique | CM4: Directe electro | CN4: à Réservoir | CO4: Directe mécanique | CP4: Directe electro | CR4: Mitigeurs | CS4: Tempo. Méca | CT4: Tempo. Electro | CU4: Autres | CV4: Mitigeurs | CW4: Tempo. Méca | CX4: Tempo. Electro | CY4: à Réservoir | CZ4: Directe méca. | DA4: Directe electro indiv | DB4: Directe electro collect. | DC4: à Réservoir | DD4: Directe mécanique | DE4: Directe electro | DF4: Justification Durée de Vie réelle | DH4: Mitigeurs | DI4: Tempo. Méca | DJ4: Tempo. Electro | DK4: Autres | DL4: Justification Mix Lavabos 2025 | DM4: Mitigeurs | DN4: Tempo. Méca | DO4: Tempo. Electro | DP4: Autres | DQ4: Évolution Lavabos 2025 → 2030 | DS4: Mitigeurs | DT4: Tempo. Méca | DU4: Tempo. Electro | DV4: Justification Mix Douches 2025 | DW4: Mitigeurs | DX4: Tempo. Méca | DY4: Tempo. Electro | DZ4: Évolution Douches 2025 → 2030 | EB4: à Réservoir | EC4: Directe méca. | ED4: Directe electro indiv | EE4: Directe electro collect. | EF4: Justification Mix Urinoirs 2025 | EG4: à Réservoir | EH4: Directe méca. | EI4: Directe electro indiv | EJ4: Directe electro collect. | EK4: Évolution Urinoirs 2025 → 2030 | EM4: à Réservoir | EN4: Directe méca. | EO4: Directe electro | EP4: Justification Mix WC 2025 | EQ4: à Réservoir | ER4: Directe méca. | ES4: Directe electro | ET4: Évolution WC 2025→2030 | EV4: Split Rénovation % | EW4: Split Neuf % | EX4: Total | EY4: Rénovation | EZ4: Neuf brut | FA4: Total | FB4: Rénovation | FC4: Neuf brut | FD4: Total | FE4: Rénovation | FF4: Neuf brut | FG4: Total | FH4: Rénovation | FI4: Neuf brut | FJ4: Total | FK4: Rénovation | FL4: Neuf brut | FN4: Split % Rénovation vs. Neuf | FO4: Hypothèse % Parc 2025 rénové | FP4: Hypothèse % Réalisat° Travaux Réno | FQ4: Justification % Réalisation | FS4: Score Global (sur 5) | FT4: Classement Global sur 147 sous-segm. | FU4: Score Renovation (sur 5) | FV4: Classement sur 103 Sous-Segments | FW4: Score Neuf brut (sur 5) | FX4: Classement sur 103 Sous-Segments | FZ4: Rénovation Potentiel 2026-2030 | GA4: Neuf Potentiel 2026-2030 | GB4: Rénovation Projets Phares Programmes & Exemples 2026-2030 | GC4: Neuf Projets Phares Programmes & Exemples 2026-2030 | GD4: Rénovation Dynamique & Menaces 2026-2030 | GE4: Neuf Dynamique & Menaces 2026-2030 | GF4: Neuf & Rénovation Ventes - Dynamique & Menaces Sources & URL 2026-2030 | GH4: Total | GI4: Rénovation | GJ4: Neuf brut | GK4: Total | GL4: Rénovation | GM4: Neuf brut | GN4: Total | GO4: Rénovation | GP4: Neuf brut | GQ4: Total | GR4: Rénovation | GS4: Neuf brut | GT4: Total | GU4: Rénovation | GV4: Neuf brut | GW4: Total | GX4: Rénovation | GY4: Neuf brut | GZ4: Total | HA4: Rénovation | HB4: Neuf brut | HC4: Total | HD4: Rénovation | HE4: Neuf brut | HF4: Total | HG4: Rénovation | HH4: Neuf brut | HI4: Total | HJ4: Rénovation | HK4: Neuf brut | HL4: Total | HM4: Rénovation | HN4: Neuf brut | HO4: Total | HP4: Rénovation | HQ4: Neuf brut | HR4: Total | HS4: Rénovation | HT4: Neuf brut | HU4: Total | HV4: Rénovation | HW4: Neuf brut | HY4: Total Volumes Parc 2025 | HZ4: Entrée | IA4: Basique | IB4: Moyen | IC4: Premium | ID4: Luxe | IE4: Total Volumes Ventes 2026-2030 | IF4: Entrée | IG4: Basique | IH4: Moyen | II4: Premium | IJ4: Luxe | IK4: Score Global (sur 5) | IL4: Appréciation | IM4: Segmentation par Niveau de Confort Commentaires | IO4: Entrée | IP4: Basique | IQ4: Moyen | IR4: Premium | IS4: Luxe | IT4: Entrée | IU4: Basique | IV4: Moyen | IW4: Premium | IX4: Luxe | IY4: Entrée | IZ4: Basique | JA4: Moyen | JB4: Premium | JC4: Luxe | JD4: Entrée | JE4: Basique | JF4: Moyen | JG4: Premium | JH4: Luxe | JI4: Entrée | JJ4: Basique | JK4: Moyen | JL4: Premium | JM4: Luxe | JN4: Entrée | JO4: Basique | JP4: Moyen | JQ4: Premium | JR4: Luxe | JS4: Entrée | JT4: Basique | JU4: Moyen | JV4: Premium | JW4: Luxe | JX4: Entrée | JY4: Basique | JZ4: Moyen | KA4: Premium | KB4: Luxe | KD4: Parc | KE4: Ventes 2026-2030 | KF4: Score Global (sur 5) | KG4: Appréciation | KH4: Drivers Parc existant | KI4: Tendances Ventes 2026-2030 | KJ4: Drivers Ventes 2026-2030
A5: - | B5: - | C5: - | D5: - | E5: - | F5: - | G5: - | H5: - | I5: - | J5: - | K5: - | L5: - | M5: - | N5: - | O5: - | P5: - | Q5: - | R5: - | S5: - | T5: - | U5: - | V5: - | W5: - | X5: - | Y5: - | Z5: - | AA5: - | AB5: - | AC5: - | AD5: - | AE5: - | AF5: - | AG5: - | AH5: - | AI5: - | AJ5: - | AK5: - | AL5: - | AM5: - | AN5: - | AP5: - | AQ5: - | AR5: - | AS5: - | AU5: - | AV5: - | AW5: - | AX5: - | AZ5: - | BA5: - | BB5: - | BC5: - | BE5: - | BF5: - | BG5: - | BH5: - | BJ5: - | BK5: - | BL5: - | BM5: - | BO5: - | BP5: - | BQ5: - | BR5: - | BS5: - | BT5: - | BU5: - | BV5: - | BW5: - | BX5: - | BY5: - | BZ5: - | CA5: - | CB5: - | CC5: - | CD5: - | CE5: - | CF5: - | CG5: - | CH5: - | CI5: - | CJ5: - | CK5: - | CL5: - | CM5: - | CN5: - | CO5: - | CP5: - | CR5: - | CS5: - | CT5: - | CU5: - | CV5: - | CW5: - | CX5: - | CY5: - | CZ5: - | DA5: - | DB5: - | DC5: - | DD5: - | DE5: - | DF5: - | DH5: - | DI5: - | DJ5: - | DK5: - | DL5: - | DM5: - | DN5: - | DO5: - | DP5: - | DQ5: - | DS5: - | DT5: - | DU5: - | DV5: - | DW5: - | DX5: - | DY5: - | DZ5: - | EB5: - | EC5: - | ED5: - | EE5: - | EF5: - | EG5: - | EH5: - | EI5: - | EJ5: - | EK5: - | EM5: - | EN5: - | EO5: - | EP5: - | EQ5: - | ER5: - | ES5: - | ET5: - | EV5: - | EW5: - | EX5: - | EY5: - | EZ5: - | FA5: - | FB5: - | FC5: - | FD5: - | FE5: - | FF5: - | FG5: - | FH5: - | FI5: - | FJ5: - | FK5: - | FL5: - | FN5: - | FO5: - | FP5: - | FQ5: - | FS5: - | FT5: - | FU5: - | FV5: - | FW5: - | FX5: - | FZ5: - | GA5: - | GB5: - | GC5: - | GD5: - | GE5: - | GF5: - | GH5: - | GI5: - | GJ5: - | GK5: - | GL5: - | GM5: - | GN5: - | GO5: - | GP5: - | GQ5: - | GR5: - | GS5: - | GT5: - | GU5: - | GV5: - | GW5: - | GX5: - | GY5: - | GZ5: - | HA5: - | HB5: - | HC5: - | HD5: - | HE5: - | HF5: - | HG5: - | HH5: - | HI5: - | HJ5: - | HK5: - | HL5: - | HM5: - | HN5: - | HO5: - | HP5: - | HQ5: - | HR5: - | HS5: - | HT5: - | HU5: - | HV5: - | HW5: - | HY5: - | HZ5: - | IA5: - | IB5: - | IC5: - | ID5: - | IE5: - | IF5: - | IG5: - | IH5: - | II5: - | IJ5: - | IK5: - | IL5: - | IM5: - | IO5: - | IP5: - | IQ5: - | IR5: - | IS5: - | IT5: - | IU5: - | IV5: - | IW5: - | IX5: - | IY5: - | IZ5: - | JA5: - | JB5: - | JC5: - | JD5: - | JE5: - | JF5: - | JG5: - | JH5: - | JI5: - | JJ5: - | JK5: - | JL5: - | JM5: - | JN5: - | JO5: - | JP5: - | JQ5: - | JR5: - | JS5: - | JT5: - | JU5: - | JV5: - | JW5: - | JX5: - | JY5: - | JZ5: - | KA5: - | KB5: - | KD5: - | KE5: - | KF5: - | KG5: - | KH5: - | KI5: - | KJ5: -
B6: TOTAL | D6: TOTAL France | Q6: Total additionne lignes = 1 | R6: =IFERROR(SUMPRODUCT($Q$8:$Q$154,$AG$8:$AG$154,R$8:R$154)/SUMPRODUCT($Q$8:$Q$154,$AG$8:$AG$154),"") -> 2459.1609 | S6: =SUMPRODUCT($Q$8:$Q$154,S$8:S$154) -> 565272 | T6: =SUMPRODUCT($Q$8:$Q$154,T$8:T$154) -> 581449 | U6: =SUMPRODUCT($Q$8:$Q$154,U$8:U$154) -> 597349 | V6: =SUMPRODUCT($Q$8:$Q$154,V$8:V$154) -> 614886 | W6: =SUMPRODUCT($Q$8:$Q$154,W$8:W$154) -> 617900 | X6: =SUMPRODUCT($Q$8:$Q$154,X$8:X$154) -> 620576 | Y6: =SUMPRODUCT($Q$8:$Q$154,Y$8:Y$154) -> 624783 | Z6: =SUMPRODUCT($Q$8:$Q$154,Z$8:Z$154) -> 628795 | ... AK6: =SUMPRODUCT($Q$8:$Q$154,AK$8:AK$154) -> 647940 | AP6: =IFERROR(SUMPRODUCT($Q$21:$Q$150,$AG$21:$AG$150,AP$21:AP$150)/SUMPRODUCT($Q$21:$Q$150,$AG$21:$AG$150),"") -> 153.69949 | AQ6: =IFERROR(SUMPRODUCT($Q$8:$Q$150,$AF$8:$AF$150,AQ$8:AQ$150)/SUMPRODUCT($Q$8:$Q$150,$AF$8:$AF$150),"") -> 135.28077 | AR6: =IFERROR(SUMPRODUCT($Q$8:$Q$150,$AF$8:$AF$150,AR$8:AR$150)/SUMPRODUCT($Q$8:$Q$150,$AF$8:$AF$150),"") -> 18.072976 | AS6: =IFERROR(SUMPRODUCT($Q$8:$Q$150,$AF$8:$AF$150,AS$8:AS$150)/SUMPRODUCT($Q$8:$Q$150,$AF$8:$AF$150),"") -> 5.503625 | AU6: Moyenne pondérée / total France | AV6: Synthèse pondérée France : sanitaires collectifs >5 pers., hors individuels sauf EHPAD/USLD. | AW6: Méthode : partir d’1 minimum sanitaire réaliste, ajusté selon taille, fréquentat° probable, puis appliquer 1 moyenne pondérée terrain (éviter qu’1 cas extrême biaise le sous-segment). Enfin, correct° selon intensité d’usage : passage court, usage quotidien, activité salissante, sport, soins, etc. | AX6: Références réglementaires, guides sectoriels et hypothèses de programmation utilisés pour le programme sanitaire unitaire. | AZ6: =IFERROR(SUMPRODUCT($Q$8:$Q$150,$AF$8:$AF$150,AZ$8:AZ$150)/SUMPRODUCT($Q$8:$Q$150,$AF$8:$AF$150),"") -> 9.9092186 | BA6: =IFERROR(SUMPRODUCT($Q$8:$Q$150,$AF$8:$AF$150,BA$8:BA$150)/SUMPRODUCT($Q$8:$Q$150,$AF$8:$AF$150),"") -> 2.7928842 | BB6: =IFERROR(SUMPRODUCT($Q$8:$Q$150,$AF$8:$AF$150,BB$8:BB$150)/SUMPRODUCT($Q$8:$Q$150,$AF$8:$AF$150),"") -> 1.6893713 | BC6: =IFERROR(SUMPRODUCT($Q$8:$Q$150,$AF$8:$AF$150,BC$8:BC$150)/SUMPRODUCT($Q$8:$Q$150,$AF$8:$AF$150),"") -> 8.07789 | BD6: =SUM(BE6:BH6) -> 14135454 | BE6: =SUMPRODUCT($Q$8:$Q$150,BE$8:BE$150) -> 6233879.5 | BF6: =SUMPRODUCT($Q$8:$Q$150,BF$8:BF$150) -> 1757000.7 | BG6: =SUMPRODUCT($Q$8:$Q$150,BG$8:BG$150) -> 1062781.8 | BH6: =SUMPRODUCT($Q$8:$Q$150,BH$8:BH$150) -> 5081792.5 | BI6: =SUM(BJ6:BM6) -> 14272046 | BJ6: =SUMPRODUCT($Q$8:$Q$150,BJ$8:BJ$150) -> 6286026 | BK6: =SUMPRODUCT($Q$8:$Q$150,BK$8:BK$150) -> 1785842.1 | BL6: =SUMPRODUCT($Q$8:$Q$150,BL$8:BL$150) -> 1076541.8 | BM6: =SUMPRODUCT($Q$8:$Q$150,BM$8:BM$150) -> 5123636 | BO6: =DH6/$BE6 -> 0.30746742 | BP6: =DI6/$BE6 -> 0.52656645 | BQ6: =DJ6/$BE6 -> 0.10216087 | BR6: =DK6/$BE6 -> 0.06380525 | BS6: =DM6/$BJ6 -> 0.2764019 | BT6: =DN6/$BJ6 -> 0.53194239 | BU6: =DO6/$BJ6 -> 0.13403929 | BV6: =DP6/$BJ6 -> 0.057616411 | BW6: =DS6/$BF6 -> 0.4111116 | BX6: =DT6/$BF6 -> 0.52369723 | BY6: =DU6/$BF6 -> 0.065191171 | BZ6: =DW6/$BK6 -> 0.36880189 | CA6: =DX6/$BK6 -> 0.54850934 | CB6: =DY6/$BK6 -> 0.082688771 | CC6: =EB6/$BG6 -> 0.097009138 | CD6: =EC6/$BG6 -> 0.55065928 | CE6: =ED6/$BG6 -> 0.12918638 | CF6: =EE6/$BG6 -> 0.2231452 | CG6: =EG6/$BL6 -> 0.078718723 | CH6: =EH6/$BL6 -> 0.54543406 | CI6: =EI6/$BL6 -> 0.15522352 | CJ6: =EJ6/$BL6 -> 0.22062369 | CK6: =EM6/$BH6 -> 0.56753679 | CL6: =EN6/$BH6 -> 0.33111745 | CM6: =EO6/$BH6 -> 0.10134576 | CN6: =EQ6/$BM6 -> 0.48808905 | CO6: =ER6/$BM6 -> 0.36684788 | CP6: =ES6/$BM6 -> 0.14506307 | CR6: =IFERROR(SUMPRODUCT(DH$8:DH$150,CR$8:CR$150)/SUM(DH$8:DH$150),"") -> 12.451218 | CS6: =IFERROR(SUMPRODUCT(DI$8:DI$150,CS$8:CS$150)/SUM(DI$8:DI$150),"") -> 12.370575 | CT6: =IFERROR(SUMPRODUCT(DJ$8:DJ$150,CT$8:CT$150)/SUM(DJ$8:DJ$150),"") -> 9.0777439 | CU6: =IFERROR(SUMPRODUCT(DK$8:DK$150,CU$8:CU$150)/SUM(DK$8:DK$150),"") -> 10.91947 | CV6: =IFERROR(SUMPRODUCT(DS$8:DS$150,CV$8:CV$150)/SUM(DS$8:DS$150),"") -> 11.159253 | CW6: =IFERROR(SUMPRODUCT(DT$8:DT$150,CW$8:CW$150)/SUM(DT$8:DT$150),"") -> 9.6708083 | CX6: =IFERROR(SUMPRODUCT(DU$8:DU$150,CX$8:CX$150)/SUM(DU$8:DU$150),"") -> 8.1136961 | CY6: =IFERROR(SUMPRODUCT(EB$8:EB$150,CY$8:CY$150)/SUM(EB$8:EB$150),"") -> 10.234244 | CZ6: =IFERROR(SUMPRODUCT(EC$8:EC$150,CZ$8:CZ$150)/SUM(EC$8:EC$150),"") -> 12.081781 | DA6: =IFERROR(SUMPRODUCT(ED$8:ED$150,DA$8:DA$150)/SUM(ED$8:ED$150),"") -> 8.4232915 | DB6: =IFERROR(SUMPRODUCT(EE$8:EE$150,DB$8:DB$150)/SUM(EE$8:EE$150),"") -> 10.014847 | DC6: =IFERROR(SUMPRODUCT(EM$8:EM$150,DC$8:DC$150)/SUM(EM$8:EM$150),"") -> 12.484874 | DD6: =IFERROR(SUMPRODUCT(EN$8:EN$150,DD$8:DD$150)/SUM(EN$8:EN$150),"") -> 12.506452 | DE6: =IFERROR(SUMPRODUCT(EO$8:EO$150,DE$8:DE$150)/SUM(EO$8:EO$150),"") -> 9.1471231 | DF6: La durée de vie réelle dépend surtout de l’usage, de la maintenance, du vandalisme et du mode de rénovation, plus que de la durée théorique fabricant. Plus courte dans les sites à fort trafic ou à fortes contraintes d’hygiène, plus longue dans les environnements plus calmes. Les équipements mécaniques robustes tiennent souvent bien dans les usages intensifs, tandis que les solutions électroniques peuvent être renouvelées plus tôt pour raisons de capteurs, batteries, électrovannes ou modernisation. Part importante des remplacements se fait par lots ou lors de rénovations, pas seulement à la panne. | DH6: =SUMPRODUCT($Q$8:$Q$150,DH$8:DH$150) -> 1916714.9 | DI6: =SUMPRODUCT($Q$8:$Q$150,DI$8:DI$150) -> 3282551.8 | DJ6: =SUMPRODUCT($Q$8:$Q$150,DJ$8:DJ$150) -> 636858.58 | DK6: =SUMPRODUCT($Q$8:$Q$150,DK$8:DK$150) -> 397754.24 | DL6: La temporisation mécanique reste structurante dans les parcs intensifs ; la bascule 2025→2030 se fait surtout au profit de l'électronique sur les rénovations lourdes et les bâtiments tertiaires/publics. | DM6: =SUMPRODUCT($Q$8:$Q$150,DM$8:DM$150) -> 1737469.6 | DN6: =SUMPRODUCT($Q$8:$Q$150,DN$8:DN$150) -> 3343803.7 | DO6: =SUMPRODUCT($Q$8:$Q$150,DO$8:DO$150) -> 842574.49 | DP6: =SUMPRODUCT($Q$8:$Q$150,DP$8:DP$150) -> 362178.26 | DQ6: Dominant, le mitigeur recule, à chaque rénovation prévue et en neuf. Le tempo méca. résiste bien (vs. électro=> budget, installat°, entretien), mais électronique remplace en grande majorité le mitigeur (à nuancer en fonction du type d'ERP). | DS6: =SUMPRODUCT($Q$8:$Q$150,DS$8:DS$150) -> 722323.36 | DT6: =SUMPRODUCT($Q$8:$Q$150,DT$8:DT$150) -> 920136.39 | DU6: =SUMPRODUCT($Q$8:$Q$150,DU$8:DU$150) -> 114540.93 | DV6: Parc dominé par le tempo. mécanique et distance en nombre les mitigeurs. Electronique 5 à 6 fois moins représenté (que mécanique) => usage plus long, détection moins fiable que lavabo, moins de confort thermique potentiel. | DW6: =SUMPRODUCT($Q$8:$Q$150,DW$8:DW$150) -> 658621.92 | DX6: =SUMPRODUCT($Q$8:$Q$150,DX$8:DX$150) -> 979551.05 | DY6: =SUMPRODUCT($Q$8:$Q$150,DY$8:DY$150) -> 147669.09 | DZ6: Hausse 'électronique plus graduelle (qu'en lavabo) et variable selon ERP (exemple : plus forte sur tertiaire, commerce, que sur univers carcéral). | EB6: =SUMPRODUCT($Q$8:$Q$150,EB$8:EB$150) -> 103099.55 | EC6: =SUMPRODUCT($Q$8:$Q$150,EC$8:EC$150) -> 585230.66 | ED6: =SUMPRODUCT($Q$8:$Q$150,ED$8:ED$150) -> 137296.93 | EE6: =SUMPRODUCT($Q$8:$Q$150,EE$8:EE$150) -> 237154.66 | EF6: Parc dominé par tempo méca : robustesse, simplicité, adaptation aux usages intensifs. Electronique progresse mais reste minoritaire, freinée par contraintes maintenance/coût. | EG6: =SUMPRODUCT($Q$8:$Q$150,EG$8:EG$150) -> 84743.991 | EH6: =SUMPRODUCT($Q$8:$Q$150,EH$8:EH$150) -> 587182.54 | EI6: =SUMPRODUCT($Q$8:$Q$150,EI$8:EI$150) -> 167104.6 | EJ6: =SUMPRODUCT($Q$8:$Q$150,EJ$8:EJ$150) -> 237510.62 | EK6: Part temporisé électro. augmente légèrement => enjeux hygiène sans contact + maîtrise de conso. eau. Mécanique recule légèrement mais reste majoritaire => fiabilité en usage intensif. | EM6: =SUMPRODUCT($Q$8:$Q$150,EM$8:EM$150) -> 2884104.2 | EN6: =SUMPRODUCT($Q$8:$Q$150,EN$8:EN$150) -> 1682670.2 | EO6: =SUMPRODUCT($Q$8:$Q$150,EO$8:EO$150) -> 515018.14 | EP6: Parc WC repose surtout sur systèmes gravitaires, mécaniques, robustes, économiques, faciles à maintenir. Electronique secondaire mais présent dans lieux premium ou à forte exigence sanitaire. | EQ6: =SUMPRODUCT($Q$8:$Q$150,EQ$8:EQ$150) -> 2500790.6 | ER6: =SUMPRODUCT($Q$8:$Q$150,ER$8:ER$150) -> 1879595 | ES6: =SUMPRODUCT($Q$8:$Q$150,ES$8:ES$150) -> 743250.35 | ET6: Electronique gagne du terrain, surtout sur ERP récents-rénovés => exigences hygiène + automatisation => Progression faible : solutions méca conservent avantage coût/fiabilité. | EV6: =IFERROR(EY6/EX6,0) -> 0.79649155 | EW6: =IFERROR(EZ6/EX6,0) -> 0.20350845 | EX6: =EY6+EZ6 -> 5836549.9 | EY6: =SUM(FB6,FE6,FH6,FK6) -> 4648762.7 | EZ6: =SUM(FC6,FF6,FI6,FL6) -> 1187787.2 | FA6: =SUMPRODUCT($Q$8:$Q$150,FA$8:FA$150) -> 2513613 | FB6: =SUMPRODUCT($Q$8:$Q$150,FB$8:FB$150) -> 1999994.1 | FC6: =SUMPRODUCT($Q$8:$Q$150,FC$8:FC$150) -> 513618.91 | FD6: =SUMPRODUCT($Q$8:$Q$150,FD$8:FD$150) -> 864298.25 | FE6: =SUMPRODUCT($Q$8:$Q$150,FE$8:FE$150) -> 699040.65 | FF6: =SUMPRODUCT($Q$8:$Q$150,FF$8:FF$150) -> 165257.61 | FG6: =SUMPRODUCT($Q$8:$Q$150,FG$8:FG$150) -> 452474.42 | FH6: =SUMPRODUCT($Q$8:$Q$150,FH$8:FH$150) -> 361251.34 | ... FL6: =SUMPRODUCT($Q$8:$Q$150,FL$8:FL$150) -> 417687.61 | FN6: Agrégat Pondéré | FO6: =IFERROR(SUMPRODUCT($Q$8:$Q$150,$AF$8:$AF$150,$FO$8:$FO$150)/SUMPRODUCT($Q$8:$Q$150,$AF$8:$AF$150),"") -> 0.060675716 | FP6: =IFERROR(SUMPRODUCT($Q$8:$Q$150,$AF$8:$AF$150,$FP$8:$FP$150)/SUMPRODUCT($Q$8:$Q$150,$AF$8:$AF$150),"") -> 0.82880687 | FQ6: Taux moyen pondéré France de matérialisation des travaux sur 2026-2030. | FS6: 3.19 | FT6: - | FU6: 3.97 | FV6: - | FW6: 2.24 | FX6: - | FZ6: La rénovation domine et reste plus résiliente que le neuf, dépendant moins de créations nettes d’établissements que de cycles de remplacement incompressibles, de remises à niveau d’hygiène/usage et de travaux diffus sur un parc installé très vaste et largement assujetti à des cycles de remplacement / mise à niveau. Sous-segments phares => Restaurants, EHPAD, Bureaux >50 pers., Écoles primaires, Gymnases, Salles multisports et Mairies. | GA6: Neuf plus sélectif, dépendant des cycles économiques, porté par créations d’établissements + programmes publics-privés (santé, sport, France services, industrie, carcéral, aéroports). Rythme plus volatil, concentré sur projets structurants. Sous-segments phares en neuf => Bureaux, EHPAD, Hôtels, Enseignement supérieur, Santé, Equipements sportifs. | GB6: Fonds vert / EduRénov ; Modernisation Hôpitaux (Ségur phase 2), Plan CNSA (réhab. EHPAD ; Normes accessibilité (Ad’AP)), Réno 5000 équipements sportifs (JO héritage) ; Loi de Programmation Militaire ; Transformation tertiaire ESG, France services. | GC6: Prison : plan 15 000 places, Grands projets touristiques (resorts, parcs), Nouveaux hôpitaux + CHU (reconstructions), Cliniques privées + Pôles santé, Maisons de santé pluriprofessionnelles, Campus universitaires, Learning centers, Nouveaux terminaux aéroport, Logistique, entrepôts. | GD6: Soutenue par décret Éco Énergie Tertiaire (EET) + Age avancé du parc + Logiques d’interventions par lots (sanitaires dans projets + larges : énergie, accessibilité, mise normes). Socle Investissements publics stable + Obligations réglementaires progressives => Marché résilient, diffus, peu dépendant de cycles économiques courts | GE6: Dynamique positive, concentrée sur filières motrices (santé, enseignement sup, segments tertiaires). Forte dépendance : arbitrage budget public, décision invest. privé. Sensible => cycles éco, condit° financement, délais réalisat°. Ecart fréquent intentions vs. livraisons réelles => croissance + volatile - homogène, ciblée géographiquement | GF6: =HYPERLINK("https://www.ecologie.gouv.fr/eco-energie-tertiaire-eet","https://www.ecologie.gouv.fr/eco-energie-tertiaire-eet")&CHAR(10)&HYPERLINK("https://www.info.gouv.fr/actualite/segur-de-la-sante-de-nouveaux-investissements-pour-l-hopital","https://www.info.gouv.fr/actualite/segur-de-la-sante-de-nouveaux-investissements-pour-l-hopital")&CHAR(10)&HYPERLINK("https://www.cnsa.fr/budget-et-financement/financement-des-esms/investissement-immobilier","https://www.cnsa.fr/budget-et-financement/financement-des-esms/investissement-immobilier")&CHAR(10)&HYPERLINK("https://www.agencedusport.fr/plan-5000-equipements-generation-2024","https://www.agencedusport.fr/plan-5000-equipements-generation-2024")&CHAR(10)&HYPERLINK("https://www.france-services.gouv.fr/actualites/labellisation-nouvelles-maisons-france-services","https://www.france-services.gouv.fr/actualites/labellisation-nouvelles-maisons-france-services")&CHAR(10)&HYPERLINK("https://www.justice.gouv.fr/plan-15-000-places-prison","https://www.justice.gouv.fr/plan-15-000-places-prison")&CHAR(10)&HYPERLINK("https://www.defense.gouv.fr/ministere/politique-defense/loi-programmation-militaire-2024-2030","https://www.defense.gouv.fr/ministere/politique-defense/loi-programmation-militaire-2024-2030")&CHAR(10)&HYPERLINK("https://www.economie.gouv.fr/cedef/reindustrialisation-informations","https://www.economie.gouv.fr/cedef/reindustrialisation-informations")&CHAR(10)&HYPERLINK("https://presse.groupeadp.fr/proposition-cre2027-2034/","https://presse.groupeadp.fr/proposition-cre2027-2034/")&CHAR(10)&HYPERLINK("https://www.garesetconnexions.sncf/fr/qui-sommes-nous/notre-modele-economique","https://www.garesetconnexions.sncf/fr/qui-sommes-nous/notre-modele-economique") -> https://www.ecologie.gouv.fr/eco-energie-tertiaire-eet https://www.info.gouv.fr/actualite/segur-de-la-sante-de-nouveaux-investissements-pour-l-hopital https://www.cnsa.fr/budget-et-financement/financement-des-esms/investissement-immobilier https://www.agencedusport.fr/plan-5000-equipements-generation-2024 https://www.france-services.gouv.fr/actualites/labellisation-nouvelles-maisons-france-services https://www.justice.gouv.fr/plan-15-000-places-prison https://www.defense.gouv.fr/ministere/politique-defense/loi-programmation-militaire-2024-2030 https://www.economie.gouv.fr/cedef/reindustrialisation-informations https://presse.groupeadp.fr/proposition-cre2027-2034/ https://www.garesetconnexions.sncf/fr/qui-sommes-nous/notre-modele-economique | GH6: =SUMPRODUCT($Q$8:$Q$150,GH$8:GH$150) -> 736675.38 | GI6: =SUMPRODUCT($Q$8:$Q$150,GI$8:GI$150) -> 601284.94 | GJ6: =SUMPRODUCT($Q$8:$Q$150,GJ$8:GJ$150) -> 135390.44 | GK6: =SUMPRODUCT($Q$8:$Q$150,GK$8:GK$150) -> 1258583.4 | GL6: =SUMPRODUCT($Q$8:$Q$150,GL$8:GL$150) -> 979983.18 | GM6: =SUMPRODUCT($Q$8:$Q$150,GM$8:GM$150) -> 278600.21 | GN6: =SUMPRODUCT($Q$8:$Q$150,GN$8:GN$150) -> 343723.06 | GO6: =SUMPRODUCT($Q$8:$Q$150,GO$8:GO$150) -> 274441.61 | ... HW6: =SUMPRODUCT($Q$8:$Q$150,HW$8:HW$150) -> 62426.715 | HY6: =SUM(HZ6:ID6) -> 14135454 | HZ6: =IFERROR(IO6*BE6,0)+IFERROR(IY6*BF6,0)+IFERROR(JI6*BG6,0)+IFERROR(JS6*BH6,0) -> 865403.9 | IA6: =IFERROR(IP6*BE6,0)+IFERROR(IZ6*BF6,0)+IFERROR(JJ6*BG6,0)+IFERROR(JT6*BH6,0) -> 5140157.6 | IB6: =IFERROR(IQ6*BE6,0)+IFERROR(JA6*BF6,0)+IFERROR(JK6*BG6,0)+IFERROR(JU6*BH6,0) -> 5839913 | IC6: =IFERROR(IR6*BE6,0)+IFERROR(JB6*BF6,0)+IFERROR(JL6*BG6,0)+IFERROR(JV6*BH6,0) -> 2040655.4 | ID6: =IFERROR(IS6*BE6,0)+IFERROR(JC6*BF6,0)+IFERROR(JM6*BG6,0)+IFERROR(JW6*BH6,0) -> 249324.51 | IE6: =SUM(IF6:IJ6) -> 4648762.7 | IF6: =IFERROR(IT6*FB6,0)+IFERROR(JD6*FE6,0)+IFERROR(JN6*FH6,0)+IFERROR(JX6*FK6,0) -> 121263.17 | IG6: =IFERROR(IU6*FB6,0)+IFERROR(JE6*FE6,0)+IFERROR(JO6*FH6,0)+IFERROR(JY6*FK6,0) -> 1193269.2 | IH6: =IFERROR(IV6*FB6,0)+IFERROR(JF6*FE6,0)+IFERROR(JP6*FH6,0)+IFERROR(JZ6*FK6,0) -> 2112628.7 | II6: =IFERROR(IW6*FB6,0)+IFERROR(JG6*FE6,0)+IFERROR(JQ6*FH6,0)+IFERROR(KA6*FK6,0) -> 1043623.5 | IJ6: =IFERROR(IX6*FB6,0)+IFERROR(JH6*FE6,0)+IFERROR(JR6*FH6,0)+IFERROR(KB6*FK6,0) -> 177978.12 | IK6: 3.86 | IL6: Bonne | IO6: 0.0507 | IP6: 0.3489 | IQ6: 0.4319 | IR6: 0.1497 | IS6: 0.0188 | IT6: 0.02 | IU6: 0.2326 | IV6: 0.4683 | IW6: 0.2376 | IX6: 0.0415 | IY6: 0.072 | IZ6: 0.3519 | JA6: 0.384 | JB6: 0.1679 | JC6: 0.0242 | JD6: 0.0355 | JE6: 0.2767 | JF6: 0.4095 | JG6: 0.2317 | JH6: 0.0466 | JI6: 0.1234 | JJ6: 0.4706 | JK6: 0.3199 | JL6: 0.0759 | JM6: 0.0102 | JN6: 0.056 | JO6: 0.3741 | JP6: 0.4166 | JQ6: 0.1327 | JR6: 0.0206 | JS6: 0.0574 | JT6: 0.3634 | JU6: 0.4197 | JV6: 0.144 | JW6: 0.0155 | JX6: 0.0228 | JY6: 0.2515 | JZ6: 0.4654 | KA6: 0.2257 | KB6: 0.0346 | KD6: ±4 pts | KE6: ±5 pts | KF6: 4.15 | KG6: Bonne | KH6: Agrégation volume × mix par sous-segment ; les gros gisements (bureaux, écoles, santé, sport, hôtels, transports) pèsent davantage dans le total que les niches. | KI6: Total France pondéré par volumes 2025 et ventes 2026-2030 ; forte fréquentation tire le standard, image/privé tire premium, contrainte sanitaire renforce surtout le milieu de gamme technique. | KJ6: Agrégation volume × ventes 2026-2030 ; le neuf et les rénovations lourdes tirent le mix vers l’moyen/premium, mais la rénovation majoritaire garde un centre de gravité basique/moyen.
Q7: 0 = sous-catég. | S7: Variat° Annuelle en % => | T7: =(T6/S6)^(1/(T4-S4))-1 -> 0.0056591996 | U7: =(U6/T6)^(1/(U4-T4))-1 -> 0.0054102364 | V7: =(V6/U6)^(1/(V4-U4))-1 -> 0.005803848 | W7: =W6/V6-1 -> 0.0049017216 | X7: =X6/W6-1 -> 0.0043307979 | Y7: =Y6/X6-1 -> 0.0067791858 | Z7: =Z6/Y6-1 -> 0.0064214295 | AA7: =AA6/Z6-1 -> -0.01333662 | AB7: =AB6/AA6-1 -> -0.00053835454 | AC7: =AC6/AB6-1 -> 0.010793856 | AD7: =AD6/AC6-1 -> 0.0076870549 | ... AK7: =AK6/AJ6-1 -> 0.0021901739 | BH7: Variat° Annuelle en % => | BI7: =(BI6/BD6)^(1/(2030-2025))-1 -> 0.0019251791 | BJ7: =(BJ6/BE6)^(1/(2030-2025))-1 -> 0.0016674332 | BK7: =(BK6/BF6)^(1/(2030-2025))-1 -> 0.0032616772 | BL7: =(BL6/BG6)^(1/(2030-2025))-1 -> 0.0025761145 | BM7: =(BM6/BH6)^(1/(2030-2025))-1 -> 0.0016414035 | DH7: =DH6/SUM(DH6:DK6) -> 0.30746742 | DI7: =DI6/SUM(DH6:DK6) -> 0.52656645 | DJ7: =DJ6/SUM(DH6:DK6) -> 0.10216087 | DK7: =DK6/SUM(DH6:DK6) -> 0.06380525 | DL7: <= Split en % => | DM7: =DM6/SUM(DM6:DP6) -> 0.2764019 | DN7: =DN6/SUM(DM6:DP6) -> 0.53194239 | DO7: =DO6/SUM(DM6:DP6) -> 0.13403929 | DP7: =DP6/SUM(DM6:DP6) -> 0.057616411 | DS7: =DS6/SUM(DS6:DU6) -> 0.4111116 | DT7: =DT6/SUM(DS6:DU6) -> 0.52369723 | DU7: =DU6/SUM(DS6:DU6) -> 0.065191171 | DV7: <= Split en % => | DW7: =DW6/SUM(DW6:DY6) -> 0.36880189 | DX7: =DX6/SUM(DW6:DY6) -> 0.54850934 | DY7: =DY6/SUM(DW6:DY6) -> 0.082688771 | EB7: =EB6/SUM(EB6:EE6) -> 0.097009138 | EC7: =EC6/SUM(EB6:EE6) -> 0.55065928 | ED7: =ED6/SUM(EB6:EE6) -> 0.12918638 | EE7: =EE6/SUM(EB6:EE6) -> 0.2231452 | EF7: <= Split en % => | EG7: =EG6/SUM(EG6:EJ6) -> 0.078718723 | EH7: =EH6/SUM(EG6:EJ6) -> 0.54543406 | EI7: =EI6/SUM(EG6:EJ6) -> 0.15522352 | EJ7: =EJ6/SUM(EG6:EJ6) -> 0.22062369 | EM7: =EM6/SUM(EL6:EO6) -> 0.56753679 | EN7: =EN6/SUM(EL6:EO6) -> 0.33111745 | EO7: =EO6/SUM(EL6:EO6) -> 0.10134576 | EP7: <= Split en % => | EQ7: =EQ6/SUM(EQ6:ES6) -> 0.48808905 | ER7: =ER6/SUM(EQ6:ES6) -> 0.36684788 | ES7: =ES6/SUM(EQ6:ES6) -> 0.14506307 | EX7: Split en % => | EY7: =EY6/EX6 -> 0.79649155 | EZ7: =EZ6/EX6 -> 0.20350845 | FB7: =FB6/FA6 -> 0.79566508 | FC7: =FC6/FA6 -> 0.20433492 | FE7: =FE6/FD6 -> 0.80879563 | FF7: =FF6/FD6 -> 0.19120437 | FH7: =FH6/FG6 -> 0.79839064 | FI7: =FI6/FG6 -> 0.20160936 | FK7: =FK6/FJ6 -> 0.7917979 | FL7: =FL6/FJ6 -> 0.2082021 | GH7: Split en % => | GI7: =GI6/GH6 -> 0.81621425 | GJ7: =GJ6/GH6 -> 0.18378575 | GL7: =GL6/GK6 -> 0.77863985 | GM7: =GM6/GK6 -> 0.22136015 | GO7: =GO6/GN6 -> 0.79843815 | GP7: =GP6/GN6 -> 0.20156185 | GR7: =GR6/GQ6 -> 0.82622344 | GS7: =GS6/GQ6 -> 0.17377656 | GU7: =GU6/GT6 -> 0.8196153 | GV7: =GV6/GT6 -> 0.1803847 | GX7: =GX6/GW6 -> 0.80391269 | GY7: =GY6/GW6 -> 0.19608731 | HA7: =HA6/GZ6 -> 0.78957635 | HB7: =HB6/GZ6 -> 0.21042365 | HD7: =HD6/HC6 -> 0.84125108 | HE7: =HE6/HC6 -> 0.15874892 | HG7: =HG6/HF6 -> 0.78095827 | HH7: =HH6/HF6 -> 0.21904173 | HJ7: =HJ6/HI6 -> 0.80710178 | HK7: =HK6/HI6 -> 0.19289822 | HM7: =HM6/HL6 -> 0.81177676 | HN7: =HN6/HL6 -> 0.18822324 | HP7: =HP6/HO6 -> 0.81394148 | HQ7: =HQ6/HO6 -> 0.18605852 | HS7: =HS6/HR6 -> 0.7602412 | HT7: =HT6/HR6 -> 0.2397588 | HV7: =HV6/HU6 -> 0.78263105 | HW7: =HW6/HU6 -> 0.21736895 | HY7: Split en % => | HZ7: =HZ6/HY6 -> 0.06122222 | IA7: =IA6/HY6 -> 0.36363582 | IB7: =IB6/HY6 -> 0.41313939 | IC7: =IC6/HY6 -> 0.14436433 | ID7: =ID6/HY6 -> 0.017638238 | IF7: =IF6/IE6 -> 0.026085041 | IG7: =IG6/IE6 -> 0.25668533 | IH7: =IH6/IE6 -> 0.45444968 | II7: =II6/IE6 -> 0.2244949 | IJ7: =IJ6/IE6 -> 0.038285051 | IS7: Evolutions en Pts => | IT7: =(IT6-IO6)*100 -> -3.07 | IU7: =(IU6-IP6)*100 -> -11.63 | IV7: =(IV6-IQ6)*100 -> 3.64 | IW7: =(IW6-IR6)*100 -> 8.79 | IX7: =(IX6-IS6)*100 -> 2.27 | JC7: Evolutions en Pts => | JD7: =(JD6-IY6)*100 -> -3.65 | JE7: =(JE6-IZ6)*100 -> -7.52 | JF7: =(JF6-JA6)*100 -> 2.55 | JG7: =(JG6-JB6)*100 -> 6.38 | JH7: =(JH6-JC6)*100 -> 2.24 | JM7: Evolutions en Pts => | JN7: =(JN6-JI6)*100 -> -6.74 | JO7: =(JO6-JJ6)*100 -> -9.65 | JP7: =(JP6-JK6)*100 -> 9.67 | JQ7: =(JQ6-JL6)*100 -> 5.68 | JR7: =(JR6-JM6)*100 -> 1.04 | JW7: Evolutions en Pts => | JX7: =(JX6-JS6)*100 -> -3.46 | JY7: =(JY6-JT6)*100 -> -11.19 | JZ7: =(JZ6-JU6)*100 -> 4.57 | KA7: =(KA6-JV6)*100 -> 8.17 | KB7: =(KB6-JW6)*100 -> 1.91
A8: 1 | B8: Enfance, Enseignement, Jeunesse & Formation | C8: Petite enfance | D8: Crèches | E8: R | F8: ERP | G8: ERP | H8: oui | I8: Établissements d’éveil / petite enfance recevant du public. | J8: Crèche municipale, micro-crèche | K8: non | L8: oui | M8: Site Etablissement principal | N8: proxy public / estimation encadrée | O8: Elevé | Q8: 1 | R8: 300 | S8: 10429 | T8: 12090 | U8: 14016 | V8: 16248 | W8: 16735 | X8: 17237 | Y8: 17754 | Z8: 18287 | AA8: 18561 | AB8: 18839 | AC8: 19122 | AD8: 19409 | AE8: 19700 | AF8: 19995 | AG8: 20100 | AH8: 20180 | AI8: 20220 | AJ8: 20220 | AK8: 20180 | AL8: Ancrage sur l’Onape/Cnaf : l’offre crèches progresse en 2024 grâce aux micro-crèches financées par Paje (+9,9 %) et les Caf financent 11 500 crèches PSU (2024) ; la projection prolonge cette dynamique sans surestimer le marché. | AM8: ancrage DREES 2023 sur les EAJE, puis prolongement 2024-2026. Dynamique projetée 2027-2030: hausse modérée. Fiabilité: moyenne. | AN8: https://drees.solidarites-sante.gouv.fr/communique-de-presse-jeux-de-donnees/jeux-de-donnees/250528_DATA_donnees-departementales-sur-l-offre-daccueil-du-jeune-enfant-2023 | AP8: 40 | AQ8: 31 | AR8: 8 | AS8: 1 | AU8: Bloc enfants + bloc adultes ; comptage limité aux sanitaires collectifs, sans cabine individuelle. | AV8: Capacité type ≈ 31 usagers principaux + 8 staff + 1 parents/accompagnants. Le programme sanitaire est construit par blocs fonctionnels plausibles (public, personnel, exploitation/hébergement selon le cas) et non par simple ratio national moyen. Calibrage selon capacité simultanée, répartition de flux et organisation réelle du site. | AW8: Profil petit, capacité moyenne ≈ 40 personnes. Moyenne pondérée terrain : parc majoritairement petits/moyens sites, grands sites intégrés sans surpondération ; usage 2025 modérée. | AX8: Code du travail (sanitaires et vestiaires staff) + programmation ERP/usages d'exploitation ; source de comptage propre à la ligne en col. AP. | AZ8: 6 | BA8: 0.245 | BB8: 0 | BC8: 6 | BD8: =SUM(BE8:BH8) -> 244838.77 | BE8: =AF8*AZ8 -> 119970 | BF8: =AF8*BA8 -> 4898.775 | BG8: =AF8*BB8 -> 0 | BH8: =AF8*BC8 -> 119970 | BI8: =SUM(BJ8:BM8) -> 247104.1 | BJ8: =AK8*AZ8 -> 121080 | BK8: =AK8*BA8 -> 4944.1 | BL8: =AK8*BB8 -> 0 | BM8: =AK8*BC8 -> 121080 | BO8: 0.5 | BP8: 0.42 | BQ8: 0.04 | BR8: 0.04 | BS8: 0.48 | BT8: 0.42 | BU8: 0.06 | BV8: 0.04 | BW8: 0.9 | BX8: 0.08 | BY8: 0.02 | BZ8: 0.88 | CA8: 0.09 | CB8: 0.03 | CK8: 0.85 | CL8: 0.15 | CN8: 0.8 | CO8: 0.18 | CP8: 0.02 | CR8: 14 | CS8: 13 | CT8: 10 | CU8: 12 | CV8: 13 | CW8: 12 | CX8: 9 | DC8: 15 | DD8: 15 | DE8: 12 | DF8: Usage très régulier avec nettoyage fréquent et petites dégradations usuelles. Les temporisés mécaniques gardent un avantage tangible sur les mitigeurs en environnement partagé. L'électronique est abaissée car les cellules, alimentations et réglages vieillissent plus vite que les organes purement mécaniques. Rénovation souvent par blocs lors des vacances scolaires. Enseignement intensif sous contrainte budgétaire : Pics interclasses, usage quotidien élevé, vandalisme modéré et budgets publics souvent lissés. Le temporisé et la chasse directe tiennent mieux que le manuel/réservoir en usage intensif. | DH8: =$BE8*BO8 -> 59985 | DI8: =$BE8*BP8 -> 50387.4 | DJ8: =$BE8*BQ8 -> 4798.8 | DK8: =$BE8*BR8 -> 4798.8 | DL8: Parc commun plutôt petit et assisté : le mitigeur manuel reste majoritaire sur les lave-mains enfants/adultes, avec une part de temporisé sur zones personnel/usage intensif ; l’électronique reste marginale. Ajustement ciblé 2025 : légère baisse du mitigeur et/ou légère hausse de l’électronique pour mieux refléter la modernisation déjà visible sur les rénovations de sanitaires communs. | DM8: =$BJ8*BS8 -> 58118.4 | DN8: =$BJ8*BT8 -> 50853.6 | DO8: =$BJ8*BU8 -> 7264.8 | DP8: =$BJ8*BV8 -> 4843.2 | DQ8: Évolution modérée d’ici 2030 : le mitigeur recule un peu au profit du temporisé/électronique, mais le parc reste très manuel sur les points enfants et le renouvellement est lent. | DS8: =$BF8*BW8 -> 4408.8975 | DT8: =$BF8*BX8 -> 391.902 | DU8: =$BF8*BY8 -> 97.9755 | DV8: Sans objet. | DW8: =$BK8*BZ8 -> 4350.808 | DX8: =$BK8*CA8 -> 444.969 | DY8: =$BK8*CB8 -> 148.323 | DZ8: Sans objet. | EB8: =$BG8*CC8 -> 0 | EC8: =$BG8*CD8 -> 0 | ED8: =$BG8*CE8 -> 0 | EE8: =$BG8*CF8 -> 0 | EF8: Sans objet. | EG8: =$BL8*CG8 -> 0 | EH8: =$BL8*CH8 -> 0 | EI8: =$BL8*CI8 -> 0 | EJ8: =$BL8*CJ8 -> 0 | EK8: Sans objet. | EM8: =$BH8*CK8 -> 101974.5 | EN8: =$BH8*CL8 -> 17995.5 | EO8: =$BH8*CM8 -> 0 | EP8: Les WC restent très majoritairement à réservoir sur ce parc, plus simple et plus proche d’un usage d’habitat collectif ; la chasse directe reste minoritaire. | EQ8: =$BM8*CN8 -> 96864 | ER8: =$BM8*CO8 -> 21794.4 | ES8: =$BM8*CP8 -> 2421.6 | ET8: Les WC restent très majoritairement à réservoir ; la chasse directe gagne un peu de terrain mais sans renverser le parc d’ici 2030. | EV8: =IFERROR(EY8/EX8,0) -> 0.80146255 | EW8: =IFERROR(EZ8/EX8,0) -> 0.19853745 | EX8: =EY8+EZ8 -> 54979.446 | EY8: =SUM(FB8,FE8,FH8,FK8) -> 44063.967 | EZ8: =SUM(FC8,FF8,FI8,FL8) -> 10915.479 | FA8: =FB8+FC8 -> 26939.704 | FB8: =SUM(GI8,GL8,GO8,GR8) -> 21591.164 | FC8: =MAX(0,$BJ8-$BE8)+$BE8*$FO8 -> 5348.5401 | FD8: =FE8+FF8 -> 1100.0379 | FE8: =SUM(GU8,GX8,HA8) -> 881.6392 | FF8: =MAX(0,$BK8-$BF8)+$BF8*$FO8 -> 218.39872 | FG8: =FH8+FI8 -> 0 | FH8: =SUM(HD8,HG8,HJ8,HM8) -> 0 | FI8: =MAX(0,$BL8-$BG8)+$BG8*$FO8 -> 0 | FJ8: =FK8+FL8 -> 26939.704 | FK8: =SUM(HP8,HS8,HV8) -> 21591.164 | FL8: =MAX(0,$BM8-$BH8)+$BH8*$FO8 -> 5348.5401 | FN8: Moyenne | FO8: 0.03533 | FP8: 0.8728 | FQ8: 87,3% retenu : part des besoins réellement transformée en travaux sur 2026-2030 après prise en compte des budgets, du phasage et des arbitrages locaux. | FS8: 3.41 | FT8: =RANK($FS8,$FS$8:$FS$154,0)+COUNTIF($FS$8:$FS8,$FS8)-1 -> 54 | FU8: 3.9 | FV8: =RANK($FU8,$FU$8:$FU$154,0)+COUNTIF($FU$8:$FU8,$FU8)-1 -> 95 | FW8: 2.82 | FX8: =RANK($FW8,$FW$8:$FW$154,0)+COUNTIF($FW$8:$FW8,$FW8)-1 -> 12 | FZ8: Potentiel rénovation élevé : remise à niveau des blocs enfants/personnel, exigences d’hygiène et d’usage intensif, souvent intégrées à des travaux communaux ou délégations de service public. Les volumes restent d’abord tirés par les WC et les lavabos, plus que par les postes spécialisés. En rénovation, le marché reste favorable aux gammes robustes et simples d’entretien, compatibles avec des chantiers par tranches et des budgets contraints. | GA8: Potentiel neuf moyen à soutenu : créations et extensions encore réelles via le service public de la petite enfance, les micro-crèches et les territoires en tension, mais freinées par les coûts d’exploitation et la pénurie de personnels. Le neuf est significatif mais encore nettement inférieur à la rénovation. | GB8: Projets phares réno : réfection de blocs enfants/adultes, espaces de change et douches ponctuelles, adaptation climatique, accessibilité et reprises sanitaires lors de rénovations thermiques. | GC8: Projets phares neuf : micro-crèches, crèches municipales/associatives, créations en quartiers neufs ou opérations mixtes, extensions de capacité lorsque le besoin local est documenté. | GD8: Dynamique réno 2026-2030 : soutenue et régulière, car les communes et gestionnaires arbitrent plus facilement des travaux ciblés que des créations nettes. Menaces : budget communal, tension sur l’exploitation et travaux en site occupé. | GE8: Dynamique neuf 2026-2030 : réelle mais sélective ; la volonté politique existe avec le service public de la petite enfance, mais l’écart entre besoin théorique, financement et mise en service effective peut rester marqué. | GF8: =HYPERLINK("https://solidarites.gouv.fr/le-service-public-de-la-petite-enfance-garantir-un-accueil-de-qualite-tous-les-enfants-et-leurs-familles","https://solidarites.gouv.fr/le-service-public-de-la-petite-enfance-garantir-un-accueil-de-qualite-tous-les-enfants-et-leurs-familles")&CHAR(10)&HYPERLINK("https://solidarites.gouv.fr/outils-et-ressources-destination-des-autorites-organisatrices-de-laccueil-du-jeune-enfant","https://solidarites.gouv.fr/outils-et-ressources-destination-des-autorites-organisatrices-de-laccueil-du-jeune-enfant")&CHAR(10)&HYPERLINK("https://solidarites.gouv.fr/stephanie-rist-annonce-une-revalorisation-du-financement-des-creches-par-les-caf-de-2-en-2025","https://solidarites.gouv.fr/stephanie-rist-annonce-une-revalorisation-du-financement-des-creches-par-les-caf-de-2-en-2025")&CHAR(10)&HYPERLINK("https://www.ecologie.gouv.fr/eco-energie-tertiaire-eet","https://www.ecologie.gouv.fr/eco-energie-tertiaire-eet")&CHAR(10)&HYPERLINK("https://www.collectivites-locales.gouv.fr/les-collectivites-locales-en-chiffres-2025","https://www.collectivites-locales.gouv.fr/les-collectivites-locales-en-chiffres-2025")&CHAR(10)&HYPERLINK("https://www.collectivites-locales.gouv.fr/actualites/situation-mensuelle-comptable-des-collectivites-locales-au-31-decembre-2025","https://www.collectivites-locales.gouv.fr/actualites/situation-mensuelle-comptable-des-collectivites-locales-au-31-decembre-2025")&CHAR(10)&HYPERLINK("https://www.statistiques.developpement-durable.gouv.fr/construction-de-locaux-resultats-fin-janvier-2026-france-entiere","https://www.statistiques.developpement-durable.gouv.fr/construction-de-locaux-resultats-fin-janvier-2026-france-entiere")&CHAR(10)&HYPERLINK("https://www.insee.fr/fr/statistiques/8671745","https://www.insee.fr/fr/statistiques/8671745")&CHAR(10)&HYPERLINK("https://www.insee.fr/fr/statistiques/8906564","https://www.insee.fr/fr/statistiques/8906564") -> https://solidarites.gouv.fr/le-service-public-de-la-petite-enfance-garantir-un-accueil-de-qualite-tous-les-enfants-et-leurs-familles https://solidarites.gouv.fr/outils-et-ressources-destination-des-autorites-organisatrices-de-laccueil-du-jeune-enfant https://solidarites.gouv.fr/stephanie-rist-annonce-une-revalorisation-du-financement-des-creches-par-les-caf-de-2-en-2025 https://www.ecologie.gouv.fr/eco-energie-tertiaire-eet https://www.collectivites-locales.gouv.fr/les-collectivites-locales-en-chiffres-2025 https://www.collectivites-locales.gouv.fr/actualites/situation-mensuelle-comptable-des-collectivites-locales-au-31-decembre-2025 https://www.statistiques.developpement-durable.gouv.fr/construction-de-locaux-resultats-fin-janvier-2026-france-entiere https://www.insee.fr/fr/statistiques/8671745 https://www.insee.fr/fr/statistiques/8906564 | GH8: =GI8+GJ8 -> 13362.881 | GI8: =IFERROR($BE8*$FP8*0.2062*$BO8,0) -> 10795.582 | GJ8: =IFERROR($FC8*$BS8,0) -> 2567.2992 | GK8: =GL8+GM8 -> 11314.676 | GL8: =IFERROR($BE8*$FP8*0.2062*$BP8,0) -> 9068.2889 | GM8: =IFERROR($FC8*$BT8,0) -> 2246.3868 | GN8: =GO8+GP8 -> 1184.559 | GO8: =IFERROR($BE8*$FP8*0.2062*$BQ8,0) -> 863.64656 | GP8: =IFERROR($FC8*$BU8,0) -> 320.91241 | GQ8: =GR8+GS8 -> 1077.5882 | GR8: =IFERROR($BE8*$FP8*0.2062*$BR8,0) -> 863.64656 | GS8: =IFERROR($FC8*$BV8,0) -> 213.9416 | GT8: =GU8+GV8 -> 985.66615 | GU8: =IFERROR($BF8*$FP8*0.2062*$BW8,0) -> 793.47528 | GV8: =IFERROR($FF8*$BZ8,0) -> 192.19087 | GW8: =GX8+GY8 -> 90.187021 | GX8: =IFERROR($BF8*$FP8*0.2062*$BX8,0) -> 70.531136 | GY8: =IFERROR($FF8*$CA8,0) -> 19.655885 | GZ8: =HA8+HB8 -> 24.184746 | HA8: =IFERROR($BF8*$FP8*0.2062*$BY8,0) -> 17.632784 | HB8: =IFERROR($FF8*$CB8,0) -> 6.5519616 | HC8: =HD8+HE8 -> 0 | HD8: =IFERROR($BG8*$FP8*0.2062*$CC8,0) -> 0 | HE8: =IFERROR($FI8*$CG8,0) -> 0 | HF8: =HG8+HH8 -> 0 | HG8: =IFERROR($BG8*$FP8*0.2062*$CD8,0) -> 0 | HH8: =IFERROR($FI8*$CH8,0) -> 0 | HI8: =HJ8+HK8 -> 0 | HJ8: =IFERROR($BG8*$FP8*0.2062*$CE8,0) -> 0 | HK8: =IFERROR($FI8*$CI8,0) -> 0 | HL8: =HM8+HN8 -> 0 | HM8: =IFERROR($BG8*$FP8*0.2062*$CF8,0) -> 0 | HN8: =IFERROR($FI8*$CJ8,0) -> 0 | HO8: =HP8+HQ8 -> 22631.322 | HP8: =IFERROR($BH8*$FP8*0.2062*$CK8,0) -> 18352.489 | HQ8: =IFERROR($FL8*$CN8,0) -> 4278.8321 | HR8: =HS8+HT8 -> 4201.4118 | HS8: =IFERROR($BH8*$FP8*0.2062*$CL8,0) -> 3238.6746 | HT8: =IFERROR($FL8*$CO8,0) -> 962.73722 | HU8: =HV8+HW8 -> 106.9708 | HV8: =IFERROR($BH8*$FP8*0.2062*$CM8,0) -> 0 | HW8: =IFERROR($FL8*$CP8,0) -> 106.9708 | HY8: =SUM(HZ8:ID8) -> 244838.78 | HZ8: =IFERROR(IO8*BE8,0)+IFERROR(IY8*BF8,0)+IFERROR(JI8*BG8,0)+IFERROR(JS8*BH8,0) -> 2912.3617 | IA8: =IFERROR(IP8*BE8,0)+IFERROR(IZ8*BF8,0)+IFERROR(JJ8*BG8,0)+IFERROR(JT8*BH8,0) -> 82101.809 | IB8: =IFERROR(IQ8*BE8,0)+IFERROR(JA8*BF8,0)+IFERROR(JK8*BG8,0)+IFERROR(JU8*BH8,0) -> 131387.57 | IC8: =IFERROR(IR8*BE8,0)+IFERROR(JB8*BF8,0)+IFERROR(JL8*BG8,0)+IFERROR(JV8*BH8,0) -> 28437.029 | ID8: =IFERROR(IS8*BE8,0)+IFERROR(JC8*BF8,0)+IFERROR(JM8*BG8,0)+IFERROR(JW8*BH8,0) -> 0 | IE8: =SUM(IF8:IJ8) -> 44063.967 | IF8: =IFERROR(IT8*FB8,0)+IFERROR(JD8*FE8,0)+IFERROR(JN8*FH8,0)+IFERROR(JX8*FK8,0) -> 0 | IG8: =IFERROR(IU8*FB8,0)+IFERROR(JE8*FE8,0)+IFERROR(JO8*FH8,0)+IFERROR(JY8*FK8,0) -> 7453.5991 | IH8: =IFERROR(IV8*FB8,0)+IFERROR(JF8*FE8,0)+IFERROR(JP8*FH8,0)+IFERROR(JZ8*FK8,0) -> 24881.866 | II8: =IFERROR(IW8*FB8,0)+IFERROR(JG8*FE8,0)+IFERROR(JQ8*FH8,0)+IFERROR(KA8*FK8,0) -> 11728.502 | IJ8: =IFERROR(IX8*FB8,0)+IFERROR(JH8*FE8,0)+IFERROR(JR8*FH8,0)+IFERROR(KB8*FK8,0) -> 0 | IK8: 4.12 | IL8: Bonne | IM8: Parc existant surtout intermédiaire. Les ventes se décalent légèrement vers intermédiaire, porté par l’hygiène, la facilité d’entretien et la technicité. Le neuf est un peu plus qualitatif que la rénovation, sans renverser le centre de gravité du mix. Mix piloté par l’hygiène, la sécurité enfant et des budgets publics/associatifs encore contraints ; montée modérée en confort sur les programmes neufs ou restructurations globales. | IO8: 0.0061 | IP8: 0.3097 | IQ8: 0.5523 | IR8: 0.1319 | IS8: 0 | IT8: 0 | IU8: 0.1507 | IV8: 0.5583 | IW8: 0.291 | IX8: 0 | IY8: 0.0141 | IZ8: 0.3466 | JA8: 0.5307 | JB8: 0.1086 | JC8: 0 | JD8: 0 | JE8: 0.1767 | JF8: 0.5684 | JG8: 0.2549 | JH8: 0 | JI8: 0 | JJ8: 0 | JK8: 0 | JL8: 0 | JM8: 0 | JN8: 0 | JO8: 0 | JP8: 0 | JQ8: 0 | JR8: 0 | JS8: 0.0176 | JT8: 0.3605 | JU8: 0.5212 | JV8: 0.1007 | JW8: 0 | JX8: 0 | JY8: 0.1873 | JZ8: 0.5709 | KA8: 0.2418 | KB8: 0 | KD8: ±5 pts | KE8: ±6 pts | KF8: 3.95 | KG8: Moyenne + | KH8: Mix piloté par l’hygiène, la sécurité enfant et des budgets publics/associatifs encore contraints ; montée modérée en confort sur les programmes neufs ou restructurations globales. | KI8: contrainte sanitaire ⇒ standard/intermédiaire technique ↑ ; poids du neuf significatif ⇒ premiumisation des ventes > parc | KJ8: Crèches : petites unités, nettoyage fréquent et sécurité enfant priment sur l’effet décoratif. Ventes 2026-2030 : glissement vers davantage de moyen / premium, surtout sur lavabo (+15,9 pts sur premium+luxe), douche (+14,6 pts sur premium+luxe), WC (+14,1 pts sur premium+luxe). Le neuf pèse suffisamment (38% des ventes) pour relever le niveau de confort moyen au-dessus de la rénovation (62%). L’écart de niveau de confort entre neuf et rénovation est net.
A9: =A8+1 -> 2 | B9: Enfance, Enseignement, Jeunesse & Formation | C9: Petite enfance | D9: Haltes-garderies, jardins d’enfants (hors crèches) | E9: R | F9: ERP / variable | G9: ERP | H9: oui | I9: Établissements accueil Peite enfance | J9: Halte-garderie autonome, jardin d’enfants autonome, structure mono-accueil ponctuel ou pré-scolaire non comptée en crèche | K9: non | L9: oui | M9: Site Etablissement principal | N9: série publique directe 2024 / BPE, puis ventilation encadrée | O9: Moyenne | Q9: 1 | R9: 360 | S9: 2600 | T9: 2100 | U9: 1650 | V9: 1050 | W9: 1000 | X9: 950 | Y9: 890 | Z9: 820 | AA9: 760 | AB9: 710 | AC9: 670 | AD9: 630 | AE9: 600 | AF9: 570 | AG9: 540 | AH9: 510 | AI9: 480 | AJ9: 450 | AK9: 420 | AL9: Décroissance structurelle : transformation des anciennes haltes-garderies vers le multi-accueil/crèches et extinction progressive des jardins d’enfants. | AM9: Projection prudente : maintien d’un noyau résiduel de sites autonomes, mais poursuite du reflux jusqu’en 2030. Inclusion uniquement si non déjà absorbés dans crèches/EAJE. | AN9: https://www.drees.solidarites-sante.gouv.fr/communique-de-presse-jeux-de-donnees/jeux-de-donnees/250528_DATA_donnees-departementales-sur-l-offre-daccueil-du-jeune-enfant-2023 https://www.senat.fr/rap/l23-418/l23-418_mono.html https://www.legifrance.gouv.fr/jorf/article_jo/JORFARTI000044025660 | AP9: 30 | AQ9: 24 | AR9: 5 | AS9: 1 | AU9: Petit bloc enfants + sanitaire adulte/personnel ; pas de douches collectives hors change. | AV9: Capacité type ≈ 24 usagers principaux + 5 staff + 1 autre public. Accueil de courte durée en petite enfance, avec rotation et accompagnants ponctuels. Dimensionnement unitaire retenu : bloc enfants proche salles + 1 sanitaire adulte/PMR et point d'eau, surdimensionné pour surveillance et hygiène. Hypothèse d'usage : capacité simultanée moyenne 2026, répartition par flux réels, arrondie par blocs fonctionnels et exclusion des sanitaires strictement privatifs sauf cas explicitement collectifs. | AW9: Profil petit, capacité moyenne ≈ 30 personnes. Moyenne pondérée terrain : parc majoritairement petits/moyens sites, grands sites intégrés sans surpondération ; usage 2025 modérée. | AX9: ERP/accessibilité sanitaires publics : https://www.legifrance.gouv.fr/loda/article_lc/LEGIARTI000034485966/ ; Code du travail sanitaires salariés : https://www.legifrance.gouv.fr/codes/id/LEGISCTA000018531984 ; Bâti scolaire / sanitaires : https://batiscolaire.education.gouv.fr/fiche-espace-sanitaires-eleves-elementaire-et-secondaire-240412 | AZ9: 4 | BA9: 0.15 | BB9: 0 | BC9: 4 | BD9: =SUM(BE9:BH9) -> 4645.5 | BE9: =AF9*AZ9 -> 2280 | BF9: =AF9*BA9 -> 85.5 | BG9: =AF9*BB9 -> 0 | BH9: =AF9*BC9 -> 2280 | BI9: =SUM(BJ9:BM9) -> 3423 | BJ9: =AK9*AZ9 -> 1680 | BK9: =AK9*BA9 -> 63 | BL9: =AK9*BB9 -> 0 | BM9: =AK9*BC9 -> 1680 | BO9: 0.5 | BP9: 0.42 | BQ9: 0.04 | BR9: 0.04 | BS9: 0.48 | BT9: 0.42 | BU9: 0.06 | BV9: 0.04 | BW9: 0.9 | BX9: 0.08 | BY9: 0.02 | BZ9: 0.88 | CA9: 0.09 | CB9: 0.03 | CK9: 0.85 | CL9: 0.15 | CN9: 0.8 | CO9: 0.18 | CP9: 0.02 | CR9: 14 | CS9: 13 | CT9: 10 | CU9: 12 | CV9: 13 | CW9: 12 | CX9: 9 | DC9: 15 | DD9: 15 | DE9: 12 | DF9: Petite enfance : Durées plutôt correctes car usage encadré, mais remplacement souvent par blocs lors de travaux municipaux ou scolaires. Mix retenu : Usage encadré et hauteur/ergonomie enfant : mitigeurs et temporisations mécaniques dominent, électronique marginale ; urinoirs généralement nuls. | DH9: =$BE9*BO9 -> 1140 | DI9: =$BE9*BP9 -> 957.6 | DJ9: =$BE9*BQ9 -> 91.2 | DK9: =$BE9*BR9 -> 91.2 | DL9: Haltes-garderies, jardins d’enfants (hors crèches) : parc 2025 domine par mitigeur manuel (50%), avec tempo mecanique en appoint. Le choix reflete usage quotidien par cohortes, pics de recreations/cours et renovation par lots ; robustesse scolaire, entretien simple et contraintes de vacances scolaires. | DM9: =$BJ9*BS9 -> 806.4 | DN9: =$BJ9*BT9 -> 705.6 | DO9: =$BJ9*BU9 -> 100.8 | DP9: =$BJ9*BV9 -> 67.2 | DQ9: 2025-2030 : progression de tempo electronique (+2,0%), surtout lors des renov. lourdes/neuf ; recul de mitigeur manuel (-2,0%) mais maintien d un socle robuste pour les remplacements partiels. | DS9: =$BF9*BW9 -> 76.95 | DT9: =$BF9*BX9 -> 6.84 | DU9: =$BF9*BY9 -> 1.71 | DV9: Haltes-garderies, jardins d’enfants (hors crèches) : parc 2025 domine par mitigeur (90%), avec tempo mecanique en appoint. Le choix reflete usage quotidien par cohortes, pics de recreations/cours et renovation par lots ; robustesse scolaire, entretien simple et contraintes de vacances scolaires. | DW9: =$BK9*BZ9 -> 55.44 | DX9: =$BK9*CA9 -> 5.67 | DY9: =$BK9*CB9 -> 1.89 | DZ9: 2025-2030 : progression de tempo electronique (+1,0%), surtout lors des renov. lourdes/neuf ; recul de mitigeur (-2,0%) mais maintien d un socle robuste pour les remplacements partiels. | EB9: =$BG9*CC9 -> 0 | EC9: =$BG9*CD9 -> 0 | ED9: =$BG9*CE9 -> 0 | EE9: =$BG9*CF9 -> 0 | EF9: Sans objet. | EG9: =$BL9*CG9 -> 0 | EH9: =$BL9*CH9 -> 0 | EI9: =$BL9*CI9 -> 0 | EJ9: =$BL9*CJ9 -> 0 | EK9: Sans objet. | EM9: =$BH9*CK9 -> 1938 | EN9: =$BH9*CL9 -> 342 | EO9: =$BH9*CM9 -> 0 | EP9: Haltes-garderies, jardins d’enfants (hors crèches) : parc 2025 domine par reservoir (85%), avec chasse directe mecanique en appoint. Le choix reflete usage quotidien par cohortes, pics de recreations/cours et renovation par lots ; robustesse scolaire, entretien simple et contraintes de vacances scolaires. | EQ9: =$BM9*CN9 -> 1344 | ER9: =$BM9*CO9 -> 302.4 | ES9: =$BM9*CP9 -> 33.6 | ET9: 2025-2030 : progression de chasse directe mecanique (+3,0%), surtout lors des renov. lourdes/neuf ; recul de reservoir (-5,0%) mais maintien d un socle robuste pour les remplacements partiels. | EV9: =IFERROR(EY9/EX9,0) -> 0.92627782 | EW9: =IFERROR(EZ9/EX9,0) -> 0.07372218 | EX9: =EY9+EZ9 -> 3484.6521 | EY9: =SUM(FB9,FE9,FH9,FK9) -> 3227.756 | EZ9: =SUM(FC9,FF9,FI9,FL9) -> 256.89615 | FA9: =FB9+FC9 -> 1679.0714 | FB9: =SUM(GI9,GL9,GO9,GR9) -> 1552.9874 | FC9: =MAX(0,$BJ9-$BE9)+$BE9*$FO9 -> 126.084 | FD9: =FE9+FF9 -> 62.082716 | FE9: =SUM(GU9,GX9,HA9) -> 57.354566 | FF9: =MAX(0,$BK9-$BF9)+$BF9*$FO9 -> 4.72815 | FG9: =FH9+FI9 -> 0 | FH9: =SUM(HD9,HG9,HJ9,HM9) -> 0 | FI9: =MAX(0,$BL9-$BG9)+$BG9*$FO9 -> 0 | FJ9: =FK9+FL9 -> 1743.498 | FK9: =SUM(HP9,HS9,HV9) -> 1617.414 | FL9: =MAX(0,$BM9-$BH9)+$BH9*$FO9 -> 126.084 | FN9: Moyenne à Bonne | FO9: 0.0553 | FP9: 0.79285 | FQ9: 79,3% retenu : besoins transformes en travaux selon usage quotidien par cohortes, pics de recreations/cours et renovation par lots. Le phasage budgetaire, les fermetures partielles et la maintenance courante limitent la conversion totale. | FS9: 3.36 | FT9: =RANK($FS9,$FS$8:$FS$154,0)+COUNTIF($FS$8:$FS9,$FS9)-1 -> 66 | FU9: 4.15 | FV9: =RANK($FU9,$FU$8:$FU$154,0)+COUNTIF($FU$8:$FU9,$FU9)-1 -> 53 | FW9: 1.96 | FX9: =RANK($FW9,$FW$8:$FW$154,0)+COUNTIF($FW$8:$FW9,$FW9)-1 -> 112 | FZ9: Potentiel renovation : tire par robustesse scolaire, entretien simple et contraintes de vacances scolaires. Les remplacements sont plutot par lots, avec arbitrage entre urgence sanitaire, budget et capacite a intervenir en site occupe. | GA9: Potentiel neuf : limite pour haltes-garderies, jardins d’enfants (hors crèches), surtout via extensions, reconstructions ou projets locaux. Le neuf reste contraint par foncier, budgets et delais de mise en service. | GB9: Projets phares renovation : reprise de blocs sanitaires, accessibilite, ventilation, economie d eau, remplacement des pieces usees et adaptation aux pics de frequentation propres au sous-segment. | GC9: Projets phares neuf : creations ou reconstructions selectives, integration de sanitaires plus sobres, robustes et faciles a maintenir des la conception. | GD9: Dynamique renovation 2026-2030 : forte, car l usure et l hygiene rendent les interventions recurrentes. Menaces : arbitrages d investissement, travaux en exploitation et cout de maintenance. | GE9: Dynamique neuf 2026-2030 : faible a moderee, dependante des projets immobiliers, de la demographie locale et des budgets de maitrise d ouvrage. | GF9: =HYPERLINK("https://solidarites.gouv.fr/le-service-public-de-la-petite-enfance-garantir-un-accueil-de-qualite-tous-les-enfants-et-leurs-familles","https://solidarites.gouv.fr/le-service-public-de-la-petite-enfance-garantir-un-accueil-de-qualite-tous-les-enfants-et-leurs-familles")&CHAR(10)&HYPERLINK("https://solidarites.gouv.fr/outils-et-ressources-destination-des-autorites-organisatrices-de-laccueil-du-jeune-enfant","https://solidarites.gouv.fr/outils-et-ressources-destination-des-autorites-organisatrices-de-laccueil-du-jeune-enfant")&CHAR(10)&HYPERLINK("https://solidarites.gouv.fr/stephanie-rist-annonce-une-revalorisation-du-financement-des-creches-par-les-caf-de-2-en-2025","https://solidarites.gouv.fr/stephanie-rist-annonce-une-revalorisation-du-financement-des-creches-par-les-caf-de-2-en-2025")&CHAR(10)&HYPERLINK("https://www.ecologie.gouv.fr/eco-energie-tertiaire-eet","https://www.ecologie.gouv.fr/eco-energie-tertiaire-eet")&CHAR(10)&HYPERLINK("https://www.collectivites-locales.gouv.fr/les-collectivites-locales-en-chiffres-2025","https://www.collectivites-locales.gouv.fr/les-collectivites-locales-en-chiffres-2025")&CHAR(10)&HYPERLINK("https://www.collectivites-locales.gouv.fr/actualites/situation-mensuelle-comptable-des-collectivites-locales-au-31-decembre-2025","https://www.collectivites-locales.gouv.fr/actualites/situation-mensuelle-comptable-des-collectivites-locales-au-31-decembre-2025")&CHAR(10)&HYPERLINK("https://www.statistiques.developpement-durable.gouv.fr/construction-de-locaux-resultats-fin-janvier-2026-france-entiere","https://www.statistiques.developpement-durable.gouv.fr/construction-de-locaux-resultats-fin-janvier-2026-france-entiere")&CHAR(10)&HYPERLINK("https://www.insee.fr/fr/statistiques/8671745","https://www.insee.fr/fr/statistiques/8671745")&CHAR(10)&HYPERLINK("https://www.insee.fr/fr/statistiques/8906564","https://www.insee.fr/fr/statistiques/8906564") -> https://solidarites.gouv.fr/le-service-public-de-la-petite-enfance-garantir-un-accueil-de-qualite-tous-les-enfants-et-leurs-familles https://solidarites.gouv.fr/outils-et-ressources-destination-des-autorites-organisatrices-de-laccueil-du-jeune-enfant https://solidarites.gouv.fr/stephanie-rist-annonce-une-revalorisation-du-financement-des-creches-par-les-caf-de-2-en-2025 https://www.ecologie.gouv.fr/eco-energie-tertiaire-eet https://www.collectivites-locales.gouv.fr/les-collectivites-locales-en-chiffres-2025 https://www.collectivites-locales.gouv.fr/actualites/situation-mensuelle-comptable-des-collectivites-locales-au-31-decembre-2025 https://www.statistiques.developpement-durable.gouv.fr/construction-de-locaux-resultats-fin-janvier-2026-france-entiere https://www.insee.fr/fr/statistiques/8671745 https://www.insee.fr/fr/statistiques/8906564 | GH9: =GI9+GJ9 -> 853.37032 | GI9: =IFERROR($DH9*$FP9/MAX(0.000000001,$CR9)*(INDEX($S9:$AF9,1,MATCH(MAX(2000,MIN(2025,ROUND(2026-$CR9,0))),$S$4:$AF$4,1))+INDEX($S9:$AF9,1,MATCH(MAX(2000,MIN(2025,ROUND(2027-$CR9,0))),$S$4:$AF$4,1))+INDEX($S9:$AF9,1,MATCH(MAX(2000,MIN(2025,ROUND(2028-$CR9,0))),$S$4:$AF$4,1))+INDEX($S9:$AF9,1,MATCH(MAX(2000,MIN(2025,ROUND(2029-$CR9,0))),$S$4:$AF$4,1))+INDEX($S9:$AF9,1,MATCH(MAX(2000,MIN(2025,ROUND(2030-$CR9,0))),$S$4:$AF$4,1)))/MAX(1,$AF9),0) -> 792.85 | GJ9: =IFERROR($FC9*$BS9,0) -> 60.52032 | GK9: =GL9+GM9 -> 698.45716 | GL9: =IFERROR($DI9*$FP9/MAX(0.000000001,$CS9)*(INDEX($S9:$AF9,1,MATCH(MAX(2000,MIN(2025,ROUND(2026-$CS9,0))),$S$4:$AF$4,1))+INDEX($S9:$AF9,1,MATCH(MAX(2000,MIN(2025,ROUND(2027-$CS9,0))),$S$4:$AF$4,1))+INDEX($S9:$AF9,1,MATCH(MAX(2000,MIN(2025,ROUND(2028-$CS9,0))),$S$4:$AF$4,1))+INDEX($S9:$AF9,1,MATCH(MAX(2000,MIN(2025,ROUND(2029-$CS9,0))),$S$4:$AF$4,1))+INDEX($S9:$AF9,1,MATCH(MAX(2000,MIN(2025,ROUND(2030-$CS9,0))),$S$4:$AF$4,1)))/MAX(1,$AF9),0) -> 645.50188 | GM9: =IFERROR($FC9*$BT9,0) -> 52.95528 | GN9: =GO9+GP9 -> 63.635392 | GO9: =IFERROR($DJ9*$FP9/MAX(0.000000001,$CT9)*(INDEX($S9:$AF9,1,MATCH(MAX(2000,MIN(2025,ROUND(2026-$CT9,0))),$S$4:$AF$4,1))+INDEX($S9:$AF9,1,MATCH(MAX(2000,MIN(2025,ROUND(2027-$CT9,0))),$S$4:$AF$4,1))+INDEX($S9:$AF9,1,MATCH(MAX(2000,MIN(2025,ROUND(2028-$CT9,0))),$S$4:$AF$4,1))+INDEX($S9:$AF9,1,MATCH(MAX(2000,MIN(2025,ROUND(2029-$CT9,0))),$S$4:$AF$4,1))+INDEX($S9:$AF9,1,MATCH(MAX(2000,MIN(2025,ROUND(2030-$CT9,0))),$S$4:$AF$4,1)))/MAX(1,$AF9),0) -> 56.070352 | GP9: =IFERROR($FC9*$BU9,0) -> 7.56504 | GQ9: =GR9+GS9 -> 63.608547 | GR9: =IFERROR($DK9*$FP9/MAX(0.000000001,$CU9)*(INDEX($S9:$AF9,1,MATCH(MAX(2000,MIN(2025,ROUND(2026-$CU9,0))),$S$4:$AF$4,1))+INDEX($S9:$AF9,1,MATCH(MAX(2000,MIN(2025,ROUND(2027-$CU9,0))),$S$4:$AF$4,1))+INDEX($S9:$AF9,1,MATCH(MAX(2000,MIN(2025,ROUND(2028-$CU9,0))),$S$4:$AF$4,1))+INDEX($S9:$AF9,1,MATCH(MAX(2000,MIN(2025,ROUND(2029-$CU9,0))),$S$4:$AF$4,1))+INDEX($S9:$AF9,1,MATCH(MAX(2000,MIN(2025,ROUND(2030-$CU9,0))),$S$4:$AF$4,1)))/MAX(1,$AF9),0) -> 58.565187 | GS9: =IFERROR($FC9*$BV9,0) -> 5.04336 | GT9: =GU9+GV9 -> 56.031459 | GU9: =IFERROR($DS9*$FP9/MAX(0.000000001,$CV9)*(INDEX($S9:$AF9,1,MATCH(MAX(2000,MIN(2025,ROUND(2026-$CV9,0))),$S$4:$AF$4,1))+INDEX($S9:$AF9,1,MATCH(MAX(2000,MIN(2025,ROUND(2027-$CV9,0))),$S$4:$AF$4,1))+INDEX($S9:$AF9,1,MATCH(MAX(2000,MIN(2025,ROUND(2028-$CV9,0))),$S$4:$AF$4,1))+INDEX($S9:$AF9,1,MATCH(MAX(2000,MIN(2025,ROUND(2029-$CV9,0))),$S$4:$AF$4,1))+INDEX($S9:$AF9,1,MATCH(MAX(2000,MIN(2025,ROUND(2030-$CV9,0))),$S$4:$AF$4,1)))/MAX(1,$AF9),0) -> 51.870687 | GV9: =IFERROR($FF9*$BZ9,0) -> 4.160772 | GW9: =GX9+GY9 -> 4.8179225 | GX9: =IFERROR($DT9*$FP9/MAX(0.000000001,$CW9)*(INDEX($S9:$AF9,1,MATCH(MAX(2000,MIN(2025,ROUND(2026-$CW9,0))),$S$4:$AF$4,1))+INDEX($S9:$AF9,1,MATCH(MAX(2000,MIN(2025,ROUND(2027-$CW9,0))),$S$4:$AF$4,1))+INDEX($S9:$AF9,1,MATCH(MAX(2000,MIN(2025,ROUND(2028-$CW9,0))),$S$4:$AF$4,1))+INDEX($S9:$AF9,1,MATCH(MAX(2000,MIN(2025,ROUND(2029-$CW9,0))),$S$4:$AF$4,1))+INDEX($S9:$AF9,1,MATCH(MAX(2000,MIN(2025,ROUND(2030-$CW9,0))),$S$4:$AF$4,1)))/MAX(1,$AF9),0) -> 4.392389 | GY9: =IFERROR($FF9*$CA9,0) -> 0.4255335 | GZ9: =HA9+HB9 -> 1.2333347 | HA9: =IFERROR($DU9*$FP9/MAX(0.000000001,$CX9)*(INDEX($S9:$AF9,1,MATCH(MAX(2000,MIN(2025,ROUND(2026-$CX9,0))),$S$4:$AF$4,1))+INDEX($S9:$AF9,1,MATCH(MAX(2000,MIN(2025,ROUND(2027-$CX9,0))),$S$4:$AF$4,1))+INDEX($S9:$AF9,1,MATCH(MAX(2000,MIN(2025,ROUND(2028-$CX9,0))),$S$4:$AF$4,1))+INDEX($S9:$AF9,1,MATCH(MAX(2000,MIN(2025,ROUND(2029-$CX9,0))),$S$4:$AF$4,1))+INDEX($S9:$AF9,1,MATCH(MAX(2000,MIN(2025,ROUND(2030-$CX9,0))),$S$4:$AF$4,1)))/MAX(1,$AF9),0) -> 1.0914902 | HB9: =IFERROR($FF9*$CB9,0) -> 0.1418445 | HC9: =HD9+HE9 -> 0 | HD9: =IFERROR($EB9*$FP9/MAX(0.000000001,$CY9)*(INDEX($S9:$AF9,1,MATCH(MAX(2000,MIN(2025,ROUND(2026-$CY9,0))),$S$4:$AF$4,1))+INDEX($S9:$AF9,1,MATCH(MAX(2000,MIN(2025,ROUND(2027-$CY9,0))),$S$4:$AF$4,1))+INDEX($S9:$AF9,1,MATCH(MAX(2000,MIN(2025,ROUND(2028-$CY9,0))),$S$4:$AF$4,1))+INDEX($S9:$AF9,1,MATCH(MAX(2000,MIN(2025,ROUND(2029-$CY9,0))),$S$4:$AF$4,1))+INDEX($S9:$AF9,1,MATCH(MAX(2000,MIN(2025,ROUND(2030-$CY9,0))),$S$4:$AF$4,1)))/MAX(1,$AF9),0) -> 0 | HE9: =IFERROR($FI9*$CG9,0) -> 0 | HF9: =HG9+HH9 -> 0 | HG9: =IFERROR($EC9*$FP9/MAX(0.000000001,$CZ9)*(INDEX($S9:$AF9,1,MATCH(MAX(2000,MIN(2025,ROUND(2026-$CZ9,0))),$S$4:$AF$4,1))+INDEX($S9:$AF9,1,MATCH(MAX(2000,MIN(2025,ROUND(2027-$CZ9,0))),$S$4:$AF$4,1))+INDEX($S9:$AF9,1,MATCH(MAX(2000,MIN(2025,ROUND(2028-$CZ9,0))),$S$4:$AF$4,1))+INDEX($S9:$AF9,1,MATCH(MAX(2000,MIN(2025,ROUND(2029-$CZ9,0))),$S$4:$AF$4,1))+INDEX($S9:$AF9,1,MATCH(MAX(2000,MIN(2025,ROUND(2030-$CZ9,0))),$S$4:$AF$4,1)))/MAX(1,$AF9),0) -> 0 | HH9: =IFERROR($FI9*$CH9,0) -> 0 | HI9: =HJ9+HK9 -> 0 | HJ9: =IFERROR($ED9*$FP9/MAX(0.000000001,$DA9)*(INDEX($S9:$AF9,1,MATCH(MAX(2000,MIN(2025,ROUND(2026-$DA9,0))),$S$4:$AF$4,1))+INDEX($S9:$AF9,1,MATCH(MAX(2000,MIN(2025,ROUND(2027-$DA9,0))),$S$4:$AF$4,1))+INDEX($S9:$AF9,1,MATCH(MAX(2000,MIN(2025,ROUND(2028-$DA9,0))),$S$4:$AF$4,1))+INDEX($S9:$AF9,1,MATCH(MAX(2000,MIN(2025,ROUND(2029-$DA9,0))),$S$4:$AF$4,1))+INDEX($S9:$AF9,1,MATCH(MAX(2000,MIN(2025,ROUND(2030-$DA9,0))),$S$4:$AF$4,1)))/MAX(1,$AF9),0) -> 0 | HK9: =IFERROR($FI9*$CI9,0) -> 0 | HL9: =HM9+HN9 -> 0 | HM9: =IFERROR($EE9*$FP9/MAX(0.000000001,$DB9)*(INDEX($S9:$AF9,1,MATCH(MAX(2000,MIN(2025,ROUND(2026-$DB9,0))),$S$4:$AF$4,1))+INDEX($S9:$AF9,1,MATCH(MAX(2000,MIN(2025,ROUND(2027-$DB9,0))),$S$4:$AF$4,1))+INDEX($S9:$AF9,1,MATCH(MAX(2000,MIN(2025,ROUND(2028-$DB9,0))),$S$4:$AF$4,1))+INDEX($S9:$AF9,1,MATCH(MAX(2000,MIN(2025,ROUND(2029-$DB9,0))),$S$4:$AF$4,1))+INDEX($S9:$AF9,1,MATCH(MAX(2000,MIN(2025,ROUND(2030-$DB9,0))),$S$4:$AF$4,1)))/MAX(1,$AF9),0) -> 0 | HN9: =IFERROR($FI9*$CJ9,0) -> 0 | HO9: =HP9+HQ9 -> 1475.6691 | HP9: =IFERROR($EM9*$FP9/MAX(0.000000001,$DC9)*(INDEX($S9:$AF9,1,MATCH(MAX(2000,MIN(2025,ROUND(2026-$DC9,0))),$S$4:$AF$4,1))+INDEX($S9:$AF9,1,MATCH(MAX(2000,MIN(2025,ROUND(2027-$DC9,0))),$S$4:$AF$4,1))+INDEX($S9:$AF9,1,MATCH(MAX(2000,MIN(2025,ROUND(2028-$DC9,0))),$S$4:$AF$4,1))+INDEX($S9:$AF9,1,MATCH(MAX(2000,MIN(2025,ROUND(2029-$DC9,0))),$S$4:$AF$4,1))+INDEX($S9:$AF9,1,MATCH(MAX(2000,MIN(2025,ROUND(2030-$DC9,0))),$S$4:$AF$4,1)))/MAX(1,$AF9),0) -> 1374.8019 | HQ9: =IFERROR($FL9*$CN9,0) -> 100.8672 | HR9: =HS9+HT9 -> 265.30722 | HS9: =IFERROR($EN9*$FP9/MAX(0.000000001,$DD9)*(INDEX($S9:$AF9,1,MATCH(MAX(2000,MIN(2025,ROUND(2026-$DD9,0))),$S$4:$AF$4,1))+INDEX($S9:$AF9,1,MATCH(MAX(2000,MIN(2025,ROUND(2027-$DD9,0))),$S$4:$AF$4,1))+INDEX($S9:$AF9,1,MATCH(MAX(2000,MIN(2025,ROUND(2028-$DD9,0))),$S$4:$AF$4,1))+INDEX($S9:$AF9,1,MATCH(MAX(2000,MIN(2025,ROUND(2029-$DD9,0))),$S$4:$AF$4,1))+INDEX($S9:$AF9,1,MATCH(MAX(2000,MIN(2025,ROUND(2030-$DD9,0))),$S$4:$AF$4,1)))/MAX(1,$AF9),0) -> 242.6121 | HT9: =IFERROR($FL9*$CO9,0) -> 22.69512 | HU9: =HV9+HW9 -> 2.52168 | HV9: =IFERROR($EO9*$FP9/MAX(0.000000001,$DE9)*(INDEX($S9:$AF9,1,MATCH(MAX(2000,MIN(2025,ROUND(2026-$DE9,0))),$S$4:$AF$4,1))+INDEX($S9:$AF9,1,MATCH(MAX(2000,MIN(2025,ROUND(2027-$DE9,0))),$S$4:$AF$4,1))+INDEX($S9:$AF9,1,MATCH(MAX(2000,MIN(2025,ROUND(2028-$DE9,0))),$S$4:$AF$4,1))+INDEX($S9:$AF9,1,MATCH(MAX(2000,MIN(2025,ROUND(2029-$DE9,0))),$S$4:$AF$4,1))+INDEX($S9:$AF9,1,MATCH(MAX(2000,MIN(2025,ROUND(2030-$DE9,0))),$S$4:$AF$4,1)))/MAX(1,$AF9),0) -> 0 | HW9: =IFERROR($FL9*$CP9,0) -> 2.52168 | HY9: =SUM(HZ9:ID9) -> 4645.5 | HZ9: =IFERROR(IO9*BE9,0)+IFERROR(IY9*BF9,0)+IFERROR(JI9*BG9,0)+IFERROR(JS9*BH9,0) -> 479.7861 | IA9: =IFERROR(IP9*BE9,0)+IFERROR(IZ9*BF9,0)+IFERROR(JJ9*BG9,0)+IFERROR(JT9*BH9,0) -> 2484.1085 | IB9: =IFERROR(IQ9*BE9,0)+IFERROR(JA9*BF9,0)+IFERROR(JK9*BG9,0)+IFERROR(JU9*BH9,0) -> 1554.769 | IC9: =IFERROR(IR9*BE9,0)+IFERROR(JB9*BF9,0)+IFERROR(JL9*BG9,0)+IFERROR(JV9*BH9,0) -> 126.8364 | ID9: =IFERROR(IS9*BE9,0)+IFERROR(JC9*BF9,0)+IFERROR(JM9*BG9,0)+IFERROR(JW9*BH9,0) -> 0 | IE9: =SUM(IF9:IJ9) -> 3227.756 | IF9: =IFERROR(IT9*FB9,0)+IFERROR(JD9*FE9,0)+IFERROR(JN9*FH9,0)+IFERROR(JX9*FK9,0) -> 274.02497 | IG9: =IFERROR(IU9*FB9,0)+IFERROR(JE9*FE9,0)+IFERROR(JO9*FH9,0)+IFERROR(JY9*FK9,0) -> 1653.4936 | IH9: =IFERROR(IV9*FB9,0)+IFERROR(JF9*FE9,0)+IFERROR(JP9*FH9,0)+IFERROR(JZ9*FK9,0) -> 1139.5019 | II9: =IFERROR(IW9*FB9,0)+IFERROR(JG9*FE9,0)+IFERROR(JQ9*FH9,0)+IFERROR(KA9*FK9,0) -> 147.51459 | IJ9: =IFERROR(IX9*FB9,0)+IFERROR(JH9*FE9,0)+IFERROR(JR9*FH9,0)+IFERROR(KB9*FK9,0) -> 13.220914 | IK9: 4.16 | IL9: Bonne | IM9: Parc existant centre sur le niveau standard, avec ventes 2026-2030 legerement plus qualitatives. Haltes-garderies, jardins d’enfants (hors crèches) : usage quotidien par cohortes, pics de recreations/cours et renovation par lots; le mix reste guide par robustesse scolaire, entretien simple et contraintes de vacances scolaires. | IO9: 0.1 | IP9: 0.53 | IQ9: 0.34 | IR9: 0.03 | IS9: 0 | IT9: 0.0815 | IU9: 0.5074 | IV9: 0.3584 | IW9: 0.0484 | IX9: 0.0043 | IY9: 0.1022 | IZ9: 0.5419 | JA9: 0.3311 | JB9: 0.0248 | JC9: 0 | JD9: 0.0837 | JE9: 0.5194 | JF9: 0.3496 | JG9: 0.0432 | JH9: 0.0041 | JI9: 0 | JJ9: 0 | JK9: 0 | JL9: 0 | JM9: 0 | JN9: 0 | JO9: 0 | JP9: 0 | JQ9: 0 | JR9: 0 | JS9: 0.1066 | JT9: 0.5392 | JU9: 0.3295 | JV9: 0.0247 | JW9: 0 | JX9: 0.0882 | JY9: 0.5167 | JZ9: 0.348 | KA9: 0.0432 | KB9: 0.0039 | KD9: ±4 pts | KE9: ±4 pts | KF9: 4.19 | KG9: Bonne | KH9: Parc existant : robustesse scolaire, entretien simple et contraintes de vacances scolaires; usage quotidien par cohortes, pics de recreations/cours et renovation par lots. La montee en confort reste proportionnee au budget et au rythme de renovation. | KI9: renovation dominante => progression graduelle | KJ9: Haltes-garderies, jardins d’enfants (hors crèches) : ventes 2026-2030 en leger glissement vers moyen/premium lorsque le neuf ou les renov. lourdes interviennent. Le centre de gravite reste toutefois module par robustesse scolaire, entretien simple et contraintes de vacances scolaires et par la part dominante de travaux sur parc existant.
